Workbook

Sheet DICIEMBRE.2025
A5: CTA.CTE DICIEMBRE - 2025 - CARGAS + HIELO | K5: SEMANA DEL 1/12 AL 7/12
A6: CARGAS COMBUSTIBLE YPF | K6: RESUMEN CONSUMO
A7: FECHA | B7: FACTURA | C7: N° COMP | D7: VEHICULO | E7: PAGOS | F7: CONSUMOS | G7: SALDO | H7: LITROS | I7: OBSEVACIONES | K7: RESUMEN | L7: CONSUMO | M7: LTS
D8: SALDO ANTERIOR | G8: =SUM(E8:F8) -> 0
G9: =+G8+E9-F9 -> 0
G10: =+G9+E10-F10 -> 0
G11: =+G10+E11-F11 -> 0
G12: =+G11+E12-F12 -> 0
G13: =+G12+E13-F13 -> 0
G14: =+G13+E14-F14 -> 0
G15: =+G14+E15-F15 -> 0
G16: =+G15+E16-F16 -> 0
G17: =+G16+E17-F17 -> 0
G18: =+G17+E18-F18 -> 0
G19: =+G18+E19-F19 -> 0
G20: =+G19+E20-F20 -> 0
... G39: =+G38+E39-F39 -> 0
A40: 45991 | C40: SALDO ANTERIOR | F40: 973849.91 | G40: =+G39+E40-F40 -> -973849.91 | K40: AG 378 AV | L40: COMBUSTIBLE | M40: 0
A41: 45992 | B41: FA | C41: 92-0586 | D41: PFG 964 | F41: 26149.13 | G41: =+G40+E41-F41 -> -999999.04 | H41: 7.119 | I41: COMBUSTIBLE + HIELO | K41: AG 337 MY | L41: COMBUSTIBLE | M41: =SUM(H61) -> 11.627
A42: 45992 | B42: FA | C42: 60-7935 | D42: PFG 964 | F42: 81338.21 | G42: =+G41+E42-F42 -> -1081337.2 | H42: 45.335 | I42: COMBUSTIBLE | K42: AG 962 EW | L42: COMBUSTIBLE | M42: 0
A43: 45992 | B43: RE | C43: 50-0011 | D43: TRANSF | E43: 2000000 | G43: =+G42+E43-F43 -> 918662.75 | I43: PAGO - SALDO A FAVOR | K43: AA 183 PK | L43: COMBUSTIBLE | M43: =SUM(H46+H70+H88) -> 73.344
A44: 45992 | B44: FA | C44: 63-0528 | D44: WNO 918 | F44: 224384.16 | G44: =+G43+E44-F44 -> 694278.59 | H44: 128 | I44: COMBUSTIBLE | K44: OHA 122 | L44: COMBUSTIBLE | M44: 0
A45: 45992 | B45: FA | C45: 63-0531 | D45: HKQ 258 | F45: 528508.89 | G45: =+G44+E45-F45 -> 165769.7 | H45: 223.376 | I45: COMBUSTIBLE | K45: KEX 251 | L45: COMBUSTIBLE | M45: =SUM(H67+H87) -> 48.794
A46: 45992 | B46: FA | C46: 55-6980 | D46: AA 183 PK | F46: 58100.15 | G46: =+G45+E46-F46 -> 107669.55 | H46: 24.55 | I46: COMBUSTIBLE | K46: AF 728 AT | L46: COMBUSTIBLE | M46: =SUM(H76+H85) -> 94.965
A47: 45992 | B47: FA | C47: 55-6982 | D47: LVX 455 | F47: 13100 | G47: =+G46+E47-F47 -> 94569.55 | H47: * | I47: HIELO | K47: PFG 964 | L47: COMBUSTIBLE | M47: =SUM(H41+H42+H62+H71+H83) -> 163.838
A48: 45992 | B48: FA | C48: 63-0537 | D48: AG 958 JV | F48: 291286.9 | G48: =+G47+E48-F48 -> -196717.35 | H48: 157.565 | I48: COMBUSTIBLE | K48: NSN 325 | L48: COMBUSTIBLE | M48: 0
A49: 45992 | B49: FA | C49: 55-7000 | D49: KJR 926 | F49: 45000.15 | G49: =+G48+E49-F49 -> -241717.5 | H49: 24.55 | I49: COMBUSTIBLE | K49: LVX 455 | L49: COMBUSTIBLE | M49: =SUM(H56+H74+H84) -> 106.229
A50: 45993 | B50: FA | C50: 92-0622 | D50: LVX 455 | F50: 26200 | G50: =+G49+E50-F50 -> -267917.5 | H50: * | I50: 2 HIELO | K50: AG 958 JV | L50: COMBUSTIBLE | M50: =SUM(H48+H81) -> 340.41
A51: 45993 | B51: FA | C51: 55-7023 | D51: HLW 156 | F51: 58100.49 | G51: =+G50+E51-F51 -> -326017.99 | H51: 24.577 | I51: COMBUSTIBLE+HIELO | K51: AG 768 OI | L51: COMBUSTIBLE | M51: =SUM(H52+H54+H72+H82) -> 1217.501
A52: 45993 | B52: FA | C52: 63-0556 | D52: AG 768 OI | F52: 342355.58 | G52: =+G51+E52-F52 -> -668373.57 | H52: 185.272 | I52: COMBUSTIBLE | K52: KJR 926 | L52: COMBUSTIBLE | M52: =SUM(H49+H58+H65+H86+H89) -> 123.236
A53: 45993 | B53: RE | C53: 50-0016 | D53: TRANSF | E53: 1500000 | G53: =+G52+E53-F53 -> 831626.43 | I53: PAGO - SALDO A FAVOR | K53: IHX 980 | L53: COMBUSTIBLE | M53: 0
A54: 45993 | B54: FA | C54: 63-0571 | D54: AG 768 OI | F54: 646685.28 | G54: =+G53+E54-F54 -> 184941.15 | H54: 351.672 | I54: COMBUSTIBLE | K54: HLW 156 | L54: COMBUSTIBLE | M54: =SUM(H51) -> 24.577
A55: 45993 | B55: FA | C55: 63-0572 | D55: HKQ 258 | F55: 547935.91 | G55: =+G54+E55-F55 -> -362994.76 | H55: 299.255 | I55: COMBUSTIBLE | K55: WNO 918 | L55: COMBUSTIBLE | M55: =SUM(H44+H80) -> 287.577
A56: 45994 | B56: FA | C56: 55-7079 | D56: LVX 455 | F56: 44999.11 | G56: =+G55+E56-F56 -> -407993.87 | H56: 24.337 | I56: COMBUSTIBLE | K56: HKQ 258 | L56: COMBUSTIBLE | M56: =SUM(H45+H55+H66+H79+H90) -> 1329.765
A57: 45994 | B57: FA | C57: 55-7080 | D57: LVX 455 | F57: 12200 | G57: =+G56+E57-F57 -> -420193.87 | H57: * | I57: HIELO | K57: FTL 303 | L57: COMBUSTIBLE | M57: 0
A58: 45994 | B58: FA | C58: 92-0690 | D58: KJR 926 | F58: 69399.11 | G58: =+G57+E58-F58 -> -489592.98 | H58: 24.337 | I58: COMBUSTIBLE + 4 HIELO | K58: AUTOELEVADOR-1 | L58: COMBUSTIBLE | M58: =SUM(H60) -> 40.634
A59: 45994 | B59: FA | C59: 92-0692 | D59: HLW 156 | F59: 24400 | G59: =+G58+E59-F59 -> -513992.98 | H59: * | I59: 4 HIELO | K59: HIELO | L59: HIELO 3 Y 12 KG | M59: 49 BOLSAS
A60: 45994 | B60: FA | C60: 55-7096 | D60: MULITA | F60: 118974.92 | G60: =+G59+E60-F60 -> -632967.9 | H60: 40.634 | I60: COMBUSTIBLE + 8 HIELOS | K60: LITROS SEMANAL | M60: =SUM(M40:M58) -> 3862.497
A61: 45994 | B61: FA | C61: 92-0708 | D61: AG 337 MY | F61: 21649.47 | G61: =+G60+E61-F61 -> -654617.37 | H61: 11.627 | I61: COMBUSTIBLE
A62: 45994 | B62: FA | C62: 60-8065 | D62: PFG 964 | F62: 69399.11 | G62: =+G61+E62-F62 -> -724016.48 | H62: 24.337 | I62: COMBUSTIBLE + 4 HIELOS
A63: 45994 | B63: FA | C63: 55-7114 | D63: LVX 455 | F63: 12200 | G63: =+G62+E63-F63 -> -736216.48 | H63: * | I63: 2 HIELO
A64: 45995 | B64: FA | C64: 55-7156 | D64: LVX 455 | F64: 18300 | G64: =+G63+E64-F64 -> -754516.48 | H64: * | I64: 3 HIELO
A65: 45995 | B65: FA | C65: 55-7157 | D65: KJR 926 | F65: 69399.94 | G65: =+G64+E65-F65 -> -823916.42 | H65: 24.377 | I65: COMBUSTIBLE + 4 HIELOS
A66: 45995 | B66: FA | C66: 63-0604 | D66: HKQ 258 | F66: 315152.81 | G66: =+G65+E66-F66 -> -1139069.2 | H66: 170.722 | I66: COMBUSTIBLE
A67: 45995 | B67: FA | C67: 92-0782 | D67: KEX 251 | F67: 44999.94 | G67: =+G66+E67-F67 -> -1184069.2 | H67: 24.377 | I67: COMBUSTIBLE
A68: 45995 | B68: FA | C68: 92-0794 | D68: HLW 156 | F68: 24400 | G68: =+G67+E68-F68 -> -1208469.2 | H68: * | I68: 4 HIELO
A69: 45995 | B69: RE | C69: 50-0020 | D69: TRANSF | E69: 2500000 | G69: =+G68+E69-F69 -> 1291530.8 | I69: PAGO - SALDO A FAVOR
A70: 45995 | B70: FA | C70: 92-0801 | D70: AA 183 PK | F70: 44999.94 | G70: =+G69+E70-F70 -> 1246530.9 | H70: 24.377 | I70: COMBUSTIBLE
A71: 45995 | B71: FA | C71: 55-7206 | D71: PFG 964 | F71: 44999.94 | G71: =+G70+E71-F71 -> 1201530.9 | H71: 24.377 | I71: COMBUSTIBLE
A72: 45995 | B72: FA | C72: 92-0803 | D72: AG 768 OI | F72: 416300.69 | G72: =+G71+E72-F72 -> 785230.26 | H72: 225.515 | I72: COMBUSTIBLE
A73: 45996 | B73: FA | C73: 92-0824 | D73: KEX 251 | F73: 24400 | G73: =+G72+E73-F73 -> 760830.26 | H73: * | I73: 4 HIELO
A74: 45996 | B74: FA | C74: 55-7222 | D74: LVX 455 | F74: 63299.94 | G74: =+G73+E74-F74 -> 697530.32 | H74: 24.377 | I74: COMBUSTIBLE + 3 HIELOS
A75: 45996 | B75: FA | C75: 92-0825 | D75: LVX 455 | F75: 6100 | G75: =+G74+E75-F75 -> 691430.32 | H75: * | I75: HIELO
A76: 45996 | B76: FA | C76: 55-7225 | D76: AF 728 AT | F76: 63050.13 | G76: =+G75+E76-F76 -> 628380.19 | H76: 34.155 | I76: COMBUSTIBLE
A77: 45996 | B77: FA | C77: 92-0833 | D77: PFG 964 | F77: 12200 | G77: =+G76+E77-F77 -> 616180.19 | H77: * | I77: 2 HIELO
A78: 45996 | B78: RE | C78: 50-0021 | D78: TRANSF | E78: 2000000 | G78: =+G77+E78-F78 -> 2616180.2 | I78: PAGO - SALDO A FAVOR
A79: 45996 | B79: FA | C79: 63-0637 | D79: HKQ 258 | F79: 555649.69 | G79: =+G78+E79-F79 -> 2060530.5 | H79: 301.002 | I79: COMBUSTIBLE
A80: 45996 | B80: FA | C80: 60-8185 | D80: WNO 918 | F80: 279738.64 | G80: =+G79+E80-F80 -> 1780791.9 | H80: 159.577 | I80: COMBUSTIBLE
A81: 45996 | B81: FA | C81: 63-0640 | D81: AG 958 JV | F81: 337531.87 | G81: =+G80+E81-F81 -> 1443260 | H81: 182.845 | I81: COMBUSTIBLE
A82: 45996 | B82: FA | C82: 63-0644 | D82: AG 768 OI | F82: 840007.53 | G82: =+G81+E82-F82 -> 603252.46 | H82: 455.042 | I82: COMBUSTIBLE
A83: 45997 | B83: FA | C83: 92-0894 | D83: PFG 964 | F83: 115500.81 | G83: =+G82+E83-F83 -> 487751.65 | H83: 62.67 | I83: COMBUSTIBLE
A84: 45997 | B84: FA | C84: 55-7280 | D84: LVX 455 | F84: 106000.15 | G84: =+G83+E84-F84 -> 381751.5 | H84: 57.515 | I84: COMBUSTIBLE
A85: 45997 | B85: FA | C85: 60-8213 | D85: AF 728 AT | F85: 112072.83 | G85: =+G84+E85-F85 -> 269678.67 | H85: 60.81 | I85: COMBUSTIBLE
A86: 45997 | B86: FA | C86: 55-7289 | D86: KJR 926 | F86: 45000.53 | G86: =+G85+E86-F86 -> 224678.14 | H86: 24.417 | I86: COMBUSTIBLE
A87: 45998 | B87: FA | C87: 92-0937 | D87: KEX 251 | F87: 45000.53 | G87: =+G86+E87-F87 -> 179677.61 | H87: 24.417 | I87: COMBUSTIBLE
A88: 45998 | B88: FA | C88: 60-8246 | D88: AA 183 PK | F88: 45000.53 | G88: =+G87+E88-F88 -> 134677.08 | H88: 24.417 | I88: COMBUSTIBLE
A89: 45998 | B89: FA | C89: 55-7333 | D89: KJR 926 | F89: 47097.87 | G89: =+G88+E89-F89 -> 87579.21 | H89: 25.555 | I89: COMBUSTIBLE
A90: 45998 | B90: FA | C90: 63-0655 | D90: HKQ 258 | F90: 618160.63 | G90: =+G89+E90-F90 -> -530581.42 | H90: 335.41 | I90: COMBUSTIBLE
A91: TOTAL DE LITROS SEMANAL | H91: =SUM(H24:H90) -> 3862.497
A92: SEMANA DEL 1/12 AL 7/12 | K92: SEMANA DEL 8/12 AL 14/12
A93: 45999 | B93: FA | C93: 63-0657 | D93: AG 768 OI | F93: 860032.89 | G93: =+G90+E93-F93 -> -1390614.3 | H93: 462.632 | I93: COMBUSTIBLE | K93: RESUMEN CONSUMO
A94: 45999 | B94: FA | C94: 92-0977 | D94: KJR 926 | F94: 58100.81 | G94: =+G93+E94-F94 -> -1448715.1 | H94: 24.207 | I94: COMBUSTIBLE + HIELO | K94: RESUMEN | L94: CONSUMO | M94: LTS
A95: 45999 | B95: FA | C95: 92-0978 | D95: KEX 251 | F95: 137393.91 | G95: =+G94+E95-F95 -> -1586109 | H95: 74.495 | I95: COMBUSTIBLE | K95: AG 378 AV | L95: COMBUSTIBLE | M95: 0
A96: 45999 | B96: RE | C96: 50-0023 | D96: TRANSF | E96: 1000000 | G96: =+G95+E96-F96 -> -586109.03 | I96: PAGO - SALDO PENDIENTE | K96: AG 337 MY | L96: COMBUSTIBLE | M96: 0
A97: 45999 | B97: RE | C97: 50-0024 | D97: TRANSF | E97: 586109 | G97: =+G96+E97-F97 -> -0.03 | I97: PAGO - SALDO PENDIENTE | K97: AG 962 EW | L97: COMBUSTIBLE | M97: 0
A98: 46000 | B98: FA | C98: 55-7407 | D98: KJR 926 | F98: 58100.81 | G98: =+G97+E98-F98 -> -58100.84 | H98: 24.207 | I98: COMBUSTIBLE + HIELO | K98: AA 183 PK | L98: COMBUSTIBLE | M98: =SUM(H102+H106+H123) -> 68.351
A99: 46000 | B99: FA | C99: 55-7418 | D99: HLW 156 | F99: 58100.81 | G99: =+G98+E99-F99 -> -116201.65 | H99: 24.207 | I99: COMBUSTIBLE + HIELO | K99: KEX 251 | L99: COMBUSTIBLE | M99: =SUM(H95+H103+H120+H125) -> 197.151
A100: 46000 | B100: FA | C100: 60-8327 | D100: HKQ 258 | F100: 421909.35 | G100: =+G99+E100-F100 -> -538111 | H100: 226.955 | I100: COMBUSTIBLE | K100: OHA 122 | L100: COMBUSTIBLE | M100: 0
A101: 46000 | B101: RE | C101: 50-0027 | D101: TRANSF | E101: 3000000 | G101: =+G100+E101-F101 -> 2461889 | I101: PAGO - SALDO A FAVOR | K101: AF 728 AT | L101: COMBUSTIBLE | M101: 0
A102: 46000 | B102: FA | C102: 60-8338 | D102: AA 183 PK | F102: 51100.81 | G102: =+G101+E102-F102 -> 2410788.2 | H102: 24.207 | I102: COMBUSTIBLE + HIELO | K102: PFG 964 | L102: COMBUSTIBLE | M102: 0
A103: 46000 | B103: FA | C103: 60-8359 | D103: KEX 251 | F103: 104689.59 | G103: =+G102+E103-F103 -> 2306098.6 | H103: 56.315 | I103: COMBUSTIBLE | K103: NSN 325 | L103: COMBUSTIBLE | M103: 0
A104: 46000 | B104: FA | C104: 60-8360 | D104: AG 768 OI | F104: 795010.65 | G104: =+G103+E104-F104 -> 1511088 | H104: 427.655 | I104: COMBUSTIBLE | K104: LVX 455 | L104: COMBUSTIBLE | M104: =SUM(H124) -> 24.142
A105: 46001 | B105: FA | C105: 63-0691 | D105: AG 958 JV | F105: 243684.83 | G105: =+G104+E105-F105 -> 1267403.1 | H105: 131.225 | I105: COMBUSTIBLE | K105: AG 958 JV | L105: COMBUSTIBLE | M105: =SUM(H105+H111+H117) -> 358.517
A106: 46001 | B106: FA | C106: 92-1089 | D106: AA 183 PK | F106: 34983.5 | G106: =+G105+E106-F106 -> 1232419.6 | H106: 20.002 | I106: COMBUSTIBLE | K106: AG 768 OI | L106: COMBUSTIBLE | M106: =SUM(H93+H104+H114+H115+H126) -> 1980.11
A107: 46001 | B107: FA | C107: 55-7464 | D107: MULITA | F107: 49802.77 | G107: =+G106+E107-F107 -> 1182616.9 | H107: 20.985 | I107: COMBUSTIBLE + HIELO | K107: KJR 926 | L107: COMBUSTIBLE | M107: =SUM(H94+H98+H110) -> 72.53
A108: 46001 | B108: FA | C108: 92-1113 | D108: MULITA | F108: 38295.05 | G108: =+G107+E108-F108 -> 1144321.8 | H108: 20.622 | I108: COMBUSTIBLE | K108: IHX 980 | L108: COMBUSTIBLE | M108: 0
A109: 46001 | B109: FA | C109: 92-1138 | D109: HLW 156 | F109: 45000.68 | G109: =+G108+E109-F109 -> 1099321.1 | H109: 24.233 | I109: COMBUSTIBLE | K109: HLW 156 | L109: COMBUSTIBLE | M109: =SUM(H99+H109) -> 48.44
A110: 46002 | B110: FA | C110: 55-7515 | D110: KJR 926 | F110: 58100.46 | G110: =+G109+E110-F110 -> 1041220.7 | H110: 24.116 | I110: COMBUSTIBLE + HIELO | K110: WNO 918 | L110: COMBUSTIBLE | M110: =SUM(H121) -> 162.835
A111: 46002 | B111: FA | C111: 63-0709 | D111: AG 958 JV | F111: 184286.16 | G111: =+G110+E111-F111 -> 856934.5 | H111: 98.76 | I111: COMBUSTIBLE | K111: HKQ 258 | L111: COMBUSTIBLE | M111: =SUM(H100+H116+H122) -> 970.635
A112: 46002 | B112: FA | C112: 92-1161 | D112: OXJ 846 | F112: 66139.54 | G112: =+G111+E112-F112 -> 790794.96 | H112: 39.652 | I112: COMBUSTIBLE | K112: FTL 303 | L112: COMBUSTIBLE | M112: 0
A113: 46002 | B113: FA | C113: 55-7519 | D113: HLW 156 | F113: 26200 | G113: =+G112+E113-F113 -> 764594.96 | H113: * | I113: 2 HIELO | K113: AUTOELEVADOR-1 | L113: COMBUSTIBLE | M113: =SUM(H107+H108) -> 41.607
A114: 46002 | B114: FA | C114: 63-0715 | D114: AG 768 OI | F114: 475106.93 | G114: =+G113+E114-F114 -> 289488.03 | H114: 252.202 | I114: COMBUSTIBLE | K114: OXJ 846 | L114: ENJOY | M114: =SUM(H112) -> 39.652
A115: 46003 | B115: FA | C115: 92-1206 | D115: AG 768 OI | F115: 674033.46 | G115: =+G114+E115-F115 -> -384545.43 | H115: 359.927 | I115: COMBUSTIBLE | K115: HIELO | L115: HIELO 3 Y 12 KG | M115: 11 BOLSAS
A116: 46003 | B116: FA | C116: 92-1208 | D116: HKQ 258 | F116: 730371.12 | G116: =+G115+E116-F116 -> -1114916.5 | H116: 391.83 | I116: COMBUSTIBLE | K116: LITROS SEMANAL | M116: =SUM(M95:M114) -> 3963.97
A117: 46003 | B117: FA | C117: 92-1213 | D117: AG 958 JV | F117: 243625.52 | G117: =+G116+E117-F117 -> -1358542.1 | H117: 128.532 | I117: COMBUSTIBLE
A118: 46003 | B118: FA | C118: 55-7581 | D118: KJR 926 | F118: 26200 | G118: =+G117+E118-F118 -> -1384742.1 | H118: * | I118: 2 HIELO
A119: 46003 | B119: RE | C119: 50-0031 | D119: TRANSF | E119: 2500000 | G119: =+G118+E119-F119 -> 1115257.9 | I119: PAGO - SALDO A FAVOR
A120: 46004 | B120: FA | C120: 92-1288 | D120: KEX 251 | F120: 45000.69 | G120: =+G119+E120-F120 -> 1070257.2 | H120: 24.142 | I120: COMBUSTIBLE
A121: 46004 | B121: FA | C121: 60-8528 | D121: WNO 918 | F121: 285449.76 | G121: =+G120+E121-F121 -> 784807.48 | H121: 162.835 | I121: COMBUSTIBLE
A122: 46004 | B122: FA | C122: 60-8546 | D122: HKQ 258 | F122: 661948.4 | G122: =+G121+E122-F122 -> 122859.08 | H122: 351.85 | I122: COMBUSTIBLE + HIELO
...

Sheet ENERO.2026
A5: CTA.CTE ENERO - 2026 - CARGAS+HIELO | K5: SEMANA DEL 1/1 AL 4/1
A6: CARGAS COMBUSTIBLE YPF | K6: RESUMEN CONSUMO
A7: FECHA | B7: FACTURA | C7: N° FA/COMP | D7: VEHICULO | E7: PAGOS | F7: CONSUMOS | G7: SALDO | H7: LITROS | I7: OBSEVACIONES | K7: RESUMEN | L7: CONSUMO | M7: LTS
D8: SALDO ANTERIOR | G8: =SUM(E8:F8) -> 0
G9: =+G8+E9-F9 -> 0
G10: =+G9+E10-F10 -> 0
G11: =+G10+E11-F11 -> 0
G12: =+G11+E12-F12 -> 0
G13: =+G12+E13-F13 -> 0
G14: =+G13+E14-F14 -> 0
G15: =+G14+E15-F15 -> 0
G16: =+G15+E16-F16 -> 0
G17: =+G16+E17-F17 -> 0
G18: =+G17+E18-F18 -> 0
G19: =+G18+E19-F19 -> 0
G20: =+G19+E20-F20 -> 0
... G39: =+G38+E39-F39 -> 0
C40: SALDO ANTERIOR | F40: 329222.61 | G40: =SUM(G39+E40-F40) -> -329222.61 | K40: AG 378 AV | L40: COMBUSTIBLE | M40: 0
A41: 46024 | B41: FA | C41: 92-2374 | D41: HLW 156 | F41: 37500 | G41: =+G40-F41+E41 -> -366722.61 | H41: * | I41: 5 HIELOS | K41: AG 337 MY | L41: COMBUSTIBLE | M41: 0
A42: 46024 | B42: FA | C42: 92-2375 | D42: AF 728 AT | F42: 24400 | G42: =+G41-F42+E42 -> -391122.61 | H42: * | I42: 5 HIELOS | K42: AG 962 EW | L42: COMBUSTIBLE | M42: 0
A43: 46024 | B43: FA | C43: 60-9527 | D43: MULITA | F43: 95719.32 | G43: =+G42-F43+E43 -> -486841.93 | H43: 51.462 | I43: COMBUSTIBLE | K43: AA 183 PK | L43: COMBUSTIBLE | M43: =SUM(H58) -> 24.142
A44: 46024 | B44: FA | C44: 98-0109 | D44: KJR 926 | F44: 69400.84 | G44: =+G43-F44+E44 -> -556242.77 | H44: 24.194 | I44: COMBUSTIBLE Y 4 HIELOS | K44: KEX 251 | L44: COMBUSTIBLE | M44: =SUM(H52+H60) -> 43.416
A45: 46024 | B45: FA | C45: 55-8742 | D45: LVX 455 | F45: 88465.73 | G45: =+G44-F45+E45 -> -644708.5 | H45: 35.051 | I45: COMBUSTIBLE Y 4 HIELOS | K45: AF 728 AT | L45: COMBUSTIBLE | M45: =SUM(H59) -> 77.955
A46: 46024 | B46: FA | C46: 98-0110 | D46: AG 958 JV | F46: 333935.1 | G46: =+G45-F46+E46 -> -978643.6 | H46: 179.535 | I46: COMBUSTIBLE | K46: PFG 964 | L46: COMBUSTIBLE | M46: =SUM(H54) -> 24.103
A47: 46024 | B47: RE | C47: 50-0063 | D47: TRANSF | E47: 1000000 | G47: =+G46-F47+E47 -> 21356.4 | I47: PAGO - SALDO A FAVOR | K47: LVX 455 | L47: COMBUSTIBLE | M47: =SUM(H45) -> 35.051
A48: 46024 | B48: FA | C48: 98-0124 | D48: AG 768 OI | F48: 517846.32 | G48: =+G47-F48+E48 -> -496489.92 | H48: 278.412 | I48: COMBUSTIBLE | K48: AG 958 JV | L48: COMBUSTIBLE | M48: =SUM(H46+H50) -> 214.692
A49: 46025 | B49: FA | C49: 98-0127 | D49: MULITA | F49: 66039.52 | G49: =+G48-F49+E49 -> -562529.44 | H49: 35.372 | I49: COMBUSTIBLE | K49: AG 768 OI | L49: COMBUSTIBLE | M49: =SUM(H48) -> 278.412
A50: 46025 | B50: FA | C50: 98-0128 | D50: AG 958 JV | F50: 65638.12 | G50: =+G49-F50+E50 -> -628167.56 | H50: 35.157 | I50: COMBUSTIBLE | K50: KJR 926 | L50: COMBUSTIBLE | M50: =SUM(H44+H57) -> 43.514
A51: 46025 | B51: FA | C51: 60-9578 | D51: MULITA | F51: 74035.32 | G51: =+G50-F51+E51 -> -702202.88 | H51: 21.355 | I51: COMBUSTIBLE Y 6 HIELOS | K51: HLW 156 | L51: COMBUSTIBLE | M51: 0
A52: 46025 | B52: FA | C52: 92-2446 | D52: KEX 251 | F52: 45000.3 | G52: =+G51-F52+E52 -> -747203.18 | H52: 24.103 | I52: COMBUSTIBLE | K52: WNO 918 | L52: COMBUSTIBLE | M52: =SUM(H55) -> 114.09
A53: 46025 | B53: FA | C53: 92-2447 | D53: KEX 251 | F53: 6100 | G53: =+G52-F53+E53 -> -753303.18 | H53: * | I53: HIELO | K53: HKQ 258 | L53: COMBUSTIBLE | M53: 0
A54: 46025 | B54: FA | C54: 55-8784 | D54: PFG 964 | F54: 45000.3 | G54: =+G53-F54+E54 -> -798303.48 | H54: 24.103 | I54: COMBUSTIBLE | K54: FTL 303 | L54: COMBUSTIBLE | M54: 0
A55: 46025 | B55: FA | C55: 98-0135 | D55: WNO 918 | F55: 199999.77 | G55: =+G54-F55+E55 -> -998303.25 | H55: 114.09 | I55: COMBUSTIBLE | K55: AUTOELEVADOR | L55: COMBUSTIBLE | M55: =SUM(H43+H49+H51) -> 108.189
A56: 46026 | B56: FA | C56: 55-8814 | D56: KEX 251 | F56: 13100 | G56: =+G55-F56+E56 -> -1011403.2 | H56: * | I56: HIELO | K56: HIELO | L56: HIELO 3 Y 12 KG | M56: 27 BOLSAS
A57: 46026 | B57: FA | C57: 92-2479 | D57: KJR 926 | F57: 62212.48 | G57: =+G56-F57+E57 -> -1073615.7 | H57: 19.32 | I57: COMBUSTIBLE Y 2 HIELOS | K57: LITROS SEMANAL | M57: =SUM(M43:M55) -> 963.564
A58: 46026 | B58: FA | C58: 55-8847 | D58: AA 183 PK | F58: 45000.69 | G58: =+G57-F58+E58 -> -1118616.4 | H58: 24.142 | I58: COMBUSTIBLE
A59: 46026 | B59: FA | C59: 55-8851 | D59: AF 728 AT | F59: 145308.12 | G59: =+G58-F59+E59 -> -1263924.5 | H59: 77.955 | I59: COMBUSTIBLE
A60: 46026 | B60: FA | C60: 55-8856 | D60: KEX 251 | F60: 35999.43 | G60: =+G59-F60+E60 -> -1299924 | H60: 19.313 | I60: COMBUSTIBLE
A61: TOTAL DE LITROS SEMANAL | H61: =SUM(H41:H60) -> 963.564
A62: SEMANA DEL 1/1 AL 4/1 | K62: SEMANA DEL 5/1 AL 11/1
A63: 46027 | B63: RE | C63: 50-0064 | D63: TRANSF | E63: 1300000 | G63: =+G60-F63+E63 -> 76.03 | I63: PAGO - SALDO A FAVOR | K63: RESUMEN CONSUMO
A64: 46027 | B64: FA | C64: 55-8881 | D64: KEX 251 | F64: 75762.28 | G64: =+G63-F64+E64 -> -75686.25 | H64: 40.645 | I64: COMBUSTIBLE | K64: RESUMEN | L64: CONSUMO | M64: LTS
A65: 46027 | B65: FA | C65: 55-8882 | D65: KEX 251 | F65: 13100 | G65: =+G64-F65+E65 -> -88786.25 | H65: * | I65: HIELO | K65: AG 378 AV | L65: COMBUSTIBLE | M65: 0
A66: 46027 | B66: RE | C66: 50-0067 | D66: TRANSF | E66: 1900000 | G66: =+G65-F66+E66 -> 1811213.8 | I66: PAGO - SALDO A FAVOR | K66: AG 337 MY | L66: COMBUSTIBLE | M66: =SUM(H69) -> 69.365
A67: 46027 | B67: FA | C67: 60-9677 | D67: HLW 156 | F67: 45000.69 | G67: =+G66-F67+E67 -> 1766213.1 | H67: 24.142 | I67: COMBUSTIBLE | K67: AG 962 EW | L67: COMBUSTIBLE | M67: 0
A68: 46027 | B68: FA | C68: 55-8914 | D68: AA 183 PK | F68: 45000.69 | G68: =+G67-F68+E68 -> 1721212.4 | H68: 24.142 | I68: COMBUSTIBLE | K68: AA 183 PK | L68: COMBUSTIBLE | M68: =SUM(H68+H71+H76+H78) -> 96.399
A69: 46027 | B69: FA | C69: 55-8918 | D69: AG 337 MY | F69: 129296.36 | G69: =+G68-F69+E69 -> 1591916 | H69: 69.365 | I69: COMBUSTIBLE | K69: KEX 251 | L69: COMBUSTIBLE | M69: =SUM(H64+H70+H77+H83+H87) -> 135.798
A70: 46028 | B70: FA | C70: 60-9729 | D70: KEX 251 | F70: 44999.42 | G70: =+G69-F70+E70 -> 1546916.6 | H70: 24.051 | I70: COMBUSTIBLE | K70: AF 728 AT | L70: COMBUSTIBLE | M70: 0
A71: 46028 | B71: FA | C71: 60-9741 | D71: AA 183 PK | F71: 44999.42 | G71: =+G70-F71+E71 -> 1501917.2 | H71: 24.051 | I71: COMBUSTIBLE | K71: PFG 964 | L71: COMBUSTIBLE | M71: =SUM(H81+H86) -> 48.258
A72: 46029 | B72: FA | C72: 92-2593 | D72: LVX 455 | F72: 45000.12 | G72: =+G71-F72+E72 -> 1456917.1 | H72: 24.09 | I72: COMBUSTIBLE | K72: NSN 325 | L72: COMBUSTIBLE | M72: 0
A73: 46030 | B73: FA | C73: 55-9049 | D73: KJR 926 | F73: 45000.12 | G73: =+G72-F73+E73 -> 1411916.9 | H73: 24.09 | I73: COMBUSTIBLE | K73: LVX 455 | L73: COMBUSTIBLE | M73: =SUM(H72+H79) -> 48.206
A74: 46030 | B74: FA | C74: 55-9050 | D74: MULITA | F74: 60011 | G74: =+G73-F74+E74 -> 1351905.9 | H74: 34.292 | I74: COMBUSTIBLE | K74: AG 958 JV | L74: COMBUSTIBLE | M74: =SUM(H82) -> 182.82
A75: 46030 | B75: FA | C75: 98-0262 | D75: WNO 918 | F75: 247038.75 | G75: =+G74-F75+E75 -> 1104867.2 | H75: 141.165 | I75: COMBUSTIBLE | K75: AG 768 OI | L75: COMBUSTIBLE | M75: 0
A76: 46030 | B76: FA | C76: 55-9081 | D76: AA 183 PK | F76: 45000.12 | G76: =+G75-F76+E76 -> 1059867.1 | H76: 24.09 | I76: COMBUSTIBLE | K76: KJR 926 | L76: COMBUSTIBLE | M76: =SUM(H73+H84+H85) -> 72.348
A77: 46030 | B77: FA | C77: 55-9086 | D77: KEX 251 | F77: 45000.12 | G77: =+G76-F77+E77 -> 1014866.9 | H77: 24.09 | I77: COMBUSTIBLE | K77: HLW 156 | L77: COMBUSTIBLE | M77: =SUM(H67) -> 24.142
A78: 46031 | B78: FA | C78: 55-9102 | D78: AA 183 PK | F78: 45000.46 | G78: =+G77-F78+E78 -> 969866.48 | H78: 24.116 | I78: COMBUSTIBLE | K78: WNO 918 | L78: COMBUSTIBLE | M78: =SUM(H75) -> 141.165
A79: 46031 | B79: FA | C79: 60-9838 | D79: LVX 455 | F79: 45000.46 | G79: =+G78-F79+E79 -> 924866.02 | H79: 24.116 | I79: COMBUSTIBLE | K79: HKQ 258 | L79: COMBUSTIBLE | M79: 0
A80: 46031 | B80: RE | C80: 50-0074 | D80: TRANSF | E80: 1000000 | G80: =+G79-F80+E80 -> 1924866 | I80: PAGO - SALDO A FAVOR | K80: FTL 303 | L80: COMBUSTIBLE | M80: 0
A81: 46031 | B81: FA | C81: 55-9137 | D81: PFG 964 | F81: 45000.46 | G81: =+G80-F81+E81 -> 1879865.6 | H81: 24.116 | I81: COMBUSTIBLE | K81: AUTOELEVADOR | L81: COMBUSTIBLE | M81: =SUM(H74) -> 34.292
A82: 46032 | B82: FA | C82: 92-2740 | D82: AG 958 JV | F82: 341142.12 | G82: =+G81-F82+E82 -> 1538723.4 | H82: 182.82 | I82: COMBUSTIBLE | K82: HIELO | L82: HIELO 3 Y 12 KG | M82: 1 BOLSA
A83: 46032 | B83: FA | C83: 55-9144 | D83: KEX 251 | F83: 45000.46 | G83: =+G82-F83+E83 -> 1493723 | H83: 24.116 | I83: COMBUSTIBLE | K83: LITROS SEMANAL | M83: =SUM(M65:M81) -> 852.793
A84: 46032 | B84: FA | C84: 55-9166 | D84: KJR 926 | F84: 45000.46 | G84: =+G83-F84+E84 -> 1448722.5 | H84: 24.116 | I84: COMBUSTIBLE
A85: 46033 | B85: FA | C85: 92-2777 | D85: KJR 926 | F85: 45000.69 | G85: =+G84-F85+E85 -> 1403721.8 | H85: 24.142 | I85: COMBUSTIBLE
A86: 46033 | B86: FA | C86: 55-9213 | D86: PFG 964 | F86: 45000.69 | G86: =+G85-F86+E86 -> 1358721.1 | H86: 24.142 | I86: COMBUSTIBLE
A87: 46033 | B87: FA | C87: 55-9223 | D87: KEX 251 | F87: 39999.31 | G87: =+G86-F87+E87 -> 1318721.8 | H87: 22.896 | I87: COMBUSTIBLE
A88: TOTAL DE LITROS SEMANAL | H88: =SUM(H64:H87) -> 852.793
A89: SEMANA DEL 5/1 AL 11/1 | K89: SEMANA DEL 12/1 AL 18/1
A90: 46034 | B90: FA | C90: 55-9236 | D90: KEX 251 | F90: 39300 | G90: =+G87-F90+E90 -> 1279421.8 | H90: 3 | I90: HIELOS | K90: RESUMEN CONSUMO
A91: 46034 | B91: FA | C91: 60-9923 | D91: AA 183 PK | F91: 45000.69 | G91: =+G90-F91+E91 -> 1234421.1 | H91: 24.142 | I91: COMBUSTIBLE | K91: RESUMEN | L91: CONSUMO | M91: LTS
A92: 46034 | B92: FA | C92: 55-9266 | D92: MULITA | F92: 92737.21 | G92: =+G91-F92+E92 -> 1141683.9 | H92: 52.902 | I92: COMBUSTIBLE | K92: AG 378 AV | L92: COMBUSTIBLE | M92: 0
A93: 46035 | B93: FA | C93: 92-2855 | D93: KJR 926 | F93: 45000.69 | G93: =+G92-F93+E93 -> 1096683.2 | H93: 24.142 | I93: COMBUSTIBLE | K93: AG 337 MY | L93: COMBUSTIBLE | M93: 0
A94: 46035 | B94: FA | C94: 55-9281 | D94: KEX 251 | F94: 45000.69 | G94: =+G93-F94+E94 -> 1051682.6 | H94: 24.142 | I94: COMBUSTIBLE | K94: AG 962 EW | L94: COMBUSTIBLE | M94: 0
A95: 46035 | B95: FA | C95: 55-9289 | D95: PFG 964 | F95: 39300 | G95: =+G94-F95+E95 -> 1012382.6 | H95: 3 | I95: HIELOS | K95: AA 183 PK | L95: COMBUSTIBLE | M95: =SUM(H91+H96+H100+H110) -> 96.477
A96: 46035 | B96: FA | C96: 60-9977 | D96: AA 183 PK | F96: 45000.12 | G96: =+G95-F96+E96 -> 967382.43 | H96: 24.09 | I96: COMBUSTIBLE | K96: KEX 251 | L96: COMBUSTIBLE | M96: =SUM(H94+H98+H109) -> 72.3868
A97: 46036 | B97: FA | C97: 55-9351 | D97: PFG 964 | F97: 84300.12 | G97: =+G96-F97+E97 -> 883082.31 | H97: 24.09 | I97: COMBUSTIBLE Y 3 HIELOS | K97: AF 728 AT | L97: COMBUSTIBLE | M97: 0
A98: 46036 | B98: FA | C98: 92-2923 | D98: KEX 251 | F98: 58100.12 | G98: =+G97-F98+E98 -> 824982.19 | H98: 24.09 | I98: COMBUSTIBLE Y HIELO | K98: PFG 964 | L98: COMBUSTIBLE | M98: =SUM(H97) -> 24.09
A99: 46036 | B99: FA | C99: 98-0432 | D99: MULITA | F99: 89393.14 | G99: =+G98-F99+E99 -> 735589.05 | H99: 47.855 | I99: COMBUSTIBLE | K99: LVX 455 | L99: COMBUSTIBLE | M99: =SUM(H103+H104) -> 48.232
A100: 46036 | B100: FA | C100: 92-2947 | D100: AA 183 PK | F100: 45000.12 | G100: =+G99-F100+E100 -> 690588.93 | H100: 24.09 | I100: COMBUSTIBLE | K100: AG 958 JV | L100: COMBUSTIBLE | M100: 0
A101: 46036 | B101: FA | C101: 92-2961 | D101: KJR 926 | F101: 45000.12 | G101: =+G100-F101+E101 -> 645588.81 | H101: 24.09 | I101: COMBUSTIBLE | K101: AG 768 OI | L101: COMBUSTIBLE | M101: 0
A102: 46037 | B102: FA | C102: 55-9418 | D102: KJR 926 | F102: 12200 | G102: =+G101-F102+E102 -> 633388.81 | H102: 2 | I102: HIELOS | K102: KJR 926 | L102: COMBUSTIBLE | M102: =SUM(H93+H101+H105) -> 72.348
A103: 46037 | B103: FA | C103: 55-9420 | D103: LVX 455 | F103: 57200.46 | G103: =+G102-F103+E103 -> 576188.35 | H103: 24.116 | I103: COMBUSTIBLE Y 2 HIELOS | K103: HLW 156 | L103: COMBUSTIBLE | M103: 0
A104: 46038 | B104: FA | C104: 92-3022 | D104: LVX 455 | F104: 45000.46 | G104: =+G103-F104+E104 -> 531187.89 | H104: 24.116 | I104: COMBUSTIBLE | K104: WNO 918 | L104: COMBUSTIBLE | M104: 0
A105: 46038 | B105: FA | C105: 55-9481 | D105: KJR 926 | F105: 45000.46 | G105: =+G104-F105+E105 -> 486187.43 | H105: 24.116 | I105: COMBUSTIBLE | K105: HKQ 258 | L105: COMBUSTIBLE | M105: 0
A106: 46038 | B106: FA | C106: 55-9482 | D106: MULITA | F106: 35080 | G106: =+G105-F106+E106 -> 451107.43 | H106: 20 | I106: COMBUSTIBLE | K106: FTL 303 | L106: COMBUSTIBLE | M106: 0
A107: 46038 | B107: FA | C107: 92-3033 | D107: KJR 926 | F107: 24400 | G107: =+G106-F107+E107 -> 426707.43 | H107: 4 | I107: HIELOS | K107: AUTOELEVADOR | L107: COMBUSTIBLE | M107: =SUM(H92+H99+H106) -> 120.757
A108: 46038 | B108: RE | C108: 50-0083 | D108: TRANSF | E108: 1000000 | G108: =+G107-F108+E108 -> 1426707.4 | I108: PAGO - SALDO A FAVOR | K108: HIELO | L108: HIELO 3 Y 12 KG | M108: 18 BOLSAS
A109: 46038 | B109: FA | C109: 60-0110 | D109: KEX 251 | F109: 45000.46 | G109: =+G108-F109+E109 -> 1381707 | H109: 24.1548 | K109: LITROS SEMANAL | M109: =SUM(M92:M107) -> 434.2908
A110: 46039 | B110: FA | C110: 55-9530 | D110: AA 183 PK | F110: 45000.77 | G110: =+G109-F110+E110 -> 1336706.2 | H110: 24.155 | I110: COMBUSTIBLE
A111: TOTAL DE LITROS SEMANAL | H111: =SUM(H91:H94,H96:H101,H103:H106,H109:H110) -> 434.2908
A112: SEMANA DEL 12/1 AL 18/1 | K112: SEMANA DEL 19/1 AL 25/1
A113: 46041 | B113: FA | C113: 60-0189 | D113: AF 728 AT | F113: 160676.53 | G113: =+G110-F113+E113 -> 1176029.7 | H113: 79.257 | I113: COMBUSTIBLE Y HIELO | K113: RESUMEN CONSUMO
A114: 46041 | B114: FA | C114: 60-0190 | D114: MULITA | F114: 74442.76 | G114: =+G113-F114+E114 -> 1101586.9 | H114: 39.98 | I114: COMBUSTIBLE | K114: RESUMEN | L114: CONSUMO | M114: LTS
A115: 46041 | B115: FA | C115: 60-0202 | D115: LVX 455 | F115: 45000.82 | G115: =+G114-F115+E115 -> 1056586.1 | H115: 24.168 | I115: COMBUSTIBLE | K115: AG 378 AV | L115: COMBUSTIBLE | M115: 0
A116: 46041 | B116: FA | C116: 60-0216 | D116: KJR 926 | F116: 45000.82 | G116: =+G115-F116+E116 -> 1011585.3 | H116: 24.168 | I116: COMBUSTIBLE | K116: AG 337 MY | L116: COMBUSTIBLE | M116: =SUM(H158) -> 54.807
A117: 46041 | B117: FA | C117: 98-0613 | D117: AG 768 OI | F117: 989999.33 | G117: =+G116-F117+E117 -> 21585.94 | H117: 531.686 | I117: COMBUSTIBLE | K117: AG 962 EW | L117: COMBUSTIBLE | M117: 0
A118: 46042 | B118: FA | C118: 92-3358 | D118: AA 183 PK | F118: 45000.82 | G118: =+G117-F118+E118 -> -23414.88 | H118: 24.168 | I118: COMBUSTIBLE | K118: AA 183 PK | L118: COMBUSTIBLE | M118: =SUM(H118+H122+H128+H129+H140+H144+H155) -> 185.673
A119: 46042 | B119: FA | C119: 94-0008 | D119: AG 958 JV | F119: 335582.67 | G119: =+G118-F119+E119 -> -358997.55 | H119: 180.227 | I119: COMBUSTIBLE | K119: MOTO AMARILLA | L119: COMBUSTIBLE | M119: =SUM(H134+H152) -> 47.732
A120: 46042 | B120: FA | C120: 92-3419 | D120: HLW 156 | F120: 45000.82 | G120: =+G119-F120+E120 -> -403998.37 | H120: 24.168 | I120: COMBUSTIBLE | K120: KEX 251 | L120: COMBUSTIBLE | M120: =SUM(H124+H131+H147+H155) -> 82.682
A121: 46043 | B121: FA | C121: 92-3436 | D121: LVX 455 | F121: 45000.82 | G121: =+G120-F121+E121 -> -448999.19 | H121: 24.168 | I121: COMBUSTIBLE | K121: AF 728 AT | L121: COMBUSTIBLE | M121: =SUM(H113+H127+H143) -> 204.149
A122: 46043 | B122: FA | C122: 92-3441 | D122: AA 183 PK | F122: 45000.82 | G122: =+G121-F122+E122 -> -494000.01 | H122: 24.168 | I122: COMBUSTIBLE | K122: PFG 964 | L122: COMBUSTIBLE | M122: =SUM(H123+H135) -> 48.31
...

Sheet FEBRERO.2026
A5: CTA.CTE FEBRERO - 2026 - CARGAS | K5: SEMANA DEL 1/2 AL 7/2
A6: CARGAS COMBUSTIBLE YPF | K6: RESUMEN CONSUMO
A7: FECHA | B7: FACTURA | C7: N° FA/COMP | D7: VEHICULO | E7: PAGOS | F7: CONSUMOS | G7: SALDO | H7: LITROS | I7: OBSEVACIONES | K7: RESUMEN | L7: CONSUMO | M7: LTS
D8: SALDO ANTERIOR | G8: =SUM(E8:F8) -> 0 | K8: AG 337 MY | L8: COMBUSTIBLE
G9: =+G8+E9-F9 -> 0 | K9: AG 962 EW | L9: COMBUSTIBLE
G10: =+G9+E10-F10 -> 0 | K10: AE 919 JA | L10: COMBUSTIBLE
G11: =+G10+E11-F11 -> 0 | K11: AA 183 PK | L11: COMBUSTIBLE
G12: =+G11+E12-F12 -> 0 | K12: MOTO AMARILLA | L12: COMBUSTIBLE
G13: =+G12+E13-F13 -> 0 | K13: KEX 251 | L13: COMBUSTIBLE | M13: =SUM(H9) -> 0
G14: =+G13+E14-F14 -> 0 | K14: AF 728 AT | L14: COMBUSTIBLE | M14: =SUM(H6) -> 0
G15: =+G14+E15-F15 -> 0 | K15: PFG 964 | L15: COMBUSTIBLE
G16: =+G15+E16-F16 -> 0 | K16: LVX 455 | L16: COMBUSTIBLE
G17: =+G16+E17-F17 -> 0 | K17: AG 958 JV | L17: COMBUSTIBLE | M17: =SUM(H8) -> 0
G18: =+G17+E18-F18 -> 0 | K18: AG 768 OI | L18: COMBUSTIBLE
G19: =+G18+E19-F19 -> 0 | K19: KJR 926 | L19: COMBUSTIBLE
G20: =+G19+E20-F20 -> 0 | K20: HLW 156 | L20: COMBUSTIBLE
G21: =+G20+E21-F21 -> 0 | K21: WNO 918 | L21: COMBUSTIBLE
G22: =+G21+E22-F22 -> 0 | K22: HKQ 258 | L22: COMBUSTIBLE | M22: =SUM(H10) -> 0
G23: =+G22+E23-F23 -> 0 | K23: FTL 303 | L23: COMBUSTIBLE
G24: =+G23+E24-F24 -> 0 | K24: AUTOELEVADOR-1 | L24: COMBUSTIBLE | M24: =SUM(H11) -> 0
G25: =+G24+E25-F25 -> 0 | K25: BIDON -(COMPRESOR/HIDROLAV)
G26: =+G25+E26-F26 -> 0 | K26: HIELO | L26: HIELO 3 Y 12 KG | M26: -
G27: =+G26+E27-F27 -> 0
G28: =+G27+E28-F28 -> 0
G29: =+G28+E29-F29 -> 0
G30: =+G29+E30-F30 -> 0
G31: =+G30+E31-F31 -> 0
G32: =+G31+E32-F32 -> 0
G33: =+G32+E33-F33 -> 0
G34: =+G33+E34-F34 -> 0
G35: =+G34+E35-F35 -> 0
G36: =+G35+E36-F36 -> 0
G37: =+G36+E37-F37 -> 0
G38: =+G37+E38-F38 -> 0
G39: =+G38+E39-F39 -> 0
A40: 46053 | C40: SALDO ANTERIOR | F40: 571397.1 | G40: =+G39+E40-F40 -> -571397.1 | K40: AG 378 AV | L40: COMBUSTIBLE | M40: 0
A41: 46054 | B41: FA | C41: 94-0207 | D41: FTL 303 | F41: 350351.16 | G41: =+G40+E41-F41 -> -921748.26 | H41: 186.357 | I41: COMBUSTIBLE | K41: AG 337 MY | L41: COMBUSTIBLE | M41: =SUM(H95) -> 66.411
A42: 46054 | B42: FA | C42: 60-0907 | D42: LVX 455 | F42: 77000.87 | G42: =+G41+E42-F42 -> -998749.13 | H42: 42.1392 | I42: COMBUSTIBLE | K42: AG 962 EW | L42: COMBUSTIBLE | M42: 0
A43: 46054 | B43: FA | C43: 92-4355 | D43: LVX 455 | F43: 45001.56 | G43: =+G42+E43-F43 -> -1043750.7 | H43: 23.937 | I43: COMBUSTIBLE | K43: AE 919 JA | L43: COMBUSTIBLE | M43: 0
A44: 46054 | B44: RE | C44: 50-0099 | D44: TRANSF | E44: 1000000 | G44: =+G43+E44-F44 -> -43750.69 | I44: PAGO - SALDO PENDIENTE | K44: AA 183 PK | L44: COMBUSTIBLE | M44: =SUM(H54+H62+H63+H75+H80+H85+H89) -> 167.3632
A45: 46054 | B45: FA | C45: 98-0791 | D45: KJR 926 | F45: 44999.68 | G45: =+G44+E45-F45 -> -88750.37 | H45: 23.936 | I45: COMBUSTIBLE | K45: MOTO GRIS | L45: COMBUSTIBLE | M45: 0
A46: 46054 | B46: FA | C46: 60-0945 | D46: AG 768 OI | F46: 645012.96 | G46: =+G45+E46-F46 -> -733763.33 | H46: 343.092 | I46: COMBUSTIBLE | K46: MOTO AMARILLA | L46: COMBUSTIBLE | M46: 0
A47: 46054 | B47: FA | C47: 92-4423 | D47: AF 728 AT | F47: 144290 | G47: =+G46+E47-F47 -> -878053.33 | H47: 76.75 | I47: COMBUSTIBLE | K47: KEX 251 | L47: COMBUSTIBLE | M47: =SUM(H49+H58+H70+H82+H90+H97) -> 143.313
A48: 46055 | B48: FA | C48: 92-4452 | D48: LVX 455 | F48: 44999.68 | G48: =+G47+E48-F48 -> -923053.01 | H48: 23.936 | I48: COMBUSTIBLE | K48: AF 728 AT | L48: COMBUSTIBLE | M48: =SUM(H47+H59+H77+H94) -> 269.632
A49: 46055 | B49: FA | C49: 98-0794 | D49: KEX 251 | F49: 44999.68 | G49: =+G48+E49-F49 -> -968052.69 | H49: 23.936 | I49: COMBUSTIBLE | K49: PFG 964 | L49: COMBUSTIBLE | M49: =SUM(H50+H57+H66+H67+H83+H96) -> 285.5798
A50: 46055 | B50: FA | C50: 92-4457 | D50: PFG 964 | F50: 31899.84 | G50: =+G49+E50-F50 -> -999952.53 | H50: 16.968 | I50: COMBUSTIBLE | K50: LVX 455 | L50: COMBUSTIBLE | M50: =SUM(H42+H43+H48+H56+H78+H81+H91) -> 185.5672
A51: 46055 | B51: FA | C51: 92-4463 | D51: HLW 156 | F51: 44999.14 | G51: =+G50+E51-F51 -> -1044951.7 | H51: 25.452 | I51: COMBUSTIBLE | K51: AG 958 JV | L51: COMBUSTIBLE | M51: =SUM(H61+H84) -> 322.442
A52: 46055 | B52: FA | C52: 92-4464 | D52: KJR 926 | F52: 44999.68 | G52: =+G51+E52-F52 -> -1089951.3 | H52: 23.936 | I52: COMBUSTIBLE | K52: AG 768 OI | L52: COMBUSTIBLE | M52: =SUM(H46+H73+H87) -> 546.726
A53: 46055 | B53: FA | C53: 60-0994 | D53: HLW 156 | F53: 44999.68 | G53: =+G52+E53-F53 -> -1134951 | H53: 23.936 | I53: COMBUSTIBLE | K53: KJR 926 | L53: COMBUSTIBLE | M53: =SUM(H45+H52+H60+H68+H69+H76+H93) -> 224.881
A54: 46055 | B54: FA | C54: 92-4510 | D54: AA 183 PK | F54: 44999.68 | G54: =+G53+E54-F54 -> -1179950.7 | H54: 23.936 | I54: COMBUSTIBLE | K54: HLW 156 | L54: COMBUSTIBLE | M54: =SUM(H51+H53) -> 49.388
A55: 46055 | B55: RE | C55: 50-0101 | D55: TRANSF | E55: 2000000 | G55: =+G54+E55-F55 -> 820049.29 | I55: PAGO - SALDO A FAVOR | K55: WNO 918 | L55: COMBUSTIBLE | M55: 0
A56: 46055 | B56: FA | C56: 92-4538 | D56: LVX 455 | F56: 44999.68 | G56: =+G55+E56-F56 -> 775049.61 | H56: 23.936 | I56: COMBUSTIBLE | K56: HKQ 258 | L56: COMBUSTIBLE | M56: 0
A57: 46055 | B57: FA | C57: 92-4540 | D57: PFG 964 | F57: 44999.68 | G57: =+G56+E57-F57 -> 730049.93 | H57: 23.936 | I57: COMBUSTIBLE | K57: FTL 303 | L57: COMBUSTIBLE | M57: =SUM(H41+H71+H72+H88) -> 892.189
A58: 46056 | B58: FA | C58: 60-1012 | D58: KEX 251 | F58: 44999.68 | G58: =+G57+E58-F58 -> 685050.25 | H58: 23.936 | I58: COMBUSTIBLE | K58: AUTOELEVADOR | L58: COMBUSTIBLE | M58: 0
A59: 46056 | B59: FA | C59: 98-0820 | D59: AF 728 AT | F59: 126900 | G59: =+G58+E59-F59 -> 558150.25 | H59: 67.5 | I59: COMBUSTIBLE | K59: OXJ 846 | L59: ENJOY | M59: =SUM(H92) -> 35.007
A60: 46056 | B60: FA | C60: 60-1014 | D60: KJR 926 | F60: 79627.58 | G60: =+G59+E60-F60 -> 478522.67 | H60: 43.533 | I60: COMBUSTIBLE | K60: LITROS SEMANAL | M60: =SUM(M40:M59) -> 3188.4992
A61: 46056 | B61: FA | C61: 60-1036 | D61: AG 958 JV | F61: 318011.4 | G61: =+G60+E61-F61 -> 160511.27 | H61: 169.155 | I61: COMBUSTIBLE
A62: 46056 | B62: FA | C62: 92-4546 | D62: AA 183 PK | F62: 44999.68 | G62: =+G61+E62-F62 -> 115511.59 | H62: 23.936 | I62: COMBUSTIBLE
A63: 46056 | B63: FA | C63: 60-1039 | D63: AA 183 PK | F63: 45000 | G63: =+G62+E63-F63 -> 70511.59 | H63: 23.9362 | I63: COMBUSTIBLE
A64: 46056 | B64: RE | C64: 50-0009 | E64: 45001.56 | G64: =+G63+E64-F64 -> 115513.15 | I64: CANCELA REMITO
A65: 46056 | B65: RE | C65: 50-0010 | E65: 44999.68 | G65: =+G64+E65-F65 -> 160512.83 | I65: CANCELA REMITO
A66: 46056 | B66: FA | C66: 92-4547 | D66: PFG 964 | F66: 138879.36 | G66: =+G65+E66-F66 -> 21633.47 | H66: 73.872 | I66: COMBUSTIBLE
A67: 46056 | B67: FA | C67: 60-1059 | D67: PFG 964 | F67: 138879 | G67: =+G66+E67-F67 -> -117245.53 | H67: 73.8718 | I67: COMBUSTIBLE
A68: 46056 | B68: FA | C68: 60-1095 | D68: KJR 926 | F68: 44999.68 | G68: =+G67+E68-F68 -> -162245.21 | H68: 23.936 | I68: COMBUSTIBLE
A69: 46057 | B69: FA | C69: 92-4590 | D69: KJR 926 | F69: 112205.82 | G69: =+G68+E69-F69 -> -274451.03 | H69: 61.756 | I69: COMBUSTIBLE
A70: 46057 | B70: FA | C70: 60-1097 | D70: KEX 251 | F70: 44999.68 | G70: =+G69+E70-F70 -> -319450.71 | H70: 23.936 | I70: COMBUSTIBLE
A71: 46057 | B71: FA | C71: 94-0241 | D71: FTL 303 | F71: 468984.8 | G71: =+G70+E71-F71 -> -788435.51 | H71: 249.46 | I71: COMBUSTIBLE
A72: 46057 | B72: FA | C72: 94-0244 | D72: FTL 303 | F72: 332867.16 | G72: =+G71+E72-F72 -> -1121302.7 | H72: 177.057 | I72: COMBUSTIBLE
A73: 46057 | B73: FA | C73: 60-1099 | D73: AG 768 OI | F73: 77999.32 | G73: =+G72+E73-F73 -> -1199302 | H73: 41.489 | I73: COMBUSTIBLE
A74: 46057 | B74: RE | C74: 50-0105 | D74: TRANSF | E74: 2200000 | G74: =+G73+E74-F74 -> 1000698 | I74: PAGO - SALDO A FAVOR
A75: 46057 | B75: FA | C75: 96-0124 | D75: AA 183 PK | F75: 44999.68 | G75: =+G74+E75-F75 -> 955698.33 | H75: 23.936 | I75: COMBUSTIBLE
A76: 46058 | B76: FA | C76: 60-1144 | D76: KJR 926 | F76: 45000.17 | G76: =+G75+E76-F76 -> 910698.16 | H76: 23.949 | I76: COMBUSTIBLE
A77: 46058 | B77: FA | C77: 96-0140 | D77: AF 728 AT | F77: 150000.57 | G77: =+G76+E77-F77 -> 760697.59 | H77: 79.83 | I77: COMBUSTIBLE
A78: 46058 | B78: FA | C78: 92-4652 | D78: LVX 455 | F78: 45000.17 | G78: =+G77+E78-F78 -> 715697.42 | H78: 23.949 | I78: COMBUSTIBLE
A79: 46058 | B79: RE | C79: 50-0011 | D79: TRANSF | E79: 138879.36 | G79: =+G78+E79-F79 -> 854576.78 | I79: PAGO - SALDO A FAVOR
A80: 46058 | B80: FA | C80: 92-4663 | D80: AA 183 PK | F80: 45000.17 | G80: =+G79+E80-F80 -> 809576.61 | H80: 23.949 | I80: COMBUSTIBLE
A81: 46059 | B81: FA | C81: 96-0188 | D81: LVX 455 | F81: 45000.48 | G81: =+G80+E81-F81 -> 764576.13 | H81: 23.835 | I81: COMBUSTIBLE
A82: 46059 | B82: FA | C82: 92-4707 | D82: KEX 251 | F82: 45000.48 | G82: =+G81+E82-F82 -> 719575.65 | H82: 23.835 | I82: COMBUSTIBLE
A83: 46059 | B83: FA | C83: 96-0190 | D83: PFG 964 | F83: 45000.48 | G83: =+G82+E83-F83 -> 674575.17 | H83: 23.835 | I83: COMBUSTIBLE
A84: 46059 | B84: FA | C84: 98-0863 | D84: AG 958 JV | F84: 289405.86 | G84: =+G83+E84-F84 -> 385169.31 | H84: 153.287 | I84: COMBUSTIBLE
A85: 46059 | B85: FA | C85: 92-4716 | D85: AA 183 PK | F85: 45000.48 | G85: =+G84+E85-F85 -> 340168.83 | H85: 23.835 | I85: COMBUSTIBLE
A86: 46059 | B86: RE | C86: 50-0109 | D86: TRANSF | E86: 1000000 | G86: =+G85+E86-F86 -> 1340168.8 | I86: PAGO - SALDO A FAVOR
A87: 46059 | B87: FA | C87: 98-0865 | D87: AG 768 OI | F87: 306129.76 | G87: =+G86+E87-F87 -> 1034039.1 | H87: 162.145 | I87: COMBUSTIBLE
A88: 46059 | B88: FA | C88: 94-0296 | D88: FTL 303 | F88: 527346.72 | G88: =+G87+E88-F88 -> 506692.35 | H88: 279.315 | I88: COMBUSTIBLE
A89: 46059 | B89: FA | C89: 92-4748 | D89: AA 183 PK | F89: 45000.48 | G89: =+G88+E89-F89 -> 461691.87 | H89: 23.835 | I89: COMBUSTIBLE
A90: 46059 | B90: FA | C90: 92-4754 | D90: KEX 251 | F90: 45000.48 | G90: =+G89+E90-F90 -> 416691.39 | H90: 23.835 | I90: COMBUSTIBLE
A91: 46060 | B91: FA | C91: 92-4762 | D91: LVX 455 | F91: 45000.48 | G91: =+G90+E91-F91 -> 371690.91 | H91: 23.835 | I91: COMBUSTIBLE
A92: 46060 | B92: FA | C92: 96-0243 | D92: OXJ 846 | F92: 57621.52 | G92: =+G91+E92-F92 -> 314069.39 | H92: 35.007 | I92: COMBUSTIBLE
A93: 46060 | B93: FA | C93: 60-1237 | D93: KJR 926 | F93: 45000.48 | G93: =+G92+E93-F93 -> 269068.91 | H93: 23.835 | I93: COMBUSTIBLE
A94: 46060 | B94: FA | C94: 96-0245 | D94: AF 728 AT | F94: 86002.18 | G94: =+G93+E94-F94 -> 183066.73 | H94: 45.552 | I94: COMBUSTIBLE
A95: 46060 | B95: FA | C95: 92-4767 | D95: AG 337 MY | F95: 121091.9 | G95: =+G94+E95-F95 -> 61974.83 | H95: 66.411 | I95: COMBUSTIBLE
A96: 46060 | B96: FA | C96: 96-0265 | D96: PFG 964 | F96: 138007.14 | G96: =+G95+E96-F96 -> -76032.31 | H96: 73.097 | I96: COMBUSTIBLE
A97: 46060 | B97: FA | C97: 60-1258 | D97: KEX 251 | F97: 45000.48 | G97: =+G96+E97-F97 -> -121032.79 | H97: 23.835 | I97: COMBUSTIBLE
A98: TOTAL DE LITROS SEMANAL | H98: =SUM(H41:H97) -> 3188.4992
A99: SEMANA DEL 1/2 AL 7/2 | K99: SEMANA DEL 8/2 AL 14/2
A100: 46061 | B100: FA | C100: 94-0320 | D100: AG 958 JV | F100: 195153.54 | G100: =+G97+E100-F100 -> -316186.33 | H100: 103.42 | I100: COMBUSTIBLE | K100: RESUMEN CONSUMO
A101: 46061 | B101: FA | C101: 60-1262 | D101: KJR 926 | F101: 80013.82 | G101: =+G100+E101-F101 -> -396200.15 | H101: 43.452 | I101: COMBUSTIBLE | K101: RESUMEN | L101: CONSUMO | M101: LTS
A102: 46061 | B102: FA | C102: 96-0276 | D102: LVX 455 | F102: 44999.29 | G102: =+G101+E102-F102 -> -441199.44 | H102: 23.847 | I102: COMBUSTIBLE | K102: AG 378 AV | L102: COMBUSTIBLE | M102: 0
A103: 46061 | B103: FA | C103: 96-0279 | D103: AA 183 PK | F103: 44999.29 | G103: =+G102+E103-F103 -> -486198.73 | H103: 23.847 | I103: COMBUSTIBLE | K103: AG 337 MY | L103: COMBUSTIBLE | M103: 0
A104: 46062 | B104: FA | C104: 60-1291 | D104: MULITA | F104: 70430.91 | G104: =+G103+E104-F104 -> -556629.64 | H104: 39.435 | I104: COMBUSTIBLE | K104: AG 962 EW | L104: COMBUSTIBLE | M104: 0
...

Sheet MARZO.2026
A5: CTA.CTE MARZO - 2026 - CARGAS | K5: SEMANA DEL 1/3 AL 7/3
A6: CARGAS COMBUSTIBLE YPF | K6: RESUMEN CONSUMO
A7: FECHA | B7: FACTURA | C7: N° FA/COMP | D7: VEHICULO | E7: PAGOS | F7: CONSUMOS | G7: SALDO | H7: LITROS | I7: OBSEVACIONES | K7: RESUMEN | L7: CONSUMO | M7: LTS
A8: 46081 | C8: SALDO ANTERIOR | E8: 2937839.1 | G8: =+E8-F8 -> 2937839.1 | K8: AG 378 AV | L8: COMBUSTIBLE | M8: 0
A9: 46082 | B9: FA | C9: 92-5858 | D9: AF 728 AT | F9: 163010.51 | G9: =+G8+E9-F9 -> 2774828.6 | H9: 82.957 | I9: COMBUSTIBLE | K9: AG 337 MY | L9: COMBUSTIBLE | M9: =SUM(H15) -> 70.7399
A10: 46082 | B10: FA | C10: 92-5864 | D10: KJR 926 | F10: 45000.47 | G10: =+G9+E10-F10 -> 2729828.1 | H10: 22.901 | I10: COMBUSTIBLE | K10: AG 962 EW | L10: COMBUSTIBLE | M10: 0
A11: 46082 | B11: FA | C11: 60-2112 | D11: HLW 156 | F11: 45000.47 | G11: =+G10+E11-F11 -> 2684827.6 | H11: 22.901 | I11: COMBUSTIBLE | K11: AE 919 JA | L11: COMBUSTIBLE | M11: =SUM(H14) -> 55.472
A12: 46082 | B12: FA | C12: 96-1392 | D12: LVX 455 | F12: 45000.47 | G12: =+G11+E12-F12 -> 2639827.2 | H12: 22.901 | I12: COMBUSTIBLE | K12: AA 183 PK | L12: COMBUSTIBLE | M12: =SUM(H26+H30+H41+H43+H47+H48) -> 117.235
A13: 46082 | B13: FA | C13: 92-5880 | D13: LVX 455 | F13: 47317.2 | G13: =+G12+E13-F13 -> 2592510 | H13: 24.08 | I13: COMBUSTIBLE | K13: MOTO AMARILLA | L13: COMBUSTIBLE | M13: 0
A14: 46082 | B14: FA | C14: 96-1397 | D14: AE 919 JA | F14: 109002.48 | G14: =+G13+E14-F14 -> 2483507.5 | H14: 55.472 | I14: COMBUSTIBLE | K14: MOTO GRIS | L14: COMBUSTIBLE | M14: 0
A15: 46082 | B15: FA | C15: 92-5884 | D15: AG 337 MY | F15: 139004 | G15: =+G14+E15-F15 -> 2344503.5 | H15: 70.7399 | I15: COMBUSTIBLE | K15: KEX 251 | L15: COMBUSTIBLE | M15: 0
A16: 46082 | B16: FA | C16: 94-0729 | D16: HKQ 258 | F16: 666007.28 | G16: =+G15+E16-F16 -> 1678496.2 | H16: 338.935 | I16: COMBUSTIBLE | K16: AF 728 AT | L16: COMBUSTIBLE | M16: =SUM(H9+H22+H29+H44) -> 264.4586
A17: 46082 | B17: FA | C17: 94-0730 | D17: AG 768 OI | F17: 750011.03 | G17: =+G16+E17-F17 -> 928485.19 | H17: 381.685 | I17: COMBUSTIBLE | K17: PFG 964 | L17: COMBUSTIBLE | M17: 0
A18: 46083 | B18: FA | C18: 94-0736 | D18: FTL 303 | F18: 673197.18 | G18: =+G17+E18-F18 -> 255288.01 | H18: 362.714 | I18: COMBUSTIBLE | K18: LVX 455 | L18: COMBUSTIBLE | M18: =SUM(H12+H13) -> 46.981
A19: 46083 | B19: FA | C19: 98-1068 | D19: AG 958 JV | F19: 325687.06 | G19: =+G18+E19-F19 -> -70399.05 | H19: 165.072 | I19: COMBUSTIBLE | K19: AG 958 JV | L19: COMBUSTIBLE | M19: =SUM(H19+H23+H39+H40) -> 379.043
A20: 46083 | B20: FA | C20: 94-0742 | D20: AG 958 JV | F20: 24400 | G20: =+G19+E20-F20 -> -94799.05 | H20: * | I20: 4 HIELOS | K20: AG 768 OI | L20: COMBUSTIBLE | M20: =SUM(H17+H25+H37+H45) -> 1431.758
A21: 46083 | B21: RE | C21: 50-0145 | D21: TRANSF | E21: 1500000 | G21: =+G20+E21-F21 -> 1405200.9 | I21: PAGO - SALDO A FAVOR | K21: KJR 926 | L21: COMBUSTIBLE | M21: =SUM(H10+H24+H38+H49) -> 90.258
A22: 46083 | B22: FA | C22: 96-1452 | D22: AF 728 AT | F22: 114003 | G22: =+G21+E22-F22 -> 1291197.9 | H22: 57.7816 | I22: COMBUSTIBLE | K22: HLW 156 | L22: COMBUSTIBLE | M22: =SUM(H11+H50) -> 45.156
A23: 46083 | B23: FA | C23: 94-0746 | D23: AG 958 JV | F23: 73734.96 | G23: =+G22+E23-F23 -> 1217463 | H23: 37.372 | I23: COMBUSTIBLE | K23: WNO 918 | L23: COMBUSTIBLE | M23: =SUM(H33) -> 138.602
A24: 46084 | B24: FA | C24: 96-1489 | D24: KJR 926 | F24: 44999.59 | G24: =+G23+E24-F24 -> 1172463.4 | H24: 22.647 | I24: COMBUSTIBLE | K24: HKQ 258 | L24: COMBUSTIBLE | M24: =SUM(H16+H28) -> 660.047
A25: 46084 | B25: FA | C25: 94-0758 | D25: AG 768 OI | F25: 1190373.9 | G25: =+G24+E25-F25 -> -17910.55 | H25: 599.081 | I25: COMBUSTIBLE | K25: FTL 303 | L25: COMBUSTIBLE | M25: =SUM(H18+H34) -> 630.5236
A26: 46084 | B26: FA | C26: 96-1495 | D26: AA 183 PK | F26: 44999.59 | G26: =+G25+E26-F26 -> -62910.14 | H26: 22.647 | I26: COMBUSTIBLE | K26: AUTOELEVADOR | L26: COMBUSTIBLE | M26: =SUM(H31+H46) -> 55.427
A27: 46084 | B27: FA | C27: 60-2230 | D27: OXJ 846 | F27: 44999.16 | G27: =+G26+E27-F27 -> -107909.3 | H27: 26.377 | I27: ENJOY | K27: OXJ 846 | L27: ENJOY | M27: =SUM(H27) -> 26.377
A28: 46084 | B28: FA | C28: 94-0775 | D28: HKQ 258 | F28: 638049.54 | G28: =+G27+E28-F28 -> -745958.84 | H28: 321.112 | I28: COMBUSTIBLE | K28: HIELO | L28: 3KG Y 12KG | M28: 4 BOLSAS
A29: 46084 | B29: FA | C29: 92-6007 | D29: AF 728 AT | F29: 119895.58 | G29: =+G28+E29-F29 -> -865854.42 | H29: 60.34 | I29: COMBUSTIBLE | K29: LITROS SEMANAL | M29: =SUM(M9:M27) -> 4012.0781
A30: 46085 | B30: FA | C30: 92-6020 | D30: AA 183 PK | F30: 45000.6 | G30: =+G29+E30-F30 -> -910855.02 | H30: 22.433 | I30: COMBUSTIBLE
A31: 46085 | B31: FA | C31: 60-2244 | D31: MULITA | F31: 68821.35 | G31: =+G30+E31-F31 -> -979676.37 | H31: 36.862 | I31: COMBUSTIBLE
A32: 46085 | B32: RE | C32: 50-0148 | D32: TRANSF | E32: 900000 | G32: =+G31+E32-F32 -> -79676.37 | I32: PAGO - SALDO PENDIENTE
A33: 46085 | B33: FA | C33: 94-0783 | D33: WNO 918 | F33: 258769.93 | G33: =+G32+E33-F33 -> -338446.3 | H33: 138.602 | I33: COMBUSTIBLE
A34: 46085 | B34: FA | C34: 94-0784 | D34: FTL 303 | F34: 500000.54 | G34: =+G33+E34-F34 -> -838446.84 | H34: 267.8096 | I34: COMBUSTIBLE
A35: 46085 | B35: RE | C35: 98-0001 | D35: LINK MP | F35: 16443.9 | G35: =+G34+E35-F35 -> -854890.74 | I35: CARGO DE MERCADO PAGO
A36: 46085 | B36: FA | C36: 50-0149 | D36: TRANSF | E36: 2000000 | G36: =+G35+E36-F36 -> 1145109.3 | I36: PAGO - SALDO A FAVOR
A37: 46086 | B37: FA | C37: 98-1093 | D37: AG 768 OI | F37: 830036.76 | G37: =+G36+E37-F37 -> 315072.5 | H37: 414.19 | I37: COMBUSTIBLE
A38: 46086 | B38: FA | C38: 96-1592 | D38: KJR 926 | F38: 44999.82 | G38: =+G37+E38-F38 -> 270072.68 | H38: 22.455 | I38: COMBUSTIBLE
A39: 46086 | B39: FA | C39: 98-1097 | D39: AG 958 JV | F39: 316605.95 | G39: =+G38+E39-F39 -> -46533.27 | H39: 157.987 | I39: COMBUSTIBLE
A40: 46086 | B40: FA | C40: 98-1098 | D40: AG 958 JV | F40: 37298.45 | G40: =+G39+E40-F40 -> -83831.72 | H40: 18.612 | I40: COMBUSTIBLE
A41: 46086 | B41: FA | C41: 92-6088 | D41: AA 183 PK | F41: 44999.82 | G41: =+G40+E41-F41 -> -128831.54 | H41: 22.455 | I41: COMBUSTIBLE
A42: 46086 | B42: RE | C42: 50-0150 | D42: TRANSF | E42: 1000000 | G42: =+G41+E42-F42 -> 871168.46 | I42: PAGO - SALDO A FAVOR
A43: 46086 | B43: FA | C43: 96-1631 | D43: AA 183 PK | F43: 44999.82 | G43: =+G42+E43-F43 -> 826168.64 | H43: 22.455 | I43: COMBUSTIBLE
A44: 46086 | B44: FA | C44: 60-2321 | D44: AF 728 AT | F44: 127013.52 | G44: =+G43+E44-F44 -> 699155.12 | H44: 63.38 | I44: COMBUSTIBLE
A45: 46086 | B45: FA | C45: 98-1108 | D45: AG 768 OI | F45: 76327.35 | G45: =+G44+E45-F45 -> 622827.77 | H45: 36.802 | I45: COMBUSTIBLE
A46: 46087 | B46: FA | C46: 96-1640 | D46: MULITA | F46: 35013.59 | G46: =+G45+E46-F46 -> 587814.18 | H46: 18.565 | I46: COMBUSTIBLE
A47: 46087 | B47: FA | C47: 96-1676 | D47: AA 183 PK | F47: 10105.6 | G47: =+G46+E47-F47 -> 577708.58 | H47: 5.012 | I47: BIDON NAFTA Y AUXILIO
A48: 46087 | B48: FA | C48: 60-2370 | D48: AA 183 PK | F48: 44999.59 | G48: =+G47+E48-F48 -> 532708.99 | H48: 22.233 | I48: COMBUSTIBLE
A49: 46088 | B49: FA | C49: 92-6196 | D49: KJR 926 | F49: 44999.61 | G49: =+G48+E49-F49 -> 487709.38 | H49: 22.255 | I49: COMBUSTIBLE
A50: 46088 | B50: FA | C50: 96-1743 | D50: HLW 156 | F50: 44999.61 | G50: =+G49+E50-F50 -> 442709.77 | H50: 22.255 | I50: COMBUSTIBLE
A51: TOTAL DE LITROS SEMANAL | H51: =SUM(H9:H50) -> 4012.0781
A52: SEMANA DEL 1/3 AL 7/3 | K52: SEMANA DEL 8/3 AL 14/3
A53: 46089 | B53: FA | C53: 96-1751 | D53: KJR 926 | F53: 44999.59 | G53: =+G50+E53-F53 -> 397710.18 | H53: 22.233 | I53: COMBUSTIBLE | K53: RESUMEN CONSUMO
A54: 46089 | B54: FA | C54: 96-1759 | D54: AF 728 AT | F54: 130234.28 | G54: =+G53+E54-F54 -> 267475.9 | H54: 64.345 | I54: COMBUSTIBLE | K54: RESUMEN | L54: CONSUMO | M54: LTS
A55: 46089 | B55: FA | C55: 96-1760 | D55: MULITA | F55: 76077.74 | G55: =+G54+E55-F55 -> 191398.16 | H55: 40.062 | I55: COMBUSTIBLE | K55: AG 378 AV | L55: COMBUSTIBLE | M55: 0
A56: 46090 | B56: FA | C56: 96-1851 | D56: AA 183 PK | F56: 44999.16 | G56: =+G55+E56-F56 -> 146399 | H56: 22.178 | I56: COMBUSTIBLE | K56: AG 337 MY | L56: COMBUSTIBLE | M56: =SUM(H60) -> 68.385
A57: 46090 | B57: FA | C57: 96-1859 | D57: LVX 455 | F57: 44999.16 | G57: =+G56+E57-F57 -> 101399.84 | H57: 22.178 | I57: COMBUSTIBLE | K57: AG 962 EW | L57: COMBUSTIBLE | M57: 0
A58: 46091 | B58: FA | C58: 96-1873 | D58: LVX 455 | F58: 55011.68 | G58: =+G57+E58-F58 -> 46388.16 | H58: 28.637 | I58: COMBUSTIBLE | K58: AE 919 JA | L58: COMBUSTIBLE | M58: 0
A59: 46091 | B59: FA | C59: 96-1876 | D59: MULITA | F59: 65452.31 | G59: =+G58+E59-F59 -> -19064.15 | H59: 34.072 | I59: COMBUSTIBLE | K59: AA 183 PK | L59: COMBUSTIBLE | M59: =SUM(H56+H65+H73+H80+H86) -> 148.675
A60: 46091 | B60: FA | C60: 96-1878 | D60: AG 337 MY | F60: 138753.17 | G60: =+G59+E60-F60 -> -157817.32 | H60: 68.385 | I60: COMBUSTIBLE | K60: MOTO AMARILLA | L60: COMBUSTIBLE | M60: =SUM(H74) -> 8.535
A61: 46091 | B61: FA | C61: 98-1148 | D61: HKQ 258 | F61: 538780.66 | G61: =+G60+E61-F61 -> -696597.98 | H61: 265.54 | I61: COMBUSTIBLE | K61: MOTO GRIS | L61: COMBUSTIBLE | M61: 0
A62: 46091 | B62: FA | C62: 96-1907 | D62: KJR 926 | F62: 44999.16 | G62: =+G61+E62-F62 -> -741597.14 | H62: 22.178 | I62: COMBUSTIBLE | K62: KEX 251 | L62: COMBUSTIBLE | M62: 0
A63: 46091 | B63: FA | C63: 96-1909 | D63: AF 728 AT | F63: 149013.82 | G63: =+G62+E63-F63 -> -890610.96 | H63: 73.442 | I63: COMBUSTIBLE | K63: AF 728 AT | L63: COMBUSTIBLE | M63: =SUM(H54+H63) -> 137.787
A64: 46092 | B64: RE | C64: 50-0152 | D64: TRANSF | E64: 1500000 | G64: =+G63+E64-F64 -> 609389.04 | I64: PAGO - SALDO A FAVOR | K64: PFG 964 | L64: COMBUSTIBLE | M64: 0
A65: 46092 | B65: FA | C65: 96-1937 | D65: AA 183 PK | F65: 44999.16 | G65: =+G64+E65-F65 -> 564389.88 | H65: 22.178 | I65: COMBUSTIBLE | K65: LVX 455 | L65: COMBUSTIBLE | M65: =SUM(H57+H58+H68+H78+H83) -> 152.8185
A66: 46092 | B66: FA | C66: 92-6366 | D66: KJR 926 | F66: 44999.16 | G66: =+G65+E66-F66 -> 519390.72 | H66: 22.178 | I66: COMBUSTIBLE | K66: AG 958 JV | L66: COMBUSTIBLE | M66: =SUM(H70) -> 158.707
A67: 46092 | B67: FA | C67: 92-6371 | D67: HLW 156 | F67: 44999.06 | G67: =+G66+E67-F67 -> 474391.66 | H67: 23.112 | I67: COMBUSTIBLE | K67: AG 768 OI | L67: COMBUSTIBLE | M67: 0
A68: 46092 | B68: FA | C68: 96-1959 | D68: LVX 455 | F68: 44999.16 | G68: =+G67+E68-F68 -> 429392.5 | H68: 22.178 | I68: COMBUSTIBLE | K68: KJR 926 | L68: COMBUSTIBLE | M68: =SUM(H53+H62+H66+H72+H85) -> 110.018
A69: 46092 | B69: FA | C69: 98-1158 | D69: WNO 918 | F69: 281579.03 | G69: =+G68+E69-F69 -> 147813.47 | H69: 144.622 | I69: COMBUSTIBLE | K69: HLW 156 | L69: COMBUSTIBLE | M69: =SUM(H67+H79) -> 44.989
A70: 46092 | B70: FA | C70: 94-0935 | D70: AG 958 JV | F70: 322016.5 | G70: =+G69+E70-F70 -> -174203.03 | H70: 158.707 | I70: COMBUSTIBLE | K70: WNO 918 | L70: COMBUSTIBLE | M70: =SUM(H69+H77) -> 221.504
A71: 46093 | B71: FA | C71: 92-6398 | D71: MULITA | F71: 82290.29 | G71: =+G70+E71-F71 -> -256493.32 | H71: 40.005 | I71: COMBUSTIBLE | K71: HKQ 258 | L71: COMBUSTIBLE | M71: =SUM(H61) -> 265.54
A72: 46093 | B72: FA | C72: 92-6404 | D72: KJR 926 | F72: 45000.99 | G72: =+G71+E72-F72 -> -301494.31 | H72: 21.877 | I72: COMBUSTIBLE | K72: FTL 303 | L72: COMBUSTIBLE | M72: =SUM(H76) -> 101.266
A73: 46093 | B73: FA | C73: 92-6406 | D73: AA 183 PK | F73: 45000.99 | G73: =+G72+E73-F73 -> -346495.3 | H73: 21.877 | I73: COMBUSTIBLE | K73: AUTOELEVADOR | L73: COMBUSTIBLE | M73: =SUM(H55+H59+H71+H84) -> 134.434
A74: 46093 | B74: FA | C74: 92-6416 | D74: MOTO AMARILLA | F74: 16429.88 | G74: =+G73+E74-F74 -> -362925.18 | H74: 8.535 | I74: COMBUSTIBLE | K74: LITROS SEMANAL | M74: =SUM(M56:M73) -> 1552.6585
A75: 46093 | B75: RE | C75: 50-0156 | D75: TRANSF | E75: 2000000 | G75: =+G74+E75-F75 -> 1637074.8 | I75: PAGO - SALDO A FAVOR
A76: 46094 | B76: FA | C76: 94-0957 | D76: FTL 303 | F76: 200000.35 | G76: =+G75+E76-F76 -> 1437074.5 | H76: 101.266 | I76: COMBUSTIBLE
A77: 46094 | B77: FA | C77: 94-0958 | D77: WNO 918 | F77: 151841.95 | G77: =+G76+E77-F77 -> 1285232.5 | H77: 76.882 | I77: COMBUSTIBLE
A78: 46094 | B78: FA | C78: 92-6470 | D78: LVX 455 | F78: 119868.62 | G78: =+G77+E78-F78 -> 1165363.9 | H78: 58.2735 | I78: COMBUSTIBLE
A79: 46094 | B79: FA | C79: 92-6498 | D79: HLW 156 | F79: 45000.99 | G79: =+G78+E79-F79 -> 1120362.9 | H79: 21.877 | I79: COMBUSTIBLE
A80: 46066 | B80: FA | C80: 60-2662 | D80: AA 183 PK | F80: 45000.99 | G80: =+G79+E80-F80 -> 1075361.9 | H80: 21.877 | I80: COMBUSTIBLE
A81: 46095 | B81: RE | C81: 50-0159 | D81: TRANSF | E81: 500000 | G81: =+G80+E81-F81 -> 1575361.9 | I81: PAGO - SALDO A FAVOR
A82: 46095 | B82: RE | C82: 50-0160 | D82: TRANSF | E82: 500000 | G82: =+G81+E82-F82 -> 2075361.9 | I82: PAGO - SALDO A FAVOR
A83: 46095 | B83: FA | C83: 92-6515 | D83: LVX 455 | F83: 45000.58 | G83: =+G82+E83-F83 -> 2030361.3 | H83: 21.552 | I83: COMBUSTIBLE
A84: 46095 | B84: FA | C84: 96-2108 | D84: MULITA | F84: 40021.74 | G84: =+G83+E84-F84 -> 1990339.6 | H84: 20.295 | I84: COMBUSTIBLE
A85: 46095 | B85: FA | C85: 96-2126 | D85: KJR 926 | F85: 45000.58 | G85: =+G84+E85-F85 -> 1945339 | H85: 21.552 | I85: COMBUSTIBLE
A86: 46095 | B86: FA | C86: 96-2135 | D86: AA 183 PK | F86: 126459.72 | G86: =+G85+E86-F86 -> 1818879.3 | H86: 60.565 | I86: COMBUSTIBLE
A87: TOTAL DE LITROS SEMANAL | H87: =SUM(H53:H86) -> 1552.6585
A88: SEMANA DEL 8/3 AL 14/3 | K88: SEMANA DEL 15/3 AL 21/3
A89: 46096 | B89: FA | C89: 92-6556 | D89: HLW 156 | F89: 45000.58 | G89: =+G86+E89-F89 -> 1773878.7 | H89: 21.552 | I89: COMBUSTIBLE | K89: RESUMEN CONSUMO
A90: 46096 | B90: FA | C90: 96-2150 | D90: AA 183 PK | F90: 20065.68 | G90: =+G89+E90-F90 -> 1753813 | H90: 9.61 | I90: COMBUSTIBLE | K90: RESUMEN | L90: CONSUMO | M90: LTS
A91: 46096 | B91: FA | C91: 60-2702 | D91: PFG 964 | F91: 129021.7 | G91: =+G90+E91-F91 -> 1624791.3 | H91: 61.792 | I91: COMBUSTIBLE | K91: AG 378 AV | L91: COMBUSTIBLE | M91: 0
A92: 46097 | B92: FA | C92: 98-1193 | D92: AG 958 JV | F92: 234509.2 | G92: =+G91+E92-F92 -> 1390282.1 | H92: 110.722 | I92: COMBUSTIBLE | K92: AG 337 MY | L92: COMBUSTIBLE | M92: =SUM(H106) -> 76.092
A93: 46097 | B93: FA | C93: 98-1194 | D93: HKQ 258 | F93: 122467 | G93: =+G92+E93-F93 -> 1267815.1 | H93: 57.822 | I93: COMBUSTIBLE | K93: AG 962 EW | L93: COMBUSTIBLE | M93: 0
A94: 46097 | B94: FA | C94: 98-1195 | D94: AG 768 OI | F94: 1343693.4 | G94: =+G93+E94-F94 -> -75878.213 | H94: 635.132 | I94: COMBUSTIBLE | K94: AE 919 JA | L94: COMBUSTIBLE | M94: =SUM(H124) -> 20.529
A95: 46097 | B95: FA | C95: 96-2200 | D95: LVX 455 | F95: 139029.76 | G95: =+G94+E95-F95 -> -214907.97 | H95: 65.642 | I95: COMBUSTIBLE | K95: AA 183 PK | L95: COMBUSTIBLE | M95: =SUM(H90+H116+H118) -> 69.413
A96: 46097 | B96: FA | C96: 96-2227 | D96: KEX 251 | F96: 140004.04 | G96: =+G95+E96-F96 -> -354912.01 | H96: 66.102 | I96: COMBUSTIBLE | K96: MOTO AMARILLA | L96: COMBUSTIBLE | M96: =SUM(H100+H112) -> 20.372
A97: 46097 | B97: RE | C97: 50-0162 | D97: TRANSF | E97: 1500000 | G97: =+G96+E97-F97 -> 1145088 | I97: PAGO - SALDO A FAVOR | K97: MOTO GRIS | L97: COMBUSTIBLE | M97: 0
A98: 46098 | B98: FA | C98: 94-1016 | D98: FTL 303 | F98: 808709.11 | G98: =+G97+E98-F98 -> 336378.88 | H98: 404.962 | I98: COMBUSTIBLE | K98: KEX 251 | L98: COMBUSTIBLE | M98: =SUM(H96+H123+H125) -> 107.16
A99: 46098 | B99: FA | C99: 96-2255 | D99: MULITA | F99: 84359.94 | G99: =+G98+E99-F99 -> 252018.94 | H99: 39.83 | I99: COMBUSTIBLE | K99: AF 728 AT | L99: COMBUSTIBLE | M99: =SUM(H122) -> 84.752
A100: 46098 | B100: FA | C100: 92-6655 | D100: MOTO AMARILLA | F100: 20678.23 | G100: =+G99+E100-F100 -> 231340.71 | H100: 10.412 | I100: COMBUSTIBLE | K100: PFG 964 | L100: COMBUSTIBLE | M100: =SUM(H91+H128) -> 82.321
A101: 46098 | B101: FA | C101: 60-2801 | D101: MULITA | F101: 83538.16 | G101: =+G100+E101-F101 -> 147802.55 | H101: 39.442 | I101: COMBUSTIBLE | K101: LVX 455 | L101: COMBUSTIBLE | M101: =SUM(H95+H103+H105+H108+H117) -> 149.792
A102: 46098 | B102: RE | C102: 50-0166 | D102: TRANSF | E102: 1000000 | G102: =+G101+E102-F102 -> 1147802.5 | I102: PAGO - SALDO A FAVOR | K102: AG 958 JV | L102: COMBUSTIBLE | M102: =SUM(H92+H109) -> 259.352
A103: 46098 | B103: FA | C103: 92-6662 | D103: LVX 455 | F103: 44999.03 | G103: =+G102+E103-F103 -> 1102803.5 | H103: 21.246 | I103: COMBUSTIBLE | K103: AG 768 OI | L103: COMBUSTIBLE | M103: =SUM(H94+H107) -> 969.976
A104: 46098 | B104: FA | C104: 92-6692 | D104: HLW 156 | F104: 44999.03 | G104: =+G103+E104-F104 -> 1057804.5 | H104: 21.246 | I104: COMBUSTIBLE | K104: KJR 926 | L104: COMBUSTIBLE | M104: =SUM(H131+H132) -> 41.058
...

Sheet ABRIL.2026
A5: CTA.CTE ABRIL - 2026 - CARGAS | K5: SEMANA DEL 1/4 AL 4/4
A6: CARGAS COMBUSTIBLE YPF | K6: RESUMEN CONSUMO
A7: FECHA | B7: FACTURA | C7: N° FA/COMP | D7: VEHICULO | E7: PAGOS | F7: CONSUMOS | G7: SALDO | H7: LITROS | I7: OBSEVACIONES | K7: RESUMEN | L7: CONSUMO | M7: LTS
D8: SALDO ANTERIOR | G8: =SUM(E8:F8) -> 0 | K8: AG 337 MY | L8: COMBUSTIBLE
G9: =+G8+E9-F9 -> 0 | K9: AG 962 EW | L9: COMBUSTIBLE
G10: =+G9+E10-F10 -> 0 | K10: AE 919 JA | L10: COMBUSTIBLE
G11: =+G10+E11-F11 -> 0 | K11: AA 183 PK | L11: COMBUSTIBLE
G12: =+G11+E12-F12 -> 0 | K12: MOTO AMARILLA | L12: COMBUSTIBLE
G13: =+G12+E13-F13 -> 0 | K13: KEX 251 | L13: COMBUSTIBLE | M13: =SUM(H9) -> 0
G14: =+G13+E14-F14 -> 0 | K14: AF 728 AT | L14: COMBUSTIBLE | M14: =SUM(H6) -> 0
G15: =+G14+E15-F15 -> 0 | K15: PFG 964 | L15: COMBUSTIBLE
G16: =+G15+E16-F16 -> 0 | K16: LVX 455 | L16: COMBUSTIBLE
G17: =+G16+E17-F17 -> 0 | K17: AG 958 JV | L17: COMBUSTIBLE | M17: =SUM(H8) -> 0
G18: =+G17+E18-F18 -> 0 | K18: AG 768 OI | L18: COMBUSTIBLE
G19: =+G18+E19-F19 -> 0 | K19: KJR 926 | L19: COMBUSTIBLE
G20: =+G19+E20-F20 -> 0 | K20: HLW 156 | L20: COMBUSTIBLE
G21: =+G20+E21-F21 -> 0 | K21: WNO 918 | L21: COMBUSTIBLE
G22: =+G21+E22-F22 -> 0 | K22: HKQ 258 | L22: COMBUSTIBLE | M22: =SUM(H10) -> 0
G23: =+G22+E23-F23 -> 0 | K23: FTL 303 | L23: COMBUSTIBLE
G24: =+G23+E24-F24 -> 0 | K24: AUTOELEVADOR-1 | L24: COMBUSTIBLE | M24: =SUM(H11) -> 0
G25: =+G24+E25-F25 -> 0 | K25: BIDON -(COMPRESOR/HIDROLAV)
G26: =+G25+E26-F26 -> 0 | K26: HIELO | L26: HIELO 3 Y 12 KG | M26: -
G27: =+G26+E27-F27 -> 0
G28: =+G27+E28-F28 -> 0
G29: =+G28+E29-F29 -> 0
G30: =+G29+E30-F30 -> 0
G31: =+G30+E31-F31 -> 0
G32: =+G31+E32-F32 -> 0
G33: =+G32+E33-F33 -> 0
G34: =+G33+E34-F34 -> 0
G35: =+G34+E35-F35 -> 0
G36: =+G35+E36-F36 -> 0
G37: =+G36+E37-F37 -> 0
G38: =+G37+E38-F38 -> 0
G39: =+G38+E39-F39 -> 0
C40: SALDO ANTERIOR | F40: 471748.76 | G40: =+G39+E40-F40 -> -471748.76 | K40: AG 378 AV | L40: COMBUSTIBLE | M40: 0
A41: 46113 | B41: FA | C41: 92-7449 | D41: PFG 964 | F41: 45000.11 | G41: =+G40+E41-F41 -> -516748.87 | H41: 19.198 | I41: COMBUSTIBLE | K41: AG 337 MY | L41: COMBUSTIBLE | M41: 0
A42: 46113 | B42: FA | C42: 96-3011 | D42: AG 962 EW | F42: 128005.84 | G42: =+G41+E42-F42 -> -644754.71 | H42: 54.61 | I42: COMBUSTIBLE | K42: AG 962 EW | L42: COMBUSTIBLE | M42: =SUM(H42) -> 54.61
A43: 46113 | B43: RE | C43: 50-0194 | D43: TRANSF | E43: 2000000 | G43: =+G42+E43-F43 -> 1355245.3 | I43: PAGO - SALDO A FAVOR | K43: AE 919 JA | L43: COMBUSTIBLE | M43: =SUM(H50+H56+H68) -> 57.594
A44: 46113 | B44: FA | C44: 96-3027 | D44: MOTO AMARILLA | F44: 20181.74 | G44: =+G43+E44-F44 -> 1335063.6 | H44: 9.207 | I44: COMBUSTIBLE | K44: AA 183 PK | L44: COMBUSTIBLE | M44: =SUM(H47+H53) -> 38.4
A45: 46113 | B45: FA | C45: 92-7478 | D45: KEX 251 | F45: 45000.11 | G45: =+G44+E45-F45 -> 1290063.4 | H45: 19.198 | I45: COMBUSTIBLE | K45: MOTO GRIS | L45: COMBUSTIBLE | M45: 0
A46: 46113 | B46: FA | C46: 92-7491 | D46: KEX 251 | F46: 45000.11 | G46: =+G45+E46-F46 -> 1245063.3 | H46: 19.198 | I46: COMBUSTIBLE | K46: MOTO AMARILLA | L46: COMBUSTIBLE | M46: =SUM(H44) -> 9.207
A47: 46113 | B47: FA | C47: 98-1355 | D47: AA 183 PK | F47: 45009.49 | G47: =+G46+E47-F47 -> 1200053.8 | H47: 19.202 | I47: COMBUSTIBLE | K47: KEX 251 | L47: COMBUSTIBLE | M47: =SUM(H45+H46+H48+H63) -> 76.792
A48: 46113 | B48: FA | C48: 96-3060 | D48: KEX 251 | F48: 45000.11 | G48: =+G47+E48-F48 -> 1155053.7 | H48: 19.198 | I48: COMBUSTIBLE | K48: AF 728 AT | L48: COMBUSTIBLE | M48: =SUM(H55) -> 72.532
A49: 46113 | B49: FA | C49: 60-3472 | D49: KJR 926 | F49: 45000.11 | G49: =+G48+E49-F49 -> 1110053.6 | H49: 19.198 | I49: COMBUSTIBLE | K49: PFG 964 | L49: COMBUSTIBLE | M49: =SUM(H41+H52+H59+H62) -> 76.792
A50: 46113 | B50: FA | C50: 96-3063 | D50: AE 919 JA | F50: 45000.11 | G50: =+G49+E50-F50 -> 1065053.5 | H50: 19.198 | I50: COMBUSTIBLE | K50: LVX 455 | L50: COMBUSTIBLE | M50: =SUM(H57+H61) -> 38.396
A51: 46114 | B51: FA | C51: 96-3070 | D51: KJR 926 | F51: 45000.11 | G51: =+G50+E51-F51 -> 1020053.4 | H51: 19.198 | I51: COMBUSTIBLE | K51: AG 958 JV | L51: COMBUSTIBLE | M51: =SUM(H66) -> 158.247
A52: 46114 | B52: FA | C52: 92-7516 | D52: PFG 964 | F52: 45000.11 | G52: =+G51+E52-F52 -> 975053.29 | H52: 19.198 | I52: COMBUSTIBLE | K52: AG 768 OI | L52: COMBUSTIBLE | M52: 0
A53: 46114 | B53: FA | C53: 96-3072 | D53: AA 183 PK | F53: 45000.11 | G53: =+G52+E53-F53 -> 930053.18 | H53: 19.198 | I53: COMBUSTIBLE | K53: KJR 926 | L53: COMBUSTIBLE | M53: =SUM(H49+H51+H64+H69) -> 76.792
A54: 46114 | B54: FA | C54: 60-3496 | D54: MULITA | F54: 49199.33 | G54: =+G53+E54-F54 -> 880853.85 | H54: 22.122 | I54: COMBUSTIBLE | K54: HLW 156 | L54: COMBUSTIBLE | M54: =SUM(H67) -> 19.198
A55: 46114 | B55: FA | C55: 60-3503 | D55: AF 728 AT | F55: 170015.01 | G55: =+G54+E55-F55 -> 710838.84 | H55: 72.532 | I55: COMBUSTIBLE | K55: WNO 918 | L55: COMBUSTIBLE | M55: 0
A56: 46114 | B56: FA | C56: 60-3504 | D56: AE 919 JA | F56: 45000.11 | G56: =+G55+E56-F56 -> 665838.73 | H56: 19.198 | I56: COMBUSTIBLE | K56: HKQ 258 | L56: COMBUSTIBLE | M56: 0
A57: 46115 | B57: FA | C57: 92-7547 | D57: LVX 455 | F57: 45000.11 | G57: =+G56+E57-F57 -> 620838.62 | H57: 19.198 | I57: COMBUSTIBLE | K57: FTL 303 | L57: COMBUSTIBLE | M57: 0
A58: 46115 | B58: FA | C58: 60-3511 | D58: MULITA | F58: 103805.2 | G58: =+G57+E58-F58 -> 517033.42 | H58: 46.675 | I58: COMBUSTIBLE | K58: AUTOELEVADOR | L58: COMBUSTIBLE | M58: =SUM(H54+H58+H60+H65) -> 150.232
A59: 46115 | B59: FA | C59: 96-3120 | D59: PFG 964 | F59: 45000.11 | G59: =+G58+E59-F59 -> 472033.31 | H59: 19.198 | I59: COMBUSTIBLE | K59: LITROS SEMANAL | M59: =SUM(M39:M58) -> 828.792
A60: 46115 | B60: FA | C60: 60-3517 | D60: MULITA | F60: 100791.68 | G60: =+G59+E60-F60 -> 371241.63 | H60: 45.32 | I60: COMBUSTIBLE
A61: 46116 | B61: FA | C61: 92-7593 | D61: LVX 455 | F61: 45000.11 | G61: =+G60+E61-F61 -> 326241.52 | H61: 19.198 | I61: COMBUSTIBLE
A62: 46116 | B62: FA | C62: 92-7594 | D62: PFG 964 | F62: 45000.11 | G62: =+G61+E62-F62 -> 281241.41 | H62: 19.198 | I62: COMBUSTIBLE
A63: 46116 | B63: FA | C63: 92-7595 | D63: KEX 251 | F63: 45000.11 | G63: =+G62+E63-F63 -> 236241.3 | H63: 19.198 | I63: COMBUSTIBLE
A64: 46116 | B64: FA | C64: 92-7600 | D64: KJR 926 | F64: 45000.11 | G64: =+G63+E64-F64 -> 191241.19 | H64: 19.198 | I64: COMBUSTIBLE
A65: 46116 | B65: FA | C65: 96-3153 | D65: MULITA | F65: 80319.76 | G65: =+G64+E65-F65 -> 110921.43 | H65: 36.115 | I65: COMBUSTIBLE
A66: 46116 | B66: FA | C66: 94-1378 | D66: AG 958 JV | F66: 370930.97 | G66: =+G65+E66-F66 -> -260009.54 | H66: 158.247 | I66: COMBUSTIBLE
A67: 46116 | B67: FA | C67: 96-3158 | D67: HLW 156 | F67: 45000.11 | G67: =+G66+E67-F67 -> -305009.65 | H67: 19.198 | I67: COMBUSTIBLE
A68: 46116 | B68: FA | C68: 96-3165 | D68: AE 919 JA | F68: 45000.11 | G68: =+G67+E68-F68 -> -350009.76 | H68: 19.198 | I68: COMBUSTIBLE
A69: 46116 | B69: FA | C69: 60-3551 | D69: KJR 926 | F69: 45000.11 | G69: =+G68+E69-F69 -> -395009.87 | H69: 19.198 | I69: COMBUSTIBLE
A70: TOTAL DE LITROS SEMANAL | H70: =SUM(H26:H69) -> 828.792
A71: SEMANA DEL 1/4 AL 4/4 | K71: SEMANA DEL 5/4 AL 11/4
A72: 46117 | B72: FA | C72: 92-7621 | D72: KEX 251 | F72: 45000.11 | G72: =+G69+E72-F72 -> -440009.98 | H72: 19.198 | I72: COMBUSTIBLE | K72: RESUMEN CONSUMO
A73: 46117 | B73: FA | C73: 94-1381 | D73: AG 958 JV | F73: 101987.44 | G73: =+G72+E73-F73 -> -541997.42 | H73: 43.51 | I73: COMBUSTIBLE | K73: RESUMEN | L73: CONSUMO | M73: LTS
A74: 46117 | B74: FA | C74: 92-7636 | D74: KJR 926 | F74: 45000.11 | G74: =+G73+E74-F74 -> -586997.53 | H74: 19.198 | I74: COMBUSTIBLE | K74: AG 378 AV | L74: COMBUSTIBLE | M74: 0
A75: 46117 | B75: FA | C75: 92-7661 | D75: HLW 156 | F75: 45000.11 | G75: =+G74+E75-F75 -> -631997.64 | H75: 19.198 | I75: COMBUSTIBLE | K75: AG 337 MY | L75: COMBUSTIBLE | M75: 0
A76: 46118 | B76: FA | C76: 60-3595 | D76: LVX 455 | F76: 45000.11 | G76: =+G75+E76-F76 -> -676997.75 | H76: 19.198 | I76: COMBUSTIBLE | K76: AG 962 EW | L76: COMBUSTIBLE | M76: 0
A77: 46118 | B77: FA | C77: 96-3251 | D77: HKQ 258 | F77: 26000 | G77: =+G76+E77-F77 -> -702997.75 | H77: * | I77: 4 HIELOS | K77: AE 919 JA | L77: COMBUSTIBLE | M77: =SUM(H82+H92+H100+H105) -> 76.792
A78: 46118 | B78: FA | C78: 92-7675 | D78: PFG 964 | F78: 45000.11 | G78: =+G77+E78-F78 -> -747997.86 | H78: 19.198 | I78: COMBUSTIBLE | K78: AA 183 PK | L78: COMBUSTIBLE | M78: =SUM(H79+H86+H89+H108+H113+H114) -> 147.892
A79: 46118 | B79: FA | C79: 60-3617 | D79: AA 183 PK | F79: 45000.11 | G79: =+G78+E79-F79 -> -792997.97 | H79: 19.198 | I79: COMBUSTIBLE | K79: MOTO GRIS | L79: COMBUSTIBLE | M79: 0
A80: 46118 | B80: FA | C80: 94-1401 | D80: WNO 918 | F80: 207000 | G80: =+G79+E80-F80 -> -999997.97 | H80: 93.0755 | I80: COMBUSTIBLE | K80: MOTO AMARILLA | L80: COMBUSTIBLE | M80: =SUM(H112) -> 10.292
A81: 46118 | B81: RE | C81: 50-0196 | D81: TRANSF | E81: 2000000 | G81: =+G80+E81-F81 -> 1000002 | I81: PAGO - SALDO A FAVOR | K81: KEX 251 | L81: COMBUSTIBLE | M81: =SUM(H72+H84) -> 38.396
A82: 46118 | B82: FA | C82: 60-3627 | D82: AE 919 JA | F82: 45000.11 | G82: =+G81+E82-F82 -> 955001.92 | H82: 19.198 | I82: COMBUSTIBLE | K82: AF 728 AT | L82: COMBUSTIBLE | M82: =SUM(H83+H106) -> 159.712
A83: 46118 | B83: FA | C83: 92-7729 | D83: AF 728 AT | F83: 174358.44 | G83: =+G82+E83-F83 -> 780643.48 | H83: 74.385 | I83: COMBUSTIBLE | K83: PFG 964 | L83: COMBUSTIBLE | M83: =SUM(H78+H90+H98+H118) -> 76.792
A84: 46118 | B84: FA | C84: 92-7734 | D84: KEX 251 | F84: 45000.11 | G84: =+G83+E84-F84 -> 735643.37 | H84: 19.198 | I84: COMBUSTIBLE | K84: LVX 455 | L84: COMBUSTIBLE | M84: =SUM(H76+H87+H91+H103+H110+H115+H116) -> 134.386
A85: 46119 | B85: FA | C85: 94-1412 | D85: AG 958 JV | F85: 175242 | G85: =+G84+E85-F85 -> 560401.37 | H85: 74.7619 | I85: COMBUSTIBLE | K85: AG 958 JV | L85: COMBUSTIBLE | M85: =SUM(H73+H85+H109) -> 294.2839
A86: 46119 | B86: FA | C86: 92-7739 | D86: AA 183 PK | F86: 45000.11 | G86: =+G85+E86-F86 -> 515401.26 | H86: 19.198 | I86: COMBUSTIBLE | K86: AG 768 OI | L86: COMBUSTIBLE | M86: =SUM(H102) -> 506.465
A87: 46119 | B87: FA | C87: 98-1372 | D87: LVX 455 | F87: 45000.11 | G87: =+G86+E87-F87 -> 470401.15 | H87: 19.198 | I87: COMBUSTIBLE | K87: KJR 926 | L87: COMBUSTIBLE | M87: =SUM(H74+H96+H97+H104) -> 76.792
A88: 46119 | B88: FA | C88: 94-1428 | D88: WNO 918 | F88: 235603.89 | G88: =+G87+E88-F88 -> 234797.26 | H88: 105.937 | I88: COMBUSTIBLE | K88: HLW 156 | L88: COMBUSTIBLE | M88: =SUM(H75+H101+H107) -> 57.594
A89: 46119 | B89: FA | C89: 96-3334 | D89: AA 183 PK | F89: 121658.29 | G89: =+G88+E89-F89 -> 113138.97 | H89: 51.902 | I89: COMBUSTIBLE | K89: WNO 918 | L89: COMBUSTIBLE | M89: =SUM(H80+H88+H95) -> 273.1995
A90: 46119 | B90: FA | C90: 96-3346 | D90: PFG 964 | F90: 45000.11 | G90: =+G89+E90-F90 -> 68138.86 | H90: 19.198 | I90: COMBUSTIBLE | K90: HKQ 258 | L90: COMBUSTIBLE | M90: 0
A91: 46120 | B91: FA | C91: 96-3354 | D91: LVX 455 | F91: 45000.11 | G91: =+G90+E91-F91 -> 23138.75 | H91: 19.198 | I91: COMBUSTIBLE | K91: FTL 303 | L91: COMBUSTIBLE | M91: 0
A92: 46120 | B92: FA | C92: 92-7794 | D92: AE 919 JA | F92: 45000.11 | G92: =+G91+E92-F92 -> -21861.36 | H92: 19.198 | I92: COMBUSTIBLE | K92: AUTOELEVADOR | L92: COMBUSTIBLE | M92: =SUM(H93+H99+H117) -> 93.79
A93: 46120 | B93: FA | C93: 96-3361 | D93: MULITA | F93: 41833.44 | G93: =+G92+E93-F93 -> -63694.8 | H93: 18.81 | I93: COMBUSTIBLE | K93: HIELO | L93: 3KG Y 12KG | M93: 4 BOLSAS
A94: 46120 | B94: RE | C94: 50-0200 | D94: TRANSF | E94: 2000000 | G94: =+G93+E94-F94 -> 1936305.2 | I94: PAGO - SALDO A FAVOR | K94: LITROS SEMANAL | M94: =SUM(M75:M92) -> 1946.3864
A95: 46120 | B95: FA | C95: 98-1383 | D95: WNO 918 | F95: 164991.89 | G95: =+G94+E95-F95 -> 1771313.3 | H95: 74.187 | I95: COMBUSTIBLE
A96: 46120 | B96: FA | C96: 60-3723 | D96: KJR 926 | F96: 45000.11 | G96: =+G95+E96-F96 -> 1726313.2 | H96: 19.198 | I96: COMBUSTIBLE
A97: 46120 | B97: FA | C97: 92-7837 | D97: KJR 926 | F97: 45000.11 | G97: =+G96+E97-F97 -> 1681313.1 | H97: 19.198 | I97: COMBUSTIBLE
A98: 46121 | B98: FA | C98: 96-3402 | D98: PFG 964 | F98: 45000.11 | G98: =+G97+E98-F98 -> 1636313 | H98: 19.198 | I98: COMBUSTIBLE
A99: 46121 | B99: FA | C99: 92-7858 | D99: MULITA | F99: 124944.32 | G99: =+G98+E99-F99 -> 1511368.7 | H99: 56.18 | I99: COMBUSTIBLE
A100: 46121 | B100: FA | C100: 92-7864 | D100: AE 919 JA | F100: 45000.11 | G100: =+G99+E100-F100 -> 1466368.5 | H100: 19.198 | I100: COMBUSTIBLE
A101: 46121 | B101: FA | C101: 92-7865 | D101: HLW 156 | F101: 45000.11 | G101: =+G100+E101-F101 -> 1421368.4 | H101: 19.198 | I101: COMBUSTIBLE
A102: 46121 | B102: FA | C102: 94-1493 | D102: AG 768 OI | F102: 1187154 | G102: =+G101+E102-F102 -> 234214.48 | H102: 506.465 | I102: COMBUSTIBLE
A103: 46121 | B103: FA | C103: 92-7881 | D103: LVX 455 | F103: 45000 | G103: =+G102+E103-F103 -> 189214.48 | H103: 19.198 | I103: COMBUSTIBLE
A104: 46121 | B104: FA | C104: 92-7888 | D104: KJR 926 | F104: 45000.11 | G104: =+G103+E104-F104 -> 144214.37 | H104: 19.198 | I104: COMBUSTIBLE
...

Sheet MAYO.2026
A5: CTA.CTE MAYO - 2026 - CARGAS | K5: SEMANA DEL 1/5 AL 9/5
A6: CARGAS COMBUSTIBLE YPF | K6: RESUMEN CONSUMO
A7: FECHA | B7: FACTURA | C7: N° FA/COMP | D7: VEHICULO | E7: PAGOS | F7: CONSUMOS | G7: SALDO | H7: LITROS | I7: OBSEVACIONES | K7: RESUMEN | L7: CONSUMO | M7: LTS
A8: 46142 | C8: SALDO ANTERIOR | E8: 148710.66 | G8: =+E8-F8 -> 148710.66 | K8: AG 378 AV | L8: COMBUSTIBLE | M8: 0
A9: 46143 | B9: FA | C9: 96-4382 | D9: KEX 251 | F9: 60000.03 | G9: =+G8+E9-F9 -> 88710.63 | H9: 25.652 | I9: COMBUSTIBLE | K9: AG 337 MY | L9: COMBUSTIBLE | M9: 0
A10: 46143 | B10: FA | C10: 60-4644 | D10: LVX 455 | F10: 60000.03 | G10: =+G9+E10-F10 -> 28710.6 | H10: 25.652 | I10: COMBUSTIBLE | K10: AG 962 EW | L10: COMBUSTIBLE | M10: 0
A11: 46143 | B11: FA | C11: 60-4645 | D11: AF 728 AT | F11: 152725.01 | G11: =+G10+E11-F11 -> -124014.41 | H11: 65.295 | I11: COMBUSTIBLE | K11: AE 919 JA | L11: COMBUSTIBLE | M11: =SUM(H12+H18+H20+H31+H49+H50+H55) -> 196.283
A12: 46143 | B12: FA | C12: 60-4647 | D12: AE 919 JA | F12: 60000.03 | G12: =+G11+E12-F12 -> -184014.44 | H12: 25.652 | I12: COMBUSTIBLE | K12: AA 183 PK | L12: COMBUSTIBLE | M12: 0
A13: 46143 | B13: FA | C13: 60-4648 | D13: MULITA | F13: 90004.72 | G13: =+G12+E13-F13 -> -274019.16 | H13: 38.48 | I13: COMBUSTIBLE | K13: MOTO AMARILLA | L13: COMBUSTIBLE | M13: 0
A14: 46143 | B14: FA | C14: 92-8996 | D14: PFG 964 | F14: 60000.03 | G14: =+G13+E14-F14 -> -334019.19 | H14: 25.652 | I14: COMBUSTIBLE | K14: MOTO GRIS | L14: COMBUSTIBLE | M14: =SUM(H24) -> 11.677
A15: 46143 | B15: FA | C15: 96-4389 | D15: KJR 926 | F15: 60000.03 | G15: =+G14+E15-F15 -> -394019.22 | H15: 25.652 | I15: COMBUSTIBLE | K15: KEX 251 | L15: COMBUSTIBLE | M15: =SUM(H9+H21+H29+H44+H54+H60) -> 163.924
A16: 46144 | B16: FA | C16: 94-1988 | D16: AG 768 OI | F16: 805362.52 | G16: =+G15+E16-F16 -> -1199381.7 | H16: 343.423 | I16: COMBUSTIBLE | K16: AF 728 AT | L16: COMBUSTIBLE | M16: =SUM(H11) -> 65.295
A17: 46145 | B17: FA | C17: 92-9037 | D17: HLW 156 | F17: 59999.37 | G17: =+G16+E17-F17 -> -1259381.1 | H17: 25.597 | I17: COMBUSTIBLE | K17: PFG 964 | L17: COMBUSTIBLE | M17: =SUM(H14+H26+H45) -> 76.847
A18: 46145 | B18: FA | C18: 96-4414 | D18: AE 919 JA | F18: 40000.36 | G18: =+G17+E18-F18 -> -1299381.5 | H18: 17.065 | I18: COMBUSTIBLE | K18: LVX 455 | L18: COMBUSTIBLE | M18: =SUM(H10+H25+H30+H37+H47+H57+H67) -> 179.139
A19: 46146 | B19: RE | C19: 50-0241 | D19: TRANSF | E19: 1000000 | G19: =+G18+E19-F19 -> -299381.47 | I19: PAGO - SALDO PENDIENTE | K19: AG 958 JV | L19: COMBUSTIBLE | M19: =SUM(H33+H59) -> 260.322
A20: 46146 | B20: FA | C20: 96-4475 | D20: AE 919 JA | F20: 99999.9 | G20: =+G19+E20-F20 -> -399381.37 | H20: 42.735 | I20: COMBUSTIBLE | K20: AG 768 OI | L20: COMBUSTIBLE | M20: =SUM(H16+H42) -> 471.628
A21: 46146 | B21: FA | C21: 96-4479 | D21: KEX 251 | F21: 60000 | G21: =+G20+E21-F21 -> -459381.37 | H21: 25.641 | I21: COMBUSTIBLE | K21: KJR 926 | L21: COMBUSTIBLE | M21: =SUM(H15+H32+H34+H56+H64) -> 127.944
A22: 46146 | B22: RE | C22: 50-0242 | D22: TRANSF | E22: 1500000 | G22: =+G21+E22-F22 -> 1040618.6 | I22: PAGO - SALDO A FAVOR | K22: HLW 156 | L22: COMBUSTIBLE | M22: =SUM(H17+H28+H35+H66) -> 102.335
A23: 46146 | B23: FA | C23: 60-4808 | D23: MULITA | F23: 140400 | G23: =+G22+E23-F23 -> 900218.63 | H23: 60 | I23: COMBUSTIBLE | K23: WNO 918 | L23: COMBUSTIBLE | M23: =SUM(H61) -> 130.065
A24: 46146 | B24: FA | C24: 92-9096 | D24: MOTO GRIS | F24: 25595.98 | G24: =+G23+E24-F24 -> 874622.65 | H24: 11.677 | I24: COMBUSTIBLE | K24: HKQ 258 | L24: COMBUSTIBLE | M24: =SUM(H40) -> 186.49
A25: 46146 | B25: FA | C25: 92-9109 | D25: LVX 455 | F25: 59999.94 | G25: =+G24+E25-F25 -> 814622.71 | H25: 25.641 | I25: COMBUSTIBLE | K25: FTL 303 | L25: COMBUSTIBLE | M25: =SUM(H27+H46+H62) -> 467.729
A26: 46146 | B26: FA | C26: 92-9110 | D26: PFG 964 | F26: 59999.94 | G26: =+G25+E26-F26 -> 754622.77 | H26: 25.641 | I26: COMBUSTIBLE | K26: AUTOELEVADOR | L26: COMBUSTIBLE | M26: =SUM(H13+H23+H36+H41+H43+H48+H52+H58+H65) -> 275.228
A27: 46147 | B27: FA | C27: 94-2048 | D27: FTL 303 | F27: 299998.98 | G27: =+G26+E27-F27 -> 454623.79 | H27: 134.831 | I27: COMBUSTIBLE | K27: LITROS SEMANAL | M27: =SUM(M8:M26) -> 2714.906
A28: 46147 | B28: FA | C28: 92-9120 | D28: HLW 156 | F28: 59999.94 | G28: =+G27+E28-F28 -> 394623.85 | H28: 25.641 | I28: COMBUSTIBLE
A29: 46147 | B29: FA | C29: 96-4518 | D29: KEX 251 | F29: 59999.94 | G29: =+G28+E29-F29 -> 334623.91 | H29: 25.641 | I29: COMBUSTIBLE
A30: 46147 | B30: FA | C30: 96-4519 | D30: LVX 455 | F30: 59999.94 | G30: =+G29+E30-F30 -> 274623.97 | H30: 25.641 | I30: COMBUSTIBLE
A31: 46147 | B31: FA | C31: 96-4533 | D31: AE 919 JA | F31: 59999.94 | G31: =+G30+E31-F31 -> 214624.03 | H31: 25.641 | I31: COMBUSTIBLE
A32: 46147 | B32: FA | C32: 96-4535 | D32: KJR 926 | F32: 59999.94 | G32: =+G31+E32-F32 -> 154624.09 | H32: 25.641 | I32: COMBUSTIBLE
A33: 46147 | B33: FA | C33: 94-2068 | D33: AG 958 JV | F33: 299999.7 | G33: =+G32+E33-F33 -> -145375.61 | H33: 128.205 | I33: COMBUSTIBLE
A34: 46148 | B34: FA | C34: 96-4569 | D34: KJR 926 | F34: 59999.94 | G34: =+G33+E34-F34 -> -205375.55 | H34: 25.641 | I34: COMBUSTIBLE
A35: 46148 | B35: FA | C35: 60-4860 | D35: HLW 156 | F35: 59999.94 | G35: =+G34+E35-F35 -> -265375.49 | H35: 25.641 | I35: COMBUSTIBLE
A36: 46148 | B36: FA | C36: 96-4573 | D36: MULITA | F36: 40001.83 | G36: =+G35+E36-F36 -> -305377.32 | H36: 17.93 | I36: COMBUSTIBLE
A37: 46148 | B37: FA | C37: 96-4574 | D37: LVX 455 | F37: 59999.94 | G37: =+G36+E37-F37 -> -365377.26 | H37: 25.641 | I37: COMBUSTIBLE
A38: 46148 | B38: RE | C38: 50-0248 | D38: TRANSF MP | E38: 600000 | G38: =+G37+E38-F38 -> 234622.74 | I38: PAGO - SALDO A FAVOR
A39: 46148 | B39: RE | C39: 50-0248 | D39: TRANSF BCO | E39: 400000 | G39: =+G38+E39-F39 -> 634622.74 | I39: PAGO - SALDO A FAVOR
A40: 46148 | B40: FA | C40: 98-1634 | D40: HKQ 258 | F40: 416059.19 | G40: =G39-F40 -> 218563.55 | H40: 186.49 | I40: COMBUSTIBLE
A41: 46148 | B41: FA | C41: 98-1635 | D41: MULITA | F41: 40068.76 | G41: =+G40+E41-F41 -> 178494.79 | H41: 17.96 | I41: COMBUSTIBLE
A42: 46148 | B42: FA | C42: 98-1638 | D42: AG 768 OI | F42: 299999.7 | G42: =+G41+E42-F42 -> -121504.91 | H42: 128.205 | I42: COMBUSTIBLE
A43: 46148 | B43: FA | C43: 60-4881 | D43: MULITA | F43: 85028.58 | G43: =+G42+E43-F43 -> -206533.49 | H43: 36.337 | I43: COMBUSTIBLE
A44: 46148 | B44: FA | C44: 60-4894 | D44: KEX 251 | F44: 45000.54 | G44: =+G43+E44-F44 -> -251534.03 | H44: 19.231 | I44: COMBUSTIBLE
A45: 46149 | B45: FA | C45: 92-9215 | D45: PFG 964 | F45: 60000.79 | G45: =+G44+E45-F45 -> -311534.82 | H45: 25.554 | I45: COMBUSTIBLE
A46: 46149 | B46: FA | C46: 94-2105 | D46: FTL 303 | F46: 295735.91 | G46: =+G45+E46-F46 -> -607270.73 | H46: 132.617 | I46: COMBUSTIBLE
A47: 46149 | B47: FA | C47: 92-9220 | D47: LVX 455 | F47: 60000.79 | G47: =+G46+E47-F47 -> -667271.52 | H47: 25.554 | I47: COMBUSTIBLE
A48: 46149 | B48: FA | C48: 96-4627 | D48: MULITA | F48: 45050.46 | G48: =+G47+E48-F48 -> -712321.98 | H48: 20.202 | I48: COMBUSTIBLE
A49: 46149 | B49: FA | C49: 96-4631 | D49: AE 919 JA | F49: 60000.79 | G49: =+G48+E49-F49 -> -772322.77 | H49: 25.554 | I49: COMBUSTIBLE
A50: 46149 | B50: FA | C50: 60-4933 | D50: AE 919 JA | F50: 60000.79 | G50: =+G49+E50-F50 -> -832323.56 | H50: 25.554 | I50: COMBUSTIBLE
A51: 46149 | B51: RE | C51: 96-0002 | D51: LINK MP | F51: 18271 | G51: =+G50+E51-F51 -> -850594.56 | I51: CARGO DE MERCADO PAGO
A52: 46149 | B52: FA | C52: 96-4653 | D52: MULITA | F52: 42269.65 | G52: =+G51+E52-F52 -> -892864.21 | H52: 18.955 | I52: COMBUSTIBLE
A53: 46149 | B53: RE | C53: 50-0253 | D53: EFECT | E53: 1500000 | G53: =+G52+E53-F53 -> 607135.79 | I53: PAGO - SALDO A FAVOR
A54: 46149 | B54: FA | C54: 96-4676 | D54: KEX 251 | F54: 60000.79 | G54: =+G53+E54-F54 -> 547135 | H54: 25.554 | I54: COMBUSTIBLE
A55: 46149 | B55: FA | C55: 92-9245 | D55: AE 919 JA | F55: 80024.54 | G55: =+G54+E55-F55 -> 467110.46 | H55: 34.082 | I55: COMBUSTIBLE
A56: 46149 | B56: FA | C56: 96-4682 | D56: KJR 926 | F56: 60000.79 | G56: =+G55+E56-F56 -> 407109.67 | H56: 25.554 | I56: COMBUSTIBLE
A57: 46150 | B57: FA | C57: 92-9265 | D57: LVX 455 | F57: 60000.79 | G57: =+G56+E57-F57 -> 347108.88 | H57: 25.554 | I57: COMBUSTIBLE
A58: 46150 | B58: FA | C58: 92-9266 | D58: MULITA | F58: 40002.03 | G58: =+G57+E58-F58 -> 307106.85 | H58: 17.882 | I58: COMBUSTIBLE
A59: 46150 | B59: FA | C59: 98-1658 | D59: AG 958 JV | F59: 310210.72 | G59: =+G58+E59-F59 -> -3103.87 | H59: 132.117 | I59: COMBUSTIBLE
A60: 46150 | B60: FA | C60: 92-9287 | D60: KEX 251 | F60: 99097.34 | G60: =+G59+E60-F60 -> -102201.21 | H60: 42.205 | I60: COMBUSTIBLE
A61: 46150 | B61: FA | C61: 94-2157 | D61: WNO 918 | F61: 290955.41 | G61: =+G60+E61-F61 -> -393156.62 | H61: 130.065 | I61: COMBUSTIBLE
A62: 46150 | B62: FA | C62: 94-2162 | D62: FTL 303 | F62: 448028.68 | G62: =+G61+E62-F62 -> -841185.3 | H62: 200.281 | I62: COMBUSTIBLE
A63: 46151 | B63: RE | C63: 50-0257 | D63: TRANSF | E63: 2000000 | G63: =+G62+E63-F63 -> 1158814.7 | I63: PAGO - SALDO A FAVOR
A64: 46151 | B64: FA | C64: 92-9329 | D64: KJR 926 | F64: 59999.79 | G64: =+G63+E64-F64 -> 1098814.9 | H64: 25.456 | I64: COMBUSTIBLE
A65: 46151 | B65: FA | C65: 98-1677 | D65: MULITA | F65: 106169.75 | G65: =+G64+E65-F65 -> 992645.16 | H65: 47.482 | I65: COMBUSTIBLE
A66: 46151 | B66: FA | C66: 96-4756 | D66: HLW 156 | F66: 59999.79 | G66: =+G65+E66-F66 -> 932645.37 | H66: 25.456 | I66: COMBUSTIBLE
A67: 46151 | B67: FA | C67: 92-9349 | D67: LVX 455 | F67: 59999.79 | G67: =+G66+E67-F67 -> 872645.58 | H67: 25.456 | I67: COMBUSTIBLE
A68: TOTAL DE LITROS SEMANAL | H68: =SUM(H9:H67) -> 2714.906
A69: SEMANA DEL 1/5 AL 9/5 | K69: SEMANA DEL 10/5 AL 16/5
A70: 46152 | B70: FA | C70: 92-9364 | D70: AF 728 AT | F70: 195046.46 | G70: =+G67+E70-F70 -> 677599.12 | H70: 82.752 | I70: COMBUSTIBLE | K70: RESUMEN CONSUMO
A71: 46153 | B71: FA | C71: 96-4794 | D71: KEX 251 | F71: 59999.39 | G71: =+G70+E71-F71 -> 617599.73 | H71: 25.359 | I71: COMBUSTIBLE | K71: RESUMEN | L71: CONSUMO | M71: LTS
A72: 46153 | B72: FA | C72: 92-9429 | D72: LVX 455 | F72: 59999.39 | G72: =+G71+E72-F72 -> 557600.34 | H72: 25.359 | I72: COMBUSTIBLE | K72: AG 378 AV | L72: COMBUSTIBLE | M72: 0
A73: 46153 | B73: FA | C73: 92-9430 | D73: MULITA | F73: 84374.93 | G73: =+G72+E73-F73 -> 473225.41 | H73: 37.617 | I73: COMBUSTIBLE | K73: AG 337 MY | L73: COMBUSTIBLE | M73: =SUM(H102) -> 74.19
A74: 46153 | B74: FA | C74: 96-4822 | D74: AE 919 JA | F74: 59999.39 | G74: =+G73+E74-F74 -> 413226.02 | H74: 25.359 | I74: COMBUSTIBLE | K74: AG 962 EW | L74: COMBUSTIBLE | M74: 0
A75: 46153 | B75: FA | C75: 94-2212 | D75: HKQ 258 | F75: 828348.43 | G75: =+G74+E75-F75 -> -415122.41 | H75: 350.105 | I75: COMBUSTIBLE | K75: AE 919 JA | L75: COMBUSTIBLE | M75: =SUM(H74+H78+H84+H95+H105+H107) -> 151.698
A76: 46153 | B76: FA | C76: 92-9452 | D76: MULITA | F76: 94668.39 | G76: =+G75+E76-F76 -> -509790.8 | H76: 40.012 | I76: COMBUSTIBLE | K76: AA 183 PK | L76: COMBUSTIBLE | M76: 0
A77: 46153 | B77: RE | C77: 50-0260 | D77: TRANSF | E77: 2000000 | G77: =+G76+E77-F77 -> 1490209.2 | I77: PAGO - SALDO A FAVOR | K77: MOTO AMARILLA | L77: COMBUSTIBLE | M77: =SUM(H97) -> 10.192
A78: 46153 | B78: FA | C78: 60-5088 | D78: AE 919 JA | F78: 59999.39 | G78: =+G77+E78-F78 -> 1430209.8 | H78: 25.359 | I78: COMBUSTIBLE | K78: MOTO GRIS | L78: COMBUSTIBLE | M78: 0
A79: 46153 | B79: FA | C79: 94-2218 | D79: AG 768 OI | F79: 1310366.5 | G79: =+G78+E79-F79 -> 119843.3 | H79: 553.832 | I79: COMBUSTIBLE | K79: KEX 251 | L79: COMBUSTIBLE | M79: =SUM(H71+H81+H100+H110) -> 100.938
A80: 46154 | B80: FA | C80: 92-9473 | D80: LVX 455 | F80: 59999.39 | G80: =+G79+E80-F80 -> 59843.91 | H80: 25.359 | I80: COMBUSTIBLE | K80: AF 728 AT | L80: COMBUSTIBLE | M80: =SUM(H70+H90) -> 141.859
A81: 46154 | B81: FA | C81: 96-4871 | D81: KEX 251 | F81: 59999.39 | G81: =+G80+E81-F81 -> -155.48 | H81: 25.359 | I81: COMBUSTIBLE | K81: PFG 964 | L81: COMBUSTIBLE | M81: =SUM(H99) -> 25.105
A82: 46154 | B82: FA | C82: 94-2231 | D82: HKQ 258 | F82: 790260.56 | G82: =+G81+E82-F82 -> -790416.04 | H82: 334.007 | I82: COMBUSTIBLE | K82: LVX 455 | L82: COMBUSTIBLE | M82: =SUM(H72+H80+H87+H91+H101) -> 112.707
A83: 46154 | B83: FA | C83: 92-9482 | D83: KJR 926 | F83: 59999.39 | G83: =+G82+E83-F83 -> -850415.43 | H83: 25.359 | I83: COMBUSTIBLE | K83: AG 958 JV | L83: COMBUSTIBLE | M83: =SUM(H106) -> 185.695
A84: 46154 | B84: FA | C84: 96-4880 | D84: AE 919 JA | F84: 59999.39 | G84: =+G83+E84-F84 -> -910414.82 | H84: 25.359 | I84: COMBUSTIBLE | K84: AG 768 OI | L84: COMBUSTIBLE | M84: =SUM(H79+H88+H98) -> 1150.053
A85: 46154 | B85: FA | C85: 94-2244 | D85: WNO 918 | F85: 99999.67 | G85: =+G84+E85-F85 -> -1010414.5 | H85: 44.583 | I85: COMBUSTIBLE | K85: KJR 926 | L85: COMBUSTIBLE | M85: =SUM(H83+H108) -> 50.474
A86: 46154 | B86: RE | C86: 50-0263 | D86: TRANSF | E86: 900000 | G86: =+G85+E86-F86 -> -110414.49 | I86: PAGO - SALDO PENDIENTE | K86: HLW 156 | L86: COMBUSTIBLE | M86: =SUM(H103) -> 25.147
A87: 46154 | B87: FA | C87: 92-9519 | D87: LVX 455 | F87: 23962.72 | G87: =+G86+E87-F87 -> -134377.21 | H87: 11.515 | I87: COMBUSTIBLE | K87: WNO 918 | L87: COMBUSTIBLE | M87: =SUM(H85) -> 44.583
A88: 46154 | B88: FA | C88: 60-5131 | D88: AG 768 OI | F88: 299999.34 | G88: =+G87+E88-F88 -> -434376.55 | H88: 126.796 | I88: COMBUSTIBLE | K88: HKQ 258 | L88: COMBUSTIBLE | M88: =SUM(H75+H82+H92+H94) -> 1034.466
A89: 46155 | B89: FA | C89: 94-2268 | D89: MULITA | F89: 82681.47 | G89: =+G88+E89-F89 -> -517058.02 | H89: 36.862 | I89: COMBUSTIBLE | K89: FTL 303 | L89: COMBUSTIBLE | M89: 0
A90: 46155 | B90: FA | C90: 92-9541 | D90: AF 728 AT | F90: 140024.48 | G90: =+G89+E90-F90 -> -657082.5 | H90: 59.107 | I90: COMBUSTIBLE | K90: AUTOELEVADOR | L90: COMBUSTIBLE | M90: =SUM(H73+H76+H89+H109) -> 152.726
A91: 46155 | B91: FA | C91: 92-4543 | D91: LVX 455 | F91: 59999.66 | G91: =+G90+E91-F91 -> -717082.16 | H91: 25.327 | I91: COMBUSTIBLE | K91: LITROS SEMANAL | M91: =SUM(M72:M90) -> 3259.833
A92: 46155 | B92: FA | C92: 98-1700 | D92: HKQ 258 | F92: 479999.76 | G92: =+G91+E92-F92 -> -1197081.9 | H92: 213.999 | I92: COMBUSTIBLE
A93: 46155 | B93: RE | C93: 50-0265 | D93: TRANSF | E93: 1500000 | G93: =+G92+E93-F93 -> 302918.08 | I93: PAGO - SALDO A FAVOR
A94: 46155 | B94: FA | C94: 94-2288 | D94: HKQ 258 | F94: 323025 | G94: =+G93+E94-F94 -> -20106.92 | H94: 136.355 | I94: COMBUSTIBLE
A95: 46155 | B95: FA | C95: 96-4955 | D95: AE 919 JA | F95: 59999.66 | G95: =+G94+E95-F95 -> -80106.58 | H95: 25.327 | I95: COMBUSTIBLE
A96: 46156 | B96: RE | C96: 50-0266 | D96: TRANSF | E96: 1500000 | G96: =+G95+E96-F96 -> 1419893.4 | I96: PAGO - SALDO A FAVOR
A97: 46156 | B97: FA | C97: 96-4985 | D97: MOTO AMARILLA | F97: 22901.42 | G97: =+G96+E97-F97 -> 1396992 | H97: 10.192 | I97: COMBUSTIBLE
A98: 46126 | B98: FA | C98: 94-2320 | D98: AG 768 OI | F98: 1121925.8 | G98: =+G97+E98-F98 -> 275066.25 | H98: 469.425 | I98: COMBUSTIBLE
A99: 46156 | B99: FA | C99: 96-4998 | D99: PFG 964 | F99: 60000.95 | G99: =+G98+E99-F99 -> 215065.3 | H99: 25.105 | I99: COMBUSTIBLE
A100: 46156 | B100: FA | C100: 96-5000 | D100: KEX 251 | F100: 60000.95 | G100: =+G99+E100-F100 -> 155064.35 | H100: 25.105 | I100: COMBUSTIBLE
A101: 46157 | B101: FA | C101: 92-9644 | D101: LVX 455 | F101: 60000.74 | G101: =+G100+E101-F101 -> 95063.61 | H101: 25.147 | I101: COMBUSTIBLE
A102: 46157 | B102: FA | C102: 92-9652 | D102: AG 337 MY | F102: 177017.34 | G102: =+G101+E102-F102 -> -81953.73 | H102: 74.19 | I102: COMBUSTIBLE
A103: 46157 | B103: FA | C103: 60-5246 | D103: HLW 156 | F103: 60000.74 | G103: =+G102+E103-F103 -> -141954.47 | H103: 25.147 | I103: COMBUSTIBLE
A104: 46157 | B104: RE | C104: 50-0272 | D104: TRANSF | E104: 1500000 | G104: =+G103+E104-F104 -> 1358045.5 | I104: PAGO - SALDO A FAVOR
...

Sheet JUNIO.2026
A5: CTA.CTE JUNIO - 2026 - CARGAS | K5: SEMANA DEL 1/6 AL 6/6
A6: CARGAS COMBUSTIBLE YPF | K6: RESUMEN CONSUMO
A7: FECHA | B7: TIPO | C7: N° FA/COMP | D7: VEHICULO | E7: PAGOS | F7: CONSUMOS | G7: SALDO | H7: LITROS | I7: OBSEVACIONES | K7: RESUMEN | L7: CONSUMO | M7: LTS
A8: 46173 | C8: SALDO ANTERIOR | E8: 294999.3 | G8: =+E8-F8 -> 294999.3 | K8: AG 378 AV | L8: COMBUSTIBLE | M8: 0
A9: 46174 | B9: FA | C9: 98-1867 | D9: FTL 303 | F9: 542358.78 | G9: =+G8+E9-F9 -> -247359.48 | H9: 239.452 | I9: COMBUSTIBLE | K9: AG 337 MY | L9: COMBUSTIBLE | M9: =SUM(H28) -> 72.332
A10: 46174 | B10: FA | C10: 96-5801 | D10: KEX 251 | F10: 60000.95 | G10: =+G9+E10-F10 -> -307360.43 | H10: 25.105 | I10: COMBUSTIBLE | K10: AG 962 EW | L10: COMBUSTIBLE | M10: 0
A11: 46174 | B11: FA | C11: 92-0451 | D11: PFG 964 | F11: 60000.95 | G11: =+G10+E11-F11 -> -367361.38 | H11: 25.105 | I11: COMBUSTIBLE | K11: AE 919 JA | L11: COMBUSTIBLE | M11: =SUM(H16+H19+H29+H43) -> 100.283
A12: 46174 | B12: FA | C12: 96-5804 | D12: KJR 926 | F12: 60000.95 | G12: =+G11+E12-F12 -> -427362.33 | H12: 25.105 | I12: COMBUSTIBLE | K12: AA 183 PK | L12: COMBUSTIBLE | M12: =SUM(H14+H24+H32+H46) -> 100.22
A13: 46174 | B13: FA | C13: 96-5805 | D13: MULITA | F13: 42842.48 | G13: =+G12+E13-F13 -> -470204.81 | H13: 18.915 | I13: COMBUSTIBLE | K13: MOTO AMARILLA | L13: COMBUSTIBLE | M13: 0
A14: 46174 | B14: FA | C14: 96-5806 | D14: AA 183 PK | F14: 60000.95 | G14: =+G13+E14-F14 -> -530205.76 | H14: 25.105 | I14: COMBUSTIBLE | K14: MOTO GRIS | L14: COMBUSTIBLE | M14: 0
A15: 46174 | B15: FA | C15: 96-5807 | D15: HLW 156 | F15: 60000.95 | G15: =+G14+E15-F15 -> -590206.71 | H15: 25.105 | I15: COMBUSTIBLE | K15: KEX 251 | L15: COMBUSTIBLE | M15: =SUM(H10+H22+H33) -> 75.21
A16: 46174 | B16: FA | C16: 96-5819 | D16: AE 919 JA | F16: 60000.95 | G16: =+G15+E16-F16 -> -650207.66 | H16: 25.105 | I16: COMBUSTIBLE | K16: AF 728 AT | L16: COMBUSTIBLE | M16: 0
A17: 46174 | B17: FA | C17: 92-0475 | D17: LVX 455 | F17: 64111.75 | G17: =+G16+E17-F17 -> -714319.41 | H17: 26.825 | I17: COMBUSTIBLE | K17: PFG 964 | L17: COMBUSTIBLE | M17: =SUM(H11) -> 25.105
A18: 46175 | B18: RE | C18: 50-0293 | D18: TRANSF | E18: 1000000 | G18: =+G17+E18-F18 -> 285680.59 | I18: PAGO - SALDO A FAVOR | K18: LVX 455 | L18: COMBUSTIBLE | M18: =SUM(H17+H35+H41+H44) -> 95.653
A19: 46175 | B19: FA | C19: 60-6002 | D19: AE 919 JA | F19: 59999.31 | G19: =+G18+E19-F19 -> 225681.28 | H19: 25.031 | I19: COMBUSTIBLE | K19: AG 958 JV | L19: COMBUSTIBLE | M19: =SUM(H21+H38) -> 271.022
A20: 46175 | B20: FA | C20: 96-5868 | D20: MULITA | F20: 77713.76 | G20: =+G19+E20-F20 -> 147967.52 | H20: 34.205 | I20: COMBUSTIBLE | K20: AG 768 OI | L20: COMBUSTIBLE | M20: =SUM(H26) -> 131.271
A21: 46175 | B21: FA | C21: 94-2729 | D21: AG 958 JV | F21: 308781.54 | G21: =+G20+E21-F21 -> -160814.02 | H21: 128.82 | I21: COMBUSTIBLE | K21: KJR 926 | L21: COMBUSTIBLE | M21: =SUM(H12+H30+H39) -> 75.252
A22: 46176 | B22: FA | C22: 92-0565 | D22: KEX 251 | F22: 60000.93 | G22: =+G21+E22-F22 -> -220814.95 | H22: 25.084 | I22: COMBUSTIBLE | K22: HLW 156 | L22: COMBUSTIBLE | M22: =SUM(H15+H37+H45) -> 75.136
A23: 46176 | B23: FA | C23: 96-5917 | D23: MULITA | F23: 42876.54 | G23: =+G22+E23-F23 -> -263691.49 | H23: 18.905 | I23: COMBUSTIBLE | K23: WNO 918 | L23: COMBUSTIBLE | M23: =SUM(H25) -> 159.457
A24: 46176 | B24: FA | C24: 96-5918 | D24: AA 183 PK | F24: 60000.93 | G24: =+G23+E24-F24 -> -323692.42 | H24: 25.084 | I24: COMBUSTIBLE | K24: HKQ 258 | L24: COMBUSTIBLE | M24: =SUM(H31) -> 208.507
A25: 46176 | B25: FA | C25: 98-1892 | D25: WNO 918 | F25: 361648.48 | G25: =+G24+E25-F25 -> -685340.9 | H25: 159.457 | I25: COMBUSTIBLE | K25: FTL 303 | L25: COMBUSTIBLE | M25: =SUM(H9) -> 239.452
A26: 46176 | B26: FA | C26: 94-2745 | D26: AG 768 OI | F26: 314000.23 | G26: =+G25+E26-F26 -> -999341.13 | H26: 131.271 | I26: COMBUSTIBLE | K26: AUTOELEVADOR | L26: COMBUSTIBLE | M26: =SUM(H13+H20+H23+H34+H36+H40) -> 166.304
A27: 46176 | B27: RE | C27: 50-0297 | D27: TRANSF | E27: 1500000 | G27: =+G26+E27-F27 -> 500658.87 | I27: PAGO - SALDO A FAVOR | K27: LITROS SEMANAL | M27: =SUM(M8:M26) -> 1795.204
A28: 46176 | B28: FA | C28: 92-0593 | D28: AG 337 MY | F28: 173018.14 | G28: =+G27+E28-F28 -> 327640.73 | H28: 72.332 | I28: COMBUSTIBLE
A29: 46176 | B29: FA | C29: 60-6083 | D29: AE 919 JA | F29: 60000.93 | G29: =+G28+E29-F29 -> 267639.8 | H29: 25.084 | I29: COMBUSTIBLE
A30: 46176 | B30: FA | C30: 92-0608 | D30: KJR 926 | F30: 60000.93 | G30: =+G29+E30-F30 -> 207638.87 | H30: 25.084 | I30: COMBUSTIBLE
A31: 46177 | B31: FA | C31: 94-2772 | D31: HKQ 258 | F31: 499999.79 | G31: =+G30+E31-F31 -> -292360.92 | H31: 208.507 | I31: COMBUSTIBLE
A32: 46177 | B32: FA | C32: 92-0622 | D32: AA 183 PK | F32: 60000.36 | G32: =+G31+E32-F32 -> -352361.28 | H32: 25.021 | I32: COMBUSTIBLE
A33: 46177 | B33: FA | C33: 92-0623 | D33: KEX 251 | F33: 60000.36 | G33: =+G32+E33-F33 -> -412361.64 | H33: 25.021 | I33: COMBUSTIBLE
A34: 46177 | B34: FA | C34: 92-0624 | D34: MULITA | F34: 85292.68 | G34: =+G33+E34-F34 -> -497654.32 | H34: 37.607 | I34: COMBUSTIBLE
A35: 46177 | B35: FA | C35: 98-1898 | D35: LVX 455 | F35: 60000.36 | G35: =+G34+E35-F35 -> -557654.68 | H35: 25.021 | I35: COMBUSTIBLE
A36: 46177 | B36: FA | C36: 98-1899 | D36: MULITA | F36: 40352.26 | G36: =+G35+E36-F36 -> -598006.94 | H36: 17.792 | I36: COMBUSTIBLE
A37: 46177 | B37: FA | C37: 96-5965 | D37: HLW 156 | F37: 60000.36 | G37: =+G36+E37-F37 -> -658007.3 | H37: 25.021 | I37: COMBUSTIBLE
A38: 46177 | B38: FA | C38: 94-2777 | D38: AG 958 JV | F38: 341000.4 | G38: =+G37+E38-F38 -> -999007.7 | H38: 142.202 | I38: COMBUSTIBLE
A39: 46178 | B39: FA | C39: 96-6035 | D39: KJR 926 | F39: 60000.82 | G39: =+G38+E39-F39 -> -1059008.5 | H39: 25.063 | I39: COMBUSTIBLE
... A41: 46178 | B41: FA | C41: 96-6037 | D41: LVX 455 | F41: 45000.02 | G41: =+G40+E41-F41 -> -1192032.9 | H41: 18.797 | I41: COMBUSTIBLE
A42: 46178 | B42: RE | C42: 50-0299 | D42: TRANSF | E42: 2000000 | G42: =+G41+E42-F42 -> 807967.14 | I42: PAGO - SALDO A FAVOR
A43: 46178 | B43: FA | C43: 60-6173 | D43: AE 919 JA | F43: 60000.82 | G43: =+G42+E43-F43 -> 747966.32 | H43: 25.063 | I43: COMBUSTIBLE
A44: 46179 | B44: FA | C44: 96-6097 | D44: LVX 455 | F44: 59998.99 | G44: =+G43+E44-F44 -> 687967.33 | H44: 25.01 | I44: COMBUSTIBLE
A45: 46179 | B45: FA | C45: 92-0745 | D45: HLW 156 | F45: 59998.99 | G45: =+G44+E45-F45 -> 627968.34 | H45: 25.01 | I45: COMBUSTIBLE
A46: 46179 | B46: FA | C46: 92-0763 | D46: AA 183 PK | F46: 59998.99 | G46: =+G45+E46-F46 -> 567969.35 | H46: 25.01 | I46: COMBUSTIBLE
A47: TOTAL DE LITROS SEMANAL | H47: =SUM(H9:H46) -> 1795.204
A48: SEMANA DEL 1/6 AL 6/6 | K48: SEMANA DEL 7/6 AL 13/6
A49: 46181 | B49: FA | C49: 96-6157 | D49: AG 962 EW | F49: 100007.27 | G49: =+G46+E49-F49 -> 467962.08 | H49: 41.635 | I49: COMBUSTIBLE | K49: RESUMEN CONSUMO
A50: 46181 | B50: FA | C50: 92-0811 | D50: KJR 926 | F50: 59999.56 | G50: =+G49+E50-F50 -> 407962.52 | H50: 24.979 | I50: COMBUSTIBLE | K50: RESUMEN | L50: CONSUMO | M50: LTS
A51: 46181 | B51: FA | C51: 96-6176 | D51: AE 919 JA | F51: 59999.56 | G51: =+G50+E51-F51 -> 347962.96 | H51: 24.979 | I51: COMBUSTIBLE | K51: AG 378 AV | L51: COMBUSTIBLE | M51: 0
A52: 46181 | B52: FA | C52: 92-0833 | D52: AG 337 MY | F52: 173513.27 | G52: =+G51+E52-F52 -> 174449.69 | H52: 72.237 | I52: COMBUSTIBLE | K52: AG 337 MY | L52: COMBUSTIBLE | M52: =SUM(H52+H70) -> 117.722
A53: 46182 | B53: FA | C53: 96-6218 | D53: LVX 455 | F53: 60000.36 | G53: =+G52+E53-F53 -> 114449.33 | H53: 25.021 | I53: COMBUSTIBLE | K53: AG 962 EW | L53: COMBUSTIBLE | M53: =SUM(H49+H74) -> 81.637
A54: 46182 | B54: FA | C54: 96-6220 | D54: KEX 251 | F54: 60000.36 | G54: =+G53+E54-F54 -> 54448.97 | H54: 25.021 | I54: COMBUSTIBLE | K54: AE 919 JA | L54: COMBUSTIBLE | M54: =SUM(H51+H57+H60+H68) -> 99.98
A55: 46182 | B55: FA | C55: 96-6221 | D55: MULITA | F55: 39415.53 | G55: =+G54+E55-F55 -> 15033.44 | H55: 17.402 | I55: COMBUSTIBLE | K55: AA 183 PK | L55: COMBUSTIBLE | M55: 0
A56: 46182 | B56: FA | C56: 92-0861 | D56: PFG 964 | F56: 60000.36 | G56: =+G55+E56-F56 -> -44966.92 | H56: 25.021 | I56: COMBUSTIBLE | K56: MOTO AMARILLA | L56: COMBUSTIBLE | M56: 0
A57: 46182 | B57: FA | C57: 92-0875 | D57: AE 919 JA | F57: 60000.36 | G57: =+G56+E57-F57 -> -104967.28 | H57: 25.021 | I57: COMBUSTIBLE | K57: MOTO GRIS | L57: COMBUSTIBLE | M57: 0
A58: 46182 | B58: FA | C58: 60-6304 | D58: KJR 926 | F58: 60000.36 | G58: =+G57+E58-F58 -> -164967.64 | H58: 25.021 | I58: COMBUSTIBLE | K58: KEX 251 | L58: COMBUSTIBLE | M58: =SUM(H54+H62) -> 50.011
A59: 46183 | B59: FA | C59: 96-6267 | D59: MULITA | F59: 88017.9 | G59: =+G58+E59-F59 -> -252985.54 | H59: 38.86 | I59: COMBUSTIBLE | K59: AF 728 AT | L59: COMBUSTIBLE | M59: 0
A60: 46183 | B60: FA | C60: 96-6270 | D60: AE 919 JA | F60: 60000.99 | G60: =+G59+E60-F60 -> -312986.53 | H60: 24.99 | I60: COMBUSTIBLE | K60: PFG 964 | L60: COMBUSTIBLE | M60: =SUM(H56) -> 25.021
A61: 46183 | B61: FA | C61: 92-0916 | D61: LVX 455 | F61: 60000.99 | G61: =+G60+E61-F61 -> -372987.52 | H61: 24.99 | I61: COMBUSTIBLE | K61: LVX 455 | L61: COMBUSTIBLE | M61: =SUM(H53+H61+H71+H75) -> 100.042
A62: 46183 | B62: FA | C62: 92-0937 | D62: KEX 251 | F62: 60000.99 | G62: =+G61+E62-F62 -> -432988.51 | H62: 24.99 | I62: COMBUSTIBLE | K62: AG 958 JV | L62: COMBUSTIBLE | M62: =SUM(H67) -> 158.377
A63: 46184 | B63: FA | C63: 60-6361 | D63: MULITA | F63: 48328.3 | G63: =+G62+E63-F63 -> -481316.81 | H63: 21.29 | I63: COMBUSTIBLE | K63: AG 768 OI | L63: COMBUSTIBLE | M63: 0
A64: 46184 | B64: RE | C64: 50-0307 | D64: TRANSF | E64: 1500000 | G64: =+G63+E64-F64 -> 1018683.2 | I64: PAGO - SALDO A FAVOR | K64: KJR 926 | L64: COMBUSTIBLE | M64: =SUM(H50+H58+H65) -> 74.99
A65: 46184 | B65: FA | C65: 92-0967 | D65: KJR 926 | F65: 60000.99 | G65: =+G64+E65-F65 -> 958682.2 | H65: 24.99 | I65: COMBUSTIBLE | K65: HLW 156 | L65: COMBUSTIBLE | M65: 0
A66: 46184 | B66: FA | C66: 96-6346 | D66: MULITA | F66: 46006.09 | G66: =+G65+E66-F66 -> 912676.11 | H66: 20.267 | I66: COMBUSTIBLE | K66: WNO 918 | L66: COMBUSTIBLE | M66: 0
A67: 46185 | B67: FA | C67: 98-1966 | D67: AG 958 JV | F67: 380263.18 | G67: =+G66+E67-F67 -> 532412.93 | H67: 158.377 | I67: COMBUSTIBLE | K67: HKQ 258 | L67: COMBUSTIBLE | M67: 0
A68: 46185 | B68: FA | C68: 92-1005 | D68: AE 919 JA | F68: 60000.99 | G68: =+G67+E68-F68 -> 472411.94 | H68: 24.99 | I68: COMBUSTIBLE | K68: FTL 303 | L68: COMBUSTIBLE | M68: 0
A69: 46185 | B69: RE | C69: 50-0312 | D69: TRANSF | E69: 1000000 | G69: =+G68+E69-F69 -> 1472411.9 | I69: PAGO - SALDO A FAVOR | K69: AUTOELEVADOR | L69: COMBUSTIBLE | M69: =SUM(H55+H59+H63+H66+H72+H73) -> 137.823
A70: 46185 | B70: FA | C70: 92-1034 | D70: AG 337 MY | F70: 109027.55 | G70: =+G69+E70-F70 -> 1363384.4 | H70: 45.485 | I70: COMBUSTIBLE | K70: LITROS SEMANAL | M70: =SUM(M51:M69) -> 845.603
A71: 46185 | B71: FA | C71: 92-1041 | D71: LVX 455 | F71: 59999.31 | G71: =+G70+E71-F71 -> 1303385.1 | H71: 25.031 | I71: COMBUSTIBLE
A72: 46186 | B72: FA | C72: 92-1056 | D72: MULITA | F72: 45324.53 | G72: =+G71+E72-F72 -> 1258060.6 | H72: 20.002 | I72: COMBUSTIBLE
A73: 46186 | B73: FA | C73: 60-6433 | D73: MULITA | F73: 45324.53 | G73: =+G72+E73-F73 -> 1212736 | H73: 20.002 | I73: COMBUSTIBLE
A74: 46186 | B74: FA | C74: 92-1062 | D74: AG 962 EW | F74: 96004.8 | G74: =+G73+E74-F74 -> 1116731.2 | H74: 40.002 | I74: COMBUSTIBLE
A75: 46186 | B75: FA | C75: 98-1979 | D75: LVX 455 | F75: 60000 | G75: =+G74+E75-F75 -> 1056731.2 | H75: 25 | I75: COMBUSTIBLE
A76: TOTAL DE LITROS SEMANAL | H76: =SUM(H49:H75) -> 845.603
A77: SEMANA DEL 7/6 AL 13/6 | K77: SEMANA DEL 14/6 AL 20/6
A78: 46187 | B78: FA | C78: 92-1070 | D78: KJR 926 | F78: 60000 | G78: =+G75+E78-F78 -> 996731.22 | H78: 25 | I78: COMBUSTIBLE | K78: RESUMEN CONSUMO
A79: 46189 | B79: FA | C79: 92-1107 | D79: KJR 926 | F79: 59999.31 | G79: =+G78+E79-F79 -> 936731.91 | H79: 25.031 | I79: COMBUSTIBLE | K79: RESUMEN | L79: CONSUMO | M79: LTS
A80: 46189 | B80: FA | C80: 94-3011 | D80: AG 958 JV | F80: 407849.55 | G80: =+G79+E80-F80 -> 528882.36 | H80: 170.15 | I80: COMBUSTIBLE | K80: AG 378 AV | L80: COMBUSTIBLE | M80: 0
A81: 46189 | B81: FA | C81: 92-1126 | D81: AE 919 JA | F81: 27007.43 | G81: =+G80+E81-F81 -> 501874.93 | H81: 11.982 | I81: COMBUSTIBLE | K81: AG 337 MY | L81: COMBUSTIBLE | M81: =SUM(H83) -> 59.34
A82: 46189 | B82: FA | C82: 96-6597 | D82: MULITA | F82: 86158.07 | G82: =+G81+E82-F82 -> 415716.86 | H82: 37.905 | I82: COMBUSTIBLE | K82: AG 962 EW | L82: COMBUSTIBLE | M82: =SUM(H89) -> 38.385
A83: 46189 | B83: FA | C83: 92-1128 | D83: AG 337 MY | F83: 142237.98 | G83: =+G82+E83-F83 -> 273478.88 | H83: 59.34 | I83: COMBUSTIBLE | K83: AE 919 JA | L83: COMBUSTIBLE | M83: =SUM(H81) -> 11.982
A84: 46189 | B84: FA | C84: 60-6554 | D84: PFG 964 | F84: 59999.31 | G84: =+G83+E84-F84 -> 213479.57 | H84: 25.031 | I84: COMBUSTIBLE | K84: MOTO AMARILLA | L84: COMBUSTIBLE | M84: 0
A85: 46190 | B85: FA | C85: 96-6641 | D85: LVX 455 | F85: 59999.31 | G85: =+G84+E85-F85 -> 153480.26 | H85: 25.031 | I85: COMBUSTIBLE | K85: MOTO GRIS | L85: COMBUSTIBLE | M85: =SUM(H87) -> 9.955
A86: 46190 | B86: FA | C86: 96-6660 | D86: HLW 156 | F86: 59999.31 | G86: =+G85+E86-F86 -> 93480.95 | H86: 25.031 | I86: COMBUSTIBLE | K86: PFG 964 | L86: COMBUSTIBLE | M86: =SUM(H84+H90) -> 50.062
A87: 46191 | B87: FA | C87: 96-6696 | D87: MOTO GRIS | F87: 22388.8 | G87: =+G86+E87-F87 -> 71092.15 | H87: 9.955 | I87: COMBUSTIBLE | K87: LVX 455 | L87: COMBUSTIBLE | M87: =SUM(H85+H88+H91+H93) -> 100.052
A88: 46191 | B88: FA | C88: 60-6626 | D88: LVX 455 | F88: 60000.99 | G88: =+G87+E88-F88 -> 11091.16 | H88: 24.99 | I88: COMBUSTIBLE | K88: AG 958 JV | L88: COMBUSTIBLE | M88: =SUM(H80) -> 170.15
A89: 46192 | B89: FA | C89: 96-6755 | D89: AG 962 EW | F89: 92008.85 | G89: =+G88+E89-F89 -> -80917.69 | H89: 38.385 | I89: COMBUSTIBLE | K89: AG 768 OI | L89: COMBUSTIBLE | M89: 0
A90: 46192 | B90: FA | C90: 96-6779 | D90: PFG 964 | F90: 59999.31 | G90: =+G89+E90-F90 -> -140917 | H90: 25.031 | I90: COMBUSTIBLE | K90: KJR 926 | L90: COMBUSTIBLE | M90: =SUM(H78+H79) -> 50.031
A91: 46192 | B91: FA | C91: 96-6780 | D91: LVX 455 | F91: 59999.31 | G91: =+G90+E91-F91 -> -200916.31 | H91: 25.031 | I91: COMBUSTIBLE | K91: HLW 156 | L91: COMBUSTIBLE | M91: =SUM(H86) -> 25.031
A92: 46193 | B92: RE | C92: 50-0322 | D92: TRANSF | E92: 1000000 | G92: =+G91+E92-F92 -> 799083.69 | I92: PAGO - SALDO A FAVOR | K92: WNO 918 | L92: COMBUSTIBLE | M92: 0
A93: 46193 | B93: FA | C93: 92-1343 | D93: LVX 455 | F93: 60000 | G93: =+G92+E93-F93 -> 739083.69 | H93: 25 | I93: COMBUSTIBLE | K93: AUTOELEVADOR | L93: COMBUSTIBLE | M93: =SUM(H82) -> 37.905
A94: TOTAL DE LITROS SEMANAL | H94: =SUM(H78:H93) -> 552.893 | K94: LITROS SEMANAL | M94: =SUM(M80:M93) -> 552.893
A95: SEMANA DEL 14/6 AL 20/6
A96: 46195 | B96: FA | C96: 60-6757 | D96: MULITA | F96: 82475.81 | G96: =+G93+E96-F96 -> 656607.88 | H96: 36.285 | I96: COMBUSTIBLE | K96: SEMANA DEL 21/6 AL 30/6
A97: 46196 | B97: FA | C97: 96-6905 | D97: MULITA | F97: 81021 | G97: =+G96+E97-F97 -> 575586.88 | H97: 35.645 | I97: COMBUSTIBLE | K97: RESUMEN CONSUMO
A98: 46196 | B98: FA | C98: 60-6809 | D98: MULITA | F98: 40000 | G98: =+G97+E98-F98 -> 535586.88 | H98: 17.5979 | I98: COMBUSTIBLE | K98: RESUMEN | L98: CONSUMO | M98: LTS
A99: 46197 | B99: FA | C99: 98-2041 | D99: MULITA | F99: 112853.25 | G99: =+G98+E99-F99 -> 422733.63 | H99: 49.737 | I99: COMBUSTIBLE | K99: AG 378 AV | L99: COMBUSTIBLE | M99: 0
A100: 46197 | B100: FA | C100: 96-6950 | D100: LVX 455 | F100: 59999.31 | G100: =+G99+E100-F100 -> 362734.32 | H100: 25.031 | I100: COMBUSTIBLE | K100: AG 337 MY | L100: COMBUSTIBLE | M100: =SUM(H105+H111) -> 127.222
A101: 46197 | B101: FA | C101: 94-3190 | D101: AG 768 OI | F101: 299998.93 | G101: =+G100+E101-F101 -> 62735.39 | H101: 125.156 | I101: COMBUSTIBLE | K101: AG 962 EW | L101: COMBUSTIBLE | M101: =SUM(H102) -> 45.9
A102: 46197 | B102: FA | C102: 96-6972 | D102: AG 962 EW | F102: 110022.3 | G102: =+G101+E102-F102 -> -47286.91 | H102: 45.9 | I102: COMBUSTIBLE | K102: MOTO AMARILLA | L102: COMBUSTIBLE | M102: 0
A103: 46197 | B103: FA | C103: 94-3197 | D103: WNO 918 | F103: 273618.71 | G103: =+G102+E103-F103 -> -320905.62 | H103: 120.59 | I103: COMBUSTIBLE | K103: MOTO GRIS | L103: COMBUSTIBLE | M103: =SUM(H115) -> 13.31
A104: 46197 | B104: FA | C104: 96-6981 | D104: PFG 964 | F104: 59999.31 | G104: =+G103+E104-F104 -> -380904.93 | H104: 25.031 | I104: COMBUSTIBLE | K104: PFG 964 | L104: COMBUSTIBLE | M104: =SUM(H104+H107+H108+H112+H116) -> 124.897
A105: 46197 | B105: FA | C105: 92-1494 | D105: AG 337 MY | F105: 162013.23 | G105: =+G104+E105-F105 -> -542918.16 | H105: 67.59 | I105: COMBUSTIBLE | K105: LVX 455 | L105: COMBUSTIBLE | M105: =SUM(H100) -> 25.031
...

Sheet JULIO.2026
A5: CTA.CTE JULIO - 2026 - CARGAS | K5: SEMANA DEL 1/7 AL 4/7
A6: CARGAS COMBUSTIBLE YPF | K6: RESUMEN CONSUMO
A7: FECHA | B7: TIPO | C7: N° FA/COMP | D7: VEHICULO | E7: PAGOS | F7: CONSUMOS | G7: SALDO | H7: LITROS | I7: OBSEVACIONES | K7: RESUMEN | L7: CONSUMO | M7: LTS
A8: 46203 | C8: SALDO ANTERIOR | F8: 181680.85 | G8: =+E8-F8 -> -181680.85 | K8: AG 378 AV | L8: COMBUSTIBLE | M8: 0
A9: 46204 | B9: FA | C9: 94-3349 | D9: AG 958 JV | F9: 441269.4 | G9: =+G8+E9-F9 -> -622950.25 | H9: 183.48 | I9: COMBUSTIBLE | K9: AG 337 MY | L9: COMBUSTIBLE | M9: 0
A10: 46204 | B10: FA | C10: 92-1787 | D10: MULITA | F10: 86948.99 | G10: =+G9+E10-F10 -> -709899.24 | H10: 38.422 | I10: COMBUSTIBLE | K10: AG 962 EW | L10: COMBUSTIBLE | M10: =SUM(H11) -> 38.257
A11: 46204 | B11: FA | C11: 92-1790 | D11: AG 962 EW | F11: 92008.09 | G11: =+G10+E11-F11 -> -801907.33 | H11: 38.257 | I11: COMBUSTIBLE | K11: MOTO AMARILLA | L11: COMBUSTIBLE | M11: 0
A12: 46204 | B12: RE | C12: 50-0336 | D12: TRANSF | E12: 1000000 | G12: =+G11+E12-F12 -> 198092.67 | I12: PAGO - SALDO A FAVOR | K12: MOTO GRIS | L12: COMBUSTIBLE | M12: 0
A13: 46204 | B13: FA | C13: 96-7314 | D13: PFG 964 | F13: 59999.94 | G13: =+G12+E13-F13 -> 138092.73 | H13: 24.948 | I13: COMBUSTIBLE | K13: PFG 964 | L13: COMBUSTIBLE | M13: =SUM(H13+H16) -> 49.875
A14: 46205 | B14: FA | C14: 92-1830 | D14: HLW 156 | F14: 59999.36 | G14: =+G13+E14-F14 -> 78093.37 | H14: 24.896 | I14: COMBUSTIBLE | K14: LVX 455 | L14: COMBUSTIBLE | M14: =SUM(H18) -> 24.927
A15: 46206 | B15: FA | C15: 96-7369 | D15: PFG 964 | F15: 59999.29 | G15: =+G14+E15-F15 -> 18094.08 | H15: 24.927 | I15: COMBUSTIBLE | K15: AG 958 JV | L15: COMBUSTIBLE | M15: =SUM(H9) -> 183.48
A16: 46206 | B16: FA | C16: 96-7370 | D16: KJR 926 | F16: 59999.29 | G16: =+G15+E16-F16 -> -41905.21 | H16: 24.927 | I16: COMBUSTIBLE | K16: AG 768 OI | L16: COMBUSTIBLE | M16: 0
A17: 46206 | B17: FA | C17: 94-3419 | D17: WNO 918 | F17: 288843.82 | G17: =+G16+E17-F17 -> -330749.03 | H17: 127.807 | I17: COMBUSTIBLE | K17: KJR 926 | L17: COMBUSTIBLE | M17: =SUM(H16) -> 24.927
A18: 46206 | B18: FA | C18: 92-1933 | D18: LVX 455 | F18: 59999.29 | G18: =+G17+E18-F18 -> -390748.32 | H18: 24.927 | I18: COMBUSTIBLE | K18: HLW 156 | L18: COMBUSTIBLE | M18: =SUM(H14) -> 24.896
A19: TOTAL DE LITROS SEMANAL | H19: =SUM(H9:H18) -> 512.591 | K19: WNO 918 | L19: COMBUSTIBLE | M19: =SUM(H17) -> 127.807
A20: SEMANA DEL 1/7 AL 4/7 | K20: AUTOELEVADOR | L20: COMBUSTIBLE | M20: =SUM(H10) -> 38.422
A21: 46208 | B21: FA | C21: 92-2021 | D21: LVX 455 | F21: 60000.91 | G21: =+G18+E21-F21 -> -450749.23 | H21: 24.876 | I21: COMBUSTIBLE | K21: LITROS SEMANAL | M21: =SUM(M8:M20) -> 512.591
A22: 46209 | B22: FA | C22: 96-7493 | D22: HLW 156 | F22: 59999.36 | G22: =+G21+E22-F22 -> -510748.59 | H22: 24.896 | I22: COMBUSTIBLE
A23: 46209 | B23: FA | C23: 96-7494 | D23: KJR 926 | F23: 59999.36 | G23: =+G22+E23-F23 -> -570747.95 | H23: 24.896 | I23: COMBUSTIBLE | K23: SEMANA DEL 5/7 AL 11/7
A24: 46209 | B24: RE | C24: 50-0343 | D24: TRANSF | E24: 1000000 | G24: =+G23+E24-F24 -> 429252.05 | I24: PAGO - SALDO A FAVOR | K24: RESUMEN CONSUMO
A25: 46209 | B25: FA | C25: 92-2083 | D25: AG 378 AW | F25: 133000.67 | G25: =+G24+E25-F25 -> 296251.38 | H25: 55.187 | I25: COMBUSTIBLE | K25: RESUMEN | L25: CONSUMO | M25: LTS
A26: 46209 | B26: FA | C26: 92-2087 | D26: LVX 455 | F26: 59999.36 | G26: =+G25+E26-F26 -> 236252.02 | H26: 24.896 | I26: COMBUSTIBLE | K26: AG 378 AV | L26: COMBUSTIBLE | M26: 0
A27: 46211 | B27: FA | C27: 96-7585 | D27: MULITA | F27: 50000.27 | G27: =+G26+E27-F27 -> 186251.75 | H27: 20.747 | I27: COMBUSTIBLE | K27: AG 378 AW | L27: COMBUSTIBLE | M27: =SUM(H25) -> 55.187
A28: 46211 | B28: FA | C28: 82-2150 | D28: MULITA | F28: 89670.02 | G28: =+G27+E28-F28 -> 96581.73 | H28: 39.677 | I28: COMBUSTIBLE | K28: AG 337 MY | L28: COMBUSTIBLE | M28: =SUM(H30) -> 73.03
A29: 46211 | B29: FA | C29: 92-2172 | D29: LVX 455 | F29: 59999.36 | G29: =+G28+E29-F29 -> 36582.37 | H29: 24.896 | I29: COMBUSTIBLE | K29: AG 962 EW | L29: COMBUSTIBLE | M29: =SUM(H31) -> 51.76
A30: 46211 | B30: FA | C30: 82-2187 | D30: AG 337 MY | F30: 176002.3 | G30: =+G29+E30-F30 -> -139419.93 | H30: 73.03 | I30: COMBUSTIBLE | K30: MOTO AMARILLA | L30: COMBUSTIBLE | M30: 0
A31: 46212 | B31: FA | C31: 96-7640 | D31: AG 962 EW | F31: 125000.4 | G31: =+G30+E31-F31 -> -264420.33 | H31: 51.76 | I31: COMBUSTIBLE | K31: MOTO GRIS | L31: COMBUSTIBLE | M31: 0
A32: 46212 | B32: FA | C32: 60-7349 | D32: LVX 455 | F32: 60000.68 | G32: =+G31+E32-F32 -> -324421.01 | H32: 24.845 | I32: COMBUSTIBLE | K32: PFG 964 | L32: COMBUSTIBLE | M32: =SUM(H35) -> 24.876
A33: 46213 | B33: FA | C33: 96-7676 | D33: HLW 156 | F33: 60000.91 | G33: =+G32+E33-F33 -> -384421.92 | H33: 24.876 | I33: COMBUSTIBLE | K33: LVX 455 | L33: COMBUSTIBLE | M33: =SUM(H21+H26+H29+H32+H36) -> 124.389
A34: 46213 | B34: FA | C34: 92-2255 | D34: KJR 926 | F34: 65000.99 | G34: =+G33+E34-F34 -> -449422.91 | H34: 26.949 | I34: COMBUSTIBLE | K34: AG 958 JV | L34: COMBUSTIBLE | M34: 0
A35: 46213 | B35: FA | C35: 92-2278 | D35: PFG 964 | F35: 60000.91 | G35: =+G34+E35-F35 -> -509423.82 | H35: 24.876 | I35: COMBUSTIBLE | K35: AG 768 OI | L35: COMBUSTIBLE | M35: 0
A36: 46213 | B36: FA | C36: 92-2282 | D36: LVX 455 | F36: 60000.91 | G36: =+G35+E36-F36 -> -569424.73 | H36: 24.876 | I36: COMBUSTIBLE | K36: KJR 926 | L36: COMBUSTIBLE | M36: =SUM(H23+H34) -> 51.845
A37: TOTAL DE LITROS SEMANAL | H37: =SUM(H21:H36) -> 491.283 | K37: HLW 156 | L37: COMBUSTIBLE | M37: =SUM(H22+H33) -> 49.772
A38: SEMANA DEL 5/7 AL 11/7 | K38: WNO 918 | L38: COMBUSTIBLE | M38: 0
A39: 46216 | B39: FA | C39: 96-7846 | D39: LVX 455 | F39: 59999.36 | G39: =+G36+E39-F39 -> -629424.09 | H39: 24.896 | I39: COMBUSTIBLE | K39: AUTOELEVADOR | L39: COMBUSTIBLE | M39: =SUM(H27+H28) -> 60.424
A40: 46217 | B40: FA | C40: 98-2171 | D40: AG 768 OI | F40: 499999.75 | G40: =+G39+E40-F40 -> -1129423.8 | H40: 207.125 | I40: COMBUSTIBLE | K40: LITROS SEMANAL | M40: =SUM(M26:M39) -> 491.283
A41: 46217 | B41: RE | C41: 50-0352 | D41: TRANSF | E41: 1000000 | G41: =+G40+E41-F41 -> -129423.84 | I41: PAGO - SALDO PENDIENTE
A42: 46217 | B42: FA | C42: 96-7888 | D42: KJR 926 | F42: 59999.97 | G42: =+G41+E42-F42 -> -189423.81 | H42: 24.855 | I42: COMBUSTIBLE | K42: SEMANA DEL 12/7 AL 18/7
A43: 46217 | B43: FA | C43: 96-7889 | D43: HLW 156 | F43: 59999.97 | G43: =+G42+E43-F43 -> -249423.78 | H43: 24.855 | I43: COMBUSTIBLE | K43: RESUMEN CONSUMO
A44: 46217 | B44: FA | C44: 92-2437 | D44: MOTO GRIS | F44: 29513.84 | G44: =+G43+E44-F44 -> -278937.62 | H44: 13.065 | I44: COMBUSTIBLE | K44: RESUMEN | L44: CONSUMO | M44: LTS
A45: 46219 | B45: FA | C45: 96-7963 | D45: LVX 455 | F45: 60017.58 | G45: =+G44+E45-F45 -> -338955.2 | H45: 24.852 | I45: COMBUSTIBLE | K45: AG 378 AV | L45: COMBUSTIBLE | M45: =SUM(H47+H58) -> 109.837
A46: 46219 | B46: RE | C46: 50-0357 | D46: TRANSF | E46: 1500000 | G46: =+G45+E46-F46 -> 1161044.8 | I46: PAGO - SALDO A FAVOR | K46: AG 378 AW | L46: COMBUSTIBLE | M46: 0
A47: 46219 | B47: FA | C47: 60-7576 | D47: AG 378 AV | F47: 135010.58 | G47: =+G46+E47-F47 -> 1026034.2 | H47: 55.905 | I47: COMBUSTIBLE | K47: AG 337 MY | L47: COMBUSTIBLE | M47: =SUM(H48) -> 74.825
A48: 46219 | B48: FA | C48: 96-7974 | D48: AG 337 MY | F48: 180702.38 | G48: =+G47+E48-F48 -> 845331.84 | H48: 74.825 | I48: COMBUSTIBLE | K48: AG 962 EW | L48: COMBUSTIBLE | M48: =SUM(H61) -> 45.6053
A49: 46219 | B49: FA | C49: 96-7977 | D49: MULITA | F49: 83902.5 | G49: =+G48+E49-F49 -> 761429.34 | H49: 37.125 | I49: COMBUSTIBLE | K49: MOTO AMARILLA | L49: COMBUSTIBLE | M49: 0
A50: 46219 | B50: FA | C50: 60-7592 | D50: AG 958 JV | F50: 543828.51 | G50: =+G49+E50-F50 -> 217600.83 | H50: 230.707 | I50: COMBUSTIBLE | K50: MOTO GRIS | L50: COMBUSTIBLE | M50: =SUM(H44) -> 13.065
A51: 46220 | B51: RE | C51: 50-0358 | D51: TRANSF | E51: 1000000 | G51: =+G50+E51-F51 -> 1217600.8 | I51: PAGO - SALDO A FAVOR | K51: PFG 964 | L51: COMBUSTIBLE | M51: =SUM(H54) -> 24.876
A52: 46220 | B52: FA | C52: 96-8018 | D52: KJR 926 | F52: 60000.91 | G52: =+G51+E52-F52 -> 1157599.9 | H52: 24.876 | I52: COMBUSTIBLE | K52: LVX 455 | L52: COMBUSTIBLE | M52: =SUM(H39+H45+H53+H63) -> 99.5
A53: 46220 | B53: FA | C53: 60-7628 | D53: LVX 455 | F53: 60000.91 | G53: =+G52+E53-F53 -> 1097599 | H53: 24.876 | I53: COMBUSTIBLE | K53: AF 728 AT | L53: COMBUSTIBLE | M53: =SUM(H56) -> 78.307
A54: 46220 | B54: FA | C54: 96-8037 | D54: PFG 964 | F54: 60000.91 | G54: =+G53+E54-F54 -> 1037598.1 | H54: 24.876 | I54: COMBUSTIBLE | K54: AG 958 JV | L54: COMBUSTIBLE | M54: =SUM(H50) -> 230.707
A55: 46220 | B55: FA | C55: 94-3767 | D55: HKQ 258 | F55: 876163.82 | G55: =+G54+E55-F55 -> 161434.28 | H55: 363.252 | I55: COMBUSTIBLE | K55: AG 768 OI | L55: COMBUSTIBLE | M55: =SUM(H40+H59) -> 712.27
A56: 46220 | B56: FA | C56: 94-3770 | D56: AF 728 AT | F56: 188876.48 | G56: =+G55+E56-F56 -> -27442.2 | H56: 78.307 | I56: COMBUSTIBLE | K56: KJR 926 | L56: COMBUSTIBLE | M56: =SUM(H42+H52) -> 49.731
A57: 46220 | B57: RE | C57: 50-0360 | D57: TRANSF | E57: 1000000 | G57: =+G56+E57-F57 -> 972557.8 | I57: PAGO - SALDO A FAVOR | K57: HLW 156 | L57: COMBUSTIBLE | M57: =SUM(H43) -> 24.855
A58: 46220 | B58: FA | C58: 60-7652 | D58: AG 378 AV | F58: 130083.98 | G58: =+G57+E58-F58 -> 842473.82 | H58: 53.932 | I58: COMBUSTIBLE | K58: HKQ 258 | L58: COMBUSTIBLE | M58: =SUM(H55) -> 363.252
A59: 46220 | B59: FA | C59: 94-3773 | D59: AG 768 OI | F59: 1218409.7 | G59: =+G58+E59-F59 -> -375935.92 | H59: 505.145 | I59: COMBUSTIBLE | K59: WNO 918 | L59: COMBUSTIBLE | M59: 0
A60: 46221 | B60: FA | C60: 96-8064 | D60: AG 962 EW | F60: 109999.26 | G60: =+G59+E60-F60 -> -485935.18 | K60: AUTOELEVADOR | L60: COMBUSTIBLE | M60: =SUM(H49) -> 37.125
A61: 46221 | B61: FA | C61: 92-2608 | D61: AG 962 EW | F61: 109999.98 | G61: =+G60+E61-F61 -> -595935.16 | H61: 45.6053 | I61: COMBUSTIBLE | K61: LITROS SEMANAL | M61: =SUM(M45:M60) -> 1863.9553
A62: 46221 | B62: NC | C62: 100-0007 | D62: NOTA DE CREDITO | E62: 109999.26 | G62: =+G61+E62-F62 -> -485935.9 | I62: DEVOLUCIÓN DE PAGO DE COMBUSTIBLE AG 962 EW (96-8064)
A63: 46221 | B63: FA | C63: 96-8070 | D63: LVX 455 | F63: 60000.91 | G63: =+G62+E63-F63 -> -545936.81 | H63: 24.876 | I63: COMBUSTIBLE
A64: TOTAL DE LITROS SEMANAL | H64: =SUM(H39:H63) -> 1863.9553
A65: SEMANA DEL 12/7 AL 18/7 | K65: SEMANA DEL 19/7 AL 25/7
A66: 46222 | B66: FA | C66: 94-3791 | D66: AG 768 OI | F66: 299999.55 | G66: =+G63+E66-F66 -> -845936.36 | H66: 124.172 | I66: COMBUSTIBLE | K66: RESUMEN CONSUMO
A67: 46223 | B67: FA | C67: 96-8112 | D67: HLW 156 | F67: 60000.53 | G67: =+G66+E67-F67 -> -905936.89 | H67: 26.502 | I67: COMBUSTIBLE | K67: RESUMEN | L67: CONSUMO | M67: LTS
A68: 46223 | B68: FA | C68: 96-8118 | D68: MULITA | F68: 76606.97 | G68: =+G67+E68-F68 -> -982543.86 | H68: 33.837 | I68: COMBUSTIBLE | K68: AG 378 AV | L68: COMBUSTIBLE | M68: 0
A69: 46223 | B69: FA | C69: 96-8134 | D69: AG 378 AW | F69: 138611.15 | G69: =+G68+E69-F69 -> -1121155 | H69: 57.515 | I69: COMBUSTIBLE | K69: AG 378 AW | L69: COMBUSTIBLE | M69: =SUM(H69+H74) -> 82.37
A70: 46223 | B70: RE | C70: 50-0364 | D70: TRANSF | E70: 2000000 | G70: =+G69+E70-F70 -> 878844.99 | I70: PAGO - SALDO A FAVOR | K70: AG 337 MY | L70: COMBUSTIBLE | M70: 0
A71: 46223 | B71: FA | C71: 94-3823 | D71: AG 768 OI | F71: 838788.45 | G71: =+G70+E71-F71 -> 40056.54 | H71: 348.045 | I71: COMBUSTIBLE | K71: AG 962 EW | L71: COMBUSTIBLE | M71: 0
A72: 46224 | B72: FA | C72: 96-8171 | D72: PFG 964 | F72: 59999.97 | G72: =+G71+E72-F72 -> -19943.43 | H72: 24.855 | I72: COMBUSTIBLE | K72: MOTO AMARILLA | L72: COMBUSTIBLE | M72: 0
A73: 46224 | B73: FA | C73: 60-7766 | D73: LVX 455 | F73: 59999.97 | G73: =+G72+E73-F73 -> -79943.4 | H73: 24.855 | I73: COMBUSTIBLE | K73: MOTO GRIS | L73: COMBUSTIBLE | M73: 0
A74: 46224 | B74: FA | C74: 96-8195 | D74: AG 378 AW | F74: 59999.97 | G74: =+G73+E74-F74 -> -139943.37 | H74: 24.855 | I74: COMBUSTIBLE | K74: PFG 964 | L74: COMBUSTIBLE | M74: =SUM(H72+H81+H86) -> 74.6369
A75: 46224 | B75: FA | C75: 98-2230 | D75: AG 958 JV | F75: 450119.03 | G75: =+G74+E75-F75 -> -590062.4 | H75: 186.4619 | I75: COMBUSTIBLE | K75: LVX 455 | L75: COMBUSTIBLE | M75: =SUM(H73+H83+H84+H90) -> 84.633
A76: 46224 | B76: FA | C76: 94-3844 | D76: AG 958 JV | F76: 450119.27 | G76: =+G75+E76-F76 -> -1040181.7 | K76: AF 728 AT | L76: COMBUSTIBLE | M76: 0
A77: 46225 | B77: FA | C77: 96-8218 | D77: MULITA | F77: 47046.42 | G77: =+G76+E77-F77 -> -1087228.1 | H77: 20.817 | I77: COMBUSTIBLE | K77: AG 958 JV | L77: COMBUSTIBLE | M77: =SUM(H75+H93) -> 310.8919
A78: 46225 | B78: NC | C78: 100-0008 | D78: NOTA DE CREDITO | E78: 450119.28 | G78: =+G77+E78-F78 -> -637108.81 | I78: DEVOLUCIÓN DE PAGO DE COMBUSTIBLE AG 958 JV (94-3844) | K78: AG 768 OI | L78: COMBUSTIBLE | M78: =SUM(H66+H71+H94+H95) -> 941.6
A79: 46225 | B79: RE | C79: 50-0367 | D79: TRANSF | E79: 2000000 | G79: =+G78+E79-F79 -> 1362891.2 | I79: PAGO - SALDO A FAVOR | K79: KJR 926 | L79: COMBUSTIBLE | M79: =SUM(H89+H97) -> 49.772
A80: 46225 | B80: FA | C80: 94-3870 | D80: HKQ 258 | F80: 942567.87 | G80: =+G79+E80-F80 -> 420323.32 | H80: 391.107 | I80: COMBUSTIBLE | K80: HLW 156 | L80: COMBUSTIBLE | M80: =SUM(H67+H82+H87) -> 76.2429
A81: 46225 | B81: FA | C81: 96-8244 | D81: PFG 964 | F81: 59999.36 | G81: =+G80+E81-F81 -> 360323.96 | H81: 24.896 | I81: COMBUSTIBLE | K81: HKQ 258 | L81: COMBUSTIBLE | M81: =SUM(H80) -> 391.107
A82: 46226 | B82: FA | C82: 96-8256 | D82: HLW 156 | F82: 59999.97 | G82: =+G81+E82-F82 -> 300323.99 | H82: 24.855 | I82: COMBUSTIBLE | K82: WNO 918 | L82: COMBUSTIBLE | M82: =SUM(H96) -> 135.34
A83: 46226 | B83: FA | C83: 92-2857 | D83: LVX 455 | F83: 21017.48 | G83: =+G82+E83-F83 -> 279306.51 | H83: 10.037 | I83: COMBUSTIBLE | K83: AUTOELEVADOR | L83: COMBUSTIBLE | M83: =SUM(H68+H77+H85+H88+H91) -> 111.546
A84: 46226 | B84: FA | C84: 92-2858 | D84: LVX 455 | F84: 59999.97 | G84: =+G83+E84-F84 -> 219306.54 | H84: 24.855 | I84: COMBUSTIBLE | K84: LITROS SEMANAL | M84: =SUM(M68:M83) -> 2258.1397
A85: 46226 | B85: FA | C85: 92-2881 | D85: MULITA | F85: 42397.6 | G85: =+G84+E85-F85 -> 176908.94 | H85: 18.76 | I85: COMBUSTIBLE
A86: 46227 | B86: FA | C86: 96-8327 | D86: PFG 964 | F86: 59999.9 | G86: =+G85+E86-F86 -> 116909.04 | H86: 24.8859 | I86: COMBUSTIBLE
A87: 46227 | B87: FA | C87: 96-8335 | D87: HLW 156 | F87: 59999.9 | G87: =+G86+E87-F87 -> 56909.14 | H87: 24.8859 | I87: COMBUSTIBLE
A88: 46227 | B88: FA | C88: 60-7924 | D88: MULITA | F88: 42007.28 | G88: =+G87+E88-F88 -> 14901.86 | H88: 18.612 | I88: COMBUSTIBLE
A89: 46227 | B89: FA | C89: 96-8354 | D89: KJR 926 | F89: 60000.15 | G89: =+G88+E89-F89 -> -45098.29 | H89: 24.886 | I89: COMBUSTIBLE
A90: 46227 | B90: FA | C90: 92-2926 | D90: LVX 455 | F90: 60000.15 | G90: =+G89+E90-F90 -> -105098.44 | H90: 24.886 | I90: COMBUSTIBLE
A91: 46198 | B91: FA | C91: 96-8377 | D91: MULITA | F91: 44212.8 | G91: =+G90+E91-F91 -> -149311.24 | H91: 19.52 | I91: COMBUSTIBLE
A92: 46228 | B92: RE | C92: 50-0375 | E92: 2000000 | G92: =+G91+E92-F92 -> 1850688.8 | I92: PAGO - SALDO A FAVOR
A93: 46228 | B93: FA | C93: 94-3951 | D93: AG 958 JV | F93: 300000.73 | G93: =+G92+E93-F93 -> 1550688 | H93: 124.43 | I93: COMBUSTIBLE
A94: 46228 | B94: FA | C94: 94-3952 | D94: AG 768 OI | F94: 631682 | G94: =+G93+E94-F94 -> 919006.03 | H94: 262 | I94: COMBUSTIBLE
A95: 46228 | B95: FA | C95: 94-3953 | D95: AG 768 OI | F95: 500000.41 | G95: =+G94+E95-F95 -> 419005.62 | H95: 207.383 | I95: COMBUSTIBLE
A96: 46228 | B96: FA | C96: 94-3954 | D96: WNO 918 | F96: 306545.1 | G96: =+G95+E96-F96 -> 112460.52 | H96: 135.34 | I96: COMBUSTIBLE
A97: 46228 | B97: FA | C97: 92-2965 | D97: KJR 926 | F97: 60000.15 | G97: =+G96+E97-F97 -> 52460.37 | H97: 24.886 | I97: COMBUSTIBLE
A98: TOTAL DE LITROS SEMANAL | H98: =SUM(H66:H97) -> 2258.1397
A99: SEMANA DEL 19/7 AL 25/7 | K99: SEMANA DEL 26/7 AL 31/7
A100: 46229 | B100: FA | C100: 96-8400 | D100: LVX 455 | F100: 60000.68 | G100: =+G97+E100-F100 -> -7540.31 | H100: 24.845 | I100: COMBUSTIBLE | K100: RESUMEN CONSUMO
A101: 46229 | B101: FA | C101: 96-8401 | D101: MULITA | F101: 45267.8 | G101: =+G100+E101-F101 -> -52808.11 | H101: 20.03 | I101: COMBUSTIBLE | K101: RESUMEN | L101: CONSUMO | M101: LTS
A102: 46229 | B102: FA | C102: 92-3005 | D102: AG 337 MY | F102: 165004.88 | G102: =+G101+E102-F102 -> -217812.99 | H102: 68.325 | I102: COMBUSTIBLE | K102: AG 378 AV | L102: COMBUSTIBLE | M102: 0
A103: 46230 | B103: FA | C103: 94-3976 | D103: HKQ 258 | F103: 777169.57 | G103: =+G102+E103-F103 -> -994982.56 | H103: 322.477 | I103: COMBUSTIBLE | K103: AG 378 AW | L103: COMBUSTIBLE | M103: 0
A104: 46230 | B104: FA | C104: 94-3980 | D104: WNO 918 | F104: 100028.05 | G104: =+G103+E104-F104 -> -1095010.6 | H104: 44.182 | I104: COMBUSTIBLE | K104: AG 337 MY | L104: COMBUSTIBLE | M104: =SUM(H102+H126) -> 113.265
...

Sheet AGOSTO.2026
A5: CTA.CTE AGOSTO - 2026 - CARGAS | K5: SEMANA DEL 1/8 AL 8/8
A6: CARGAS COMBUSTIBLE YPF | K6: RESUMEN CONSUMO
A7: FECHA | B7: TIPO | C7: N° FA/COMP | D7: VEHICULO | E7: PAGOS | F7: CONSUMOS | G7: SALDO | H7: LITROS | I7: OBSEVACIONES | K7: RESUMEN | L7: CONSUMO | M7: LTS
A8: 46233 | C8: SALDO ANTERIOR | E8: 880915.48 | G8: =+E8-F8 -> 880915.48 | K8: AG 378 AV | L8: COMBUSTIBLE | M8: =SUM(H13) -> 48.965
A9: 46237 | B9: FA | C9: 60-8302 | D9: KJR 926 | F9: 59999.36 | G9: =+G8+E9-F9 -> 820916.12 | H9: 24.896 | I9: COMBUSTIBLE | K9: AG 337 MY | L9: COMBUSTIBLE | M9: =SUM(H26) -> 70.965
A10: 46237 | B10: FA | C10: 92-3356 | D10: HLW 156 | F10: 59999.36 | G10: =+G9+E10-F10 -> 760916.76 | H10: 24.896 | I10: COMBUSTIBLE | K10: AG 962 EW | L10: COMBUSTIBLE | M10: 0
A11: 46237 | B11: FA | C11: 92-3357 | D11: MULITA | F11: 42986.57 | G11: =+G10+E11-F11 -> 717930.19 | H11: 18.987 | I11: COMBUSTIBLE | K11: MOTO AMARILLA | L11: COMBUSTIBLE | M11: 0
A12: 46237 | B12: FA | C12: 96-8798 | D12: LVX 455 | F12: 59999.36 | G12: =+G11+E12-F12 -> 657930.83 | H12: 24.896 | I12: COMBUSTIBLE | K12: MOTO GRIS | L12: COMBUSTIBLE | M12: 0
A13: 46238 | B13: FA | C13: 60-8364 | D13: AG 378 AV | F13: 118005.89 | G13: =+G12+E13-F13 -> 539924.94 | H13: 48.965 | I13: COMBUSTIBLE | K13: AF 728 AT | L13: COMBUSTIBLE | M13: =SUM(H23) -> 57.097
A14: 46238 | B14: FA | C14: 92-3417 | D14: AG 378 AV | F14: 118005.65 | G14: =+G13+E14-F14 -> 421919.29 | K14: PFG 964 | L14: COMBUSTIBLE | M14: 0
A15: 46238 | B15: NC | C15: 100-0010 | D15: NOTA DE CREDITO | E15: 118005.66 | G15: =+G14+E15-F15 -> 539924.95 | I15: DEVOLUCIÓN DE PAGO DE COMBUSTIBLE AG 378 AV (92-3417) | K15: LVX 455 | L15: COMBUSTIBLE | M15: =SUM(H12+H17+H30) -> 74.483
A16: 46238 | B16: FA | C16: 92-3439 | D16: KJR 926 | F16: 59999.36 | G16: =+G15+E16-F16 -> 479925.59 | H16: 24.896 | I16: COMBUSTIBLE | K16: AG 958 JV | L16: COMBUSTIBLE | M16: 0
A17: 46239 | B17: FA | C17: 60-8441 | D17: LVX 455 | F17: 59999.36 | G17: =+G16+E17-F17 -> 419926.23 | H17: 24.896 | I17: COMBUSTIBLE | K17: AG 768 OI | L17: COMBUSTIBLE | M17: =SUM(H25) -> 781.103
A18: 46239 | B18: FA | C18: 60-8451 | D18: KJR 926 | F18: 59999.36 | G18: =+G17+E18-F18 -> 359926.87 | H18: 24.896 | I18: COMBUSTIBLE | K18: KJR 926 | L18: COMBUSTIBLE | M18: =SUM(H9+H16+H18+H21+H27+H31) -> 149.027
A19: 46240 | B19: FA | C19: 96-8926 | D19: MULITA | F19: 136155.88 | G19: =+G18+E19-F19 -> 223770.99 | H19: 60.007 | I19: COMBUSTIBLE | K19: HLW 156 | L19: COMBUSTIBLE | M19: =SUM(H10+H20+H29) -> 74.544
A20: 46240 | B20: FA | C20: 60-8483 | D20: HLW 156 | F20: 59999.61 | G20: =+G19+E20-F20 -> 163771.38 | H20: 24.824 | I20: COMBUSTIBLE | K20: WNO 918 | L20: COMBUSTIBLE | M20: =SUM(H28) -> 43.917
A21: 46240 | B21: FA | C21: 92-3509 | D21: KJR 926 | F21: 59999.61 | G21: =+G20+E21-F21 -> 103771.77 | H21: 24.824 | I21: COMBUSTIBLE | K21: HKQ 258 | L21: COMBUSTIBLE | M21: =SUM(H24) -> 340.66
A22: 46240 | B22: RE | C22: 50-0398 | D22: TRANSF | E22: 2000000 | G22: =+G21+E22-F22 -> 2103771.8 | I22: PAGO - SALDO A FAVOR | K22: AUTOELEVADOR | L22: COMBUSTIBLE | M22: =SUM(H11+H19) -> 78.994
A23: 46240 | B23: FA | C23: 92-3515 | D23: AF 728 AT | F23: 138003.45 | G23: =+G22+E23-F23 -> 1965768.3 | H23: 57.097 | I23: COMBUSTIBLE | K23: LITROS SEMANAL | M23: =SUM(M8:M22) -> 1719.755
A24: 46240 | B24: FA | C24: 94-4286 | D24: HKQ 258 | F24: 823375.22 | G24: =+G23+E24-F24 -> 1142393.1 | H24: 340.66 | I24: COMBUSTIBLE
A25: 46240 | B25: FA | C25: 94-4290 | D25: AG 768 OI | F25: 1887925.9 | G25: =+G24+E25-F25 -> -745532.85 | H25: 781.103 | I25: COMBUSTIBLE
A26: 46240 | B26: FA | C26: 92-3539 | D26: AG 337 MY | F26: 171522.41 | G26: =+G25+E26-F26 -> -917055.26 | H26: 70.965 | I26: COMBUSTIBLE
A27: 46241 | B27: FA | C27: 60-8512 | D27: KJR 926 | F27: 59999.61 | G27: =+G26+E27-F27 -> -977054.87 | H27: 24.824 | I27: COMBUSTIBLE
A28: 46241 | B28: FA | C28: 94-4301 | D28: WNO 918 | F28: 99999.01 | G28: =+G27+E28-F28 -> -1077053.9 | H28: 43.917 | I28: COMBUSTIBLE
A29: 46241 | B29: FA | C29: 96-9014 | D29: HLW 156 | F29: 59999.61 | G29: =+G28+E29-F29 -> -1137053.5 | H29: 24.824 | I29: COMBUSTIBLE
A30: 46242 | B30: FA | C30: 98-2362 | D30: LVX 455 | F30: 59999.13 | G30: =+G29+E30-F30 -> -1197052.6 | H30: 24.691 | I30: COMBUSTIBLE
A31: 46242 | B31: FA | C31: 96-9043 | D31: KJR 926 | F31: 59999.13 | G31: =+G30+E31-F31 -> -1257051.7 | H31: 24.691 | I31: COMBUSTIBLE
A32: 46242 | B32: RE | C32: 50-0401 | D32: TRANSF | E32: 3000000 | G32: =+G31+E32-F32 -> 1742948.3 | I32: PAGO - SALDO A FAVOR
A33: TOTAL DE LITROS SEMANAL | H33: =SUM(H9:H32) -> 1719.755
A34: SEMANA DEL 1/8 AL 8/8 | K34: SEMANA DEL 9/8 AL 15/8
A35: 46243 | B35: FA | C35: 96-9071 | D35: KJR 926 | F35: 59999.13 | G35: =+G32+E35-F35 -> 1682949.1 | H35: 24.691 | I35: COMBUSTIBLE | K35: RESUMEN CONSUMO
A36: 46243 | B36: FA | C36: 60-8595 | D36: MULITA | F36: 45664.57 | G36: =+G35+E36-F36 -> 1637284.6 | H36: 20.002 | I36: COMBUSTIBLE | K36: RESUMEN | L36: CONSUMO | M36: LTS
A37: 46243 | B37: FA | C37: 60-8596 | D37: HLW 156 | F37: 65000.07 | G37: =+G36+E37-F37 -> 1572284.5 | H37: 26.749 | I37: COMBUSTIBLE | K37: AG 378 AV | L37: COMBUSTIBLE | M37: 0
A38: 46244 | B38: FA | C38: 94-4356 | D38: WNO 918 | F38: 223065.08 | G38: =+G37+E38-F38 -> 1349219.4 | H38: 97.707 | I38: COMBUSTIBLE | K38: AG 337 MY | L38: COMBUSTIBLE | M38: 0
A39: 46244 | B39: FA | C39: 94-4357 | D39: AG 958 JV | F39: 367531.6 | G39: =+G38+E39-F39 -> 981687.8 | H39: 150.937 | I39: COMBUSTIBLE | K39: AG 962 EW | L39: COMBUSTIBLE | M39: =SUM(H40+H64) -> 81.712
A40: 46244 | B40: FA | C40: 96-9108 | D40: AG 962 EW | F40: 98999.8 | G40: =+G39+E40-F40 -> 882688 | H40: 40.657 | I40: COMBUSTIBLE | K40: MOTO AMARILLA | L40: COMBUSTIBLE | M40: 0
A41: 46244 | B41: FA | C41: 92-3684 | D41: PFG 964 | F41: 60000.84 | G41: =+G40+E41-F41 -> 822687.16 | H41: 24.641 | I41: COMBUSTIBLE | K41: MOTO GRIS | L41: COMBUSTIBLE | M41: 0
A42: 46244 | B42: FA | C42: 94-4367 | D42: HKQ 258 | F42: 724120.3 | G42: =+G41+E42-F42 -> 98566.86 | H42: 297.38 | I42: COMBUSTIBLE | K42: AF 728 AT | L42: COMBUSTIBLE | M42: 0
A43: 46244 | B43: FA | C43: 92-3691 | D43: MULITA | F43: 90000.43 | G43: =+G42+E43-F43 -> 8566.43 | H43: 39.422 | I43: COMBUSTIBLE | K43: PFG 964 | L43: COMBUSTIBLE | M43: =SUM(H41+H51+H56+H59+H68) -> 123.113
A44: 46245 | B44: FA | C44: 96-9143 | D44: KJR 926 | F44: 64999.35 | G44: =+G43+E44-F44 -> -56432.92 | H44: 26.65 | I44: COMBUSTIBLE | K44: KEX 251 | L44: COMBUSTIBLE | M44: =SUM(H55+H66+H70) -> 73.903
A45: 46245 | B45: FA | C45: 98-2369 | D45: HLW 156 | F45: 59999.89 | G45: =+G44+E45-F45 -> -116432.81 | H45: 24.6002 | I45: COMBUSTIBLE | K45: LVX 455 | L45: COMBUSTIBLE | M45: =SUM(H52+H61) -> 49.2
A46: 46245 | B46: FA | C46: 98-2370 | D46: MULITA | F46: 39999.99 | G46: =+G45+E46-F46 -> -156432.8 | H46: 17.5208 | I46: COMBUSTIBLE | K46: AG 958 JV | L46: COMBUSTIBLE | M46: =SUM(H39+H63) -> 327.149
A47: 46245 | B47: FA | C47: 96-9144 | D47: HLW 156 | F47: 59999.4 | G47: =+G46+E47-F47 -> -216432.2 | K47: AG 768 OI | L47: COMBUSTIBLE | M47: 0
A48: 46245 | B48: FA | C48: 96-9146 | D48: MULITA | F48: 40000.44 | G48: =+G47+E48-F48 -> -256432.64 | K48: KJR 926 | L48: COMBUSTIBLE | M48: =SUM(H35+H44+H54+H65) -> 100.6127
A49: 46245 | B49: NC | C49: 100-0011 | D49: NOTA DE CREDITO | E49: 40000.44 | G49: =+G48+E49-F49 -> -216432.2 | I49: DEVOLUCIÓN DE PAGO DE COMBUSTIBLE MULITA (96-9146) | K49: HLW 156 | L49: COMBUSTIBLE | M49: =SUM(H37+H45+H57+H58+H67) -> 118.1322
A50: 46245 | B50: NC | C50: 100-0012 | D50: NOTA DE CREDITO | E50: 59999.4 | G50: =+G49+E50-F50 -> -156432.8 | I50: DEVOLUCIÓN DE PAGO DE COMBUSTIBLE HLW 156 (96-9144) | K50: WNO 918 | L50: COMBUSTIBLE | M50: =SUM(H38+H53) -> 116.792
A51: 46245 | B51: FA | C51: 60-8706 | D51: PFG 964 | F51: 59999.4 | G51: =+G50+E51-F51 -> -216432.2 | H51: 24.6 | I51: COMBUSTIBLE | K51: HKQ 258 | L51: COMBUSTIBLE | M51: =SUM(H42) -> 297.38
A52: 46245 | B52: FA | C52: 96-9170 | D52: LVX 455 | F52: 59999.4 | G52: =+G51+E52-F52 -> -276431.6 | H52: 24.6 | I52: COMBUSTIBLE | K52: AUTOELEVADOR | L52: COMBUSTIBLE | M52: =SUM(H36+H43+H46+H60+H69) -> 145.4088
A53: 46246 | B53: FA | C53: 94-4415 | D53: WNO 918 | F53: 43494.72 | G53: =+G52+E53-F53 -> -319926.32 | H53: 19.085 | I53: COMBUSTIBLE | K53: LITROS SEMANAL | M53: =SUM(M37:M52) -> 1433.4027
A54: 46246 | B54: FA | C54: 96-9205 | D54: KJR 926 | F54: 60000.1 | G54: =+G53+E54-F54 -> -379926.42 | H54: 24.6407 | I54: COMBUSTIBLE
A55: 46246 | B55: FA | C55: 96-9206 | D55: KEX 251 | F55: 60000.84 | G55: =+G54+E55-F55 -> -439927.26 | H55: 24.641 | I55: COMBUSTIBLE
A56: 46246 | B56: FA | C56: 96-9224 | D56: PFG 964 | F56: 60000.84 | G56: =+G55+E56-F56 -> -499928.1 | H56: 24.641 | I56: COMBUSTIBLE
A57: 46247 | B57: FA | C57: 92-3813 | D57: HLW 156 | F57: 59999.4 | G57: =+G56+E57-F57 -> -559927.5 | H57: 24.6 | I57: COMBUSTIBLE
A58: 46247 | B58: FA | C58: 92-3817 | D58: HLW 156 | F58: 40001.01 | G58: =+G57+E58-F58 -> -599928.51 | H58: 17.552 | I58: COMBUSTIBLE
A59: 46247 | B59: FA | C59: 92-3829 | D59: PFG 964 | F59: 59999.4 | G59: =+G58+E59-F59 -> -659927.91 | H59: 24.6 | I59: COMBUSTIBLE
A60: 46247 | B60: FA | C60: 92-3831 | D60: MULITA | F60: 79929.09 | G60: =+G59+E60-F60 -> -739857 | H60: 35.072 | I60: COMBUSTIBLE
A61: 46247 | B61: FA | C61: 92-3833 | D61: LVX 455 | F61: 59999.4 | G61: =+G60+E61-F61 -> -799856.4 | H61: 24.6 | I61: COMBUSTIBLE
A62: 46248 | B62: RE | C62: 50-0409 | D62: TRANSF | E62: 2000000 | G62: =+G61+E62-F62 -> 1200143.6 | I62: PAGO - SALDO A FAVOR
A63: 46248 | B63: FA | C63: 94-4471 | D63: AG 958 JV | F63: 429252.43 | G63: =+G62+E63-F63 -> 770891.17 | H63: 176.212 | I63: COMBUSTIBLE
A64: 46248 | B64: FA | C64: 96-9310 | D64: AG 962 EW | F64: 100009.98 | G64: =+G63+E64-F64 -> 670881.19 | H64: 41.055 | I64: COMBUSTIBLE
A65: 46248 | B65: FA | C65: 96-9324 | D65: KJR 926 | F65: 60001.12 | G65: =+G64+E65-F65 -> 610880.07 | H65: 24.631 | I65: COMBUSTIBLE
A66: 46248 | B66: FA | C66: 96-9337 | D66: KEX 251 | F66: 60001.12 | G66: =+G65+E66-F66 -> 550878.95 | H66: 24.631 | I66: COMBUSTIBLE
A67: 46249 | B67: FA | C67: 92-3911 | D67: HLW 156 | F67: 60001.12 | G67: =+G66+E67-F67 -> 490877.83 | H67: 24.631 | I67: COMBUSTIBLE
A68: 46249 | B68: FA | C68: 92-3912 | D68: PFG 964 | F68: 60001.12 | G68: =+G67+E68-F68 -> 430876.71 | H68: 24.631 | I68: COMBUSTIBLE
A69: 46249 | B69: FA | C69: 92-3913 | D69: MULITA | F69: 76233.94 | G69: =+G68+E69-F69 -> 354642.77 | H69: 33.392 | I69: COMBUSTIBLE
A70: 46249 | B70: FA | C70: 60-8874 | D70: KEX 251 | F70: 60001.12 | G70: =+G69+E70-F70 -> 294641.65 | H70: 24.631 | I70: COMBUSTIBLE
A71: TOTAL DE LITROS SEMANAL | H71: =SUM(H35:H70) -> 1433.4027
A72: SEMANA DEL 9/8 AL 15/8 | K72: SEMANA DEL 16/8 AL 22/8
A73: 46250 | B73: FA | C73: 92-3951 | D73: KJR 926 | F73: 59999.4 | G73: =+G70+E73-F73 -> 234642.25 | H73: 24.6 | I73: COMBUSTIBLE | K73: RESUMEN CONSUMO
A74: 46250 | B74: FA | C74: 96-9388 | D74: PFG 964 | F74: 59999.4 | G74: =+G73+E74-F74 -> 174642.85 | H74: 24.6 | I74: COMBUSTIBLE | K74: RESUMEN | L74: CONSUMO | M74: LTS
A75: 46250 | B75: FA | C75: 94-4513 | D75: WNO 918 | F75: 250379.54 | G75: =+G74+E75-F75 -> -75736.69 | H75: 109.912 | I75: COMBUSTIBLE | K75: AG 378 AV | L75: COMBUSTIBLE | M75: 0
A76: 46251 | B76: FA | C76: 92-3990 | D76: MULITA | F76: 41411.45 | G76: =+G75+E76-F76 -> -117148.14 | H76: 18.147 | I76: COMBUSTIBLE | K76: AG 337 MY | L76: COMBUSTIBLE | M76: =SUM(H97) -> 73.51
A77: 46251 | B77: FA | C77: 92-3991 | D77: HLW 156 | F77: 60000.05 | G77: =+G76+E77-F77 -> -177148.19 | H77: 24.6508 | I77: COMBUSTIBLE | K77: AG 962 EW | L77: COMBUSTIBLE | M77: =SUM(H93) -> 50.12
A78: 46251 | B78: FA | C78: 96-9408 | D78: PFG 964 | F78: 60000.53 | G78: =+G77+E78-F78 -> -237148.72 | H78: 24.651 | I78: COMBUSTIBLE | K78: MOTO AMARILLA | L78: COMBUSTIBLE | M78: 0
A79: 46251 | B79: FA | C79: 94-4533 | D79: HKQ 258 | F79: 990000.29 | G79: =+G78+E79-F79 -> -1227149 | H79: 406.738 | I79: COMBUSTIBLE | K79: MOTO GRIS | L79: COMBUSTIBLE | M79: 0
A80: 46252 | B80: FA | C80: 92-4034 | D80: PFG 964 | F80: 60000.84 | G80: =+G79+E80-F80 -> -1287149.8 | H80: 24.641 | I80: COMBUSTIBLE | K80: AF 728 AT | L80: COMBUSTIBLE | M80: =SUM(H89) -> 71.192
A81: 46252 | B81: FA | C81: 60-8973 | D81: LVX 455 | F81: 60000.84 | G81: =+G80+E81-F81 -> -1347150.7 | H81: 24.641 | I81: COMBUSTIBLE | K81: PFG 964 | L81: COMBUSTIBLE | M81: =SUM(H74+H78+H80+H94+H99) -> 123.1232
A82: 46252 | B82: RE | C82: 50-0411 | D82: TRANSF | E82: 1500000 | G82: =+G81+E82-F82 -> 152849.31 | I82: PAGO - SALDO A FAVOR | K82: KEX 251 | L82: COMBUSTIBLE | M82: =SUM(H83) -> 73.112
A83: 46252 | B83: FA | C83: 92-4068 | D83: KEX 251 | F83: 178027.72 | G83: =+G82+E83-F83 -> -25178.41 | H83: 73.112 | I83: COMBUSTIBLE | K83: LVX 455 | L83: COMBUSTIBLE | M83: =SUM(H81+H92) -> 49.282
A84: 46252 | B84: FA | C84: 94-4577 | D84: AG 768 OI | F84: 990000.39 | G84: =+G83+E84-F84 -> -1015178.8 | H84: 406.571 | I84: COMBUSTIBLE | K84: AG 958 JV | L84: COMBUSTIBLE | M84: =SUM(H87+H101) -> 164.102
A85: 46253 | B85: FA | C85: 60-9019 | D85: HLW 156 | F85: 59999.4 | G85: =+G84+E85-F85 -> -1075178.2 | H85: 24.6 | I85: COMBUSTIBLE | K85: AG 768 OI | L85: COMBUSTIBLE | M85: =SUM(H84+H96) -> 529.522
A86: 46253 | B86: RE | C86: 50-0412 | D86: TRANSF | E86: 2000000 | G86: =+G85+E86-F86 -> 924821.8 | I86: PAGO - SALDO A FAVOR | K86: KJR 926 | L86: COMBUSTIBLE | M86: =SUM(H73+H88) -> 49.241
A87: 46253 | B87: FA | C87: 94-4594 | D87: AG 958 JV | F87: 99999 | G87: =+G86+E87-F87 -> 824822.8 | H87: 41 | I87: COMBUSTIBLE | K87: HLW 156 | L87: COMBUSTIBLE | M87: =SUM(H77+H85+H91) -> 71.8408
A88: 46254 | B88: FA | C88: 96-9566 | D88: KJR 926 | F88: 60000.84 | G88: =+G87+E88-F88 -> 764821.96 | H88: 24.641 | I88: COMBUSTIBLE | K88: WNO 918 | L88: COMBUSTIBLE | M88: =SUM(H75) -> 109.912
A89: 46254 | B89: FA | C89: 94-4610 | D89: AF 728 AT | F89: 173352.52 | G89: =+G88+E89-F89 -> 591469.44 | H89: 71.192 | I89: COMBUSTIBLE | K89: HKQ 258 | L89: COMBUSTIBLE | M89: =SUM(H79) -> 406.738
A90: 46254 | B90: FA | C90: 96-9569 | D90: MULITA | F90: 41245.2 | G90: =+G89+E90-F90 -> 550224.24 | H90: 18.09 | I90: COMBUSTIBLE | K90: AUTOELEVADOR | L90: COMBUSTIBLE | M90: =SUM(H76+H90+H95+H100) -> 71.214
A91: 46254 | B91: FA | C91: 96-9575 | D91: HLW 156 | F91: 55006.65 | G91: =+G90+E91-F91 -> 495217.59 | H91: 22.59 | I91: COMBUSTIBLE | K91: LITROS SEMANAL | M91: =SUM(M75:M90) -> 1842.909
A92: 46254 | B92: FA | C92: 96-9576 | D92: LVX 455 | F92: 60000.84 | G92: =+G91+E92-F92 -> 435216.75 | H92: 24.641 | I92: COMBUSTIBLE
A93: 46254 | B93: FA | C93: 60-9085 | D93: AG 962 EW | F93: 122042.2 | G93: =+G92+E93-F93 -> 313174.55 | H93: 50.12 | I93: COMBUSTIBLE
A94: 46254 | B94: FA | C94: 60-9087 | D94: PFG 964 | F94: 60000.84 | G94: =+G93+E94-F94 -> 253173.71 | H94: 24.641 | I94: COMBUSTIBLE
A95: 46255 | B95: FA | C95: 96-9641 | D95: MULITA | F95: 36423 | G95: =+G94+E95-F95 -> 216750.71 | H95: 15.975 | I95: COMBUSTIBLE
A96: 46255 | B96: FA | C96: 94-4664 | D96: AG 768 OI | F96: 300000.44 | G96: =+G95+E96-F96 -> -83249.73 | H96: 122.951 | I96: COMBUSTIBLE
A97: 46255 | B97: FA | C97: 92-4175 | D97: AG 337 MY | F97: 179364.4 | G97: =+G96+E97-F97 -> -262614.13 | H97: 73.51 | I97: COMBUSTIBLE
A98: 46255 | B98: RE | C98: 50-0425 | D98: TRANSF | E98: 1000000 | G98: =+G97+E98-F98 -> 737385.87 | I98: PAGO - SALDO A FAVOR
A99: 46255 | B99: FA | C99: 96-9693 | D99: PFG 964 | F99: 60000.09 | G99: =+G98+E99-F99 -> 677385.78 | H99: 24.5902 | I99: COMBUSTIBLE
A100: 46256 | B100: FA | C100: 94-4690 | D100: MULITA | F100: 43267.55 | G100: =+G99+E100-F100 -> 634118.23 | H100: 19.002 | I100: COMBUSTIBLE
A101: 46256 | B101: FA | C101: 94-4691 | D101: AG 958 JV | F101: 299999.57 | G101: =+G100+E101-F101 -> 334118.66 | H101: 123.102 | I101: COMBUSTIBLE
A102: TOTAL DE LITROS SEMANAL | H102: =SUM(H73:H101) -> 1842.909
A103: SEMANA DEL 16/8 AL 22/8 | K103: SEMANA DEL 23/8 AL 31/8
A104: 46257 | B104: FA | C104: 92-4217 | D104: KJR 926 | F104: 59998.94 | G104: =+G101+E104-F104 -> 274119.72 | H104: 24.62 | I104: COMBUSTIBLE | K104: RESUMEN CONSUMO
...

Sheet SEPTIMBRE.2026
A5: CTA.CTE - 2026 - CARGAS | K5: SEMANA DEL / AL /
A6: CARGAS COMBUSTIBLE YPF | K6: RESUMEN CONSUMO
A7: FECHA | B7: TIPO | C7: N° FA/COMP | D7: VEHICULO | E7: PAGOS | F7: CONSUMOS | G7: SALDO | H7: LITROS | I7: OBSEVACIONES | K7: RESUMEN | L7: CONSUMO | M7: LTS
A8: 46203 | C8: SALDO ANTERIOR | G8: =+E8-F8 -> 0 | K8: AG 378 AV | L8: COMBUSTIBLE | M8: 0
K9: AG 337 MY | L9: COMBUSTIBLE | M9: 0
K10: AG 962 EW | L10: COMBUSTIBLE | M10: 0
K11: AE 919 JA | L11: COMBUSTIBLE | M11: =SUM(H12+H18+H23+H36+H37+H49) -> 0
K12: AA 183 PK | L12: COMBUSTIBLE | M12: =SUM(H16+H33+H41+H53) -> 0
K13: MOTO AMARILLA | L13: COMBUSTIBLE | M13: 0
K14: MOTO GRIS | L14: COMBUSTIBLE | M14: =SUM(H46) -> 0
K15: KEX 251 | L15: COMBUSTIBLE | M15: 0
K16: AF 728 AT | L16: COMBUSTIBLE | M16: =SUM(H13+H39+H56) -> 0
K17: PFG 964 | L17: COMBUSTIBLE | M17: =SUM(H17+H34+H48+H55) -> 0
K18: LVX 455 | L18: COMBUSTIBLE | M18: =SUM(H10+H24+H45+H50+H51) -> 0
K19: AG 958 JV | L19: COMBUSTIBLE | M19: =SUM(H8+H42) -> 0
K20: AG 768 OI | L20: COMBUSTIBLE | M20: =SUM(H15) -> 0
K21: KJR 926 | L21: COMBUSTIBLE | M21: =SUM(H14+H31+H54) -> 0
K22: HLW 156 | L22: COMBUSTIBLE | M22: =SUM(H26+H40+H52) -> 0
K23: WNO 918 | L23: COMBUSTIBLE | M23: =SUM(H19+H29) -> 0
K24: HKQ 258 | L24: COMBUSTIBLE | M24: =SUM(H6+H44) -> 0
K25: FTL 303 | L25: COMBUSTIBLE | M25: =SUM(H28) -> 0
K26: AUTOELEVADOR | L26: COMBUSTIBLE | M26: =SUM(H11+H20+H27+H32+H35) -> 0
K27: LITROS SEMANAL | M27: =SUM(M7:M26) -> 0
A112: TOTAL | E112: =SUM(E8:E111) -> 0 | F112: =SUM(F8:F111) -> 0 | G112: =+G111 -> 0 | H112: =SUM(H9:H111) -> 0

Sheet OCTUBRE.2026
A5: CTA.CTE - 2026 - CARGAS | K5: SEMANA DEL / AL /
A6: CARGAS COMBUSTIBLE YPF | K6: RESUMEN CONSUMO
A7: FECHA | B7: TIPO | C7: N° FA/COMP | D7: VEHICULO | E7: PAGOS | F7: CONSUMOS | G7: SALDO | H7: LITROS | I7: OBSEVACIONES | K7: RESUMEN | L7: CONSUMO | M7: LTS
A8: 46203 | C8: SALDO ANTERIOR | G8: =+E8-F8 -> 0 | K8: AG 378 AV | L8: COMBUSTIBLE | M8: 0
K9: AG 337 MY | L9: COMBUSTIBLE | M9: 0
K10: AG 962 EW | L10: COMBUSTIBLE | M10: 0
K11: AE 919 JA | L11: COMBUSTIBLE | M11: =SUM(H12+H18+H23+H36+H37+H49) -> 0
K12: AA 183 PK | L12: COMBUSTIBLE | M12: =SUM(H16+H33+H41+H53) -> 0
K13: MOTO AMARILLA | L13: COMBUSTIBLE | M13: 0
K14: MOTO GRIS | L14: COMBUSTIBLE | M14: =SUM(H46) -> 0
K15: KEX 251 | L15: COMBUSTIBLE | M15: 0
K16: AF 728 AT | L16: COMBUSTIBLE | M16: =SUM(H13+H39+H56) -> 0
K17: PFG 964 | L17: COMBUSTIBLE | M17: =SUM(H17+H34+H48+H55) -> 0
K18: LVX 455 | L18: COMBUSTIBLE | M18: =SUM(H10+H24+H45+H50+H51) -> 0
K19: AG 958 JV | L19: COMBUSTIBLE | M19: =SUM(H8+H42) -> 0
K20: AG 768 OI | L20: COMBUSTIBLE | M20: =SUM(H15) -> 0
K21: KJR 926 | L21: COMBUSTIBLE | M21: =SUM(H14+H31+H54) -> 0
K22: HLW 156 | L22: COMBUSTIBLE | M22: =SUM(H26+H40+H52) -> 0
K23: WNO 918 | L23: COMBUSTIBLE | M23: =SUM(H19+H29) -> 0
K24: HKQ 258 | L24: COMBUSTIBLE | M24: =SUM(H6+H44) -> 0
K25: FTL 303 | L25: COMBUSTIBLE | M25: =SUM(H28) -> 0
K26: AUTOELEVADOR | L26: COMBUSTIBLE | M26: =SUM(H11+H20+H27+H32+H35) -> 0
K27: LITROS SEMANAL | M27: =SUM(M7:M26) -> 0
A112: TOTAL | E112: =SUM(E8:E111) -> 0 | F112: =SUM(F8:F111) -> 0 | G112: =+G111 -> 0 | H112: =SUM(H9:H111) -> 0

Sheet NOVIEMBRE.2026
A5: CTA.CTE - 2026 - CARGAS | K5: SEMANA DEL / AL /
A6: CARGAS COMBUSTIBLE YPF | K6: RESUMEN CONSUMO
A7: FECHA | B7: TIPO | C7: N° FA/COMP | D7: VEHICULO | E7: PAGOS | F7: CONSUMOS | G7: SALDO | H7: LITROS | I7: OBSEVACIONES | K7: RESUMEN | L7: CONSUMO | M7: LTS
A8: 46203 | C8: SALDO ANTERIOR | G8: =+E8-F8 -> 0 | K8: AG 378 AV | L8: COMBUSTIBLE | M8: 0
K9: AG 337 MY | L9: COMBUSTIBLE | M9: 0
K10: AG 962 EW | L10: COMBUSTIBLE | M10: 0
K11: AE 919 JA | L11: COMBUSTIBLE | M11: =SUM(H12+H18+H23+H36+H37+H49) -> 0
K12: AA 183 PK | L12: COMBUSTIBLE | M12: =SUM(H16+H33+H41+H53) -> 0
K13: MOTO AMARILLA | L13: COMBUSTIBLE | M13: 0
K14: MOTO GRIS | L14: COMBUSTIBLE | M14: =SUM(H46) -> 0
K15: KEX 251 | L15: COMBUSTIBLE | M15: 0
K16: AF 728 AT | L16: COMBUSTIBLE | M16: =SUM(H13+H39+H56) -> 0
K17: PFG 964 | L17: COMBUSTIBLE | M17: =SUM(H17+H34+H48+H55) -> 0
K18: LVX 455 | L18: COMBUSTIBLE | M18: =SUM(H10+H24+H45+H50+H51) -> 0
K19: AG 958 JV | L19: COMBUSTIBLE | M19: =SUM(H8+H42) -> 0
K20: AG 768 OI | L20: COMBUSTIBLE | M20: =SUM(H15) -> 0
K21: KJR 926 | L21: COMBUSTIBLE | M21: =SUM(H14+H31+H54) -> 0
K22: HLW 156 | L22: COMBUSTIBLE | M22: =SUM(H26+H40+H52) -> 0
K23: WNO 918 | L23: COMBUSTIBLE | M23: =SUM(H19+H29) -> 0
K24: HKQ 258 | L24: COMBUSTIBLE | M24: =SUM(H6+H44) -> 0
K25: FTL 303 | L25: COMBUSTIBLE | M25: =SUM(H28) -> 0
K26: AUTOELEVADOR | L26: COMBUSTIBLE | M26: =SUM(H11+H20+H27+H32+H35) -> 0
K27: LITROS SEMANAL | M27: =SUM(M7:M26) -> 0
A112: TOTAL | E112: =SUM(E8:E111) -> 0 | F112: =SUM(F8:F111) -> 0 | G112: =+G111 -> 0 | H112: =SUM(H9:H111) -> 0

Sheet DICIEMBRE.2026
A5: CTA.CTE - 2026 - CARGAS | K5: SEMANA DEL / AL /
A6: CARGAS COMBUSTIBLE YPF | K6: RESUMEN CONSUMO
A7: FECHA | B7: TIPO | C7: N° FA/COMP | D7: VEHICULO | E7: PAGOS | F7: CONSUMOS | G7: SALDO | H7: LITROS | I7: OBSEVACIONES | K7: RESUMEN | L7: CONSUMO | M7: LTS
A8: 46203 | C8: SALDO ANTERIOR | G8: =+E8-F8 -> 0 | K8: AG 378 AV | L8: COMBUSTIBLE | M8: 0
K9: AG 337 MY | L9: COMBUSTIBLE | M9: 0
K10: AG 962 EW | L10: COMBUSTIBLE | M10: 0
K11: AE 919 JA | L11: COMBUSTIBLE | M11: =SUM(H12+H18+H23+H36+H37+H49) -> 0
K12: AA 183 PK | L12: COMBUSTIBLE | M12: =SUM(H16+H33+H41+H53) -> 0
K13: MOTO AMARILLA | L13: COMBUSTIBLE | M13: 0
K14: MOTO GRIS | L14: COMBUSTIBLE | M14: =SUM(H46) -> 0
K15: KEX 251 | L15: COMBUSTIBLE | M15: 0
K16: AF 728 AT | L16: COMBUSTIBLE | M16: =SUM(H13+H39+H56) -> 0
K17: PFG 964 | L17: COMBUSTIBLE | M17: =SUM(H17+H34+H48+H55) -> 0
K18: LVX 455 | L18: COMBUSTIBLE | M18: =SUM(H10+H24+H45+H50+H51) -> 0
K19: AG 958 JV | L19: COMBUSTIBLE | M19: =SUM(H8+H42) -> 0
K20: AG 768 OI | L20: COMBUSTIBLE | M20: =SUM(H15) -> 0
K21: KJR 926 | L21: COMBUSTIBLE | M21: =SUM(H14+H31+H54) -> 0
K22: HLW 156 | L22: COMBUSTIBLE | M22: =SUM(H26+H40+H52) -> 0
K23: WNO 918 | L23: COMBUSTIBLE | M23: =SUM(H19+H29) -> 0
K24: HKQ 258 | L24: COMBUSTIBLE | M24: =SUM(H6+H44) -> 0
K25: FTL 303 | L25: COMBUSTIBLE | M25: =SUM(H28) -> 0
K26: AUTOELEVADOR | L26: COMBUSTIBLE | M26: =SUM(H11+H20+H27+H32+H35) -> 0
K27: LITROS SEMANAL | M27: =SUM(M7:M26) -> 0
A112: TOTAL | E112: =SUM(E8:E111) -> 0 | F112: =SUM(F8:F111) -> 0 | G112: =+G111 -> 0 | H112: =SUM(#REF!+#REF!+#REF!+#REF!) -> #REF!

Sheet TRANSF.EFECT DE COMBUSTIBLE 
A2: PAGOS MENSUAL 2026
A3: MES | B3: OBSERVACION | C3: MONTO EN PESOS | D3: PORCENTAJE
A4: ENERO | B4: PAGOS MENSUALES TRANS/EFECT | C4: =SUM(ENERO.2026!E198) -> 14275896 | D4: =C4/$C$16 -> 0.093163197
A5: FEBRERO | B5: PAGOS MENSUALES TRANS/EFECT | C5: =SUM(FEBRERO.2026!E247) -> 23928881 | D5: =C5/$C$16 -> 0.15615769
A6: MARZO | B6: PAGOS MENSUALES TRANS/EFECT | C6: =SUM(MARZO.2026!E213) -> 27277839 | D6: =C6/$C$16 -> 0.17801269
A7: ABRIL | B7: PAGOS MENSUALES TRANS/EFECT | C7: =SUM(ABRIL.2026!E249) -> 22000000 | D7: =C7/$C$16 -> 0.14356999
A8: MAYO | B8: PAGOS MENSUALES TRANS/EFECT | C8: =SUM(MAYO.2026!E205) -> 23048711 | D8: =C8/$C$16 -> 0.15041378
A9: JUNIO | B9: PAGOS MENSUALES TRANS/EFECT | C9: =SUM(JUNIO.2026!E118) -> 9294999.3 | D9: =C9/$C$16 -> 0.060658316
A10: JULIO | B10: PAGOS MENSUALES TRANS/EFECT | C10: =SUM(JULIO.2026!E130) -> 17810119 | D10: =C10/$C$16 -> 0.11622721
A11: AGOSTO | B11: PAGOS MENSUALES TRANS/EFECT | C11: =SUM(AGOSTO.2026!E142) -> 15598921 | D11: =C11/$C$16 -> 0.10179713
A12: SEPTIEMBRE | B12: PAGOS MENSUALES TRANS/EFECT | D12: =C12/$C$16 -> 0
A13: OCTUBRE | B13: PAGOS MENSUALES TRANS/EFECT | D13: =C13/$C$16 -> 0
A14: NOVIEMBRE | B14: PAGOS MENSUALES TRANS/EFECT | D14: =C14/$C$16 -> 0
A15: DICIEMBRE | B15: PAGOS MENSUALES TRANS/EFECT | D15: =C15/$C$16 -> 0
A16: TOTAL ANUAL | C16: =SUM(C4:C15) -> 1.5323537e+08

Sheet CONSUMO DE COMBUSTIBLE EN PESOS
A2: CONSUMO MENSUAL 2026
A3: MES | B3: OBSERVACION | C3: MONTO EN PESOS | D3: PORCENTAJE
A4: ENERO | B4: COMBUSTIBLE CONSUMIDO EN PESOS | C4: =SUM(ENERO.2026!F198) -> 14847294 | D4: =C4/$C$16 -> 0.09762217
A5: FEBRERO | B5: COMBUSTIBLE CONSUMIDO EN PESOS | C5: =SUM(FEBRERO.2026!F247) -> 20991042 | D5: =C5/$C$16 -> 0.13801781
A6: MARZO | B6: COMBUSTIBLE CONSUMIDO EN PESOS | C6: =SUM(MARZO.2026!F213) -> 27749588 | D6: =C6/$C$16 -> 0.18245581
A7: ABRIL | B7: COMBUSTIBLE CONSUMIDO EN PESOS | C7: =SUM(ABRIL.2026!F249) -> 21851289 | D7: =C7/$C$16 -> 0.14367401
A8: MAYO | B8: COMBUSTIBLE CONSUMIDO EN PESOS | C8: =SUM(MAYO.2026!F205) -> 22753711 | D8: =C8/$C$16 -> 0.14960751
A9: JUNIO | B9: COMBUSTIBLE CONSUMIDO EN PESOS | C9: =SUM(JUNIO.2026!F118) -> 9476680.1 | D9: =C9/$C$16 -> 0.062309947
A10: JULIO | B10: COMBUSTIBLE CONSUMIDO EN PESOS | C10: =SUM(JULIO.2026!E130+JULIO.2026!G151) -> 18559835 | D10: =C10/$C$16 -> 0.12203244
A11: AGOSTO | B11: COMBUSTIBLE CONSUMIDO EN PESOS | C11: =SUM(AGOSTO.2026!F142) -> 15859924 | D11: =C11/$C$16 -> 0.10428029
A12: SEPTIEMBRE | B12: COMBUSTIBLE CONSUMIDO EN PESOS | D12: =C12/$C$16 -> 0
A13: OCTUBRE | B13: COMBUSTIBLE CONSUMIDO EN PESOS | D13: =C13/$C$16 -> 0
A14: NOVIEMBRE | B14: COMBUSTIBLE CONSUMIDO EN PESOS | D14: =C14/$C$16 -> 0
A15: DICIEMBRE | B15: COMBUSTIBLE CONSUMIDO EN PESOS | D15: =C15/$C$16 -> 0
A16: TOTAL ANUAL | C16: =SUM(C4:C15) -> 1.5208936e+08

Sheet CONSUMO DE LITROS
A2: LITROS MENSUAL 2026
A3: MES | B3: OBSERVACION | C3: MONTO EN LITROS (LTS) | D3: PORCENTAJE
A4: ENERO | B4: LITROS DE COMBUSTIBLE | C4: =SUM(ENERO.2026!H198) -> 7615.8795 | D4: =C4/$C$16 -> 0.11208527
A5: FEBRERO | B5: LITROS DE COMBUSTIBLE | C5: =SUM(FEBRERO.2026!H247) -> 10735.878 | D5: =C5/$C$16 -> 0.15800325
A6: MARZO | B6: LITROS DE COMBUSTIBLE | C6: =SUM(MARZO.2026!H213) -> 13158.28 | D6: =C6/$C$16 -> 0.19365449
A7: ABRIL | B7: LITROS DE COMBUSTIBLE | C7: =SUM(ABRIL.2026!H249) -> 9192.9291 | D7: =C7/$C$16 -> 0.13529519
A8: MAYO | B8: LITROS DE COMBUSTIBLE | C8: =SUM(MAYO.2026!H205) -> 9700.754 | D8: =C8/$C$16 -> 0.14276901
A9: JUNIO | B9: LITROS DE COMBUSTIBLE | C9: =SUM(JUNIO.2026!H118) -> 4009.9589 | D9: =C9/$C$16 -> 0.059015811
A10: JULIO | B10: LITROS DE COMBUSTIBLE | C10: =SUM(JULIO.2026!H130+JULIO.2026!H151) -> 7045.5677 | D10: =C10/$C$16 -> 0.10369181
A11: AGOSTO | B11: LITROS DE COMBUSTIBLE | C11: =SUM(AGOSTO.2026!H142) -> 6487.9499 | D11: =C11/$C$16 -> 0.095485175
A12: SEPTIEMBRE | B12: LITROS DE COMBUSTIBLE | D12: =C12/$C$16 -> 0
A13: OCTUBRE | B13: LITROS DE COMBUSTIBLE | D13: =C13/$C$16 -> 0
A14: NOVIEMBRE | B14: LITROS DE COMBUSTIBLE | D14: =C14/$C$16 -> 0
A15: DICIEMBRE | B15: LITROS DE COMBUSTIBLE | D15: =C15/$C$16 -> 0
A16: TOTAL ANUAL DE LTS | C16: =SUM(C4:C15) -> 67947.196

Sheet CARGAS AUTORIZADAS
A4: FLOTA VEHICULOS CARGAS AUTORIZADAS-2026
B5: TIPO DE VEHICULO | C5: DOMINIO | D5: MODELO | E5: 46126
A6: 1 | B6: CAMIONETA | C6: AG 337 MY | D6: FORD RANGER-2024 | E6: SIN LIMITE DE CARGA
A7: 2 | B7: CAMIONETA | C7: AG 378 AV | D7: TOYOTA SW4 | E7: SIN LIMITE DE CARGA
A8: 3 | B8: CAMIONETA | C8: AG 378 AW | D8: FORD RANGER-2024 | E8: SIN LIMITE DE CARGA
A9: 4 | B9: CAMIONETA | C9: AG 962 EW | D9: NISSAN FRONTIER | E9: SIN LIMITE DE CARGA
A10: 5 | B10: CAMIONETA | C10: PFG 964 | D10: FORD RANGER-2015 | E10: 60000
A11: 6 | B11: CAMIONETA | C11: AA 183 PK | D11: TOYOTA HILUX-2016 | E11: 60000
A12: 7 | B12: CAMIONETA | C12: LVX 455 | D12: TOYOTA HILUX-2012 | E12: 60000
A13: 8 | B13: CAMIONETA | C13: KJR 926 | D13: FORD RANGER-2011 | E13: 60000
A14: 9 | B14: CAMIONETA | C14: KEX 251 | D14: FORD RANGER-2011 | E14: 60000
A15: 10 | B15: CAMIONETA | C15: AE 919 JA | D15: TOYOTA HILUX-2021 | E15: 60000
A16: 11 | B16: CAMIONETA | C16: HLW 156 | D16: FORD RANGER- 2008 | E16: 60000
A17: 12 | B17: AUTOELEVADORES | C17: DOS57 | D17: AZUL/ROJO/4X4 | E17: SIN LIMITE DE CARGA
A18: 13 | B18: CAMION | C18: WNO 918 | D18: MERCEDES BENZ-1968 | E18: SIN LIMITE DE CARGA
A19: 14 | B19: CAMION | C19: HKQ 258 | D19: VOLKWAGEN-2008 | E19: SIN LIMITE DE CARGA
A20: 15 | B20: CAMION | C20: FTL 303 | D20: VOLVO-2006 | E20: SIN LIMITE DE CARGA
A21: 16 | B21: CAMION | C21: AG 768 OI | D21: MERCEDES -2024 | E21: SIN LIMITE DE CARGA
A22: 17 | B22: CAMION-PLANCHA | C22: AG 958 JV | D22: MERCEDES -2025 | E22: SIN LIMITE DE CARGA
A23: 18 | B23: MINIBUS | C23: AF 728 AT | D23: SPRINTER | E23: SIN LIMITE DE CARGA
A24: 19 | B24: MOTOCICLETA | C24: A26 2CPD | D24: CF 700 | E24: SIN LIMITE DE CARGA
A25: 20 | B25: MOTOCICLETA | C25: A19 3NED | D25: ROYAL ENFILN- METEOR 350 | E25: SIN LIMITE DE CARGA
