Workbook

Sheet PRÉSTAMO BANCOR
A2: PRÉSTAMO BANCOR
A3: EMPRESA: Dos57 SRL | G3: CAPITAL: $90.000.000,00
A4: CUIT: 30-71617506-1
A5: BANCO: BANCOR
A6: TASA: VARIABLE - BADLAR 20
A7: CUOTAS: 12
A9: N° CUOTA | B9: VENCIMIENTO | C9: CAPITAL | D9: INTERÉS | E9: IMPUESTO | F9: TOTAL CUOTA | G9: FECHA DE PAGO | H9: ESTADO DE PAGO
A10: 1 | B10: 46127 | C10: 7500000 | D10: 3109600.2 | E10: 528676.14 | F10: =SUM(C10:E10) -> 11138276 | G10: 46136 | H10: PAGADO
A11: 2 | B11: 46157 | C11: 7500000 | D11: 3000000 | E11: 500000 | F11: =SUM(C11:E11) -> 11000000 | G11: 46157 | H11: PAGADO
A12: 3 | B12: 46189 | C12: 7500000 | D12: 3000000 | E12: 500000 | F12: =SUM(C12:E12) -> 11000000 | G12: 46190 | H12: PAGADO
A13: 4 | B13: 46218 | C13: 7500000 | D13: 3000000 | E13: 500000 | F13: =SUM(C13:E13) -> 11000000 | G13: 46218 | H13: PAGADO
A14: 5 | B14: 46252 | C14: 7500000 | D14: 3000000 | E14: 500000 | F14: =SUM(C14:E14) -> 11000000
A15: 6 | B15: 46280 | C15: 7500000 | D15: 3000000 | E15: 500000 | F15: =SUM(C15:E15) -> 11000000
A16: 7 | B16: 46310 | C16: 7500000 | D16: 3000000 | E16: 500000 | F16: =SUM(C16:E16) -> 11000000
A17: 8 | B17: 46342 | C17: 7500000 | D17: 3000000 | E17: 500000 | F17: =SUM(C17:E17) -> 11000000
A18: 9 | B18: 46371 | C18: 7500000 | D18: 3000000 | E18: 500000 | F18: =SUM(C18:E18) -> 11000000
A19: 10 | B19: 46037 | C19: 7500000 | D19: 3000000 | E19: 500000 | F19: =SUM(C19:E19) -> 11000000
A20: 11 | B20: 46068 | C20: 7500000 | D20: 3000000 | E20: 500000 | F20: =SUM(C20:E20) -> 11000000
A21: 12 | B21: 46096 | C21: 7500000 | D21: 3000000 | E21: 500000 | F21: =SUM(C21:E21) -> 11000000
A22: TOTAL PRÉSTAMO BANCOR | F22: =SUM(F10:F21) -> 1.3213828e+08

Sheet PRÉSTAMO GALICIA
A2: PRÉSTAMO GALICIA - GARANTIZAR
A3: EMPRESA: Dos57 SRL | I3: CAPITAL: $50.000.000,00
A4: CUIT: 30-71617506-1
A5: BANCO: GALICIA
A6: TASA: FIJA
A7: CUOTAS: 12
A9: N° CUOTA | B9: VENCIMIENTO | C9: CAPITAL | D9: INTERÉS NOMINAL | E9: IVA INTERÉS NOMINAL | F9: SELLOS | G9: IVAP INTERÉS NOMINAL | H9: TOTAL CUOTA | I9: FECHA DE PAGO | J9: ESTADO DE PAGO
A10: 1 | B10: 46153 | C10: 4166666.7 | D10: 1491780.8 | E10: 156636.99 | F10: 54246.58 | G10: 22376.71 | H10: =SUM(C10:G10) -> 5891707.8 | I10: 46153 | J10: PAGADO
A11: 2 | B11: 46182 | C11: 4166666.7 | D11: 1201712.3 | E11: 126179.79 | F11: 43698.63 | G11: 18025.68 | H11: =SUM(C11:G11) -> 5556283.1 | I11: 46182 | J11: PAGADO
A12: 3 | B12: 46216 | C12: 4166666.7 | D12: 1280821.9 | E12: 134486.3 | F12: 46575.34 | G12: 19212.33 | H12: =SUM(C12:G12) -> 5647762.6 | I12: 46216 | J12: PAGADO
A13: 4 | B13: 46244 | C13: 4166666.7 | D13: 949315.07 | E13: 99678.08 | F13: 34520.55 | G13: 14239.73 | H13: =SUM(C13:G13) -> 5264420.1
A14: 5 | B14: 46274 | C14: 4166666.7 | D14: 904109.59 | E14: 94931.51 | F14: 32876.71 | G14: 13561.64 | H14: =SUM(C14:G14) -> 5212146.1
A15: 6 | B15: 46304 | C15: 4166666.7 | D15: 791095.89 | E15: 83065.07 | F15: 28767.12 | G15: 11866.44 | H15: =SUM(C15:G15) -> 5081461.2
A16: 7 | B16: 46335 | C16: 4166666.7 | D16: 700684.93 | E16: 73571.92 | F16: 25479.45 | G16: 10510.27 | H16: =SUM(C16:G16) -> 4976913.2
A17: 8 | B17: 46365 | C17: 4166666.7 | D17: 565068.49 | E17: 59332.19 | F17: 20547.95 | G17: 8476.03 | H17: =SUM(C17:G17) -> 4820091.3
A18: 9 | B18: 46398 | C18: 4166666.7 | D18: 497260.27 | E18: 52212.33 | F18: 18082.19 | G18: 7458.9 | H18: =SUM(C18:G18) -> 4741680.4
A19: 10 | B19: 46427 | C19: 4166666.7 | D19: 327739.73 | E19: 34412.67 | F19: 11917.81 | G19: 4916.1 | H19: =SUM(C19:G19) -> 4545653
A20: 11 | B20: 46455 | C20: 4166666.7 | D20: 210958.9 | E20: 22150.68 | F20: 7671.23 | G20: 3164.38 | H20: =SUM(C20:G20) -> 4410611.9
A21: 12 | B21: 46486 | C21: 4166666.6 | D21: 116780.82 | E21: 12261.99 | F21: 4246.58 | G21: 1751.71 | H21: =SUM(C21:G21) -> 4301707.7
A22: TOTAL PRÉSTAMO GALICIA - GARANTIZAR | H22: =SUM(H10:H21) -> 60450438

Sheet PRÉSTAMO NACIÓN
A2: PRÉSTAMO NACIÓN
A3: EMPRESA: Dos57 SRL | H3: CAPITAL: $239.000.000
A4: CUIT: 30-71617506-1
A5: BANCO: NACIÓN
A6: TASA: Tamar + 4 puntos
A7: CUOTAS: 12
A9: N° CUOTA | B9: VENCIMIENTO | C9: CAPITAL | D9: INTERÉS | E9: IVA R.I. DIFERENCIAL | F9: IVA PERCEP. RG 2408/08 | G9: TOTAL CUOTA | H9: FECHA DE PAGO | I9: ESTADO DE PAGO
A10: 1 | B10: 46253 | C10: 19916667 | D10: 5230171.2 | E10: 549167.98 | F10: 78452.57 | G10: =SUM(C10:F10) -> 25774459
A11: 2 | B11: 46283 | C11: 19916667 | D11: 4794323.6 | E11: 503403.98 | F11: 71914.85 | G11: =SUM(C11:F11) -> 25286309
A12: 3 | B12: 46314 | C12: 19916667 | D12: 4503758.6 | E12: 472894.65 | F12: 67556.38 | G12: =SUM(C12:F12) -> 24960876
A13: 4 | B13: 46343 | C13: 19916667 | D13: 3791874.1 | E13: 398146.78 | F13: 56878.11 | G13: =SUM(C13:F13) -> 24163566
A14: 5 | B14: 46373 | C14: 19916667 | D14: 3486780.8 | E14: 366111.99 | F14: 52301.71 | G14: =SUM(C14:F14) -> 23821861
A15: 6 | B15: 46040 | C15: 19916667 | D15: 3254328.8 | E15: 341704.52 | F15: 48814.93 | G15: =SUM(C15:F15) -> 23561515
A16: 7 | B16: 46068 | C16: 19916667 | D16: 2440746.6 | E16: 256278.39 | F16: 36611.2 | G16: =SUM(C16:F16) -> 22650303
A17: 8 | B17: 46098 | C17: 19916667 | D17: 2179238 | E17: 228819.99 | F17: 32688.57 | G17: =SUM(C17:F17) -> 22357413
A18: 9 | B18: 46128 | C18: 19916667 | D18: 1743390.4 | E18: 183055.99 | F18: 26150.86 | G18: =SUM(C18:F18) -> 21869264
A19: 10 | B19: 46159 | C19: 19916667 | D19: 1351127.6 | E19: 141868.39 | F19: 20266.91 | G19: =SUM(C19:F19) -> 21429930
A20: 11 | B20: 46188 | C20: 19916667 | D20: 842638.7 | E20: 88477.06 | F20: 12639.58 | G20: =SUM(C20:F20) -> 20860422
A21: 12 | B21: 46218 | C21: 19916667 | D21: 435847.6 | E21: 45764 | F21: 6537.71 | G21: =SUM(C21:F21) -> 20404816
A22: TOTAL PRÉSTAMO NACIÓN | G22: =SUM(G10:G21) -> 2.7714073e+08

Sheet PRÉSTAMOS 2026 - RESÚMEN
A2: RESÚMEN PRÉSTAMOS DOS57 2026
A4: BANCO | B4: N° CUOTA | C4: CAPITAL | D4: TOTAL A PAGAR | E4: VENCIMIENTO | F4: FECHA DE PAGO | G4: ESTADO DE PAGO
A5: BANCOR | B5: 1 | C5: 7500000 | D5: 11138276 | E5: 46127 | F5: =+'PRÉSTAMO BANCOR'!G10 -> 46136 | G5: =+'PRÉSTAMO BANCOR'!H10 -> PAGADO
B6: 2 | C6: 7500000 | D6: 11000000 | E6: 46157 | F6: =+'PRÉSTAMO BANCOR'!G11 -> 46157 | G6: =+'PRÉSTAMO BANCOR'!H11 -> PAGADO
B7: 3 | C7: 7500000 | D7: 11000000 | E7: 46189 | F7: =+'PRÉSTAMO BANCOR'!G12 -> 46190 | G7: =+'PRÉSTAMO BANCOR'!H12 -> PAGADO
B8: 4 | C8: 7500000 | D8: 11000000 | E8: 46218 | F8: =+'PRÉSTAMO BANCOR'!G13 -> 46218 | G8: =+'PRÉSTAMO BANCOR'!H13 -> PAGADO
B9: 5 | C9: 7500000 | D9: 11000000 | E9: 46252
B10: 6 | C10: 7500000 | D10: 11000000 | E10: 46280
B11: 7 | C11: 7500000 | D11: 11000000 | E11: 46310
B12: 8 | C12: 7500000 | D12: 11000000 | E12: 46342
B13: 9 | C13: 7500000 | D13: 11000000 | E13: 46371
B14: 10 | C14: 7500000 | D14: 11000000 | E14: 46037
B15: 11 | C15: 7500000 | D15: 11000000 | E15: 46068
B16: 12 | C16: 7500000 | D16: 11000000 | E16: 46096
A18: GALICIA | B18: 1 | C18: 4166666.7 | D18: =+'PRÉSTAMO GALICIA'!H10 -> 5891707.8 | E18: 46153 | F18: =+'PRÉSTAMO GALICIA'!I10 -> 46153 | G18: =+'PRÉSTAMO GALICIA'!J10 -> PAGADO
B19: 2 | C19: 4166666.7 | D19: =+'PRÉSTAMO GALICIA'!H11 -> 5556283.1 | E19: 46182 | F19: =+'PRÉSTAMO GALICIA'!I11 -> 46182 | G19: =+'PRÉSTAMO GALICIA'!J11 -> PAGADO
B20: 3 | C20: 4166666.7 | D20: =+'PRÉSTAMO GALICIA'!H12 -> 5647762.6 | E20: 46216 | F20: =+'PRÉSTAMO GALICIA'!I12 -> 46216 | G20: =+'PRÉSTAMO GALICIA'!J12 -> PAGADO
B21: 4 | C21: 4166666.7 | D21: =+'PRÉSTAMO GALICIA'!H13 -> 5264420.1 | E21: 46244
B22: 5 | C22: 4166666.7 | D22: =+'PRÉSTAMO GALICIA'!H14 -> 5212146.1 | E22: 46274
B23: 6 | C23: 4166666.7 | D23: =+'PRÉSTAMO GALICIA'!H15 -> 5081461.2 | E23: 46304
B24: 7 | C24: 4166666.7 | D24: =+'PRÉSTAMO GALICIA'!H16 -> 4976913.2 | E24: 46335
B25: 8 | C25: 4166666.7 | D25: =+'PRÉSTAMO GALICIA'!H17 -> 4820091.3 | E25: 46365
B26: 9 | C26: 4166666.7 | D26: =+'PRÉSTAMO GALICIA'!H18 -> 4741680.4 | E26: 46398
B27: 10 | C27: 4166666.7 | D27: =+'PRÉSTAMO GALICIA'!H19 -> 4545653 | E27: 46427
B28: 11 | C28: 4166666.7 | D28: =+'PRÉSTAMO GALICIA'!H20 -> 4410611.9 | E28: 46455
B29: 12 | C29: 4166666.7 | D29: =+'PRÉSTAMO GALICIA'!H21 -> 4301707.7 | E29: 46486
A31: NACIÓN | B31: 1 | C31: =+'PRÉSTAMO NACIÓN'!C10 -> 19916667 | D31: =+'PRÉSTAMO NACIÓN'!G10 -> 25774459 | E31: 46253
B32: 2 | C32: =+'PRÉSTAMO NACIÓN'!C11 -> 19916667 | D32: =+'PRÉSTAMO NACIÓN'!G11 -> 25286309 | E32: 46283
B33: 3 | C33: =+'PRÉSTAMO NACIÓN'!C12 -> 19916667 | D33: =+'PRÉSTAMO NACIÓN'!G12 -> 24960876 | E33: 46314
B34: 4 | C34: =+'PRÉSTAMO NACIÓN'!C13 -> 19916667 | D34: =+'PRÉSTAMO NACIÓN'!G13 -> 24163566 | E34: 46343
B35: 5 | C35: =+'PRÉSTAMO NACIÓN'!C14 -> 19916667 | D35: =+'PRÉSTAMO NACIÓN'!G14 -> 23821861 | E35: 46373
B36: 6 | C36: =+'PRÉSTAMO NACIÓN'!C15 -> 19916667 | D36: =+'PRÉSTAMO NACIÓN'!G15 -> 23561515 | E36: 46040
B37: 7 | C37: =+'PRÉSTAMO NACIÓN'!C16 -> 19916667 | D37: =+'PRÉSTAMO NACIÓN'!G16 -> 22650303 | E37: 46068
B38: 8 | C38: =+'PRÉSTAMO NACIÓN'!C17 -> 19916667 | D38: =+'PRÉSTAMO NACIÓN'!G17 -> 22357413 | E38: 46098
B39: 9 | C39: =+'PRÉSTAMO NACIÓN'!C18 -> 19916667 | D39: =+'PRÉSTAMO NACIÓN'!G18 -> 21869264 | E39: 46128
B40: 10 | C40: =+'PRÉSTAMO NACIÓN'!C19 -> 19916667 | D40: =+'PRÉSTAMO NACIÓN'!G19 -> 21429930 | E40: 46159
B41: 11 | C41: =+'PRÉSTAMO NACIÓN'!C20 -> 19916667 | D41: =+'PRÉSTAMO NACIÓN'!G20 -> 20860422 | E41: 46188
B42: 12 | C42: =+'PRÉSTAMO NACIÓN'!C21 -> 19916667 | D42: =+'PRÉSTAMO NACIÓN'!G21 -> 20404816 | E42: 46218
