Workbook

Sheet EVENTOS
A1: PLANILLA EVENTOS - DOS57 SRL - JULIO 2026
A3: DATOS EVENTOS | F3: CARGA AUTOMÁTICA EN PLANILLA | J3: CARGA MANUAL EN PLANILLA
A4: ITEM | B4: FECHA | C4: CALIFICACION | D4: NOMBRE DEL EVENTO | E4: LUGAR | F4: FURIA | G4: FAUSTO | H4: MILTON | I4: CHARA | J4: CHOLI | K4: PEPO | L4: MARIO | M4: JAZ | N4: FLOR
A5: 1 | B5: 46207 | C5: LAYHER | D5: LOS PUMAS VS ESCOCIA | E5: ESTADIO MARIO ALBERTO KEMPES | F5: 1 | H5: 1 | I5: 1
A6: 2 | B6: 46213 | C6: VALLADO | D6: FERIA | E6: VILLA LIBERTADOR
A7: 3 | B7: 46214 | C7: VARIOS | D7: CORDOBA CERCA TUYO | E7: PLAZA VACA ECHADA
A8: 4 | B8: 46219 | C8: VALLADO | D8: FIESTA PRIVADA | E8: SALA DEL REY
A9: 5 | B9: 46221 | C9: LAYHER | D9: LA KONGA | E9: AL RESCOLDO
A10: 6 | B10: 46221 | C10: VALLADO | D10: FERIA | E10: VILLA LIBERTADOR
A11: 7 | B11: 46228 | C11: LAYHER | D11: ALTA PEÑA | E11: CHATEAU PARK | G11: 1 | I11: 1
A12: 8 | B12: 46228 | C12: LAYHER | D12: ANIVERSARIO SANTIAGO DEL ESTERO | E12: SANTIAGO DEL ESTERO | H12: 1 | J12: 1 | K12: 1 | L12: 1
A13: 9 | B13: 46228 | C13: LAYHER | D13: MOMENTS | E13: FORJA | G13: 1
A14: 10 | B14: 46228 | C14: LAYHER | D14: Q LOKURA | E14: PLAZA DE LA MÚSICA
A15: 11 | B15: 46228 | C15: LAYHER | D15: CORDOBA CERCA TUYO | E15: CIUDAD DE LOS CUARTETOS
A16: 12 | B16: 46234 | C16: VALLADO | D16: TALLERES VS VELEZ | E16: ESTADIO MARIO ALBERTO KEMPES | I16: 1
A17: 13 | B17: 46234 | C17: VALLADO | D17: FERIA | E17: VILLA LIBERTADOR
A18: TOTALES | F18: =SUBTOTAL(109,EVENTOS!$F$5:$F$17) -> 1 | G18: =SUBTOTAL(109,EVENTOS!$G$5:$G$17) -> 2 | H18: =SUM(EVENTOS!$H$5:$H$17) -> 2 | I18: =SUM(EVENTOS!$I$5:$I$17) -> 3 | J18: =SUM(EVENTOS!$J$5:$J$17) -> 1 | K18: =SUM(EVENTOS!$K$5:$K$17) -> 1 | L18: =SUM(EVENTOS!$L$5:$L$17) -> 1 | M18: =SUM(EVENTOS!$M$5:$M$17) -> 0 | N18: =SUM(EVENTOS!$N$5:$N$17) -> 0

Sheet VIAJES LUIS
A1: Nombre | C1: LUIS LEDESMA
A2: Mes | C2: JULIO
A3: ITEM | B3: DIA | C3: FECHA | D3: EVENTO | E3: RECORRIDO | H3: EJIDO | K3: VUELTAS | L3: OBSERVACION
E4: INICIO | F4: DESTINO | G4: FINAL | H4: PROVINCIAL | I4: NACIONAL | J4: NACIONAL +1000
A5: 1 | B5: MIERCOLES | C5: 46204 | D5: VACACIONES
A6: 2 | B6: JUEVES | C6: 46205 | D6: VACACIONES
A7: 3 | B7: VIERNES | C7: 46206 | D7: VACACIONES
A8: 4 | B8: SÁBADO | C8: 46207 | D8: VACACIONES
A9: 5 | B9: DOMINGO | C9: 46208 | D9: VACACIONES
A10: 6 | B10: LUNES | C10: 46209 | D10: KEMPES
A11: 7 | B11: MARTES | C11: 46210 | D11: LIBRE
A12: 8 | B12: MIÉRCOLES | C12: 46211 | D12: POLO
A13: 9 | B13: JUEVES | C13: 46212 | D13: POLO
A14: 10 | B14: VIERNES | C14: 46213 | D14: CAMINO DE LAS SIERRAS
A15: 11 | B15: SÁBADO | C15: 46214 | D15: LIBRE
A16: 12 | B16: DOMINGO | C16: 46215 | D16: LIBRE
A17: 13 | B17: LUNES | C17: 46216 | D17: CAMINO DE LAS SIERRAS
A18: 14 | B18: MARTES | C18: 46217 | D18: BUSQUEDA ADOQUINES | E18: POLO | F18: CABALEN/RIO CUARTO | G18: POLO | H18: 1 | K18: 1
A19: 15 | B19: MIÉRCOLES | C19: 46218 | D19: LIBRE
A20: 16 | B20: JUEVES | C20: 46219 | D20: POLO
A21: 17 | B21: VIERNES | C21: 46220 | D21: ANIVERSARIO SGO DEL ESTERO | E21: POLO | F21: SGO DEL ESTERO | I21: 1 | K21: 1
A22: 18 | B22: SÁBADO | C22: 46221 | G22: POLO
A23: 19 | B23: DOMINGO | C23: 46222 | D23: ANIVERSARIO SGO DEL ESTERO | E23: POLO | F23: SGO DEL ESTERO | I23: 1 | K23: 1
A24: 20 | B24: LUNES | C24: 46223 | G24: POLO
A25: 21 | B25: MARTES | C25: 46224 | D25: AL RESCOLDO | E25: POLO | F25: LOS CEDROS | G25: POLO | H25: 1 | K25: 1
A26: 22 | B26: MIÉRCOLES | C26: 46225 | D26: ANIVERSARIO SGO DEL ESTERO | E26: POLO | F26: SGO DEL ESTERO
A27: 23 | B27: JUEVES | C27: 46226 | G27: REGRESO CBA COLECTIVO
A28: 24 | B28: VIERNES | C28: 46227 | D28: KEMPES
A29: 25 | B29: SÁBADO | C29: 46228 | D29: KEMPES + FORJA
A30: 26 | B30: DOMINGO | C30: 46229 | D30: ANIVERSARIO SGO DEL ESTERO | E30: VIAJE MB CON TATI | F30: SGO DEL ESTERO | G30: REGRESA PERLA-POLO | I30: 1 | K30: 1
A31: 27 | B31: LUNES | C31: 46230 | D31: ANIVERSARIO SGO DEL ESTERO | E31: POLO | F31: SGO DEL ESTERO | G31: POLO | I31: 1 | K31: 1
A32: 28 | B32: MARTES | C32: 46231 | D32: ANIVERSARIO SGO DEL ESTERO | E32: POLO | F32: SGO DEL ESTERO | G32: POLO | I32: 1 | K32: 1
A33: 29 | B33: MIÉRCOLES | C33: 46232 | D33: LIBRE
A34: 30 | B34: JUEVES | C34: 46233 | D34: CARPETA
A35: 31 | B35: VIERNES | C35: 46234 | D35: CARPETA
A36: TOTAL | H36: =SUM(H5:H35) -> 2 | I36: =SUM(I5:I35) -> 5 | J36: =SUM(J5:J35) -> 0 | K36: =SUM(K5:K35) -> 7

Sheet MAYRA
J2: AUMENTO
J3: FEBRERO/MARZO
A5: SUELDO JULIO 2026 | G5: SUELDO | I5: =+I6+D12+G12+B12+H12+A12+D8 -> 2979079.9 | J5: AGUINALDOS | L5: MAYRA ONTIVERO
A6: Nombre: MAYRA ONTIVERO DNI: 32787676 | D6: Escalafon: | E6: ADM | F6: 1 | G6: SUELDO ACORDADO | I6: =2279462.98*17.1%+2279462.98 -> 2669251.1 | J6: JULIO | K6: 2669251.1 | L6: Mes: JULIO 2026
A7: SUELDO ENJOY | B7: SUELDO BASICO | C7: 0.32 | D7: EXTRAS | F7: VALES/DESCUENTOS/MULTAS | H7: SUB TOTAL ENJOY | J7: AGOSTO | L7: Sueldo Basico | M7: =+I6 -> 2669251.1
B8: =+I6*32% -> 854160.37 | D8: 0 | F8: =+D54 -> 0 | H8: =+B8+D8-F8 -> 854160.37 | J8: SEPTIEMBRE | L8: Viatico | M8: =+A12 -> 87734.716
A9: SUELDO DOS57 | B9: SUELDO BASICO | C9: 0.68 | D9: EXTRAS | F9: VALES/DESCUENTOS/MULTAS | H9: SUB TOTAL DOS57 | J9: OCTUBRE | L9: Premio Presentismo | M9: =+B12 -> 154806.63
B10: =+I6*68% -> 1815090.8 | D10: =+B12+D12+G12+A12+H12 -> 309828.72 | F10: =+I54 -> 12000 | H10: =+B10+D10-F10 -> 2112919.5 | J10: NOVIEMBRE | L10: Antigüedad | M10: =+G12 -> 23420
A11: VIATICOS | B11: PREMIO PRESENTISMO | D11: TELEFONO | F11: ANTIGÜEDAD | G11: 2 | H11: VACACIONES/AGUINALDOS/ EXTRAS | J11: DICIEMBRE | L11: Telefono | M11: =D12 -> 43867.37
A12: =+M18 -> 87734.716 | B12: =+M20 -> 154806.63 | D12: =+M22 -> 43867.37 | F12: 45323 | G12: =+M25 -> 23420 | J12: TOTAL | K12: =SUM(K6:K11) -> 2669251.1 | L12: Vacas/Aguinaldos/Extras | M12: =+H12 -> 0
A13: % DEL ACUERDO | B13: TIPO DE SEGURO | D13: INICIO DEL ACUERDO | F13: VIGENCIA DEL ACUERDO | H13: IMPORTE TOTAL A COBRAR | J13: 6 MESES | K13: =+K12/6 -> 444875.19 | L13: Total | M13: =SUM(M7:M12) -> 2979079.9
A14: 17,1% Básico + Viático + Teléfono + Presentismo + Antigüedad | B14: ART | D14: 46143 | F14: 9 MESES | H14: =+H8+H10 -> 2967079.9 | J14: AGUINALDOS | K14: =+K13/2 -> 222437.6 | L14: Vales | M14: =+F8+F10 -> 12000
A15: Convocatoria | B15: Dia | D15: Fecha | E15: Inicio de Actividades | G15: Fin de Actividades | I15: Hrs trabajadas | L15: A cobrar | M15: =+M13-M14 -> 2967079.9
A16: LIBRE | B16: MIÉRCOLES | D16: 46204 | I16: 0
A17: 9:00 a. m. | B17: JUEVES | D17: 46205 | E17: 9:16 a. m. | G17: 6:02 p. m. | I17: 8.77 | L17: VIÁTICO
A18: 9:00 a. m. | B18: VIERNES | D18: 46206 | E18: 9:00 a. m. | G18: 5:36 p. m. | I18: 8.6 | L18: 1 Cat | M18: =74922.9*17.1%+74922.9 -> 87734.716
A19: LIBRE | B19: SÁBADO | D19: 46207 | I19: 0 | L19: PREMIO PRESENTISMO
A20: LIBRE | B20: DOMINGO | D20: 46208 | I20: 0 | L20: 1 Cat | M20: =132200.37*17.1%+132200.37 -> 154806.63
A21: 9:00 a. m. | B21: LUNES | D21: 46209 | E21: 9:37 a. m. | G21: 6:04 p. m. | I21: 8.45 | L21: TELÉFONO
A22: HOME OFFICE | B22: MARTES | D22: 46210 | E22: 9:00 a. m. | G22: 1:00 p. m. | I22: 4 | L22: 1 Cat | M22: =37461.46*17.1%+37461.46 -> 43867.37
A23: 9:00 a. m. | B23: MIÉRCOLES | D23: 46211 | E23: 9:06 a. m. | G23: 6:21 p. m. | I23: 9.25 | L23: ANTIGÜEDAD
A24: 9:00 a. m. | B24: JUEVES | D24: 46212 | E24: 9:00 a. m. | G24: 6:08 p. m. | I24: 9.13 | L24: 1 Años | M24: =12500*17.1%+12500 -> 14637.5
A25: 9:00 a. m. | B25: VIERNES | D25: 46213 | E25: 9:14 a. m. | G25: 6:12 p. m. | I25: 8.97 | L25: 2 Años | M25: =20000*17.1%+20000 -> 23420
A26: LIBRE | B26: SÁBADO | D26: 46214 | I26: 0 | L26: 3 Años | M26: =27500*17.1%+27500 -> 32202.5
A27: LIBRE | B27: DOMINGO | D27: 46215 | I27: 0 | L27: 4 Años | M27: =35000*17.1%+35000 -> 40985
A28: VACACIONES | B28: LUNES | D28: 46216 | I28: 8 | L28: 5 Años | M28: =42500*17.1%+42500 -> 49767.5
A29: VACACIONES | B29: MARTES | D29: 46217 | I29: 8 | L29: 6 Años | M29: =63750*17.1%+63750 -> 74651.25
A30: VACACIONES | B30: MIÉRCOLES | D30: 46218 | I30: 8 | L30: 7 Años | M30: =127500*17.1%+127500 -> 149302.5
A31: VACACIONES | B31: JUEVES | D31: 46219 | I31: 8 | L31: 8 Años | M31: =200000*17.1%+200000 -> 234200
A32: VACACIONES | B32: VIERNES | D32: 46220 | I32: 8
A33: VACACIONES | B33: SÁBADO | D33: 46221 | I33: 8
A34: VACACIONES | B34: DOMINGO | D34: 46222 | I34: 8
A35: LIBRE | B35: LUNES | D35: 46223 | I35: 0
A36: 9:00 a. m. | B36: MARTES | D36: 46224 | E36: 9:00 a. m. | G36: 7:00 p. m. | I36: 10 | J36: NEPER
A37: 9:00 a. m. | B37: MIÉRCOLES | D37: 46225 | E37: 9:16 a. m. | G37: 6:04 p. m. | I37: 8.8 | J37: NO LLEGADA TARDE- AUTORIZO MATIAS
A38: 9:00 a. m. | B38: JUEVES | D38: 46226 | E38: 9:12 a. m. | G38: 6:08 p. m. | I38: 8.93
A39: 9:00 a. m. | B39: VIERNES | D39: 46227 | E39: 9:15 a. m. | G39: 6:24 p. m. | I39: 9.15
A40: LIBRE | B40: SÁBADO | D40: 46228 | I40: 0
A41: LIBRE | B41: DOMINGO | D41: 46229 | I41: 0
A42: 9:00 a. m. | B42: LUNES | D42: 46230 | E42: 9:11 a. m. | G42: 6:02 p. m. | I42: 8.85
A43: HOME OFFICE | B43: MARTES | D43: 46231 | E43: 9:00 a. m. | G43: 6:00 p. m. | I43: 9
A44: HOME OFFICE | B44: MIÉRCOLES | D44: 46232 | E44: 9:00 a. m. | G44: 6:00 p. m. | I44: 9
A45: 9:00 a. m. | B45: JUEVES | D45: 46233 | E45: 9:05 a. m. | G45: 6:09 p. m. | I45: 9.07
A46: 9:00 a. m. | B46: VIERNES | D46: 46234 | E46: 9:19 a. m. | G46: 6:10 p. m. | I46: 8.85
G47: TOTALES | I47: =SUM(I16:I46) -> 194.82
A48: ENJOY | E48: DOS57
A49: DETALLE DE PRESTAMOS / DESCUENTOS / MULTAS | E49: DETALLE DE PRESTAMOS / DESCUENTOS / MULTAS
A50: FECHA | B50: DETALLE | D50: MONTO | E50: FECHA | F50: DETALLE | I50: IMPORTE
E51: 46234 | F51: RECARGA MATAFUEGO | I51: 12000
A54: TOTAL | D54: =SUM(D51:D53) -> 0 | E54: TOTAL | I54: =SUM(I51:I53) -> 12000
E55: PENDIENTE A PAGAR PRESTAMOS | I55: 0

Sheet ANDRE
I2: AUMENTO
I3: FEBRERO/MARZO
A5: =+MAYRA!A5 -> SUELDO JULIO 2026 | F5: SUELDO | H5: =A8+C8+E8+G8+B10+C10+G12 -> 2104265 | I5: AGUINALDOS | K5: =+B6 -> ANDREA OLIVETTO
A6: Nombre: | B6: ANDREA OLIVETTO | D6: DNI: | E6: 22793039 | F6: Escalafon: | G6: ADM | H6: 2 | I6: JULIO | J6: 1522461.8 | K6: =+MAYRA!L6 -> Mes: JULIO 2026
A7: SUELDO BASICO | C7: PREMIO INCENTIVO | E7: VIATICO | G7: PREMIO PRESENTISMO | I7: AGOSTO | K7: Sueldo Basico | L7: =+A8 -> 1522461.8
A8: =1300138.21*17.1%+1300138.21 -> 1522461.8 | C8: =+L19 -> 67983.236 | E8: =+L21 -> 236219.85 | G8: =+L23 -> 127587.89 | I8: SEPTIEMBRE | K8: Premio Incentivo | L8: =+C8 -> 67983.236
A9: ANTIGÜEDAD | B9: 4 | C9: VACACIONES/AGUINALDOS/EXTRAS | E9: VALES/DESCUENTOS/MULTAS | G9: TIPO DE SEGURO | I9: OCTUBRE | K9: Viatico | L9: =+E8 -> 236219.85
A10: 44621 | B10: =+L28 -> 40985 | C10: 0 | E10: =+D55+H55 -> 800000 | G10: ART | I10: NOVIEMBRE | K10: Premio Presentismo | L10: =+G8 -> 127587.89
A11: HRS ACORDADAS | B11: HRS TRABAJADAS | C11: HRS EXTRAS TRABAJADAS | E11: VALOR HRS EXTRAS | G11: IMPORTE HRS EXTRAS TRABAJADAS | I11: DICIEMBRE | K11: Antigüedad | L11: =+B10 -> 40985
A12: 200 | B12: =+H48 -> 221.72 | C12: =+B12-A12 -> 21.72 | E12: =4286.65*17.1%+4286.65 -> 5019.6671 | G12: =+C12*E12 -> 109027.17 | I12: TOTAL | J12: =SUM(J6:J11) -> 1522461.8 | K12: Vacas/Aguinaldos/Extras | L12: =+C10 -> 0
A13: INICIO DEL ACUERDO | C13: VIGENCIA DEL ACUERDO | E13: % DEL ACUERDO | I13: 6 MESES | J13: =+J12/6 -> 253743.64 | K13: Hrs Extras | L13: =+G12 -> 109027.17
A14: 46143 | C14: 9 MESES | E14: 17,1% Básico + Premio Incentivo + Viatico + Presentismo + Hs Extra + Antigüedad | I14: AGUINALDOS | J14: =+J13/2 -> 126871.82 | K14: Total | L14: =SUM(L7:L13) -> 2104265
A15: IMPORTE TOTAL A COBRAR | G15: =+H5-E10 -> 1304265 | K15: Vales | L15: =+E10 -> 800000
A16: Convocatoria | B16: Dia | C16: Fecha | D16: Inicio de Actividades | F16: Fin de Actividades | H16: Hrs trabajadas | K16: A cobrar | L16: =+L14-L15 -> 1304265
A17: 9:00 a. m. | B17: MIERCOLES | C17: 46204 | D17: 8:49 a. m. | F17: 6:09 p. m. | H17: 9.33
A18: 9:00 a. m. | B18: JUEVES | C18: 46205 | D18: 8:48 a. m. | F18: 6:30 p. m. | H18: 9.7 | K18: PREMIO INCENTIVO
A19: 9:00 a. m. | B19: VIERNES | C19: 46206 | D19: 9:03 a. m. | F19: 5:51 p. m. | H19: 8.8 | K19: 1 Cat | L19: =58055.71*17.1%+58055.71 -> 67983.236
A20: LIBRE | B20: SÁBADO | C20: 46207 | H20: 0 | K20: VIÁTICO
A21: LIBRE | B21: DOMINGO | C21: 46208 | H21: 0 | K21: 1 Cat | L21: =201724.89*17.1%+201724.89 -> 236219.85
A22: 9:00 a. m. | B22: LUNES | C22: 46209 | D22: 8:55 a. m. | F22: 6:22 p. m. | H22: 9.45 | K22: PREMIO PRESENTISMO
A23: HOME OFFICE | B23: MARTES | C23: 46210 | D23: 9:00 a. m. | F23: 1:00 p. m. | H23: 4 | K23: 1 Cat | L23: =108956.35*17.1%+108956.35 -> 127587.89
A24: 9:00 a. m. | B24: MIÉRCOLES | C24: 46211 | D24: 9:09 a. m. | F24: 6:25 p. m. | H24: 9.27 | K24: ANTIGÜEDAD
A25: 9:00 a. m. | B25: JUEVES | C25: 46212 | D25: 8:55 a. m. | F25: 6:35 p. m. | H25: 9.67 | K25: 1 Años | L25: =12500*17.1%+12500 -> 14637.5
A26: 9:00 a. m. | B26: VIERNES | C26: 46213 | D26: 8:57 a. m. | F26: 7:14 p. m. | H26: 10.28 | K26: 2 Años | L26: =20000*17.1%+20000 -> 23420
A27: LIBRE | B27: SÁBADO | C27: 46214 | H27: 0 | K27: 3 Años | L27: =27500*17.1%+27500 -> 32202.5
A28: LIBRE | B28: DOMINGO | C28: 46215 | H28: 0 | K28: 4 Años | L28: =35000*17.1%+35000 -> 40985
A29: VACACIONES | B29: LUNES | C29: 46216 | H29: 8 | K29: 5 Años | L29: =42500*17.1%+42500 -> 49767.5
A30: VACACIONES | B30: MARTES | C30: 46217 | H30: 8 | K30: 6 Años | L30: =63750*17.1%+63750 -> 74651.25
A31: VACACIONES | B31: MIÉRCOLES | C31: 46218 | H31: 8 | K31: 7 Años | L31: =127500*17.1%+127500 -> 149302.5
A32: VACACIONES-POLO | B32: JUEVES | C32: 46219 | D32: 1:00 p. m. | F32: 6:34 p. m. | H32: 8 | K32: 8 Años | L32: =200000*17.1%+200000 -> 234200
A33: VACACIONES | B33: VIERNES | C33: 46220 | H33: 8
A34: VACACIONES | B34: SÁBADO | C34: 46221 | H34: 8
A35: VACACIONES | B35: DOMINGO | C35: 46222 | H35: 8
A36: 9:00 a. m. | B36: LUNES | C36: 46223 | D36: 8:43 a. m. | F36: 5:50 p. m. | H36: 9.12
A37: 9:00 a. m. | B37: MARTES | C37: 46224 | D37: 8:59 a. m. | F37: 6:41 p. m. | H37: 9.7 | I37: REUNION NEPER
A38: 9:00 a. m. | B38: MIÉRCOLES | C38: 46225 | D38: 8:52 a. m. | F38: 6:14 p. m. | H38: 9.37
A39: 9:00 a. m. | B39: JUEVES | C39: 46226 | D39: 8:59 a. m. | F39: 6:37 p. m. | H39: 9.63
A40: 9:00 a. m. | B40: VIERNES | C40: 46227 | D40: 9:13 a. m. | F40: 6:40 p. m. | H40: 9.45
A41: LIBRE | B41: SÁBADO | C41: 46228 | H41: 0
A42: LIBRE | B42: DOMINGO | C42: 46229 | H42: 0
A43: 9:00 a. m. | B43: LUNES | C43: 46230 | D43: 8:59 a. m. | F43: 6:11 p. m. | H43: 9.2
A44: 9:00 a. m. | B44: MARTES | C44: 46231 | D44: 8:47 a. m. | F44: 5:33 p. m. | H44: 8.77
A45: 9:00 a. m. | B45: MIÉRCOLES | C45: 46232 | D45: 8:23 a. m. | F45: 7:05 p. m. | H45: 10.7
A46: 9:00 a. m. | B46: JUEVES | C46: 46233 | D46: 8:55 a. m. | F46: 6:49 p. m. | H46: 9.9
A47: 9:00 a. m. | B47: VIERNES | C47: 46234 | D47: 9:08 a. m. | F47: 6:31 p. m. | H47: 9.38
F48: TOTALES | H48: =SUM(H17:H47) -> 221.72
A50: VALES | E50: DETALLE DE PRESTAMOS / DESCUENTOS / MULTAS
A51: FECHA | B51: DETALLE | D51: MONTO | E51: FECHA | F51: DETALLE | H51: IMPORTE
A52: 46219 | B52: ADELANTO MULTAS | D52: 300000
A53: 46226 | B53: ADELANTO | D53: 400000
A54: 46233 | B54: ADELANTO | D54: 100000
A55: TOTAL | D55: =SUM(D52:D54) -> 800000 | E55: PENDIENTE DE PAGO | H55: =+H52 -> 0
E56: PENDIENTE A PAGAR PRESTAMOS | H56: 0
A57: HRS PENDIENTES
A58: MES | D58: HRS
A59: ACUMULADO 2024 | D59: -396.88
A60: ENERO | D60: 0
A61: FEBRERO | D61: 0
A62: MARZO | D62: 0
A63: ABRIL
A64: MAYO
A65: JUNIO
A66: JULIO
A67: AGOSTO
A68: SEPTIEMBRE
A69: OCTUBRE
A70: NOVIEMBRE
A71: DICIEMBRE
A72: TOTAL | D72: =SUM(D59:D71) -> -396.88

Sheet LORE
I2: AUMENTO
I3: FEBRERO/MARZO
A5: =+MAYRA!A5 -> SUELDO JULIO 2026 | F5: SUELDO | H5: =A8+C8+E8+G8+B10+C10+G12 -> 1456957.1 | I5: AGUINALDOS | K5: =+B6 -> HERRERA LORENA
A6: Nombre: | B6: HERRERA LORENA | D6: DNI: | E6: 30474212 | F6: Escalafon: | G6: ADM | H6: 3 | I6: JULIO | J6: 1001007.7 | K6: =+MAYRA!L6 -> Mes: JULIO 2026
A7: SUELDO BASICO | C7: PREMIO INCENTIVO | E7: VIATICO | G7: PREMIO PRESENTISMO | I7: AGOSTO | K7: Sueldo Basico | L7: =+A8 -> 1001007.7
A8: =854831.48*17.1%+854831.48 -> 1001007.7 | C8: =+L19 -> 47455.173 | E8: =+L21 -> 106774.16 | G8: =+L23 -> 122484.36 | I8: SEPTIEMBRE | K8: Premio Incentivo | L8: =+C8 -> 47455.173
A9: ANTIGÜEDAD | B9: 3 | C9: VACACIONES/AGUINALDOS/EXTRAS | E9: VALES/DESCUENTOS/MULTAS | G9: TIPO DE SEGURO | I9: OCTUBRE | K9: Viatico | L9: =+E8 -> 106774.16
A10: 44835 | B10: =+L27 -> 32202.5 | C10: 0 | E10: =+D54+H54 -> 300000 | G10: ART | I10: NOVIEMBRE | K10: Premio Presentismo | L10: =+G8 -> 122484.36
A11: HRS ACORDADAS | B11: HRS TRABAJADAS | C11: HRS EXTRAS TRABAJADAS | E11: VALOR HRS EXTRAS | G11: IMPORTE HRS EXTRAS TRABAJADAS | I11: DICIEMBRE | K11: Antigüedad | L11: =+B10 -> 32202.5
A12: 180 | B12: =+H48 -> 219.9 | C12: =+B12-A12 -> 39.9 | E12: =3146.92*17.1%+3146.92 -> 3685.0433 | G12: =+C12*E12 -> 147033.23 | I12: TOTAL | J12: =SUM(J6:J11) -> 1001007.7 | K12: Vacas/Aguinaldos/Extras | L12: =+C10 -> 0
A13: INICIO DEL ACUERDO | C13: VIGENCIA DEL ACUERDO | E13: % DEL ACUERDO | I13: 6 MESES | J13: =+J12/6 -> 166834.61 | K13: Hrs Extras | L13: =+G12 -> 147033.23
A14: 46143 | C14: 9 MESES | E14: 17,1% Básico + Premio Incentivo + Viatico + Presentismo + Hs Extra + Antigüedad | I14: AGUINALDOS | J14: =+J13/2 -> 83417.305 | K14: Total | L14: =SUM(L7:L13) -> 1456957.1
A15: IMPORTE TOTAL A COBRAR | G15: =+H5-E10 -> 1156957.1 | K15: Vales | L15: =+E10 -> 300000
A16: Convocatoria | B16: Dia | C16: Fecha | D16: Inicio de Actividades | F16: Fin de Actividades | H16: Hrs trabajadas | K16: A cobrar | L16: =+L14-L15 -> 1156957.1
A17: VACACIONES | B17: MIERCOLES | C17: 46204 | H17: 8
A18: VACACIONES | B18: JUEVES | C18: 46205 | H18: 8 | K18: PREMIO INCENTIVO
A19: VACACIONES | B19: VIERNES | C19: 46206 | H19: 8 | K19: 1 Cat | L19: =40525.34*17.1%+40525.34 -> 47455.173
A20: VACACIONES | B20: SÁBADO | C20: 46207 | H20: 8 | K20: VIÁTICO
A21: VACACIONES | B21: DOMINGO | C21: 46208 | H21: 8 | K21: 1 Cat | L21: =91182.03*17.1%+91182.03 -> 106774.16
A22: VACACIONES | B22: LUNES | C22: 46209 | H22: 8 | K22: PREMIO PRESENTISMO
A23: VACACIONES | B23: MARTES | C23: 46210 | H23: 8 | K23: 1 Cat | L23: =104598.09*17.1%+104598.09 -> 122484.36
A24: VACACIONES | B24: MIÉRCOLES | C24: 46211 | H24: 8 | K24: ANTIGÜEDAD
A25: VACACIONES | B25: JUEVES | C25: 46212 | H25: 8 | K25: 1 Años | L25: =12500*17.1%+12500 -> 14637.5
A26: VACACIONES | B26: VIERNES | C26: 46213 | H26: 8 | K26: 2 Años | L26: =20000*17.1%+20000 -> 23420
A27: VACACIONES | B27: SÁBADO | C27: 46214 | H27: 8 | K27: 3 Años | L27: =27500*17.1%+27500 -> 32202.5
A28: VACACIONES | B28: DOMINGO | C28: 46215 | H28: 8 | K28: 4 Años | L28: =35000*17.1%+35000 -> 40985
A29: 9:00 a. m. | B29: LUNES | C29: 46216 | D29: 9:06 a. m. | F29: 6:36 p. m. | H29: 9.5 | K29: 5 Años | L29: =42500*17.1%+42500 -> 49767.5
A30: 9:00 a. m. | B30: MARTES | C30: 46217 | D30: 8:53 a. m. | F30: 6:09 p. m. | H30: 9.27 | K30: 6 Años | L30: =63750*17.1%+63750 -> 74651.25
A31: LIBRE | B31: MIÉRCOLES | C31: 46218 | H31: 0 | K31: 7 Años | L31: =127500*17.1%+127500 -> 149302.5
A32: 9:00 a. m. | B32: JUEVES | C32: 46219 | D32: 8:51 a. m. | F32: 6:35 p. m. | H32: 9.73 | K32: 8 Años | L32: =200000*17.1%+200000 -> 234200
A33: 9:00 a. m. | B33: VIERNES | C33: 46220 | D33: 8:46 a. m. | F33: 6:28 p. m. | H33: 9.7
A34: LIBRE | B34: SÁBADO | C34: 46221 | H34: 0
A35: LIBRE | B35: DOMINGO | C35: 46222 | H35: 0
A36: 9:00 a. m. | B36: LUNES | C36: 46223 | D36: 8:41 a. m. | F36: 6:07 p. m. | H36: 9.43
A37: 9:00 a. m. | B37: MARTES | C37: 46224 | D37: 9:00 a. m. | F37: 6:36 p. m. | H37: 9.6
A38: 9:00 a. m. | B38: MIÉRCOLES | C38: 46225 | D38: 8:46 a. m. | F38: 6:48 p. m. | H38: 10.03
A39: LIBRE | B39: JUEVES | C39: 46226 | H39: 0
A40: 9:00 a. m. | B40: VIERNES | C40: 46227 | D40: 8:49 a. m. | F40: 6:39 p. m. | H40: 9.83
A41: LIBRE | B41: SÁBADO | C41: 46228 | H41: 0
A42: LIBRE | B42: DOMINGO | C42: 46229 | H42: 0
A43: 9:00 a. m. | B43: LUNES | C43: 46230 | D43: 8:50 a. m. | F43: 4:30 p. m. | H43: 7.67
A44: 9:00 a. m. | B44: MARTES | C44: 46231 | D44: 9:06 a. m. | F44: 6:07 p. m. | H44: 9.02
A45: 9:00 a. m. | B45: MIÉRCOLES | C45: 46232 | D45: 8:01 a. m. | F45: 7:04 p. m. | H45: 11.05
A46: 9:00 a. m. | B46: JUEVES | C46: 46233 | D46: 8:54 a. m. | F46: 6:22 p. m. | H46: 9.47
A47: 9:00 a. m. | B47: VIERNES | C47: 46234 | D47: 8:56 a. m. | F47: 6:32 p. m. | H47: 9.6
F48: TOTALES | H48: =SUM(H17:H47) -> 219.9
A50: VALES | E50: DETALLE DE PRESTAMOS / DESCUENTOS / MULTAS
A51: FECHA | B51: DETALLE | D51: MONTO | E51: FECHA | F51: DETALLE | H51: IMPORTE
A52: 46227 | B52: ADELANTO | D52: 300000
A54: TOTAL | D54: =SUM(D52:D53) -> 300000 | E54: PENDIENTE DE PAGO | H54: =+H53 -> 0
E55: PENDIENTE A PAGAR PRESTAMOS | H55: 0
A56: HRS PENDIENTES
A57: MES | D57: HRS
A58: ACUMULADO 2024 | D58: -396.88
A59: ENERO | D59: 0
A60: FEBRERO | D60: 0
A61: MARZO | D61: 0
A62: ABRIL
A63: MAYO
A64: JUNIO
A65: JULIO
A66: AGOSTO
A67: SEPTIEMBRE
A68: OCTUBRE
A69: NOVIEMBRE
A70: DICIEMBRE
A71: TOTAL | D71: =SUM(D58:D70) -> -396.88

Sheet JAZ
I2: AUMENTO
I3: FEBRERO/MARZO
A5: =+MAYRA!A5 -> SUELDO JULIO 2026 | F5: SUELDO | H5: =A8+C8+E8+G8+B10+C10+G10+G12 -> 1536653.9 | I5: AGUINALDOS | K5: =+B6 -> JAZMIN VALDIVIA
A6: Nombre: | B6: JAZMIN VALDIVIA | D6: DNI: | E6: 41993007 | F6: Escalafon: | H6: 2 | I6: JULIO | J6: 1211253.2 | K6: =+MAYRA!L6 -> Mes: JULIO 2026
A7: SUELDO BASICO | C7: PREMIO INCENTIVO | E7: VIATICO | G7: PREMIO PRESENTISMO | I7: AGOSTO | K7: Sueldo Basico | L7: =+A8 -> 1211253.2
A8: =1034375.1*17.1%+1034375.1 -> 1211253.2 | C8: =+L20 -> 65333.439 | E8: =+L22 -> 52266.754 | G8: =+L24 -> 132904.04 | I8: SEPTIEMBRE | K8: Premio Incentivo | L8: =+C8 -> 65333.439
A9: ANTIGÜEDAD | B9: 3 | C9: VACACIONES/AGUINALDOS/EXTRAS | E9: VALES/DESCUENTOS/MULTAS | G9: PREMIO CASA | I9: OCTUBRE | K9: Viatico | L9: =+E8 -> 52266.754
A10: 45108 | B10: =+L28 -> 32202.5 | C10: 0 | E10: =+D59+H59 -> 707336.5 | G10: 0 | I10: NOVIEMBRE | K10: Premio Presentismo | L10: =+G8 -> 132904.04
A11: HRS ACORDADAS | B11: HRS TRABAJADAS | C11: HRS EXTRAS TRABAJADAS | E11: VALOR HRS EXTRAS | G11: IMPORTE HRS EXTRAS TRABAJADAS | I11: DICIEMBRE | K11: Antigüedad | L11: =+B10 -> 32202.5
A12: 200 | B12: =+H48 -> 209.8 | C12: =B12-A12 -> 9.8 | E12: =3720.34*17.1%+3720.34 -> 4356.5181 | G12: =+C12*E12 -> 42693.878 | I12: TOTAL | J12: =SUM(J6:J11) -> 1211253.2 | K12: Vacas/Aguinaldos/Extras | L12: =+C10 -> 0
A13: TIPO DE SEGURO | B13: INICIO DEL ACUERDO | D13: VIGENCIA DEL ACUERDO | F13: % DEL ACUERDO | I13: 6 MESES | J13: =+J12/6 -> 201875.54 | K13: Premio Casa | L13: =+G10 -> 0
A14: ART | B14: 46143 | D14: 9 MESES | F14: 17,1% Básico + Premio Incentivo + Viatico + Presentismo + Hs Extra + Antigüedad + Premio Casa | I14: AGUINALDOS | J14: =+J13/2 -> 100937.77 | K14: Hrs Extras | L14: =+G12 -> 42693.878
A15: IMPORTE TOTAL A COBRAR | G15: =+H5-E10 -> 829317.35 | K15: Total | L15: =SUM(L7:L14) -> 1536653.9
A16: Convocatoria | B16: Dia | C16: Fecha | D16: Inicio de Actividades | F16: Fin de Actividades | H16: Hrs trabajadas | K16: Vales | L16: =+E10 -> 707336.5
A17: VACACIONES | B17: MIERCOLES | C17: 46204 | H17: 8 | K17: A cobrar | L17: =+L15-L16 -> 829317.35
A18: VACACIONES | B18: JUEVES | C18: 46205 | H18: 8
A19: VACACIONES | B19: VIERNES | C19: 46206 | H19: 8 | K19: PREMIO INCENTIVO
A20: VACACIONES | B20: SÁBADO | C20: 46207 | H20: 8 | K20: 1 Cat | L20: =55792.86*17.1%+55792.86 -> 65333.439
A21: VACACIONES | B21: DOMINGO | C21: 46208 | H21: 8 | K21: VIÁTICO
A22: VACACIONES | B22: LUNES | C22: 46209 | H22: 8 | K22: 1 Cat | L22: =44634.29*17.1%+44634.29 -> 52266.754
A23: VACACIONES | B23: MARTES | C23: 46210 | H23: 8 | K23: PREMIO PRESENTISMO
A24: VACACIONES | B24: MIÉRCOLES | C24: 46211 | H24: 8 | K24: 1 Cat | L24: =113496.19*17.1%+113496.19 -> 132904.04
A25: VACACIONES | B25: JUEVES | C25: 46212 | H25: 8 | K25: ANTIGÜEDAD
A26: VACACIONES | B26: VIERNES | C26: 46213 | H26: 8 | K26: 1 Años | L26: =12500*17.1%+12500 -> 14637.5
A27: LIBRE | B27: SÁBADO | C27: 46214 | H27: 0 | K27: 2 Años | L27: =20000*17.1%+20000 -> 23420
A28: LIBRE | B28: DOMINGO | C28: 46215 | H28: 0 | K28: 3 Años | L28: =27500*17.1%+27500 -> 32202.5
A29: 9:00 a. m. | B29: LUNES | C29: 46216 | D29: 9:05 a. m. | F29: 6:43 p. m. | H29: 9.63 | K29: 4 Años | L29: =35000*17.1%+35000 -> 40985
A30: 9:00 a. m. | B30: MARTES | C30: 46217 | D30: 9:03 a. m. | F30: 6:11 p. m. | H30: 9.13 | K30: 5 Años | L30: =42500*17.1%+42500 -> 49767.5
A31: LIBRE | B31: MIÉRCOLES | C31: 46218 | H31: 0 | K31: 6 Años | L31: =63750*17.1%+63750 -> 74651.25
A32: 9:00 a. m. | B32: JUEVES | C32: 46219 | D32: 9:09 a. m. | F32: 6:35 p. m. | H32: 9.43 | K32: 7 Años | L32: =127500*17.1%+127500 -> 149302.5
A33: 9:00 a. m. | B33: VIERNES | C33: 46220 | D33: 9:03 a. m. | F33: 7:05 p. m. | H33: 10.03 | K33: 8 Años | L33: =200000*17.1%+200000 -> 234200
A34: LIBRE | B34: SÁBADO | C34: 46221 | H34: 0 | K34: PREMIO CASA
A35: LIBRE | B35: DOMINGO | C35: 46222 | H35: 0 | K35: 1 Cat (X Show) | L35: =100000*17.1%+100000 -> 117100
A36: 9:00 a. m. | B36: LUNES | C36: 46223 | D36: 9:08 a. m. | F36: 6:18 p. m. | H36: 9.17
A37: 9:00 a. m. | B37: MARTES | C37: 46224 | D37: 9:00 a. m. | F37: 6:26 p. m. | H37: 9.43
A38: 9:00 a. m. | B38: MIÉRCOLES | C38: 46225 | D38: 9:22 a. m. | F38: 6:53 p. m. | H38: 9.52
A39: 9:00 a. m. | B39: JUEVES | C39: 46226 | D39: 9:18 a. m. | F39: 6:20 p. m. | H39: 9.03
A40: 9:00 a. m. | B40: VIERNES | C40: 46227 | D40: 8:59 a. m. | F40: 6:40 p. m. | H40: 9.68
A41: LIBRE | B41: SÁBADO | C41: 46228 | H41: 0
A42: LIBRE | B42: DOMINGO | C42: 46229 | H42: 0
A43: 9:00 a. m. | B43: LUNES | C43: 46230 | D43: 9:03 a. m. | F43: 6:15 p. m. | H43: 9.2
A44: 9:00 a. m. | B44: MARTES | C44: 46231 | D44: 9:13 a. m. | F44: 6:07 p. m. | H44: 8.9
A45: 9:00 a. m. | B45: MIÉRCOLES | C45: 46232 | D45: 8:54 a. m. | F45: 6:18 p. m. | H45: 9.4
A46: 11:00 a. m. | B46: JUEVES | C46: 46233 | D46: 10:17 a. m. | F46: 6:18 p. m. | H46: 8.02
A47: 9:00 a. m. | B47: VIERNES | C47: 46234 | D47: 9:11 a. m. | F47: 6:25 p. m. | H47: 9.23
F48: TOTALES | H48: =SUM(H17:H47) -> 209.8
A50: VALES | E50: DETALLE DE PRESTAMOS / DESCUENTOS / MULTAS | J50: RESUMEN DEVOLUCIÓN DOLARES MATI
A51: FECHA | B51: DETALLE | D51: MONTO | E51: FECHA | F51: DETALLE | H51: IMPORTE | J51: 46054 | K51: PRÉSTAMO USD PASAJES ITALIA | L51: 1950
A52: 46227 | B52: ADELANTO | D52: 100000 | E52: 46054 | F52: PRÉSTAMO PASAJE ITALIA | H52: 1950 | J52: 46082 | K52: CUOTA 1 | L52: 312.5
E53: 46082 | F53: CUOTA 1 PRÉSTAMO USD $312,50 | H53: 450000 | J53: 46113 | K53: CUOTA 2 | L53: 319.14
E54: 46113 | F54: CUOTA 2 PRÉSTAMO USD $319,14 | H54: 450000 | J54: 46143 | K54: CUOTA 3 | L54: 316.9
E55: 46143 | F55: CUOTA 3 PRÉSTAMO USD $ | H55: 450000 | J55: 46174 | K55: CUOTA 4 | L55: 313.58
E56: 46174 | F56: CUOTA 4 PRÉSTAMO USD $ | H56: 450000 | J56: 46204 | K56: CUOTA 5 | L56: 296.05
E57: 46204 | F57: CUOTA 5 PRÉSTAMO USD $ | H57: 450000 | J57: 46235 | K57: CUOTA 6 | L57: 391.83
E58: 46235 | F58: CUOTA 6 PRÉSTAMO USD $ | H58: 607336.5 | J58: PENDIENTE DE PAGO | L58: =+L51-L52-L53-L54-L55-L56-L57 -> 0
A59: TOTAL | D59: =SUM(D52:D58) -> 100000 | E59: PENDIENTE DE PAGO | H59: =+H58 -> 607336.5
E60: PENDIENTE A PAGAR PRESTAMOS | H60: 0
A61: HRS PENDIENTES
A62: MES | D62: HRS
A63: ACUMULADO 2024 | D63: -396.88
A64: ENERO | D64: 0
A65: FEBRERO | D65: 0
A66: MARZO | D66: 0
A67: ABRIL
A68: MAYO
A69: JUNIO
A70: JULIO
A71: AGOSTO
A72: SEPTIEMBRE
A73: OCTUBRE
A74: NOVIEMBRE
A75: DICIEMBRE
A76: TOTAL | D76: =SUM(D63:D75) -> -396.88

Sheet FLOR
I2: AUMENTO
I3: SEPTIEMBRE/OCTUBRE
A5: =+MAYRA!A5 -> SUELDO JULIO 2026 | F5: SUELDO | H5: =+A8+C8+E8+G8+B10+C10+A12+E12+G14 -> 1080000 | I5: AGUINALDOS | K5: =+B6 -> FLORENCIA GOMEZ
A6: Nombre: | B6: FLORENCIA GOMEZ | D6: DNI: | F6: Escalafon: | H6: 1 | I6: JULIO | J6: 1000000 | K6: =+MAYRA!L6 -> Mes: JULIO 2026
A7: SUELDO BASICO | C7: PREMIO INCENTIVO | E7: VIATICO | G7: PREMIO PRESENTISMO | I7: AGOSTO | K7: Sueldo Basico | L7: =+A8 -> 1000000
A8: 1000000 | C8: 0 | E8: =+L23 -> 80000 | G8: 0 | I8: SEPTIEMBRE | K8: Premio Incentivo | L8: =+C8 -> 0
A9: ANTIGÜEDAD | B9: 0 | C9: VACACIONES/AGUINALDOS/EXTRAS | E9: VALES/DESCUENTOS/MULTAS | G9: TIPO DE SEGURO | I9: OCTUBRE | K9: Viatico | L9: =+E8 -> 80000
A10: 46082 | B10: 0 | C10: 0 | E10: =+D56+H56 -> 300000 | G10: AP | I10: NOVIEMBRE | K10: Premio Presentismo | L10: =+G8 -> 0
A11: PREMIO PRODUCCIÓN 1 | C11: 0 | E11: PREMIO PRODUCCIÓN 2 | G11: 0 | I11: DICIEMBRE | K11: Antigüedad | L11: =+B10 -> 0
A12: =+L36*C11 -> 0 | E12: =+L37*G11 -> 0 | I12: TOTAL | J12: =SUM(J6:J11) -> 1000000 | K12: Vacas/Aguinaldos/Extras | L12: =+C10 -> 0
A13: HRS ACORDADAS | B13: HRS TRABAJADAS | C13: HRS EXTRAS TRABAJADAS | E13: VALOR HRS EXTRAS | G13: IMPORTE HRS EXTRAS TRABAJADAS | I13: 6 MESES | J13: =+J12/6 -> 166666.67 | K13: Premio Producción 1 | L13: =+A12 -> 0
A14: 220 | B14: =+H50 -> 197.08 | C14: =+B14-A14 -> -22.92 | E14: 4000 | G14: 0 | I14: AGUINALDOS | J14: =+J13/2 -> 83333.333 | K14: Premio Producción 2 | L14: =+E12 -> 0
A15: INICIO DEL ACUERDO | C15: VIGENCIA DEL ACUERDO | E15: % DEL ACUERDO | K15: Hrs Extras | L15: =+G14 -> 0
A16: 46082 | C16: 6 MESES | E16: 14,5% + 20,5% Extraordinario - Básico + Hs. Extra + Produccion Show + Viatico // 14,5% Presentismo + Premio + Telefono | K16: Total | L16: =SUM(L7:L15) -> 1080000
A17: IMPORTE TOTAL A COBRAR | G17: =+H5-E10 -> 780000 | K17: Vales | L17: =+E10 -> 300000
A18: Convocatoria | B18: Dia | C18: Fecha | D18: Inicio de Actividades | F18: Fin de Actividades | H18: Hrs trabajadas | K18: A cobrar | L18: =+L16-L17 -> 780000
A19: 9:00 a. m. | B19: MIERCOLES | C19: 46204 | D19: 9:19 a. m. | F19: 6:05 p. m. | H19: 8.77
A20: 9:00 a. m. | B20: JUEVES | C20: 46205 | D20: 9:30 a. m. | F20: 6:11 p. m. | H20: 8.68 | K20: PREMIO INCENTIVO
A21: 9:00 a. m. | B21: VIERNES | C21: 46206 | D21: 9:29 a. m. | F21: 5:33 p. m. | H21: 8.07 | K21: 1 Cat | L21: 45000
A22: 9:00 a. m. | B22: SÁBADO | C22: 46207 | D22: 9:06 a. m. | F22: 3:46 p. m. | H22: 6.67 | K22: VIÁTICO
A23: LIBRE | B23: DOMINGO | C23: 46208 | H23: 0 | K23: 1 Cat | L23: 80000
A24: 9:00 a. m. | B24: LUNES | C24: 46209 | D24: 8:55 a. m. | F24: 6:06 p. m. | H24: 9.18 | K24: PREMIO PRESENTISMO
A25: LIBRE | B25: MARTES | C25: 46210 | H25: 0 | K25: 1 Cat | L25: 100000
A26: 9:00 a. m. | B26: MIÉRCOLES | C26: 46211 | D26: 9:16 a. m. | F26: 6:04 p. m. | H26: 8.8 | K26: ANTIGÜEDAD
A27: 9:00 a. m. | B27: JUEVES | C27: 46212 | D27: 8:47 a. m. | F27: 6:08 p. m. | H27: 9.35 | K27: 1 Años | L27: 12500
A28: 9:00 a. m. | B28: VIERNES | C28: 46213 | D28: 11:20 a. m. | F28: 6:12 p. m. | H28: 6.87 | I28: NO LLEGADA TARDE-AUTORIZO MATIAS | K28: 2 Años | L28: 20000
A29: LIBRE | B29: SÁBADO | C29: 46214 | H29: 0 | K29: 3 Años | L29: 27500
A30: LIBRE | B30: DOMINGO | C30: 46215 | H30: 0 | K30: 4 Años | L30: 35000
A31: 9:00 a. m. | B31: LUNES | C31: 46216 | D31: 9:40 a. m. | F31: 6:42 p. m. | H31: 9.03 | K31: 5 Años | L31: 42500
A32: 9:00 a. m. | B32: MARTES | C32: 46217 | D32: 9:17 a. m. | F32: 6:06 p. m. | H32: 8.82 | K32: 6 Años | L32: 63750
A33: LIBRE | B33: MIÉRCOLES | C33: 46218 | H33: 0 | K33: 7 Años | L33: 127500
A34: 9:00 a. m. | B34: JUEVES | C34: 46219 | D34: 8:02 a. m. | F34: 6:23 p. m. | H34: 10.35 | K34: 8 Años | L34: 200000
A35: 9:00 a. m. | B35: VIERNES | C35: 46220 | D35: 9:20 a. m. | F35: 6:24 p. m. | H35: 9.07 | K35: PREMIO PRODUCCION
A36: LIBRE | B36: SÁBADO | C36: 46221 | H36: 0 | K36: 1 Cat (X Show hasta 7 días) | L36: 150000
A37: LIBRE | B37: DOMINGO | C37: 46222 | H37: 0 | K37: 2 Cat (X Show + 7 días) | L37: 300000
A38: 9:00 a. m. | B38: LUNES | C38: 46223 | D38: 9:22 a. m. | F38: 6:32 p. m. | H38: 9.17
A39: 9:00 a. m. | B39: MARTES | C39: 46224 | D39: 9:16 a. m. | F39: 6:51 p. m. | H39: 9.58 | I39: NO LLEGADA TARDE-AUTORIZO MATIAS
A40: 9:00 a. m. | B40: MIÉRCOLES | C40: 46225 | D40: 9:43 a. m. | F40: 6:14 p. m. | H40: 8.52
A41: 9:00 a. m. | B41: JUEVES | C41: 46226 | D41: 8:13 a. m. | F41: 6:13 p. m. | H41: 10
A42: 9:00 a. m. | B42: VIERNES | C42: 46227 | D42: 8:26 a. m. | F42: 6:40 p. m. | H42: 10.23
A43: 9:00 a. m. | B43: SÁBADO | C43: 46228 | D43: 9:20 a. m. | F43: 6:21 p. m. | H43: 9.02
A44: LIBRE | B44: DOMINGO | C44: 46229 | H44: 0
A45: 9:00 a. m. | B45: LUNES | C45: 46230 | D45: 9:20 a. m. | F45: 6:26 p. m. | H45: 9.1
A46: 9:00 a. m. | B46: MARTES | C46: 46231 | D46: 9:30 a. m. | F46: 6:07 p. m. | H46: 8.62
A47: LIBRE | B47: MIÉRCOLES | C47: 46232 | H47: 0
A48: 9:00 a. m. | B48: JUEVES | C48: 46233 | D48: 7:59 a. m. | F48: 6:23 p. m. | H48: 10.4
A49: 9:00 a. m. | B49: VIERNES | C49: 46234 | D49: 9:38 a. m. | F49: 6:25 p. m. | H49: 8.78
F50: TOTALES | H50: =SUM(H19:H49) -> 197.08
A52: VALES | E52: DETALLE DE PRESTAMOS / DESCUENTOS / MULTAS
A53: FECHA | B53: DETALLE | D53: MONTO | E53: FECHA | F53: DETALLE | H53: IMPORTE
A54: 46227 | B54: ADELANTO | D54: 300000
A56: TOTAL | D56: =SUM(D54:D55) -> 300000 | E56: PENDIENTE DE PAGO | H56: =+H54 -> 0
E57: PENDIENTE A PAGAR PRESTAMOS | H57: 0
A58: HRS PENDIENTES
A59: MES | D59: HRS
A60: ACUMULADO 2024 | D60: -396.88
A61: ENERO | D61: 0
A62: FEBRERO | D62: 0
A63: MARZO | D63: 0
A64: ABRIL
A65: MAYO
A66: JUNIO
A67: JULIO
A68: AGOSTO
A69: SEPTIEMBRE
A70: OCTUBRE
A71: NOVIEMBRE
A72: DICIEMBRE
A73: TOTAL | D73: =SUM(D60:D72) -> -396.88

Sheet FURIA
I2: AUMENTO
I3: FEBRERO/MARZO
A5: =+MAYRA!A5 -> SUELDO JULIO 2026 | F5: SUELDO | H5: =+A8+C8+E8+G8+B10+C10+G10+G12 -> 2391133.6 | I5: AGUINALDOS | K5: =+B6 -> JUAN VESSONI
A6: Nombre: | B6: JUAN VESSONI | D6: DNI: | E6: 28654907 | F6: Escalafon: | H6: 1 | I6: JULIO | J6: 1625757.6 | K6: =+MAYRA!L6 -> Mes: JULIO 2026
A7: SUELDO BASICO | C7: PREMIO INCENTIVO | E7: VIATICO | G7: PREMIO PRESENTISMO | I7: AGOSTO | K7: Sueldo Basico | L7: =+A8 -> 1625757.6
A8: =1388349.82*17.1%+1388349.82 -> 1625757.6 | C8: 0 | E8: =+L22 -> 138884.21 | G8: 0 | I8: SEPTIEMBRE | K8: Premio Incentivo | L8: =+C8 -> 0
A9: ANTIGÜEDAD | B9: 4 | C9: VACACIONES/AGUINALDOS/EXTRAS | E9: VALES/DESCUENTOS/MULTAS | G9: PREMIO PRODUCCIÓN | H9: =+EVENTOS!F18 -> 1 | I9: OCTUBRE | K9: Viatico | L9: =+E8 -> 138884.21
A10: 44501 | B10: =+L29 -> 40985 | C10: 300000 | E10: =+D54+H54 -> 800000 | G10: =+L35*H9 -> 140206.46 | I10: NOVIEMBRE | K10: Premio Presentismo | L10: =+G8 -> 0
A11: HRS ACORDADAS | B11: HRS TRABAJADAS | C11: HRS EXTRAS TRABAJADAS | E11: VALOR HRS EXTRAS | G11: IMPORTE HRS EXTRAS TRABAJADAS | I11: DICIEMBRE | K11: Antigüedad | L11: =+B10 -> 40985
A12: 220 | B12: =+H48 -> 247.66 | C12: =+B12-A12 -> 27.66 | E12: =4485.98*17.1%+4485.98 -> 5253.0826 | G12: =+C12*E12 -> 145300.26 | I12: TOTAL | J12: =SUM(J6:J11) -> 1625757.6 | K12: Vacas/Aguinaldos/Extras | L12: =+C10 -> 300000
A13: TIPO DE SEGURO | B13: INICIO DEL ACUERDO | D13: VIGENCIA DEL ACUERDO | F13: % DEL ACUERDO | I13: 6 MESES | J13: =+J12/6 -> 270959.61 | K13: Premio Producción | L13: =+G10 -> 140206.46
A14: ART | B14: 46143 | D14: 9 MESES | F14: 17,1% Básico + Premio Incentivo + Viatico + Presentismo + Hs Extra + Antigüedad + Premio Producción | I14: AGUINALDOS | J14: =+J13/2 -> 135479.8 | K14: Hrs Extras | L14: =+G12 -> 145300.26
A15: IMPORTE TOTAL A COBRAR | G15: =+H5-E10 -> 1591133.6 | K15: Total | L15: =SUM(L7:L14) -> 2391133.6
A16: Convocatoria | B16: Dia | C16: Fecha | D16: Inicio de Actividades | F16: Fin de Actividades | H16: Hrs trabajadas | K16: Vales | L16: =+E10 -> 800000
A17: 9:00 a. m. | B17: MIERCOLES | C17: 46204 | D17: 9:40 a. m. | F17: 5:30 p. m. | H17: 7.83 | I17: KEMPES | K17: A cobrar | L17: =+L15-L16 -> 1591133.6
A18: 9:00 a. m. | B18: JUEVES | C18: 46205 | D18: 9:00 a. m. | F18: 5:40 p. m. | H18: 8.67 | I18: KEMPES
A19: 9:00 a. m. | B19: VIERNES | C19: 46206 | D19: 9:08 a. m. | F19: 5:33 p. m. | H19: 8.42 | I19: KEMPES | K19: PREMIO INCENTIVO
A20: 9:00 a. m. | B20: SÁBADO | C20: 46207 | D20: 11:00 a. m. | F20: 6:00 p. m. | H20: 7 | I20: KEMPES | K20: 1 Cat | L20: =77092*17.1%+77092 -> 90274.732
A21: LIBRE | B21: DOMINGO | C21: 46208 | H21: 0 | K21: VIÁTICO
A22: VACACIONES | B22: LUNES | C22: 46209 | H22: 8 | K22: 1 Cat | L22: =118603.08*17.1%+118603.08 -> 138884.21
A23: VACACIONES | B23: MARTES | C23: 46210 | H23: 8 | K23: PREMIO PRESENTISMO
A24: VACACIONES | B24: MIÉRCOLES | C24: 46211 | H24: 8 | K24: 1 Cat | L24: =113496.19*17.1%+113496.19 -> 132904.04
A25: VACACIONES | B25: JUEVES | C25: 46212 | H25: 8 | K25: ANTIGÜEDAD
A26: VACACIONES | B26: VIERNES | C26: 46213 | H26: 8 | K26: 1 Años | L26: =12500*17.1%+12500 -> 14637.5
A27: VACACIONES | B27: SÁBADO | C27: 46214 | H27: 8 | K27: 2 Años | L27: =20000*17.1%+20000 -> 23420
A28: VACACIONES | B28: DOMINGO | C28: 46215 | H28: 8 | K28: 3 Años | L28: =27500*17.1%+27500 -> 32202.5
A29: 9:00 a. m. | B29: LUNES | C29: 46216 | D29: 8:53 a. m. | F29: 6:02 p. m. | H29: 9.15 | K29: 4 Años | L29: =35000*17.1%+35000 -> 40985
A30: 9:00 a. m. | B30: MARTES | C30: 46217 | D30: 9:17 a. m. | F30: 6:05 p. m. | H30: 8.8 | K30: 5 Años | L30: =42500*17.1%+42500 -> 49767.5
A31: LIBRE | B31: MIÉRCOLES | C31: 46218 | H31: 0 | K31: 6 Años | L31: =63750*17.1%+63750 -> 74651.25
A32: 9:00 a. m. | B32: JUEVES | C32: 46219 | D32: 7:42 a. m. | F32: 6:19 p. m. | H32: 10.62 | K32: 7 Años | L32: =127500*17.1%+127500 -> 149302.5
A33: 9:00 a. m. | B33: VIERNES | C33: 46220 | D33: 9:44 a. m. | F33: 6:24 p. m. | H33: 8.67 | K33: 8 Años | L33: =200000*17.1%+200000 -> 234200
A34: 9:00 a. m. | B34: SÁBADO | C34: 46221 | D34: 9:09 a. m. | F34: 5:48 p. m. | H34: 8.65 | K34: PREMIO PRODUCCION
A35: LIBRE | B35: DOMINGO | C35: 46222 | H35: 0 | K35: 1 Cat (X Show) | L35: =119732.25*17.1%+119732.25 -> 140206.46
A36: 9:00 a. m. | B36: LUNES | C36: 46223 | D36: 8:54 a. m. | F36: 6:34 p. m. | H36: 9.67
A37: 9:00 a. m. | B37: MARTES | C37: 46224 | D37: 8:05 a. m. | F37: 6:59 p. m. | H37: 10.9
A38: 8:00 a. m. | B38: MIÉRCOLES | C38: 46225 | D38: 8:02 a. m. | F38: 6:14 p. m. | H38: 10.2
A39: 8:00 a. m. | B39: JUEVES | C39: 46226 | D39: 8:12 a. m. | F39: 6:13 p. m. | H39: 10.02
A40: 8:00 a. m. | B40: VIERNES | C40: 46227 | D40: 8:26 a. m. | F40: 6:13 p. m. | H40: 9.78
A41: 7:30 a. m. | B41: SÁBADO | C41: 46228 | D41: 8:00 a. m. | F41: 6:22 p. m. | H41: 10.37
A42: LIBRE | B42: DOMINGO | C42: 46229 | H42: 0
A43: 6:30 a. m. | B43: LUNES | C43: 46230 | D43: 6:44 a. m. | F43: 6:40 p. m. | H43: 11.93
A44: 6:30 a. m. | B44: MARTES | C44: 46231 | D44: 6:19 a. m. | F44: 6:07 p. m. | H44: 11.8
A45: 7:30 a. m. | B45: MIÉRCOLES | C45: 46232 | D45: 7:31 a. m. | F45: 6:01 p. m. | H45: 10.5
A46: 9:00 a. m. | B46: JUEVES | C46: 46233 | D46: 9:03 a. m. | F46: 6:17 p. m. | H46: 9.23
A47: 9:00 a. m. | B47: VIERNES | C47: 46234 | D47: 9:02 a. m. | F47: 6:29 p. m. | H47: 9.45
F48: TOTALES | H48: =SUM(H17:H47) -> 247.66
A50: VALES | E50: DETALLE DE PRESTAMOS / DESCUENTOS / MULTAS
A51: FECHA | B51: DETALLE | D51: MONTO | E51: FECHA | F51: DETALLE | H51: IMPORTE
A52: 46219 | B52: ADELANTO | D52: 800000
A54: TOTAL | D54: =SUM(D52:D53) -> 800000 | E54: PENDIENTE DE PAGO | H54: =+H53 -> 0
E55: PENDIENTE A PAGAR PRESTAMOS | H55: 0
A56: HRS PENDIENTES
A57: MES | D57: HRS
A58: ACUMULADO 2024 | D58: -396.88
A59: ENERO | D59: 0
A60: FEBRERO | D60: 0
A61: MARZO | D61: 0
A62: ABRIL
A63: MAYO
A64: JUNIO
A65: JULIO
A66: AGOSTO
A67: SEPTIEMBRE
A68: OCTUBRE
A69: NOVIEMBRE
A70: DICIEMBRE
A71: TOTAL | D71: =SUM(D58:D70) -> -396.88

Sheet MARIO
I2: AUMENTO
I3: AGOSTO/SEPTIEMBRE
A5: =+MAYRA!A5 -> SUELDO JULIO 2026 | F5: SUELDO | H5: =+A8+C8+E8+G8+H8+B10+C10+A12+E12+G14 -> 2639630.3 | I5: AGUINALDOS | K5: =+B6 -> MARIO LOPEZ
A6: Nombre: | B6: MARIO LOPEZ | D6: DNI: | E6: 30125181 | F6: Escalafon: | H6: 1 | I6: JULIO | J6: 1587600 | K6: =+MAYRA!L6 -> Mes: JULIO 2026
A7: SUELDO BASICO | C7: PREMIO INCENTIVO | E7: VIATICO | G7: PREMIO PRESENTISMO | H7: TELÉFONO | I7: AGOSTO | K7: Sueldo Basico | L7: =+A8 -> 1587600
A8: =1176000*35%+1176000 -> 1587600 | C8: =+L22 -> 54960 | E8: =+L24 -> 81000 | G8: =+L26 -> 97554 | H8: =+L28 -> 23358 | I8: SEPTIEMBRE | K8: Premio Incentivo | L8: =+C8 -> 54960
A9: ANTIGÜEDAD | B9: 1 | C9: VACACIONES/AGUINALDOS/EXTRAS | E9: VALES/DESCUENTOS/MULTAS | G9: TIPO DE SEGURO | I9: OCTUBRE | K9: Viatico | L9: =+E8 -> 81000
A10: 45689 | B10: 12500 | C10: 0 | E10: =+D59+H60 -> 250000 | G10: ART | I10: NOVIEMBRE | K10: Premio Presentismo | L10: =+G8 -> 97554
A11: PREMIO PRODUCCIÓN 1 | C11: 0 | E11: PREMIO PRODUCCIÓN 2 | G11: 1 | I11: DICIEMBRE | K11: Teléfono | L11: =+H8 -> 23358
A12: =+L39*C11 -> 0 | E12: =+L40*G11 -> 303750 | I12: TOTAL | J12: =SUM(J6:J11) -> 1587600 | K12: Antigüedad | L12: =+B10 -> 12500
A13: HRS ACORDADAS | B13: HRS TRABAJADAS | C13: HRS EXTRAS TRABAJADAS | E13: VALOR HRS EXTRAS | G13: IMPORTE HRS EXTRAS TRABAJADAS | I13: 6 MESES | J13: =+J12/6 -> 264600 | K13: Vacas/Aguinaldos/Extras | L13: =+C10 -> 0
A14: 200 | B14: =+H50 -> 309.25 | C14: =+B14-A14 -> 109.25 | E14: =3372*30%+3372 -> 4383.6 | G14: =+C14*E14 -> 478908.3 | I14: AGUINALDOS | J14: =+J13/2 -> 132300 | K14: Premio Producción 1 | L14: =+A12 -> 0
A15: INICIO DEL ACUERDO | C15: VIGENCIA DEL ACUERDO | E15: % DEL ACUERDO | K15: Premio Producción 2 | L15: =+E12 -> 303750
A16: 46054 | C16: 6 MESES | E16: 14,5% + 20,5% Extraordinario - Básico + Hs. Extra + Produccion Show + Viatico // 14,5% Presentismo + Premio + Telefono | K16: Hrs Extras | L16: =+G14 -> 478908.3
A17: IMPORTE TOTAL A COBRAR | G17: =+H5-E10 -> 2389630.3 | K17: Total | L17: =SUM(L7:L16) -> 2639630.3
A18: Convocatoria | B18: Dia | C18: Fecha | D18: Inicio de Actividades | F18: Fin de Actividades | H18: Hrs trabajadas | K18: Vales | L18: =+E10 -> 250000
A19: VACACIONES | B19: MIERCOLES | C19: 46204 | H19: 8 | K19: A cobrar | L19: =+L17-L18 -> 2389630.3
A20: X | B20: JUEVES | C20: 46205 | D20: 8:00 a. m. | F20: 8:00 p. m. | H20: 12 | I20: AVANZADA RIO CUARTO/MANEJO CAMIONETA VECK
A21: VACACIONES | B21: VIERNES | C21: 46206 | H21: 8 | K21: PREMIO INCENTIVO
A22: VACACIONES | B22: SÁBADO | C22: 46207 | H22: 8 | K22: 1 Cat | L22: =48000*14.5%+48000 -> 54960
A23: VACACIONES | B23: DOMINGO | C23: 46208 | H23: 8 | K23: VIÁTICO
A24: VACACIONES | B24: LUNES | C24: 46209 | H24: 8 | K24: 1 Cat | L24: =60000*35%+60000 -> 81000
A25: VACACIONES | B25: MARTES | C25: 46210 | H25: 8 | K25: PREMIO PRESENTISMO
A26: VACACIONES | B26: MIÉRCOLES | C26: 46211 | H26: 8 | K26: 1 Cat | L26: =85200*14.5%+85200 -> 97554
A27: VACACIONES | B27: JUEVES | C27: 46212 | H27: 8 | K27: TELÉFONO
A28: VACACIONES | B28: VIERNES | C28: 46213 | H28: 8 | K28: 1 Cat | L28: =20400*14.5%+20400 -> 23358
A29: VACACIONES | B29: SÁBADO | C29: 46214 | H29: 8 | K29: ANTIGÜEDAD
A30: VACACIONES | B30: DOMINGO | C30: 46215 | H30: 8 | K30: 1 Años | L30: 12500
A31: 9:00 a. m. | B31: LUNES | C31: 46216 | D31: 9:05 a. m. | F31: 6:36 p. m. | H31: 9.52 | K31: 2 Años | L31: 20000
A32: 9:00 a. m. | B32: MARTES | C32: 46217 | D32: 8:53 a. m. | F32: 6:09 p. m. | H32: 9.27 | K32: 3 Años | L32: 27500
A33: LIBRE | B33: MIÉRCOLES | C33: 46218 | H33: 0 | K33: 4 Años | L33: 35000
A34: 9:00 a. m. | B34: JUEVES | C34: 46219 | D34: 8:51 a. m. | F34: 6:35 p. m. | H34: 9.73 | K34: 5 Años | L34: 42500
A35: 9:00 a. m. | B35: VIERNES | C35: 46220 | D35: 8:46 a. m. | F35: 6:28 p. m. | H35: 9.7 | K35: 6 Años | L35: 63750
A36: 7:30 a. m. | B36: SÁBADO | C36: 46221 | D36: 7:00 a. m. | F36: 8:05 p. m. | H36: 13.08 | I36: Viaje Sgo del Estero/ Camioneta Veck | K36: 7 Años | L36: 127500
A37: 7:00 a. m. | B37: DOMINGO | C37: 46222 | D37: 7:00 a. m. | F37: 3:00 p. m. | H37: 8 | I37: Debio esperar guardia en el predio | K37: 8 Años | L37: 200000
A38: 7:00 a. m. | B38: LUNES | C38: 46223 | D38: 7:00 a. m. | F38: 9:00 p. m. | H38: 14 | I38: Sgo del Estero | K38: PREMIO PRODUCCION
A39: 8:00 a. m. | B39: MARTES | C39: 46224 | D39: 8:00 a. m. | F39: 9:20 p. m. | H39: 13.33 | I39: Sgo del Estero | K39: 1 Cat (X Show hasta 7 días) | L39: =112500*35%+112500 -> 151875
A40: 8:00 a. m. | B40: MIÉRCOLES | C40: 46225 | D40: 8:00 a. m. | F40: 7:00 p. m. | H40: 11 | I40: Sgo del Estero | K40: 2 Cat (X Show + 7 días) | L40: =225000*35%+225000 -> 303750
A41: 8:00 a. m. | B41: JUEVES | C41: 46226 | D41: 8:00 a. m. | F41: 7:00 p. m. | H41: 11 | I41: Sgo del Estero
A42: 8:00 a. m. | B42: VIERNES | C42: 46227 | D42: 8:00 a. m. | F42: 7:00 p. m. | H42: 11 | I42: Sgo del Estero
A43: 7:00 a. m. | B43: SÁBADO | C43: 46228 | D43: 7:00 a. m. | F43: 2:00 a. m. | H43: 19 | I43: Sgo del Estero/Guardia
A44: 7:00 a. m. | B44: DOMINGO | C44: 46229 | D44: 7:00 a. m. | F44: 7:30 p. m. | H44: 12.5 | I44: Sgo del Estero
A45: 8:00 a. m. | B45: LUNES | C45: 46230 | D45: 8:00 a. m. | F45: 7:00 p. m. | H45: 11 | I45: Sgo del Estero
A46: 8:00 a. m. | B46: MARTES | C46: 46231 | D46: 8:00 a. m. | F46: 1:00 a. m. | H46: 17 | I46: Sgo del Estero/Regreso Cba camioneta Veck
A47: 8:00 a. m. | B47: MIÉRCOLES | C47: 46232 | D47: 8:01 a. m. | F47: 7:04 p. m. | H47: 11.05
A48: 9:00 a. m. | B48: JUEVES | C48: 46233 | D48: 8:54 a. m. | F48: 6:22 p. m. | H48: 9.47
A49: 9:00 a. m. | B49: VIERNES | C49: 46234 | D49: 8:56 a. m. | F49: 6:32 p. m. | H49: 9.6
F50: TOTALES | H50: =SUM(H19:H49) -> 309.25
A52: VALES | E52: DETALLE DE PRESTAMOS / DESCUENTOS / MULTAS
A53: FECHA | B53: DETALLE | D53: MONTO | E53: FECHA | F53: DETALLE | H53: IMPORTE
E54: 46150 | F54: MULTA LA ANGOSTURA | H54: 123850
E55: 46163 | F55: PRÉSTAMO CORPO | H55: 750000
E56: 46174 | F56: CUOTA 1 - PRÉSTAMO CORPO | H56: 250000
E57: 46204 | F57: CUOTA 2 - PRÉSTAMO CORPO | H57: 250000
E58: 46204 | F58: PENALIDAD SAN BLAS GRUA | H58: 262500
A59: TOTAL | D59: =SUM(D54:D58) -> 0 | E59: 46235 | F59: CUOTA 3 - PRÉSTAMO CORPO | H59: 250000
E60: PENDIENTE DE PAGO | H60: =+H59 -> 250000
A61: HRS PENDIENTES | E61: PENDIENTE A PAGAR PRESTAMOS | H61: 0
A62: MES | D62: HRS
A63: ACUMULADO 2024 | D63: -396.88
A64: ENERO | D64: 0
A65: FEBRERO | D65: 0
A66: MARZO | D66: 0
A67: ABRIL
A68: MAYO
A69: JUNIO
A70: JULIO
A71: AGOSTO
A72: SEPTIEMBRE
A73: OCTUBRE
A74: NOVIEMBRE
A75: DICIEMBRE
A76: TOTAL | D76: =SUM(D63:D75) -> -396.88

Sheet FAUSTO
I2: AUMENTO
I3: FEBRERO/MARZO
A5: =+MAYRA!A5 -> SUELDO JULIO 2026 | F5: SUELDO | H5: =+A8+C8+E8+G8+B10+C10+G12+C14+F14 -> 1685923.2 | I5: AGUINALDOS | K5: =+B6 -> DENIS CELIZ
A6: Nombre: | B6: DENIS CELIZ | D6: DNI: | E6: 36145011 | F6: Escalafon: | H6: 2 | I6: JULIO | J6: 1270457.1 | K6: =+MAYRA!L6 -> Mes: JULIO 2026
A7: SUELDO BASICO | C7: PREMIO INCENTIVO | E7: VIATICO | G7: PREMIO PRESENTISMO | I7: AGOSTO | K7: Sueldo Basico | L7: =+A8 -> 1270457.1
A8: =1084933.5*17.1%+1084933.5 -> 1270457.1 | C8: 0 | E8: =+L23 -> 63098.012 | G8: 0 | I8: SEPTIEMBRE | K8: Premio Incentivo | L8: =+C8 -> 0
A9: ANTIGÜEDAD | B9: 4 | C9: VACACIONES/AGUINALDOS/EXTRAS | E9: VALES/DESCUENTOS/MULTAS | G9: TIPO DE SEGURO | I9: OCTUBRE | K9: Viatico | L9: =+E8 -> 63098.012
A10: 44440 | B10: =+L30 -> 40985 | C10: 0 | E10: =+D56+H56 -> 205450 | G10: ART | I10: NOVIEMBRE | K10: Premio Presentismo | L10: =+G8 -> 0
A11: HRS ACORDADAS | B11: HRS TRABAJADAS | C11: HRS EXTRAS TRABAJADAS | E11: VALOR HRS EXTRAS | G11: IMPORTE HRS EXTRAS TRABAJADAS | I11: DICIEMBRE | K11: Antigüedad | L11: =+B10 -> 40985
A12: 220 | B12: =+H50 -> 241.87 | C12: =+B12-A12 -> 21.87 | E12: =3984.18*17.1%+3984.18 -> 4665.4748 | G12: =+C12*E12 -> 102033.93 | I12: TOTAL | J12: =SUM(J6:J11) -> 1270457.1 | K12: Vacas/Aguinaldos/Extras | L12: =+C10 -> 0
A13: PREMIOS COMPLEMENTARIOS | C13: PREMIO PRODUCCIÓN | E13: =+EVENTOS!G18 -> 2 | F13: PREMIO GUARDIAS | H13: 2 | I13: 6 MESES | J13: =+J12/6 -> 211742.85 | K13: Hrs Extras | L13: =+G12 -> 102033.93
C14: =+L36*E13 -> 182970.37 | F14: =+L38*H13 -> 26378.766 | I14: AGUINALDOS | J14: =+J13/2 -> 105871.43 | K14: Premio Producción | L14: =+C14 -> 182970.37
A15: INICIO DEL ACUERDO | C15: VIGENCIA DEL ACUERDO | E15: % DEL ACUERDO | K15: Premio Guardias | L15: =+F14 -> 26378.766
A16: 46143 | C16: 9 MESES | E16: 17,1% Básico + Premio Incentivo + Viatico + Presentismo + Hs Extra + Antigüedad + Premio Producción + Premio Guardias | K16: Total | L16: =SUM(L7:L15) -> 1685923.2
A17: IMPORTE TOTAL A COBRAR | G17: =+H5-E10 -> 1480473.2 | K17: Vales | L17: =+E10 -> 205450
A18: Convocatoria | B18: Dia | C18: Fecha | D18: Inicio de Actividades | F18: Fin de Actividades | H18: Hrs trabajadas | K18: A cobrar | L18: =+L16-L17 -> 1480473.2
A19: 9:00 a. m. | B19: MIERCOLES | C19: 46204 | D19: 9:01 a. m. | F19: 6:02 p. m. | H19: 9.02
A20: 9:00 a. m. | B20: JUEVES | C20: 46205 | D20: 8:48 a. m. | F20: 5:59 p. m. | H20: 9.18 | K20: PREMIO INCENTIVO
A21: 9:00 a. m. | B21: VIERNES | C21: 46206 | D21: 9:11 a. m. | F21: 5:33 p. m. | H21: 8.37 | K21: 1 Cat | L21: =54725.82*17.1%+54725.82 -> 64083.935
A22: 9:00 a. m. | B22: SÁBADO | C22: 46207 | D22: 9:30 a. m. | F22: 8:30 p. m. | H22: 11 | I22: KEMPES/GUARDIA | K22: VIÁTICO
A23: LIBRE | B23: DOMINGO | C23: 46208 | H23: 0 | K23: 1 Cat | L23: =53883.87*17.1%+53883.87 -> 63098.012
A24: 9:00 a. m. | B24: LUNES | C24: 46209 | D24: 8:48 a. m. | F24: 7:31 p. m. | H24: 10.72 | K24: PREMIO PRESENTISMO
A25: LIBRE | B25: MARTES | C25: 46210 | H25: 0 | K25: 1 Cat | L25: =113496.19*17.1%+113496.19 -> 132904.04
A26: 9:00 a. m. | B26: MIÉRCOLES | C26: 46211 | D26: 9:19 a. m. | F26: 6:01 p. m. | H26: 8.7 | K26: ANTIGÜEDAD
A27: 9:00 a. m. | B27: JUEVES | C27: 46212 | D27: 9:54 a. m. | F27: 6:01 p. m. | H27: 8.12 | K27: 1 Años | L27: =12500*17.1%+12500 -> 14637.5
A28: 9:00 a. m. | B28: VIERNES | C28: 46213 | D28: 8:55 a. m. | F28: 6:08 p. m. | H28: 9.22 | K28: 2 Años | L28: =20000*17.1%+20000 -> 23420
A29: 9:00 a. m. | B29: SÁBADO | C29: 46214 | D29: 9:26 a. m. | F29: 2:05 p. m. | H29: 4.65 | K29: 3 Años | L29: =27500*17.1%+27500 -> 32202.5
A30: LIBRE | B30: DOMINGO | C30: 46215 | H30: 0 | K30: 4 Años | L30: =35000*17.1%+35000 -> 40985
A31: 9:00 a. m. | B31: LUNES | C31: 46216 | D31: 9:24 a. m. | F31: 6:02 p. m. | H31: 8.63 | K31: 5 Años | L31: =42500*17.1%+42500 -> 49767.5
A32: 9:00 a. m. | B32: MARTES | C32: 46217 | D32: 9:24 a. m. | F32: 6:00 p. m. | H32: 8.6 | K32: 6 Años | L32: =63750*17.1%+63750 -> 74651.25
A33: LIBRE | B33: MIÉRCOLES | C33: 46218 | H33: 0 | K33: 7 Años | L33: =127500*17.1%+127500 -> 149302.5
A34: 9:00 a. m. | B34: JUEVES | C34: 46219 | D34: 9:10 a. m. | F34: 6:23 p. m. | H34: 9.22 | K34: 8 Años | L34: =200000*17.1%+200000 -> 234200
A35: 9:00 a. m. | B35: VIERNES | C35: 46220 | D35: 9:04 a. m. | F35: 7:02 p. m. | H35: 9.97 | K35: PREMIO PRODUCCION
A36: 9:00 a. m. | B36: SÁBADO | C36: 46221 | D36: 9:11 a. m. | F36: 5:53 p. m. | H36: 8.7 | K36: 1 Cat (X Show) | L36: =78125.69*17.1%+78125.69 -> 91485.183
A37: 9:00 a. m. | B37: DOMINGO | C37: 46222 | D37: 9:05 a. m. | F37: 2:09 p. m. | H37: 5.07 | K37: PREMIO GUARDIAS
A38: 9:00 a. m. | B38: LUNES | C38: 46223 | D38: 9:12 a. m. | F38: 6:07 p. m. | H38: 8.92 | K38: 1 Cat (X Show) | L38: =11263.35*17.1%+11263.35 -> 13189.383
A39: 9:00 a. m. | B39: MARTES | C39: 46224 | D39: 9:14 a. m. | F39: 6:28 p. m. | H39: 9.23
A40: 9:00 a. m. | B40: MIÉRCOLES | C40: 46225 | D40: 10:45 a. m. | F40: 8:01 p. m. | H40: 9.27 | I40: NO LLEGADA TARDE-AUTORIZO MATIAS
A41: 8:00 a. m. | B41: JUEVES | C41: 46226 | D41: 8:16 a. m. | F41: 12:02 a. m. | H41: 15.77
A42: 8:00 a. m. | B42: VIERNES | C42: 46227 | D42: 8:13 a. m. | F42: 9:45 p. m. | H42: 13.53
A43: 4:00 p. m. | B43: SÁBADO | C43: 46228 | D43: 3:53 p. m. | F43: 5:34 a. m. | H43: 13.68 | I43: GUARDIA FORJA
A44: 1:00 p. m. | B44: DOMINGO | C44: 46229 | D44: 1:04 p. m. | F44: 7:55 p. m. | H44: 6.85
A45: 8:00 a. m. | B45: LUNES | C45: 46230 | D45: 8:06 a. m. | F45: 8:13 p. m. | H45: 12.12
A46: 8:00 a. m. | B46: MARTES | C46: 46231 | D46: 8:06 a. m. | F46: 8:03 p. m. | H46: 11.95
A47: 7:30 a. m. | B47: MIÉRCOLES | C47: 46232 | D47: 7:53 a. m. | F47: 7:16 p. m. | H47: 11.38
A48: FRANCO | B48: JUEVES | C48: 46233 | H48: 0
A49: FRANCO | B49: VIERNES | C49: 46234 | H49: 0
F50: TOTALES | H50: =SUM(H19:H49) -> 241.87
A52: VALES | E52: DETALLE DE PRESTAMOS / DESCUENTOS / MULTAS
A53: FECHA | B53: DETALLE | D53: MONTO | E53: FECHA | F53: DETALLE | H53: IMPORTE
A54: 46227 | B54: ADELANTO | D54: 100000 | E54: 46223 | F54: MULTA - HLW156 | H54: 105450
A56: TOTAL | D56: =SUM(D54:D55) -> 100000 | E56: PENDIENTE DE PAGO | H56: =+H54 -> 105450
E57: PENDIENTE A PAGAR PRESTAMOS | H57: 0
A58: HRS PENDIENTES
A59: MES | D59: HRS
A60: ACUMULADO 2024 | D60: -396.88
A61: ENERO | D61: 0
A62: FEBRERO | D62: 0
A63: MARZO | D63: 0
A64: ABRIL
A65: MAYO
A66: JUNIO
A67: JULIO
A68: AGOSTO
A69: SEPTIEMBRE
A70: OCTUBRE
A71: NOVIEMBRE
A72: DICIEMBRE
A73: TOTAL | D73: =SUM(D60:D72) -> -396.88

Sheet MILTON
I2: AUMENTO
I3: FEBRERO/MARZO
A5: =+MAYRA!A5 -> SUELDO JULIO 2026 | F5: SUELDO | H5: =+A8+C8+E8+G8+B10+C10+G12+C14+F14 -> 1684333.1 | I5: AGUINALDOS | K5: =+B6 -> MILTON DIAZ
A6: Nombre: | B6: MILTON DIAZ | D6: DNI: | F6: Escalafon: | H6: 2 | I6: JULIO | J6: 1114523.1 | K6: =+MAYRA!L6 -> Mes: JULIO 2026
A7: SUELDO BASICO | C7: PREMIO INCENTIVO | E7: VIATICO | G7: PREMIO PRESENTISMO | I7: AGOSTO | K7: Sueldo Basico | L7: =+A8 -> 1114523.1
A8: =951770.34*17.1%+951770.34 -> 1114523.1 | C8: =+L21 -> 60011.689 | E8: =+L23 -> 60011.689 | G8: =+L25 -> 138169.66 | I8: SEPTIEMBRE | K8: Premio Incentivo | L8: =+C8 -> 60011.689
A9: ANTIGÜEDAD | B9: 2 | C9: VACACIONES/AGUINALDOS/EXTRAS | E9: VALES/DESCUENTOS/MULTAS | G9: TIPO DE SEGURO | I9: OCTUBRE | K9: Viatico | L9: =+E8 -> 60011.689
A10: 45292 | B10: =+L28 -> 23420 | C10: 40000 | E10: =+D57+H57 -> 100000 | G10: AP | I10: NOVIEMBRE | K10: Premio Presentismo | L10: =+G8 -> 138169.66
A11: HRS ACORDADAS | B11: HRS TRABAJADAS | C11: HRS EXTRAS TRABAJADAS | E11: VALOR HRS EXTRAS | G11: IMPORTE HRS EXTRAS TRABAJADAS | I11: DICIEMBRE | K11: Antigüedad | L11: =+B10 -> 23420
A12: 220 | B12: =+H50 -> 243.76 | C12: =+B12-A12 -> 23.76 | E12: =3840.53*17.1%+3840.53 -> 4497.2606 | G12: =+C12*E12 -> 106854.91 | I12: TOTAL | J12: =SUM(J6:J11) -> 1114523.1 | K12: Vacas/Aguinaldos/Extras | L12: =+C10 -> 40000
A13: PREMIOS COMPLEMENTARIOS | C13: PREMIO PRODUCCIÓN | E13: =+EVENTOS!H18 -> 2 | F13: PREMIO GUARDIAS | H13: 1 | I13: 6 MESES | J13: =+J12/6 -> 185753.85 | K13: Hrs Extras | L13: =+G12 -> 106854.91
C14: =+L36*E13 -> 128131.76 | F14: =+L38*H13 -> 13210.285 | I14: AGUINALDOS | J14: =+J13/2 -> 92876.923 | K14: Premio Producción | L14: =+C14 -> 128131.76
A15: INICIO DEL ACUERDO | C15: VIGENCIA DEL ACUERDO | E15: % DEL ACUERDO | K15: Premio Guardias | L15: =+F14 -> 13210.285
A16: 46143 | C16: 9 MESES | E16: 17,1% Básico + Premio Incentivo + Viatico + Presentismo + Hs Extra + Antigüedad + Premio Producción + Premio Guardias | K16: Total | L16: =SUM(L7:L15) -> 1684333.1
A17: IMPORTE TOTAL A COBRAR | G17: =+H5-E10 -> 1584333.1 | K17: Vales | L17: =+E10 -> 100000
A18: Convocatoria | B18: Dia | C18: Fecha | D18: Inicio de Actividades | F18: Fin de Actividades | H18: Hrs trabajadas | K18: A cobrar | L18: =+L16-L17 -> 1584333.1
A19: 9:00 a. m. | B19: MIERCOLES | C19: 46204 | D19: 9:10 a. m. | F19: 6:00 p. m. | H19: 8.83
A20: 9:00 a. m. | B20: JUEVES | C20: 46205 | D20: 9:05 a. m. | F20: 6:00 p. m. | H20: 8.92 | K20: PREMIO INCENTIVO
A21: 9:00 a. m. | B21: VIERNES | C21: 46206 | D21: 9:15 a. m. | F21: 5:32 p. m. | H21: 8.28 | K21: 1 Cat | L21: =51248.24*17.1%+51248.24 -> 60011.689
A22: 9:00 a. m. | B22: SÁBADO | C22: 46207 | D22: 9:05 a. m. | F22: 8:30 p. m. | H22: 11.42 | I22: GUARDIA KEMPES | K22: VIÁTICO
A23: LIBRE | B23: DOMINGO | C23: 46208 | H23: 0 | K23: 1 Cat | L23: =51248.24*17.1%+51248.24 -> 60011.689
A24: VACACIONES | B24: LUNES | C24: 46209 | H24: 8 | K24: PREMIO PRESENTISMO
A25: VACACIONES | B25: MARTES | C25: 46210 | H25: 8 | K25: 1 Cat | L25: =117992.88*17.1%+117992.88 -> 138169.66
A26: VACACIONES | B26: MIÉRCOLES | C26: 46211 | H26: 8 | K26: ANTIGÜEDAD
A27: VACACIONES | B27: JUEVES | C27: 46212 | H27: 8 | K27: 1 Años | L27: =12500*17.1%+12500 -> 14637.5
A28: VACACIONES | B28: VIERNES | C28: 46213 | H28: 8 | K28: 2 Años | L28: =20000*17.1%+20000 -> 23420
A29: VACACIONES | B29: SÁBADO | C29: 46214 | H29: 8 | K29: 3 Años | L29: =27500*17.1%+27500 -> 32202.5
A30: VACACIONES | B30: DOMINGO | C30: 46215 | H30: 8 | K30: 4 Años | L30: =35000*17.1%+35000 -> 40985
A31: 9:00 a. m. | B31: LUNES | C31: 46216 | D31: 9:05 a. m. | F31: 6:03 p. m. | H31: 8.97 | K31: 5 Años | L31: =42500*17.1%+42500 -> 49767.5
A32: 9:00 a. m. | B32: MARTES | C32: 46217 | D32: 9:03 a. m. | F32: 6:02 p. m. | H32: 8.98 | K32: 6 Años | L32: =63750*17.1%+63750 -> 74651.25
A33: LIBRE | B33: MIÉRCOLES | C33: 46218 | H33: 0 | K33: 7 Años | L33: =127500*17.1%+127500 -> 149302.5
A34: 9:00 a. m. | B34: JUEVES | C34: 46219 | D34: 9:09 a. m. | F34: 6:24 p. m. | H34: 9.25 | K34: 8 Años | L34: =200000*17.1%+200000 -> 234200
A35: 9:00 a. m. | B35: VIERNES | C35: 46220 | D35: 9:03 a. m. | F35: 7:05 p. m. | H35: 10.03 | K35: PREMIO PRODUCCION
A36: X | B36: SÁBADO | C36: 46221 | D36: 12:00 p. m. | F36: 8:05 p. m. | H36: 8.08 | I36: VIAJE SGO DEL ESTERO/Camioneta Veck | K36: 1 Cat (X Show) | L36: =54710.4*17.1%+54710.4 -> 64065.878
A37: 7:00 a. m. | B37: DOMINGO | C37: 46222 | D37: 7:00 a. m. | F37: 2:00 p. m. | H37: 7 | I37: SGO DEL ESTERO | K37: PREMIO GUARDIAS
A38: 7:00 a. m. | B38: LUNES | C38: 46223 | D38: 7:00 a. m. | F38: 9:00 p. m. | H38: 14 | I38: SGO DEL ESTERO | K38: 1 Cat (X Show) | L38: =11281.2*17.1%+11281.2 -> 13210.285
A39: 8:00 a. m. | B39: MARTES | C39: 46224 | D39: 8:00 a. m. | F39: 9:00 p. m. | H39: 13 | I39: SGO DEL ESTERO
A40: 8:00 a. m. | B40: MIÉRCOLES | C40: 46225 | D40: 8:00 a. m. | F40: 7:00 p. m. | H40: 11 | I40: SGO DEL ESTERO
A41: 8:00 a. m. | B41: JUEVES | C41: 46226 | D41: 8:00 a. m. | F41: 7:00 p. m. | H41: 11 | I41: SGO DEL ESTERO
A42: 8:00 a. m. | B42: VIERNES | C42: 46227 | D42: 8:00 a. m. | F42: 7:00 p. m. | H42: 11 | I42: SGO DEL ESTERO
A43: 7:00 a. m. | B43: SÁBADO | C43: 46228 | D43: 7:00 a. m. | F43: 4:00 p. m. | H43: 9 | I43: SGO DEL ESTERO/Guardia
A44: 9:00 a. m. | B44: DOMINGO | C44: 46229 | D44: 7:00 a. m. | F44: 7:30 p. m. | H44: 12.5 | I44: SGO DEL ESTERO
A45: 8:00 a. m. | B45: LUNES | C45: 46230 | D45: 8:00 a. m. | F45: 7:00 p. m. | H45: 11 | I45: SGO DEL ESTERO
A46: 8:00 a. m. | B46: MARTES | C46: 46231 | D46: 8:00 a. m. | F46: 1:30 p. m. | H46: 5.5 | I46: SGO DEL ESTERO/Regreso Cba Sprinter
A47: FRANCO | B47: MIÉRCOLES | C47: 46232 | H47: 0
A48: FRANCO | B48: JUEVES | C48: 46233 | H48: 0
A49: FRANCO | B49: VIERNES | C49: 46234 | H49: 0
F50: TOTALES | H50: =SUM(H19:H49) -> 243.76
A52: VALES | E52: DETALLE DE PRESTAMOS / DESCUENTOS / MULTAS
A53: FECHA | B53: DETALLE | D53: MONTO | E53: FECHA | F53: DETALLE | H53: IMPORTE
A54: 46227 | B54: ADELANTO | D54: 100000
A57: TOTAL | D57: =SUM(D54:D56) -> 100000 | E57: PENDIENTE DE PAGO | H57: =+H56 -> 0
E58: PENDIENTE A PAGAR PRESTAMOS | H58: 0
A59: HRS PENDIENTES
A60: MES | D60: HRS
A61: ACUMULADO 2024 | D61: -396.88
A62: ENERO | D62: 0
A63: FEBRERO | D63: 0
A64: MARZO | D64: 0
A65: ABRIL
A66: MAYO
A67: JUNIO
A68: JULIO
A69: AGOSTO
A70: SEPTIEMBRE
A71: OCTUBRE
A72: NOVIEMBRE
A73: DICIEMBRE
A74: TOTAL | D74: =SUM(D61:D73) -> -396.88

Sheet CHARA
I2: AUMENTO
I3: FEBRERO/MARZO
A5: =+MAYRA!A5 -> SUELDO JULIO 2026 | F5: SUELDO | H5: =+A8+C8+E8+G8+B10+C10+G12+C14+F14 -> 1630567.9 | I5: AGUINALDOS | K5: =+B6 -> FABRIZIO SOSA
A6: Nombre: | B6: FABRIZIO SOSA | D6: DNI: | F6: Escalafon: | H6: 2 | I6: JULIO | J6: 1183837.6 | K6: =+MAYRA!L6 -> Mes: JULIO 2026
A7: SUELDO BASICO | C7: PREMIO INCENTIVO | E7: VIATICO | G7: PREMIO PRESENTISMO | I7: AGOSTO | K7: Sueldo Basico | L7: =+A8 -> 1183837.6
A8: =1010962.96*17.1%+1010962.96 -> 1183837.6 | C8: 0 | E8: =+L23 -> 76937.791 | G8: 0 | I8: SEPTIEMBRE | K8: Premio Incentivo | L8: =+C8 -> 0
A9: ANTIGÜEDAD | B9: 2 | C9: VACACIONES/AGUINALDOS/EXTRAS | E9: VALES/DESCUENTOS/MULTAS | G9: TIPO DE SEGURO | I9: OCTUBRE | K9: Viatico | L9: =+E8 -> 76937.791
A10: 45292 | B10: =+L28 -> 23420 | C10: 0 | E10: =+D57+H57 -> 0 | G10: ART | I10: NOVIEMBRE | K10: Premio Presentismo | L10: =+G8 -> 0
A11: HRS ACORDADAS | B11: HRS TRABAJADAS | C11: HRS EXTRAS TRABAJADAS | E11: VALOR HRS EXTRAS | G11: IMPORTE HRS EXTRAS TRABAJADAS | I11: DICIEMBRE | K11: Antigüedad | L11: =+B10 -> 23420
A12: 220 | B12: =+H50 -> 262.25 | C12: =+B12-A12 -> 42.25 | E12: =3712.52*17.1%+3712.52 -> 4347.3609 | G12: =+C12*E12 -> 183676 | I12: TOTAL | J12: =SUM(J6:J11) -> 1183837.6 | K12: Vacas/Aguinaldos/Extras | L12: =+C10 -> 0
A13: PREMIOS COMPLEMENTARIOS | C13: PREMIO VALLADO | E13: =+EVENTOS!I18 -> 3 | F13: PREMIO GUARDIAS | H13: 1 | I13: 6 MESES | J13: =+J12/6 -> 197306.27 | K13: Hrs Extras | L13: =+G12 -> 183676
C14: =+L36*E13 -> 149507.13 | F14: =+L38*H13 -> 13189.383 | I14: AGUINALDOS | J14: =+J13/2 -> 98653.136 | K14: Premio Vallado | L14: =+C14 -> 149507.13
A15: INICIO DEL ACUERDO | C15: VIGENCIA DEL ACUERDO | E15: % DEL ACUERDO | K15: Premio Guardias | L15: =+F14 -> 13189.383
A16: 46143 | C16: 9 MESES | E16: 17,1% Básico + Premio Incentivo + Viatico + Presentismo + Hs Extra + Antigüedad + Premio Vallado + Premio Guardias | K16: Total | L16: =SUM(L7:L15) -> 1630567.9
A17: IMPORTE TOTAL A COBRAR | G17: =+H5-E10 -> 1630567.9 | K17: Vales | L17: =+E10 -> 0
A18: Convocatoria | B18: Dia | C18: Fecha | D18: Inicio de Actividades | F18: Fin de Actividades | H18: Hrs trabajadas | K18: A cobrar | L18: =+L16-L17 -> 1630567.9
A19: 9:00 a. m. | B19: MIERCOLES | C19: 46204 | D19: 9:20 a. m. | F19: 6:02 p. m. | H19: 8.7
A20: 9:00 a. m. | B20: JUEVES | C20: 46205 | D20: 9:21 a. m. | F20: 6:02 p. m. | H20: 8.68 | K20: PREMIO INCENTIVO
A21: 9:00 a. m. | B21: VIERNES | C21: 46206 | D21: 9:31 a. m. | F21: 5:33 p. m. | H21: 8.03 | K21: 1 Cat | L21: =42096.77*17.1%+42096.77 -> 49295.318
A22: 9:00 a. m. | B22: SÁBADO | C22: 46207 | D22: 9:14 a. m. | F22: 8:39 p. m. | H22: 11.42 | I22: GUARDIA KEMPES | K22: VIÁTICO
A23: LIBRE | B23: DOMINGO | C23: 46208 | H23: 0 | K23: 1 Cat | L23: =65702.64*17.1%+65702.64 -> 76937.791
A24: VACACIONES | B24: LUNES | C24: 46209 | H24: 8 | K24: PREMIO PRESENTISMO
A25: VACACIONES | B25: MARTES | C25: 46210 | H25: 8 | K25: 1 Cat | L25: =117992.88*17.1%+117992.88 -> 138169.66
A26: VACACIONES | B26: MIÉRCOLES | C26: 46211 | H26: 8 | K26: ANTIGÜEDAD
A27: VACACIONES | B27: JUEVES | C27: 46212 | H27: 8 | K27: 1 Años | L27: =12500*17.1%+12500 -> 14637.5
A28: VACACIONES | B28: VIERNES | C28: 46213 | H28: 8 | K28: 2 Años | L28: =20000*17.1%+20000 -> 23420
A29: VACACIONES | B29: SÁBADO | C29: 46214 | H29: 8 | K29: 3 Años | L29: =27500*17.1%+27500 -> 32202.5
A30: VACACIONES | B30: DOMINGO | C30: 46215 | H30: 8 | K30: 4 Años | L30: =35000*17.1%+35000 -> 40985
A31: LIBRE | B31: LUNES | C31: 46216 | H31: 0 | K31: 5 Años | L31: =42500*17.1%+42500 -> 49767.5
A32: LIBRE | B32: MARTES | C32: 46217 | H32: 0 | K32: 6 Años | L32: =63750*17.1%+63750 -> 74651.25
A33: LIBRE | B33: MIÉRCOLES | C33: 46218 | H33: 0 | K33: 7 Años | L33: =127500*17.1%+127500 -> 149302.5
A34: 9:00 a. m. | B34: JUEVES | C34: 46219 | D34: 9:09 a. m. | F34: 6:24 p. m. | H34: 9.25 | K34: 8 Años | L34: =200000*17.1%+200000 -> 234200
A35: 9:00 a. m. | B35: VIERNES | C35: 46220 | D35: 9:08 a. m. | F35: 7:25 p. m. | H35: 10.28 | K35: PREMIO VALLADO
A36: 9:00 a. m. | B36: SÁBADO | C36: 46221 | D36: 9:11 a. m. | F36: 5:55 p. m. | H36: 8.73 | K36: 1 Cat (X Show) | L36: =42558.25*17.1%+42558.25 -> 49835.711
A37: 9:00 a. m. | B37: DOMINGO | C37: 46222 | D37: 9:12 a. m. | F37: 1:32 p. m. | H37: 4.33 | K37: PREMIO GUARDIAS
A38: 9:00 a. m. | B38: LUNES | C38: 46223 | D38: 9:11 a. m. | F38: 7:09 p. m. | H38: 9.97 | K38: 1 Cat (X Show) | L38: =11263.35*17.1%+11263.35 -> 13189.383
A39: 9:00 a. m. | B39: MARTES | C39: 46224 | D39: 9:08 a. m. | F39: 6:58 p. m. | H39: 9.83
A40: 8:00 a. m. | B40: MIÉRCOLES | C40: 46225 | D40: 8:08 a. m. | F40: 8:04 p. m. | H40: 11.93
A41: 8:00 a. m. | B41: JUEVES | C41: 46226 | D41: 8:10 a. m. | F41: 11:54 p. m. | H41: 15.73
A42: 8:00 a. m. | B42: VIERNES | C42: 46227 | D42: 8:07 a. m. | F42: 9:45 p. m. | H42: 13.63
A43: 7:30 a. m. | B43: SÁBADO | C43: 46228 | D43: 7:48 a. m. | F43: 6:26 p. m. | H43: 10.63
A44: 8:00 a. m. | B44: DOMINGO | C44: 46229 | D44: 8:13 a. m. | F44: 7:45 p. m. | H44: 11.53
A45: 8:00 a. m. | B45: LUNES | C45: 46230 | D45: 8:04 a. m. | F45: 8:04 p. m. | H45: 12
A46: 8:00 a. m. | B46: MARTES | C46: 46231 | D46: 8:15 a. m. | F46: 8:06 p. m. | H46: 11.85
A47: 7:30 a. m. | B47: MIÉRCOLES | C47: 46232 | D47: 8:16 a. m. | F47: 7:16 p. m. | H47: 11
A48: 9:00 a. m. | B48: JUEVES | C48: 46233 | D48: 9:06 a. m. | F48: 6:14 p. m. | H48: 9.13
A49: 8:00 a. m. | B49: VIERNES | C49: 46234 | D49: 8:56 a. m. | F49: 6:32 p. m. | H49: 9.6
F50: TOTALES | H50: =SUM(H19:H49) -> 262.25
A52: VALES | E52: DETALLE DE PRESTAMOS / DESCUENTOS / MULTAS
A53: FECHA | B53: DETALLE | D53: MONTO | E53: FECHA | F53: DETALLE | H53: IMPORTE
A57: TOTAL | D57: =SUM(D54:D56) -> 0 | E57: PENDIENTE DE PAGO | H57: =+H56 -> 0
E58: PENDIENTE A PAGAR PRESTAMOS | H58: 0
A59: HRS PENDIENTES
A60: MES | D60: HRS
A61: ACUMULADO 2024 | D61: -396.88
A62: ENERO | D62: 0
A63: FEBRERO | D63: 0
A64: MARZO | D64: 0
A65: ABRIL
A66: MAYO
A67: JUNIO
A68: JULIO
A69: AGOSTO
A70: SEPTIEMBRE
A71: OCTUBRE
A72: NOVIEMBRE
A73: DICIEMBRE
A74: TOTAL | D74: =SUM(D61:D73) -> -396.88

Sheet TONI
I2: AUMENTO
I3: FEBRERO/MARZO
A5: =+MAYRA!A5 -> SUELDO JULIO 2026 | F5: SUELDO | H5: =+A8+C8+E8+G8+B10+C10+G10+G12 -> 1943826.2 | I5: AGUINALDOS | K5: =+B6 -> ANTONIO VELEZ
A6: Nombre: | B6: ANTONIO VELEZ | D6: DNI: | E6: 34688648 | F6: Escalafon: | H6: 2 | I6: JULIO | J6: 1320792.2 | K6: =+MAYRA!L6 -> Mes: JULIO 2026
A7: SUELDO BASICO | C7: PREMIO INCENTIVO | E7: VIATICO | G7: PREMIO PRESENTISMO | I7: AGOSTO | K7: Sueldo Basico | L7: =+A8 -> 1320792.2
A8: =1127918.18*17.1%+1127918.18 -> 1320792.2 | C8: =+L20 -> 64622.909 | E8: =+L22 -> 65597.933 | G8: =+L24 -> 138169.66 | I8: SEPTIEMBRE | K8: Premio Incentivo | L8: =+C8 -> 64622.909
A9: ANTIGÜEDAD | B9: 7 | C9: VACACIONES/AGUINALDOS/EXTRAS | E9: VALES/DESCUENTOS/MULTAS | G9: PREMIO DEPÓSITO | I9: OCTUBRE | K9: Viatico | L9: =+E8 -> 65597.933
A10: 43344 | B10: =+L32 -> 149302.5 | C10: 0 | E10: =+D54+H54 -> 0 | G10: =+L35 -> 150483.9 | I10: NOVIEMBRE | K10: Premio Presentismo | L10: =+G8 -> 138169.66
A11: HRS ACORDADAS | B11: HRS TRABAJADAS | C11: HRS EXTRAS TRABAJADAS | E11: VALOR HRS EXTRAS | G11: IMPORTE HRS EXTRAS TRABAJADAS | I11: DICIEMBRE | K11: Antigüedad | L11: =+B10 -> 149302.5
A12: 220 | B12: =+H48 -> 231.31 | C12: =+B12-A12 -> 11.31 | E12: =4142.03*17.1%+4142.03 -> 4850.3171 | G12: =+C12*E12 -> 54857.087 | I12: TOTAL | J12: =SUM(J6:J11) -> 1320792.2 | K12: Vacas/Aguinaldos/Extras | L12: =+C10 -> 0
A13: TIPO DE SEGURO | B13: INICIO DEL ACUERDO | D13: VIGENCIA DEL ACUERDO | F13: % DEL ACUERDO | I13: 6 MESES | J13: =+J12/6 -> 220132.03 | K13: Premio Depósito | L13: =+G10 -> 150483.9
A14: ART | B14: 46143 | D14: 9 MESES | F14: 17,1% Básico + Premio Incentivo + Viatico + Presentismo + Hs Extra + Antigüedad + Premio Guardias // 17,1% + 25% (Excepción) Premio Depósito | I14: AGUINALDOS | J14: =+J13/2 -> 110066.02 | K14: Hrs Extras | L14: =+G12 -> 54857.087
A15: IMPORTE TOTAL A COBRAR | G15: =+H5-E10 -> 1943826.2 | K15: Total | L15: =SUM(L7:L14) -> 1943826.2
A16: Convocatoria | B16: Dia | C16: Fecha | D16: Inicio de Actividades | F16: Fin de Actividades | H16: Hrs trabajadas | K16: Vales | L16: =+E10 -> 0
A17: 9:00 a. m. | B17: MIERCOLES | C17: 46204 | D17: 8:49 a. m. | F17: 6:05 p. m. | H17: 9.27 | K17: A cobrar | L17: =+L15-L16 -> 1943826.2
A18: 9:00 a. m. | B18: JUEVES | C18: 46205 | D18: 8:48 a. m. | F18: 6:11 p. m. | H18: 9.38
A19: 9:00 a. m. | B19: VIERNES | C19: 46206 | D19: 9:03 a. m. | F19: 5:51 p. m. | H19: 8.8 | K19: PREMIO INCENTIVO
A20: 9:00 a. m. | B20: SÁBADO | C20: 46207 | D20: 8:51 a. m. | F20: 2:58 p. m. | H20: 6.12 | K20: 1 Cat | L20: =56894.03*17.1%+54894.03 -> 64622.909
A21: LIBRE | B21: DOMINGO | C21: 46208 | H21: 0 | K21: VIÁTICO
A22: 9:00 a. m. | B22: LUNES | C22: 46209 | D22: 8:55 a. m. | F22: 6:09 p. m. | H22: 9.23 | K22: 1 Cat | L22: =56018.73*17.1%+56018.73 -> 65597.933
A23: LIBRE | B23: MARTES | C23: 46210 | H23: 0 | K23: PREMIO PRESENTISMO
A24: 9:00 a. m. | B24: MIÉRCOLES | C24: 46211 | D24: 9:09 a. m. | F24: 6:24 p. m. | H24: 9.25 | K24: 1 Cat | L24: =117992.88*17.1%+117992.88 -> 138169.66
A25: 9:00 a. m. | B25: JUEVES | C25: 46212 | D25: 8:55 a. m. | F25: 6:35 p. m. | H25: 9.67 | K25: ANTIGÜEDAD
A26: 9:00 a. m. | B26: VIERNES | C26: 46213 | D26: 8:57 a. m. | F26: 6:58 p. m. | H26: 10.02 | K26: 1 Años | L26: =12500*17.1%+12500 -> 14637.5
A27: 9:00 a. m. | B27: SÁBADO | C27: 46214 | D27: 8:51 a. m. | F27: 4:25 p. m. | H27: 7.57 | K27: 2 Años | L27: =20000*17.1%+20000 -> 23420
A28: LIBRE | B28: DOMINGO | C28: 46215 | H28: 0 | K28: 3 Años | L28: =27500*17.1%+27500 -> 32202.5
A29: VACACIONES | B29: LUNES | C29: 46216 | H29: 8 | K29: 4 Años | L29: =35000*17.1%+35000 -> 40985
A30: VACACIONES | B30: MARTES | C30: 46217 | H30: 8 | K30: 5 Años | L30: =42500*17.1%+42500 -> 49767.5
A31: VACACIONES | B31: MIÉRCOLES | C31: 46218 | H31: 8 | K31: 6 Años | L31: =63750*17.1%+63750 -> 74651.25
A32: VACACIONES | B32: JUEVES | C32: 46219 | H32: 8 | K32: 7 Años | L32: =127500*17.1%+127500 -> 149302.5
A33: VACACIONES | B33: VIERNES | C33: 46220 | H33: 8 | K33: 8 Años | L33: =200000*17.1%+200000 -> 234200
A34: VACACIONES | B34: SÁBADO | C34: 46221 | H34: 8 | K34: PREMIO DEPÓSITO
A35: VACACIONES | B35: DOMINGO | C35: 46222 | H35: 8 | K35: 1 Cat | L35: =105900*42.1%+105900 -> 150483.9
A36: VACACIONES | B36: LUNES | C36: 46223 | H36: 8 | K36: PREMIO GUARDIAS
A37: VACACIONES | B37: MARTES | C37: 46224 | H37: 8 | K37: 1 Cat (X Show) | L37: =11281.2*17.1%+11281.2 -> 13210.285
A38: VACACIONES | B38: MIÉRCOLES | C38: 46225 | H38: 8
A39: VACACIONES | B39: JUEVES | C39: 46226 | H39: 8
A40: VACACIONES | B40: VIERNES | C40: 46227 | H40: 8
A41: VACACIONES | B41: SÁBADO | C41: 46228 | H41: 8
A42: VACACIONES | B42: DOMINGO | C42: 46229 | H42: 8
A43: VACACIONES | B43: LUNES | C43: 46230 | H43: 8
A44: VACACIONES | B44: MARTES | C44: 46231 | H44: 8
A45: VACACIONES | B45: MIÉRCOLES | C45: 46232 | H45: 8
A46: VACACIONES | B46: JUEVES | C46: 46233 | H46: 8
A47: VACACIONES | B47: VIERNES | C47: 46234 | H47: 8
F48: TOTALES | H48: =SUM(H17:H47) -> 231.31
A50: VALES | E50: DETALLE DE PRESTAMOS / DESCUENTOS / MULTAS
A51: FECHA | B51: DETALLE | D51: MONTO | E51: FECHA | F51: DETALLE | H51: IMPORTE
A54: TOTAL | D54: =SUM(D52:D53) -> 0 | E54: PENDIENTE DE PAGO | H54: =+H53 -> 0
E55: PENDIENTE A PAGAR PRESTAMOS | H55: 0
A56: HRS PENDIENTES
A57: MES | D57: HRS
A58: ACUMULADO 2024 | D58: -396.88
A59: ENERO | D59: 0
A60: FEBRERO | D60: 0
A61: MARZO | D61: 0
A62: ABRIL
A63: MAYO
A64: JUNIO
A65: JULIO
A66: AGOSTO
A67: SEPTIEMBRE
A68: OCTUBRE
A69: NOVIEMBRE
A70: DICIEMBRE
A71: TOTAL | D71: =SUM(D58:D70) -> -396.88

Sheet DAVID
I2: AUMENTO
I3: ABRIL/MAYO
A5: =+MAYRA!A5 -> SUELDO JULIO 2026 | F5: SUELDO | H5: =+A8+C8+E8+G8+B10+C10+G10+G12 -> 2298936.4 | I5: AGUINALDOS | K5: =+B6 -> DAVID AGUIRRE
A6: Nombre: | B6: DAVID AGUIRRE | D6: DNI: | F6: Escalafon: | H6: 2 | I6: JULIO | K6: =+MAYRA!L6 -> Mes: JULIO 2026
A7: SUELDO BASICO | C7: PREMIO INCENTIVO | E7: PREMIO PRODUCCION SHOW | G7: PREMIO PRESENTISMO | I7: AGOSTO | K7: Sueldo Basico | L7: =+A8 -> 1495000
A8: 1495000 | C8: =L20 -> 65428.13 | E8: 0 | G8: =L24 -> 135691.81 | I8: SEPTIEMBRE | K8: Premio Incentivo | L8: =+C8 -> 65428.13
A9: ANTIGÜEDAD | B9: 0 | C9: VACACIONES/AGUINALDOS/EXTRAS | E9: VALES/DESCUENTOS/MULTAS | G9: PREMIO CONTROL PARQUE AUT | I9: OCTUBRE | K9: Premio Producción Show | L9: =+E8 -> 0
A10: 46023 | B10: 0 | C10: 0 | E10: =+D56+H56 -> 650000 | G10: =L35 -> 287500 | I10: NOVIEMBRE | K10: Premio Presentismo | L10: =+G8 -> 135691.81
A11: HRS ACORDADAS | B11: HRS TRABAJADAS | C11: HRS EXTRAS TRABAJADAS | E11: VALOR HRS EXTRAS | G11: IMPORTE HRS EXTRAS TRABAJADAS | I11: DICIEMBRE | K11: Antigüedad | L11: =+B10 -> 0
A12: 200 | B12: =+H48 -> 256.53 | C12: =+B12-A12 -> 56.53 | E12: 5577.86 | G12: =+C12*E12 -> 315316.43 | I12: TOTAL | J12: =SUM(J6:J11) -> 0 | K12: Vacas/Aguinaldos/Extras | L12: =+C10 -> 0
A13: TIPO DE SEGURO | B13: INICIO DEL ACUERDO | D13: VIGENCIA DEL ACUERDO | F13: % DEL ACUERDO | I13: 6 MESES | J13: =+J12/6 -> 0 | K13: Premio Control Parque Automotor | L13: =+G10 -> 287500
A14: ART | B14: 46204 | D14: 9 MESES | F14: 11,5% + 7,5% (Excepción) Básico + Premio + Viatico + Guardia // 11,5% + 15% (Excepción) Presentismo + Hs Extra // 11,5% + 65% (Excepción) Deposito | I14: AGUINALDOS | J14: =+J13/2 -> 0 | K14: Hrs Extras | L14: =+G12 -> 315316.43
A15: IMPORTE TOTAL A COBRAR | G15: =+H5-E10 -> 1648936.4 | K15: Total | L15: =SUM(L7:L14) -> 2298936.4
A16: Convocatoria | B16: Dia | C16: Fecha | D16: Inicio de Actividades | F16: Fin de Actividades | H16: Hrs trabajadas | K16: Vales | L16: =+E10 -> 650000
A17: 9:00 a. m. | B17: MIERCOLES | C17: 46204 | D17: 8:49 a. m. | F17: 6:06 p. m. | H17: 9.28 | K17: A cobrar | L17: =+L15-L16 -> 1648936.4
A18: 9:00 a. m. | B18: JUEVES | C18: 46205 | D18: 8:48 a. m. | F18: 6:11 p. m. | H18: 9.38
A19: 9:00 a. m. | B19: VIERNES | C19: 46206 | D19: 9:04 a. m. | F19: 5:51 p. m. | H19: 8.78 | K19: PREMIO INCENTIVO
A20: 9:00 a. m. | B20: SÁBADO | C20: 46207 | D20: 8:51 a. m. | F20: 2:58 p. m. | H20: 6.12 | K20: 1 Cat | L20: 65428.13
A21: LIBRE | B21: DOMINGO | C21: 46208 | H21: 0 | K21: VIÁTICO
A22: VACACIONES | B22: LUNES | C22: 46209 | H22: 8 | K22: 1 Cat
A23: VACACIONES | B23: MARTES | C23: 46210 | H23: 8 | K23: PREMIO PRESENTISMO
A24: VACACIONES | B24: MIÉRCOLES | C24: 46211 | H24: 8 | K24: 1 Cat | L24: 135691.81
A25: VACACIONES | B25: JUEVES | C25: 46212 | H25: 8 | K25: ANTIGÜEDAD
A26: VACACIONES | B26: VIERNES | C26: 46213 | H26: 8 | K26: 1 Años | L26: 12500
A27: VACACIONES | B27: SÁBADO | C27: 46214 | H27: 8 | K27: 2 Años | L27: 20000
A28: VACACIONES | B28: DOMINGO | C28: 46215 | H28: 8 | K28: 3 Años | L28: 27500
A29: 9:00 a. m. | B29: LUNES | C29: 46216 | D29: 8:46 a. m. | F29: 6:07 p. m. | H29: 9.35 | K29: 4 Años | L29: 35000
A30: 9:00 a. m. | B30: MARTES | C30: 46217 | D30: 8:36 a. m. | F30: 6:01 p. m. | H30: 9.42 | K30: 5 Años | L30: 42500
A31: LIBRE | B31: MIÉRCOLES | C31: 46218 | H31: 0 | K31: 6 Años | L31: 63750
A32: 9:00 a. m. | B32: JUEVES | C32: 46219 | D32: 9:00 a. m. | F32: 6:33 p. m. | H32: 9.55 | K32: 7 Años | L32: 127500
A33: 9:00 a. m. | B33: VIERNES | C33: 46220 | D33: 8:36 a. m. | F33: 6:26 p. m. | H33: 9.83 | K33: 8 Años | L33: 200000
A34: 9:00 a. m. | B34: SÁBADO | C34: 46221 | D34: 8:26 a. m. | F34: 4:23 p. m. | H34: 7.95 | K34: PREMIO PARQUE AUTOMOTOR
A35: LIBRE | B35: DOMINGO | C35: 46222 | H35: 0 | K35: 1 Cat | L35: 287500
A36: 9:00 a. m. | B36: LUNES | C36: 46223 | D36: 8:45 a. m. | F36: 12:46 a. m. | H36: 16.02 | I36: VIAJE SGO DEL ESTERO | K36: PREMIO GUARDIAS
A37: 10:00 a. m. | B37: MARTES | C37: 46224 | D37: 9:35 a. m. | F37: 6:26 p. m. | H37: 8.85 | K37: 1 Cat (X Show) | L37: 12974.53
A38: 8:00 a. m. | B38: MIÉRCOLES | C38: 46225 | D38: 7:36 a. m. | F38: 6:10 p. m. | H38: 10.57 | K38: PREMIO PRODUCCION SHOW
A39: 8:00 a. m. | B39: JUEVES | C39: 46226 | D39: 7:56 a. m. | F39: 6:12 p. m. | H39: 10.27 | K39: 1 Cat | L39: 172500
A40: 8:00 a. m. | B40: VIERNES | C40: 46227 | D40: 7:44 a. m. | F40: 6:32 p. m. | H40: 10.8
A41: 7:00 a. m. | B41: SÁBADO | C41: 46228 | D41: 6:45 a. m. | F41: 6:22 p. m. | H41: 11.62
A42: LIBRE | B42: DOMINGO | C42: 46229 | H42: 0
A43: 6:30 a. m. | B43: LUNES | C43: 46230 | D43: 6:44 a. m. | F43: 6:40 p. m. | H43: 11.93
A44: 6:30 a. m. | B44: MARTES | C44: 46231 | D44: 6:19 a. m. | F44: 6:05 p. m. | H44: 11.77
A45: 8:00 a. m. | B45: MIÉRCOLES | C45: 46232 | D45: 7:49 a. m. | F45: 6:01 p. m. | H45: 10.2
A46: 9:00 a. m. | B46: JUEVES | C46: 46233 | D46: 8:55 a. m. | F46: 6:17 p. m. | H46: 9.37
A47: 9:00 a. m. | B47: VIERNES | C47: 46234 | D47: 9:02 a. m. | F47: 6:30 p. m. | H47: 9.47
F48: TOTALES | H48: =SUM(H17:H47) -> 256.53
A50: VALES | E50: DETALLE DE PRESTAMOS / DESCUENTOS / MULTAS
A51: FECHA | B51: DETALLE | D51: MONTO | E51: FECHA | F51: DETALLE | H51: IMPORTE
A52: 46219 | B52: ADELANTO | D52: 650000
A56: TOTAL | D56: =SUM(D52:D55) -> 650000 | E56: PENDIENTE DE PAGO | H56: =+H55 -> 0
E57: PENDIENTE A PAGAR PRESTAMOS | H57: 0
A58: HRS PENDIENTES
A59: MES | D59: HRS
A60: ACUMULADO 2024 | D60: -396.88
A61: ENERO | D61: 0
A62: FEBRERO | D62: 0
A63: MARZO | D63: 0
A64: ABRIL
A65: MAYO
A66: JUNIO
A67: JULIO
A68: AGOSTO
A69: SEPTIEMBRE
A70: OCTUBRE
A71: NOVIEMBRE
A72: DICIEMBRE
A73: TOTAL | D73: =SUM(D60:D72) -> -396.88

Sheet CARLOS
I2: AUMENTO
I3: ENERO/FEBRERO
A5: =+MAYRA!A5 -> SUELDO JULIO 2026 | F5: SUELDO | H5: =+A8+C8+E8+G8+B10+C10+G10+G12 -> 2039290.8 | I5: AGUINALDOS | K5: =+B6 -> CARLOS CARRIZO
A6: Nombre: | B6: CARLOS CARRIZO | D6: DNI: | E6: 37315890 | F6: Escalafon: | H6: 2 | I6: JULIO | J6: 1400375 | K6: =+MAYRA!L6 -> Mes: JULIO 2026
A7: SUELDO BASICO | C7: PREMIO INCENTIVO | E7: VIATICO | G7: PREMIO PRESENTISMO | I7: AGOSTO | K7: Sueldo Basico | L7: =+A8 -> 1400375
A8: =1120300*25%+1120300 -> 1400375 | C8: =+L20 -> 58762.08 | E8: =+L22 -> 65291.2 | G8: =+L24 -> 123153.92 | I8: SEPTIEMBRE | K8: Premio Incentivo | L8: =+C8 -> 58762.08
A9: ANTIGÜEDAD | B9: 1 | C9: VACACIONES/AGUINALDOS/EXTRAS | E9: VALES/DESCUENTOS/MULTAS | G9: PREMIO JEFE HERRERÍA | I9: OCTUBRE | K9: Viatico | L9: =+E8 -> 65291.2
A10: 45748 | B10: =+L26 -> 14600 | C10: 0 | E10: =+D56+H56 -> 300000 | G10: =+L35 -> 202500 | I10: NOVIEMBRE | K10: Premio Presentismo | L10: =+G8 -> 123153.92
A11: HRS ACORDADAS | B11: HRS TRABAJADAS | C11: HRS EXTRAS TRABAJADAS | E11: VALOR HRS EXTRAS | G11: IMPORTE HRS EXTRAS TRABAJADAS | I11: DICIEMBRE | K11: Antigüedad | L11: =+B10 -> 14600
A12: 200 | B12: =+H48 -> 233.12 | C12: =+B12-A12 -> 33.12 | E12: =4217.6*25%+4217.6 -> 5272 | G12: =+C12*E12 -> 174608.64 | I12: TOTAL | J12: =SUM(J6:J11) -> 1400375 | K12: Vacas/Aguinaldos/Extras | L12: =+C10 -> 0
A13: TIPO DE SEGURO | B13: INICIO DEL ACUERDO | D13: VIGENCIA DEL ACUERDO | F13: % DEL ACUERDO | I13: 6 MESES | J13: =+J12/6 -> 233395.83 | K13: Premio Jefe Herrería | L13: =+G10 -> 202500
A14: AP | B14: 46113 | D14: 9 MESES | F14: 16,8% (IPC) + 8,2% (Excepción) Básico + Hs Extra + Premio Herreria // 16,8% (IPC) Viático + Premio Incentivo + Antigüedad + Presentismo + 16,8% (IPC) + 18,2% (Excepción) | I14: AGUINALDOS | J14: =+J13/2 -> 116697.92 | K14: Hrs Extras | L14: =+G12 -> 174608.64
A15: IMPORTE TOTAL A COBRAR | G15: =+H5-E10 -> 1739290.8 | K15: Total | L15: =SUM(L7:L14) -> 2039290.8
A16: Convocatoria | B16: Dia | C16: Fecha | D16: Inicio de Actividades | F16: Fin de Actividades | H16: Hrs trabajadas | K16: Vales | L16: =+E10 -> 300000
A17: 9:00 a. m. | B17: MIERCOLES | C17: 46204 | D17: 8:51 a. m. | F17: 5:59 p. m. | H17: 9.13 | K17: A cobrar | L17: =+L15-L16 -> 1739290.8
A18: 9:00 a. m. | B18: JUEVES | C18: 46205 | D18: 8:55 a. m. | F18: 6:00 p. m. | H18: 9.08
A19: 9:00 a. m. | B19: VIERNES | C19: 46206 | D19: 8:59 a. m. | F19: 5:29 p. m. | H19: 8.5 | K19: PREMIO INCENTIVO
A20: 9:00 a. m. | B20: SÁBADO | C20: 46207 | D20: 9:13 a. m. | F20: 1:25 p. m. | H20: 4.2 | K20: 1 Cat | L20: =50310*16.8%+50310 -> 58762.08
A21: LIBRE | B21: DOMINGO | C21: 46208 | H21: 0 | K21: VIÁTICO
A22: 9:00 a. m. | B22: LUNES | C22: 46209 | D22: 8:52 a. m. | F22: 6:02 p. m. | H22: 9.17 | K22: 1 Cat | L22: =55900*16.8%+55900 -> 65291.2
A23: LIBRE | B23: MARTES | C23: 46210 | H23: 0 | K23: PREMIO PRESENTISMO
A24: 9:00 a. m. | B24: MIÉRCOLES | C24: 46211 | D24: 8:51 a. m. | F24: 6:00 p. m. | H24: 9.15 | K24: 1 Cat | L24: =105440*16.8%+105440 -> 123153.92
A25: 9:00 a. m. | B25: JUEVES | C25: 46212 | D25: 8:53 a. m. | F25: 6:01 p. m. | H25: 9.13 | K25: ANTIGÜEDAD
A26: 9:00 a. m. | B26: VIERNES | C26: 46213 | D26: 8:50 a. m. | F26: 6:07 p. m. | H26: 9.28 | K26: 1 Años | L26: =12500*16.8%+12500 -> 14600
A27: 9:00 a. m. | B27: SÁBADO | C27: 46214 | D27: 8:52 a. m. | F27: 1:20 p. m. | H27: 4.47 | K27: 2 Años | L27: =20000*16.8%+20000 -> 23360
A28: LIBRE | B28: DOMINGO | C28: 46215 | H28: 0 | K28: 3 Años | L28: =27500*16.8%+27500 -> 32120
A29: VACACIONES | B29: LUNES | C29: 46216 | H29: 8 | K29: 4 Años | L29: =35000*16.8%+35000 -> 40880
A30: VACACIONES | B30: MARTES | C30: 46217 | H30: 8 | K30: 5 Años | L30: =42500*16.8%+42500 -> 49640
A31: VACACIONES | B31: MIÉRCOLES | C31: 46218 | H31: 8 | K31: 6 Años | L31: =63750*16.8%+63750 -> 74460
A32: VACACIONES | B32: JUEVES | C32: 46219 | H32: 8 | K32: 7 Años | L32: =127500*16.8%+127500 -> 148920
A33: VACACIONES | B33: VIERNES | C33: 46220 | H33: 8 | K33: 8 Años | L33: =200000*16.8%+200000 -> 233600
A34: VACACIONES | B34: SÁBADO | C34: 46221 | H34: 8 | K34: PREMIO JEFE HERRERÍA
A35: VACACIONES | B35: DOMINGO | C35: 46222 | H35: 8 | K35: 1 Cat | L35: =150000*35%+150000 -> 202500
A36: VACACIONES | B36: LUNES | C36: 46223 | H36: 8
A37: VACACIONES | B37: MARTES | C37: 46224 | H37: 8
A38: VACACIONES | B38: MIÉRCOLES | C38: 46225 | H38: 8
A39: VACACIONES | B39: JUEVES | C39: 46226 | H39: 8
A40: VACACIONES | B40: VIERNES | C40: 46227 | H40: 8
A41: VACACIONES | B41: SÁBADO | C41: 46228 | H41: 8
A42: VACACIONES | B42: DOMINGO | C42: 46229 | H42: 8
A43: 8:00 a. m. | B43: LUNES | C43: 46230 | D43: 7:55 a. m. | F43: 6:33 p. m. | H43: 10.63
A44: 8:00 a. m. | B44: MARTES | C44: 46231 | D44: 7:53 a. m. | F44: 6:00 p. m. | H44: 10.12
A45: 8:00 a. m. | B45: MIÉRCOLES | C45: 46232 | D45: 7:55 a. m. | F45: 6:00 p. m. | H45: 10.08
A46: 9:00 a. m. | B46: JUEVES | C46: 46233 | D46: 8:56 a. m. | F46: 6:02 p. m. | H46: 9.1
A47: 9:00 a. m. | B47: VIERNES | C47: 46234 | D47: 8:58 a. m. | F47: 6:03 p. m. | H47: 9.08
F48: TOTALES | H48: =SUM(H17:H47) -> 233.12
A50: VALES | E50: DETALLE DE PRESTAMOS / DESCUENTOS / MULTAS
A51: FECHA | B51: DETALLE | D51: MONTO | E51: FECHA | F51: DETALLE | H51: IMPORTE
A52: 46227 | B52: ADELANTO | D52: 300000
A56: TOTAL | D56: =SUM(D52:D55) -> 300000 | E56: PENDIENTE DE PAGO | H56: =+H55 -> 0
E57: PENDIENTE A PAGAR PRESTAMOS | H57: 0
A58: HRS PENDIENTES
A59: MES | D59: HRS
A60: ACUMULADO 2024 | D60: -396.88
A61: ENERO | D61: 0
A62: FEBRERO | D62: 0
A63: MARZO | D63: 0
A64: ABRIL
A65: MAYO
A66: JUNIO
A67: JULIO
A68: AGOSTO
A69: SEPTIEMBRE
A70: OCTUBRE
A71: NOVIEMBRE
A72: DICIEMBRE
A73: TOTAL | D73: =SUM(D60:D72) -> -396.88

Sheet POLA
I2: AUMENTO
I3: FEBRERO/MARZO
A5: =+MAYRA!A5 -> SUELDO JULIO 2026 | F5: SUELDO | H5: =+A8+C8+E8+G8+B10+C10+G10+G12 -> 1674811.3 | I5: AGUINALDOS | K5: =+B6 -> DAMIAN SANTILLAN
A6: Nombre: | B6: DAMIAN SANTILLAN | D6: DNI: | E6: 36234439 | F6: Escalafon: | H6: 2 | I6: JULIO | J6: 1175919 | K6: =+MAYRA!L6 -> Mes: JULIO 2026
A7: SUELDO BASICO | C7: PREMIO INCENTIVO | E7: VIATICO | G7: PREMIO PRESENTISMO | I7: AGOSTO | K7: Sueldo Basico | L7: =+A8 -> 1175919
A8: =1004200.67*17.1%+1004200.67 -> 1175919 | C8: =+L20 -> 92555.606 | E8: =+L22 -> 51419.781 | G8: =+L24 -> 138169.66 | I8: SEPTIEMBRE | K8: Premio Incentivo | L8: =+C8 -> 92555.606
A9: ANTIGÜEDAD | B9: 5 | C9: VACACIONES/AGUINALDOS/EXTRAS | E9: VALES/DESCUENTOS/MULTAS | G9: PREMIO HERRERÍA | I9: OCTUBRE | K9: Viatico | L9: =+E8 -> 51419.781
A10: 44378 | B10: =+L30 -> 49767.5 | C10: 0 | E10: =+D54+H54 -> 200000 | G10: =+L35 -> 87825 | I10: NOVIEMBRE | K10: Premio Presentismo | L10: =+G8 -> 138169.66
A11: HRS ACORDADAS | B11: HRS TRABAJADAS | C11: HRS EXTRAS TRABAJADAS | E11: VALOR HRS EXTRAS | G11: IMPORTE HRS EXTRAS TRABAJADAS | I11: DICIEMBRE | K11: Antigüedad | L11: =+B10 -> 49767.5
A12: 200 | B12: =+H48 -> 218.33 | C12: =+B12-A12 -> 18.33 | E12: =3687.72*17.1%+3687.72 -> 4318.3201 | G12: =+C12*E12 -> 79154.808 | I12: TOTAL | J12: =SUM(J6:J11) -> 1175919 | K12: Vacas/Aguinaldos/Extras | L12: =+C10 -> 0
A13: TIPO DE SEGURO | B13: INICIO DEL ACUERDO | D13: VIGENCIA DEL ACUERDO | F13: % DEL ACUERDO | I13: 6 MESES | J13: =+J12/6 -> 195986.5 | K13: Premio Herrería | L13: =+G10 -> 87825
A14: ART | B14: 46143 | D14: 9 MESES | F14: 17,1% Básico + Premio Incentivo + Viatico + Presentismo + Hs Extra + Antigüedad + Premio Herrería | I14: AGUINALDOS | J14: =+J13/2 -> 97993.248 | K14: Hrs Extras | L14: =+G12 -> 79154.808
A15: IMPORTE TOTAL A COBRAR | G15: =+H5-E10 -> 1474811.3 | K15: Total | L15: =SUM(L7:L14) -> 1674811.3
A16: Convocatoria | B16: Dia | C16: Fecha | D16: Inicio de Actividades | F16: Fin de Actividades | H16: Hrs trabajadas | K16: Vales | L16: =+E10 -> 200000
A17: 9:00 a. m. | B17: MIERCOLES | C17: 46204 | D17: 9:16 a. m. | F17: 6:00 p. m. | H17: 8.73 | K17: A cobrar | L17: =+L15-L16 -> 1474811.3
A18: 9:00 a. m. | B18: JUEVES | C18: 46205 | D18: 9:06 a. m. | F18: 6:07 p. m. | H18: 9.02
A19: 9:00 a. m. | B19: VIERNES | C19: 46206 | D19: 9:14 a. m. | F19: 5:29 p. m. | H19: 8.25 | K19: PREMIO INCENTIVO
A20: 9:00 a. m. | B20: SÁBADO | C20: 46207 | D20: 9:22 a. m. | F20: 2:36 p. m. | H20: 5.23 | K20: 1 Cat | L20: =79039.8*17.1%+79039.8 -> 92555.606
A21: LIBRE | B21: DOMINGO | C21: 46208 | H21: 0 | K21: VIÁTICO
A22: 9:00 a. m. | B22: LUNES | C22: 46209 | D22: 8:55 a. m. | F22: 6:03 p. m. | H22: 9.13 | K22: 1 Cat | L22: =43911*17.1%+43911 -> 51419.781
A23: LIBRE | B23: MARTES | C23: 46210 | H23: 0 | K23: PREMIO PRESENTISMO
A24: 9:00 a. m. | B24: MIÉRCOLES | C24: 46211 | D24: 9:12 a. m. | F24: 6:07 p. m. | H24: 8.92 | K24: 1 Cat | L24: =117992.88*17.1%+117992.88 -> 138169.66
A25: 9:00 a. m. | B25: JUEVES | C25: 46212 | D25: 9:09 a. m. | F25: 6:06 p. m. | H25: 8.95 | K25: ANTIGÜEDAD
A26: 9:00 a. m. | B26: VIERNES | C26: 46213 | D26: 8:53 a. m. | F26: 6:12 p. m. | H26: 9.32 | K26: 1 Años | L26: =12500*17.1%+12500 -> 14637.5
A27: 9:00 a. m. | B27: SÁBADO | C27: 46214 | D27: 9:00 a. m. | F27: 1:47 p. m. | H27: 4.78 | K27: 2 Años | L27: =20000*17.1%+20000 -> 23420
A28: LIBRE | B28: DOMINGO | C28: 46215 | H28: 0 | K28: 3 Años | L28: =27500*17.1%+27500 -> 32202.5
A29: 9:00 a. m. | B29: LUNES | C29: 46216 | D29: 9:02 a. m. | F29: 6:05 p. m. | H29: 9.05 | K29: 4 Años | L29: =35000*17.1%+35000 -> 40985
A30: 9:00 a. m. | B30: MARTES | C30: 46217 | D30: 9:04 a. m. | F30: 6:01 p. m. | H30: 8.95 | K30: 5 Años | L30: =42500*17.1%+42500 -> 49767.5
A31: LIBRE | B31: MIÉRCOLES | C31: 46218 | H31: 0 | K31: 6 Años | L31: =63750*17.1%+63750 -> 74651.25
A32: 9:00 a. m. | B32: JUEVES | C32: 46219 | D32: 9:15 a. m. | F32: 6:02 p. m. | H32: 8.78 | K32: 7 Años | L32: =127500*17.1%+127500 -> 149302.5
A33: 9:00 a. m. | B33: VIERNES | C33: 46220 | D33: 9:04 a. m. | F33: 6:10 p. m. | H33: 9.1 | K33: 8 Años | L33: =200000*17.1%+200000 -> 234200
A34: LIBRE | B34: SÁBADO | C34: 46221 | H34: 0 | K34: PREMIO HERRERÍA
A35: LIBRE | B35: DOMINGO | C35: 46222 | H35: 0 | K35: 1 Cat | L35: =75000*17.1%+75000 -> 87825
A36: 9:00 a. m. | B36: LUNES | C36: 46223 | D36: 9:06 a. m. | F36: 6:30 p. m. | H36: 9.4
A37: 8:00 a. m. | B37: MARTES | C37: 46224 | D37: 8:16 a. m. | F37: 6:54 p. m. | H37: 10.63
A38: 8:00 a. m. | B38: MIÉRCOLES | C38: 46225 | D38: 7:51 a. m. | F38: 6:48 p. m. | H38: 10.95
A39: 8:00 a. m. | B39: JUEVES | C39: 46226 | D39: 8:06 a. m. | F39: 6:07 p. m. | H39: 10.02
A40: 8:00 a. m. | B40: VIERNES | C40: 46227 | D40: 8:06 a. m. | F40: 6:06 p. m. | H40: 10
A41: 7:30 a. m. | B41: SÁBADO | C41: 46228 | D41: 7:35 a. m. | F41: 6:20 p. m. | H41: 10.75
A42: LIBRE | B42: DOMINGO | C42: 46229 | H42: 0
A43: 8:00 a. m. | B43: LUNES | C43: 46230 | D43: 8:01 a. m. | F43: 6:03 p. m. | H43: 10.03
A44: 8:00 a. m. | B44: MARTES | C44: 46231 | D44: 8:07 a. m. | F44: 6:00 p. m. | H44: 9.88
A45: 8:00 a. m. | B45: MIÉRCOLES | C45: 46232 | D45: 8:04 a. m. | F45: 6:04 p. m. | H45: 10
A46: 9:00 a. m. | B46: JUEVES | C46: 46233 | D46: 8:49 a. m. | F46: 6:03 p. m. | H46: 9.23
A47: 9:00 a. m. | B47: VIERNES | C47: 46234 | D47: 9:03 a. m. | F47: 6:17 p. m. | H47: 9.23
F48: TOTALES | H48: =SUM(H17:H47) -> 218.33
A50: VALES | E50: DETALLE DE PRESTAMOS / DESCUENTOS / MULTAS
A51: FECHA | B51: DETALLE | D51: MONTO | E51: FECHA | F51: DETALLE | H51: IMPORTE
A52: 46227 | B52: ADELANTO | D52: 200000
A54: TOTAL | D54: =SUM(D52:D53) -> 200000 | E54: PENDIENTE DE PAGO | H54: =+H53 -> 0
E55: PENDIENTE A PAGAR PRESTAMOS | H55: 0
A56: HRS PENDIENTES
A57: MES | D57: HRS
A58: ACUMULADO 2024 | D58: -396.88
A59: ENERO | D59: 0
A60: FEBRERO | D60: 0
A61: MARZO | D61: 0
A62: ABRIL
A63: MAYO
A64: JUNIO
A65: JULIO
A66: AGOSTO
A67: SEPTIEMBRE
A68: OCTUBRE
A69: NOVIEMBRE
A70: DICIEMBRE
A71: TOTAL | D71: =SUM(D58:D70) -> -396.88

Sheet LUIS
I2: AUMENTO
I3: ABRIL/MAYO
A5: =+MAYRA!A5 -> SUELDO JULIO 2026 | F5: SUELDO | H5: =+A8+C8+H8+A10+C12+E12+G12 -> 2259750 | I5: AGUINALDOS | K5: =+B6 -> LUIS LEDESMA
A6: Nombre: | B6: LUIS LEDESMA | D6: DNI: | F6: Escalafon: | H6: 2 | I6: JULIO | K6: =+MAYRA!L6 -> Mes: JULIO 2026
A7: SUELDO BASICO | C7: PREMIO PRESENTISMO | E7: ANTIGÜEDAD | H7: 0 | I7: AGOSTO | K7: Sueldo Basico | L7: =+A8 -> 1610000
A8: 1610000 | C8: 115000 | E8: 46023 | H8: 0 | I8: SEPTIEMBRE | K8: Premio Presentismo | L8: =+C8 -> 115000
A9: VACACIONES/AGUINALDOS/EXTRAS | D9: VALES/DESCUENTOS/MULTAS | G9: TIPO DE SEGURO | I9: OCTUBRE | K9: Antigüedad | L9: =+H8 -> 0
A10: =+J14 -> 0 | D10: =+D55+H55 -> 565300 | G10: AP | I10: NOVIEMBRE | K10: Vacas/Aguinaldos/Extras | L10: =+A10 -> 0
A11: PREMIOS VIAJES | C11: PROVINCIAL | D11: =+'VIAJES LUIS'!H36 -> 2 | E11: NACIONAL | F11: =+'VIAJES LUIS'!I36 -> 5 | G11: NACIONAL + 1.000 | H11: =+'VIAJES LUIS'!J36 -> 0 | I11: DICIEMBRE | K11: Premios Viajes | L11: =+C12+E12+G12 -> 534750
C12: =+L28*D11 -> 103500 | E12: =+L29*F11 -> 431250 | G12: =+L30*H11 -> 0 | I12: TOTAL | J12: =SUM(J6:J11) -> 0 | K12: Total | L12: =SUM(L7:L11) -> 2259750
A13: INICIO DEL ACUERDO | C13: VIGENCIA DEL ACUERDO | E13: % DEL ACUERDO | I13: 6 MESES | J13: =+J12/6 -> 0 | K13: Vales | L13: =+D10 -> 565300
A14: 46204 | C14: 9 MESES | E14: 10% - 15% Basico | I14: AGUINALDOS | J14: =+J13/2 -> 0 | K14: A cobrar | L14: =+L12-L13 -> 1694450
A15: IMPORTE TOTAL A COBRAR | G15: =+H5-D10 -> 1694450
A16: Convocatoria | B16: Dia | C16: Fecha | D16: Inicio de Actividades | F16: Fin de Actividades | H16: Hrs trabajadas | K16: PREMIO PRESENTISMO
A17: VACACIONES | B17: MIERCOLES | C17: 46204 | H17: 8 | K17: 1 Cat | L17: 100000
A18: VACACIONES | B18: JUEVES | C18: 46205 | H18: 8 | K18: ANTIGÜEDAD
A19: VACACIONES | B19: VIERNES | C19: 46206 | H19: 8 | K19: 1 Años | L19: 12500
A20: VACACIONES | B20: SÁBADO | C20: 46207 | H20: 8 | K20: 2 Años | L20: 20000
A21: VACACIONES | B21: DOMINGO | C21: 46208 | H21: 8 | K21: 3 Años | L21: 27500
A22: 9:00 a. m. | B22: LUNES | C22: 46209 | D22: 8:55 a. m. | F22: 6:02 p. m. | H22: 9.12 | K22: 4 Años | L22: 35000
A23: LIBRE | B23: MARTES | C23: 46210 | H23: 0 | K23: 5 Años | L23: 42500
A24: 9:00 a. m. | B24: MIÉRCOLES | C24: 46211 | D24: 8:51 a. m. | F24: 6:01 p. m. | H24: 9.17 | K24: 6 Años | L24: 63750
A25: 9:00 a. m. | B25: JUEVES | C25: 46212 | D25: 8:47 a. m. | F25: 6:00 p. m. | H25: 9.22 | K25: 7 Años | L25: 127500
A26: 2:00 p. m. | B26: VIERNES | C26: 46213 | D26: 1:41 p. m. | F26: 9:20 p. m. | H26: 7.65 | K26: 8 Años | L26: 200000
A27: LIBRE | B27: SÁBADO | C27: 46214 | H27: 0 | K27: PREMIOS VIAJES
A28: LIBRE | B28: DOMINGO | C28: 46215 | H28: 0 | K28: PROVINCIAL | L28: 51750
A29: 9:00 a. m. | B29: LUNES | C29: 46216 | D29: 8:46 a. m. | F29: 6:00 p. m. | H29: 9.23 | K29: NACIONAL | L29: 86250
A30: 9:00 a. m. | B30: MARTES | C30: 46217 | D30: 8:51 a. m. | F30: 9:06 p. m. | H30: 12.25 | I30: CABALEN/RIO CUARTO | K30: NACIONAL + 1.000 | L30: 115000
A31: LIBRE | B31: MIÉRCOLES | C31: 46218 | H31: 0
A32: 9:00 a. m. | B32: JUEVES | C32: 46219 | D32: 8:43 a. m. | F32: 6:23 p. m. | H32: 9.67
A33: 9:00 a. m. | B33: VIERNES | C33: 46220 | D33: 8:53 a. m. | F33: 12:46 a. m. | H33: 15.88 | I33: VIAJE SGO ESTERO
A34: 9:00 a. m. | B34: SÁBADO | C34: 46221 | D34: 8:00 a. m. | F34: 9:34 p. m. | H34: 13.57 | I34: REGRESO CBA
A35: 9:00 a. m. | B35: DOMINGO | C35: 46222 | D35: 7:34 p. m. | F35: 3:30 a. m. | H35: 7.93 | I35: VIAJE SGO ESTERO
A36: 9:00 a. m. | B36: LUNES | C36: 46223 | D36: 7:30 a. m. | F36: 6:01 p. m. | H36: 10.52 | I36: REGRESO CBA
A37: 8:00 a. m. | B37: MARTES | C37: 46224 | D37: 7:50 a. m. | F37: 6:59 p. m. | H37: 11.15 | I37: Rescoldo
A38: 8:00 a. m. | B38: MIÉRCOLES | C38: 46225 | D38: 7:51 a. m. | F38: 10:00 p. m. | H38: 14.15 | I38: Viaje Sgo Estero
A39: SGO DEL ESTERO | B39: JUEVES | C39: 46226 | D39: 7:30 a. m. | F39: 3:20 p. m. | H39: 7.83 | I39: Regreso Cba Colectivo
A40: 8:00 a. m. | B40: VIERNES | C40: 46227 | D40: 7:56 a. m. | F40: 7:21 p. m. | H40: 11.42
A41: 7:30 a. m. | B41: SÁBADO | C41: 46228 | D41: 7:18 a. m. | F41: 6:24 p. m. | H41: 11.1
A42: 6:00 a. m. | B42: DOMINGO | C42: 46229 | D42: 12:30 p. m. | F42: 1:15 a. m. | H42: 12.75 | I42: Viaje MB con Tati/Regreso Cba Perla
A43: 8:00 a. m. | B43: LUNES | C43: 46230 | D43: 7:14 a. m. | F43: 1:34 a. m. | H43: 18.33 | I43: Viaje Sgo/Regreso Cba
A44: 7:30 a. m. | B44: MARTES | C44: 46231 | D44: 7:52 a. m. | F44: 12:40 a. m. | H44: 16.8 | I44: Viaje Sgo/Regreso Cba
A45: LIBRE | B45: MIÉRCOLES | C45: 46232 | H45: 0
A46: CARPETA | B46: JUEVES | C46: 46233 | H46: 8
A47: CARPETA | B47: VIERNES | C47: 46234 | H47: 8
F48: TOTALES | H48: =SUM(H17:H47) -> 273.74
A50: VALES | E50: DETALLE DE PRESTAMOS / DESCUENTOS / MULTAS
A51: FECHA | B51: DETALLE | D51: MONTO | E51: FECHA | F51: DETALLE | H51: IMPORTE
A52: 46227 | B52: ADELANTO | D52: 500000
A53: 46238 | B53: DIF. DE CAJA STGO DEL ESTERO | D53: 65300
A55: TOTAL | D55: =SUM(D52:D54) -> 565300 | E55: PENDIENTE DE PAGO | H55: =+H54 -> 0
E56: PENDIENTE A PAGAR PRESTAMOS | H56: 0
A57: HRS PENDIENTES
A58: MES | D58: HRS
A59: ACUMULADO 2024 | D59: -396.88
A60: ENERO | D60: 0
A61: FEBRERO | D61: 0
A62: MARZO | D62: 0
A63: ABRIL
A64: MAYO
A65: JUNIO
A66: JULIO
A67: AGOSTO
A68: SEPTIEMBRE
A69: OCTUBRE
A70: NOVIEMBRE
A71: DICIEMBRE
A72: TOTAL | D72: =SUM(D59:D71) -> -396.88

Sheet GERARDO
I2: AUMENTO
I3: FEBRERO/MARZO
A5: =+MAYRA!A5 -> SUELDO JULIO 2026 | F5: SUELDO | H5: =A8+C8+E8+G8+B10+C10+G12 -> 1570226.6 | I5: AGUINALDOS | K5: =+B6 -> GERARDO MACHADO
A6: Nombre: | B6: GERARDO MACHADO | D6: DNI: | E6: 42473547 | F6: Escalafon: | H6: 3 | I6: JULIO | J6: 1194489.2 | K6: =+MAYRA!L6 -> Mes: JULIO 2026
A7: SUELDO BASICO | C7: PREMIO INCENTIVO | E7: VIATICO | G7: PREMIO PRESENTISMO | I7: AGOSTO | K7: Sueldo Basico | L7: =+A8 -> 1194489.2
A8: =1020059.12*17.1%+1020059.12 -> 1194489.2 | C8: =+L19 -> 62003.572 | E8: =+L21 -> 66963.857 | G8: =+L23 -> 127638.44 | I8: SEPTIEMBRE | K8: Premio Incentivo | L8: =+C8 -> 62003.572
A9: ANTIGÜEDAD | B9: 3 | C9: VACACIONES/AGUINALDOS/EXTRAS | E9: VALES/DESCUENTOS/MULTAS | G9: TIPO DE SEGURO | I9: OCTUBRE | K9: Viatico | L9: =+E8 -> 66963.857
A10: 44835 | B10: =+L27 -> 32202.5 | C10: 0 | E10: =+D54+H54 -> 400000 | G10: ART | I10: NOVIEMBRE | K10: Premio Presentismo | L10: =+G8 -> 127638.44
A11: HRS ACORDADAS | B11: HRS TRABAJADAS | C11: HRS EXTRAS TRABAJADAS | E11: VALOR HRS EXTRAS | G11: IMPORTE HRS EXTRAS TRABAJADAS | I11: DICIEMBRE | K11: Antigüedad | L11: =+B10 -> 32202.5
A12: 220 | B12: =+H48 -> 241.07 | C12: =+B12-A12 -> 21.07 | E12: =3523.25*17.1%+3523.25 -> 4125.7257 | G12: =+C12*E12 -> 86929.042 | I12: TOTAL | J12: =SUM(J6:J11) -> 1194489.2 | K12: Vacas/Aguinaldos/Extras | L12: =+C10 -> 0
A13: INICIO DEL ACUERDO | C13: VIGENCIA DEL ACUERDO | E13: % DEL ACUERDO | I13: 6 MESES | J13: =+J12/6 -> 199081.54 | K13: Hrs Extras | L13: =+G12 -> 86929.042
A14: 46143 | C14: 9 MESES | E14: 17,1% Básico + Premio Incentivo + Viatico + Presentismo + Hs Extra + Antigüedad | I14: AGUINALDOS | J14: =+J13/2 -> 99540.769 | K14: Total | L14: =SUM(L7:L13) -> 1570226.6
A15: IMPORTE TOTAL A COBRAR | G15: =+H5-E10 -> 1170226.6 | K15: Vales | L15: =+E10 -> 400000
A16: Convocatoria | B16: Dia | C16: Fecha | D16: Inicio de Actividades | F16: Fin de Actividades | H16: Hrs trabajadas | K16: A cobrar | L16: =+L14-L15 -> 1170226.6
A17: 9:00 a. m. | B17: MIERCOLES | C17: 46204 | D17: 8:55 a. m. | F17: 5:59 p. m. | H17: 9.07
A18: 9:00 a. m. | B18: JUEVES | C18: 46205 | D18: 9:00 a. m. | F18: 6:01 p. m. | H18: 9.02 | K18: PREMIO INCENTIVO
A19: 9:00 a. m. | B19: VIERNES | C19: 46206 | D19: 8:56 a. m. | F19: 5:29 p. m. | H19: 8.55 | K19: 1 Cat | L19: =52949.25*17.1%+52949.25 -> 62003.572
A20: 9:00 a. m. | B20: SÁBADO | C20: 46207 | D20: 8:58 a. m. | F20: 3:26 p. m. | H20: 6.47 | K20: VIÁTICO
A21: LIBRE | B21: DOMINGO | C21: 46208 | H21: 0 | K21: 1 Cat | L21: =57185.19*17.1%+57185.19 -> 66963.857
A22: 9:00 a. m. | B22: LUNES | C22: 46209 | D22: 8:51 a. m. | F22: 6:03 p. m. | H22: 9.2 | K22: PREMIO PRESENTISMO
A23: LIBRE | B23: MARTES | C23: 46210 | H23: 0 | K23: 1 Cat | L23: =108999.52*17.1%+108999.52 -> 127638.44
A24: 9:00 a. m. | B24: MIÉRCOLES | C24: 46211 | D24: 9:01 a. m. | F24: 6:00 p. m. | H24: 8.98 | K24: ANTIGÜEDAD
A25: 9:00 a. m. | B25: JUEVES | C25: 46212 | D25: 8:55 a. m. | F25: 6:00 p. m. | H25: 9.08 | K25: 1 Años | L25: =12500*17.1%+12500 -> 14637.5
A26: 9:00 a. m. | B26: VIERNES | C26: 46213 | D26: 9:01 a. m. | F26: 6:06 p. m. | H26: 9.08 | K26: 2 Años | L26: =20000*17.1%+20000 -> 23420
A27: 9:00 a. m. | B27: SÁBADO | C27: 46214 | D27: 8:57 a. m. | F27: 3:08 p. m. | H27: 6.18 | K27: 3 Años | L27: =27500*17.1%+27500 -> 32202.5
A28: LIBRE | B28: DOMINGO | C28: 46215 | H28: 0 | K28: 4 Años | L28: =35000*17.1%+35000 -> 40985
A29: 9:00 a. m. | B29: LUNES | C29: 46216 | D29: 8:55 a. m. | F29: 6:01 p. m. | H29: 9.1 | K29: 5 Años | L29: =42500*17.1%+42500 -> 49767.5
A30: 9:00 a. m. | B30: MARTES | C30: 46217 | D30: 9:01 a. m. | F30: 6:01 p. m. | H30: 9 | K30: 6 Años | L30: =63750*17.1%+63750 -> 74651.25
A31: LIBRE | B31: MIÉRCOLES | C31: 46218 | H31: 0 | K31: 7 Años | L31: =127500*17.1%+127500 -> 149302.5
A32: 12:30 a. m. | B32: JUEVES | C32: 46219 | D32: 11:30 a. m. | F32: 9:00 p. m. | H32: 9.5 | I32: VIAJE BS AS | K32: 8 Años | L32: =200000*17.1%+200000 -> 234200
A33: x | B33: VIERNES | C33: 46220 | D33: 7:00 a. m. | F33: 7:50 p. m. | H33: 12.83 | I33: REGRESO CBA
A34: 7:30 a. m. | B34: SÁBADO | C34: 46221 | D34: 7:28 a. m. | F34: 3:15 p. m. | H34: 7.78 | I34: VIAJE SGO ESTERO/REGRESO CAMION
A35: LIBRE | B35: DOMINGO | C35: 46222 | H35: 0
A36: 9:00 a. m. | B36: LUNES | C36: 46223 | D36: 8:58 a. m. | F36: 6:46 p. m. | H36: 9.8
A37: 10:00 a. m. | B37: MARTES | C37: 46224 | D37: 9:29 a. m. | F37: 6:03 p. m. | H37: 8.57
A38: 8:00 a. m. | B38: MIÉRCOLES | C38: 46225 | D38: 8:01 a. m. | F38: 6:05 p. m. | H38: 10.07
A39: 8:00 a. m. | B39: JUEVES | C39: 46226 | D39: 8:01 a. m. | F39: 7:05 p. m. | H39: 11.07
A40: 9:00 a. m. | B40: VIERNES | C40: 46227 | D40: 8:58 a. m. | F40: 9:51 p. m. | H40: 12.88
A41: 7:30 a. m. | B41: SÁBADO | C41: 46228 | D41: 7:28 a. m. | F41: 7:33 p. m. | H41: 12.08
A42: 8:00 a. m. | B42: DOMINGO | C42: 46229 | D42: 7:59 a. m. | F42: 7:36 p. m. | H42: 11.62
A43: 8:00 a. m. | B43: LUNES | C43: 46230 | D43: 8:01 a. m. | F43: 7:08 p. m. | H43: 11.12
A44: 6:30 a. m. | B44: MARTES | C44: 46231 | D44: 1:00 p. m. | F44: 9:32 p. m. | H44: 8.53 | I44: Viaje Sgo Colectivo/Regreso Cba Sprinter
A45: 8:00 a. m. | B45: MIÉRCOLES | C45: 46232 | D45: 8:03 a. m. | F45: 7:46 p. m. | H45: 11.72
A46: FRANCO | B46: JUEVES | C46: 46233 | H46: 0
A47: 9:00 a. m. | B47: VIERNES | C47: 46234 | D47: 9:02 a. m. | F47: 6:48 p. m. | H47: 9.77
F48: TOTALES | H48: =SUM(H17:H47) -> 241.07
A50: VALES | E50: DETALLE DE PRESTAMOS / DESCUENTOS / MULTAS
A51: FECHA | B51: DETALLE | D51: MONTO | E51: FECHA | F51: DETALLE | H51: IMPORTE
A52: 46227 | B52: ADELANTO | D52: 400000
A54: TOTAL | D54: =SUM(D52:D53) -> 400000 | E54: PENDIENTE DE PAGO | H54: =SUM(H52:H53) -> 0
E55: PENDIENTE A PAGAR PRESTAMOS | H55: 0
A56: HRS PENDIENTES
A57: MES | D57: HRS
A58: ACUMULADO 2024 | D58: -396.88
A59: ENERO | D59: 0
A60: FEBRERO | D60: 0
A61: MARZO | D61: 0
A62: ABRIL
A63: MAYO
A64: JUNIO
A65: JULIO
A66: AGOSTO
A67: SEPTIEMBRE
A68: OCTUBRE
A69: NOVIEMBRE
A70: DICIEMBRE
A71: TOTAL | D71: =SUM(D58:D70) -> -396.88

Sheet LEANDRO
I2: AUMENTO
I3: FEBRERO/MARZO
A5: =+MAYRA!A5 -> SUELDO JULIO 2026 | F5: SUELDO | H5: =A8+C8+E8+F8+B10+C10+G12 -> 1297083.4 | I5: AGUINALDOS | K5: =+B6 -> LEANDRO NAVARRO
A6: Nombre: | B6: LEANDRO NAVARRO | D6: DNI: | F6: Escalafon: | H6: 3 | I6: JULIO | J6: 1094570.9 | K6: =+MAYRA!L6 -> Mes: JULIO 2026
A7: SUELDO BASICO | C7: PREMIO INCENTIVO | F7: PREMIO PRESENTISMO | I7: AGOSTO | K7: Sueldo Basico | L7: =+A8 -> 1094570.9
A8: =934731.77*17.1%+934731.77 -> 1094570.9 | C8: =+L18 -> 46188.479 | F8: =+L20 -> 132904.04 | I8: SEPTIEMBRE | K8: Premio Incentivo | L8: =+C8 -> 46188.479
A9: ANTIGÜEDAD | B9: 2 | C9: VACACIONES/AGUINALDOS/EXTRAS | E9: VALES/DESCUENTOS/MULTAS | G9: TIPO DE SEGURO | I9: OCTUBRE | K9: Premio Presentismo | L9: =+F8 -> 132904.04
A10: 45292 | B10: =+L23 -> 23420 | C10: 0 | E10: =+D56+H60 -> 1110000 | G10: AP | I10: NOVIEMBRE | K10: Antigüedad | L10: =+B10 -> 23420
A11: HRS ACORDADAS | B11: HRS TRABAJADAS | C11: HRS EXTRAS TRABAJADAS | E11: VALOR HRS EXTRAS | G11: IMPORTE HRS EXTRAS TRABAJADAS | I11: DICIEMBRE | K11: Vacas/Aguinaldos/Extras | L11: =+C10 -> 0
A12: 240 | B12: =+H49 -> 213.15 | C12: =+B12-A12 -> -26.85 | E12: =2963.3*17.1%+2963.3 -> 3470.0243 | G12: 0 | I12: TOTAL | J12: =SUM(J6:J11) -> 1094570.9 | K12: Hrs Extras | L12: =+G12 -> 0
A13: INICIO DEL ACUERDO | C13: VIGENCIA DEL ACUERDO | E13: % DEL ACUERDO | I13: 6 MESES | J13: =+J12/6 -> 182428.48 | K13: Total | L13: =SUM(L7:L12) -> 1297083.4
A14: 46143 | C14: 9 MESES | E14: 17,1% Básico + Premio Incentivo + Viatico + Presentismo + Hs Extra + Antigüedad | I14: AGUINALDOS | J14: =+J13/2 -> 91214.242 | K14: Vales | L14: =+E10 -> 1110000
A15: IMPORTE TOTAL A COBRAR | G15: =+H5-E10 -> 187083.42 | K15: A cobrar | L15: =+L13-L14 -> 187083.42
A16: Convocatoria | B16: Dia | C16: Fecha | D16: Inicio de Actividades | F16: Fin de Actividades | H16: Hrs trabajadas
A17: 9:00 a. m. | B17: MIERCOLES | C17: 46204 | D17: 8:49 a. m. | F17: 6:01 p. m. | H17: 9.2 | K17: PREMIO INCENTIVO
A18: 9:00 a. m. | B18: JUEVES | C18: 46205 | D18: 8:42 a. m. | F18: 6:00 p. m. | H18: 9.3 | K18: 1 Cat | L18: =39443.62*17.1%+39443.62 -> 46188.479
A19: 9:00 a. m. | B19: VIERNES | C19: 46206 | D19: 8:53 a. m. | F19: 5:50 p. m. | H19: 8.95 | K19: PREMIO PRESENTISMO
A20: 9:00 a. m. | B20: SÁBADO | C20: 46207 | D20: 8:53 a. m. | F20: 8:23 p. m. | H20: 11.5 | K20: 1 Cat | L20: =113496.19*17.1%+113496.19 -> 132904.04
A21: LIBRE | B21: DOMINGO | C21: 46208 | H21: 0 | K21: ANTIGÜEDAD
A22: 9:00 a. m. | B22: LUNES | C22: 46209 | D22: 7:31 a. m. | F22: 7:09 p. m. | H22: 11.63 | K22: 1 Años | L22: =12500*17.1%+12500 -> 14637.5
A23: LIBRE | B23: MARTES | C23: 46210 | H23: 0 | K23: 2 Años | L23: =20000*17.1%+20000 -> 23420
A24: 9:00 a. m. | B24: MIÉRCOLES | C24: 46211 | D24: 8:41 a. m. | F24: 6:02 p. m. | H24: 9.35 | K24: 3 Años | L24: =27500*17.1%+27500 -> 32202.5
A25: 9:00 a. m. | B25: JUEVES | C25: 46212 | D25: 8:37 a. m. | F25: 6:00 p. m. | H25: 9.38 | K25: 4 Años | L25: =35000*17.1%+35000 -> 40985
A26: 9:00 a. m. | B26: VIERNES | C26: 46213 | D26: 8:47 a. m. | F26: 6:30 p. m. | H26: 9.72 | K26: 5 Años | L26: =42500*17.1%+42500 -> 49767.5
A27: 9:00 a. m. | B27: SÁBADO | C27: 46214 | D27: 9:02 a. m. | F27: 7:16 p. m. | H27: 10.23 | K27: 6 Años | L27: =63750*17.1%+63750 -> 74651.25
A28: 7:30 a. m. | B28: DOMINGO | C28: 46215 | D28: 7:01 a. m. | F28: 9:50 a. m. | H28: 2.82 | K28: 7 Años | L28: =127500*17.1%+127500 -> 149302.5
B29: DOMINGO | C29: 46215 | D29: 2:00 p. m. | F29: 9:25 p. m. | H29: 7.42 | K29: 8 Años | L29: =200000*17.1%+200000 -> 234200
A30: 9:00 a. m. | B30: LUNES | C30: 46216 | D30: 8:57 a. m. | F30: 6:22 p. m. | H30: 9.42
A31: 9:00 a. m. | B31: MARTES | C31: 46217 | D31: 8:54 a. m. | F31: 6:01 p. m. | H31: 9.12
A32: LIBRE | B32: MIÉRCOLES | C32: 46218 | H32: 0
A33: 9:00 a. m. | B33: JUEVES | C33: 46219 | D33: 8:25 a. m. | F33: 12:20 a. m. | H33: 15.92 | I33: VIAJE MINA CLAVERO
A34: 9:00 a. m. | B34: VIERNES | C34: 46220 | D34: 8:59 a. m. | F34: 6:00 p. m. | H34: 9.02
A35: 9:00 a. m. | B35: SÁBADO | C35: 46221 | D35: 8:39 a. m. | F35: 5:52 p. m. | H35: 9.22
A36: 9:00 a. m. | B36: DOMINGO | C36: 46222 | D36: 9:12 a. m. | F36: 2:09 p. m. | H36: 4.95
A37: VACACIONES | B37: LUNES | C37: 46223 | H37: 8
A38: VACACIONES | B38: MARTES | C38: 46224 | H38: 8
A39: VACACIONES | B39: MIÉRCOLES | C39: 46225 | H39: 8
A40: VACACIONES | B40: JUEVES | C40: 46226 | H40: 8
A41: VACACIONES | B41: VIERNES | C41: 46227 | H41: 8
A42: VACACIONES | B42: SÁBADO | C42: 46228 | H42: 8
A43: VACACIONES | B43: DOMINGO | C43: 46229 | H43: 8
A44: FRANCO | B44: LUNES | C44: 46230 | H44: 0
A45: FRANCO | B45: MARTES | C45: 46231 | H45: 0
A46: FRANCO | B46: MIÉRCOLES | C46: 46232 | H46: 0
A47: FRANCO | B47: JUEVES | C47: 46233 | H47: 0
A48: FRANCO | B48: VIERNES | C48: 46234 | H48: 0
F49: TOTALES | H49: =SUM(H17:H48) -> 213.15
A51: VALES | E51: DETALLE DE PRESTAMOS / DESCUENTOS / MULTAS
A52: FECHA | B52: DETALLE | D52: MONTO | E52: FECHA | F52: DETALLE | H52: IMPORTE
A53: 46227 | B53: ADELANTO | D53: 300000 | E53: 46203 | F53: MULTA DORMI | H53: 50000
E54: 46212 | F54: MECÁNICO | H54: 870000
E55: 46204 | F55: CUOTA 1 - MECANICO | H55: 435000
A56: TOTAL | D56: =SUM(D53:D55) -> 300000 | E56: 46235 | F56: CUOTA 2 - MECANICO | H56: 435000
E57: 46212 | F57: TORRE DE ILUMINACIÓN | H57: 750000
A58: HRS PENDIENTES | E58: 46204 | F58: CUOTA 1 - TORRE ILUMINACION | H58: 375000
A59: MES | D59: HRS | E59: 46235 | F59: CUOTA 2 - TORRE ILUMINACION | H59: 375000
A60: ACUMULADO 2024 | D60: -396.88 | E60: PENDIENTE DE PAGO | H60: =+H56+H59 -> 810000
A61: ENERO | D61: 0 | E61: PENDIENTE A PAGAR PRESTAMOS | H61: 0
A62: FEBRERO | D62: 0
A63: MARZO | D63: 0
A64: ABRIL
A65: MAYO
A66: JUNIO
A67: JULIO
A68: AGOSTO
A69: SEPTIEMBRE
A70: OCTUBRE
A71: NOVIEMBRE
A72: DICIEMBRE
A73: TOTAL | D73: =SUM(D60:D72) -> -396.88

Sheet PABLO
I2: AUMENTO
I3: FEBRERO/MARZO
A5: =+MAYRA!A5 -> SUELDO JULIO 2026 | F5: SUELDO | H5: =A8+C8+E8+G8+B10+C10+G12 -> 1424860 | I5: AGUINALDOS | K5: =+B6 -> PABLO VESSONI
A6: Nombre: | B6: PABLO VESSONI | D6: DNI: | F6: Escalafon: | H6: 3 | I6: JULIO | J6: 1100000 | K6: =+MAYRA!L6 -> Mes: JULIO 2026
A7: SUELDO BASICO | C7: PREMIO INCENTIVO | E7: VIATICO | G7: PREMIO PRESENTISMO | I7: AGOSTO | K7: Sueldo Basico | L7: =+A8 -> 1100000
A8: 1100000 | C8: =+L19 -> 70000 | E8: =+L21 -> 70000 | G8: =+L23 -> 135000 | I8: SEPTIEMBRE | K8: Premio Incentivo | L8: =+C8 -> 70000
A9: ANTIGÜEDAD | B9: 0 | C9: VACACIONES/AGUINALDOS/EXTRAS | E9: VALES/DESCUENTOS/MULTAS | G9: TIPO DE SEGURO | I9: OCTUBRE | K9: Viatico | L9: =+E8 -> 70000
A10: 46143 | B10: 0 | C10: 0 | E10: =+D55+H55 -> 200000 | G10: AP | I10: NOVIEMBRE | K10: Premio Presentismo | L10: =+G8 -> 135000
A11: HRS ACORDADAS | B11: HRS TRABAJADAS | C11: HRS EXTRAS TRABAJADAS | E11: VALOR HRS EXTRAS | G11: IMPORTE HRS EXTRAS TRABAJADAS | I11: DICIEMBRE | K11: Antigüedad | L11: =+B10 -> 0
A12: 220 | B12: =+H48 -> 231.08 | C12: =+B12-A12 -> 11.08 | E12: 4500 | G12: =+C12*E12 -> 49860 | I12: TOTAL | J12: =SUM(J6:J11) -> 1100000 | K12: Vacas/Aguinaldos/Extras | L12: =+C10 -> 0
A13: INICIO DEL ACUERDO | C13: VIGENCIA DEL ACUERDO | E13: % DEL ACUERDO | I13: 6 MESES | J13: =+J12/6 -> 183333.33 | K13: Hrs Extras | L13: =+G12 -> 49860
A14: 46143 | C14: 9 MESES | E14: Básico + Premio Incentivo + Viatico + Presentismo + Hs Extra + Antigüedad | I14: AGUINALDOS | J14: =+J13/2 -> 91666.667 | K14: Total | L14: =SUM(L7:L13) -> 1424860
A15: IMPORTE TOTAL A COBRAR | G15: =+H5-E10 -> 1224860 | K15: Vales | L15: =+E10 -> 200000
A16: Convocatoria | B16: Dia | C16: Fecha | D16: Inicio de Actividades | F16: Fin de Actividades | H16: Hrs trabajadas | K16: A cobrar | L16: =+L14-L15 -> 1224860
A17: 9:00 a. m. | B17: MIERCOLES | C17: 46204 | D17: 8:59 a. m. | F17: 6:01 p. m. | H17: 9.03
A18: 9:00 a. m. | B18: JUEVES | C18: 46205 | D18: 8:55 a. m. | F18: 6:03 p. m. | H18: 9.13 | K18: PREMIO INCENTIVO
A19: 9:00 a. m. | B19: VIERNES | C19: 46206 | D19: 8:59 a. m. | F19: 5:00 p. m. | H19: 8.02 | K19: 1 Cat | L19: 70000
A20: 9:00 a. m. | B20: SÁBADO | C20: 46207 | D20: 8:54 a. m. | F20: 3:27 p. m. | H20: 6.55 | K20: VIÁTICO
A21: LIBRE | B21: DOMINGO | C21: 46208 | H21: 0 | K21: 1 Cat | L21: 70000
A22: 9:00 a. m. | B22: LUNES | C22: 46209 | D22: 8:55 a. m. | F22: 6:03 p. m. | H22: 9.13 | K22: PREMIO PRESENTISMO
A23: LIBRE | B23: MARTES | C23: 46210 | H23: 0 | K23: 1 Cat | L23: 135000
A24: 9:00 a. m. | B24: MIÉRCOLES | C24: 46211 | D24: 8:56 a. m. | F24: 6:01 p. m. | H24: 9.08 | K24: ANTIGÜEDAD
A25: 9:00 a. m. | B25: JUEVES | C25: 46212 | D25: 8:53 a. m. | F25: 6:02 p. m. | H25: 9.15 | K25: 1 Años | L25: =12500*17.1%+12500 -> 14637.5
A26: 9:00 a. m. | B26: VIERNES | C26: 46213 | D26: 8:57 a. m. | F26: 6:06 p. m. | H26: 9.15 | K26: 2 Años | L26: =20000*17.1%+20000 -> 23420
A27: 9:00 a. m. | B27: SÁBADO | C27: 46214 | D27: 8:51 a. m. | F27: 3:23 p. m. | H27: 6.53 | K27: 3 Años | L27: =27500*17.1%+27500 -> 32202.5
A28: LIBRE | B28: DOMINGO | C28: 46215 | H28: 0 | K28: 4 Años | L28: =35000*17.1%+35000 -> 40985
A29: 9:00 a. m. | B29: LUNES | C29: 46216 | D29: 8:54 a. m. | F29: 6:02 p. m. | H29: 9.13 | K29: 5 Años | L29: =42500*17.1%+42500 -> 49767.5
A30: 9:00 a. m. | B30: MARTES | C30: 46217 | D30: 8:51 a. m. | F30: 6:03 p. m. | H30: 9.2 | K30: 6 Años | L30: =63750*17.1%+63750 -> 74651.25
A31: LIBRE | B31: MIÉRCOLES | C31: 46218 | H31: 0 | K31: 7 Años | L31: =127500*17.1%+127500 -> 149302.5
A32: 9:00 a. m. | B32: JUEVES | C32: 46219 | D32: 8:59 a. m. | F32: 6:15 p. m. | H32: 9.27 | K32: 8 Años | L32: =200000*17.1%+200000 -> 234200
A33: 9:00 a. m. | B33: VIERNES | C33: 46220 | D33: 8:52 a. m. | F33: 6:19 p. m. | H33: 9.45
A34: 9:00 a. m. | B34: SÁBADO | C34: 46221 | D34: 8:53 a. m. | F34: 4:55 p. m. | H34: 8.03
A35: LIBRE | B35: DOMINGO | C35: 46222 | H35: 0
A36: 9:00 a. m. | B36: LUNES | C36: 46223 | D36: 8:53 a. m. | F36: 6:04 p. m. | H36: 9.18
A37: 8:00 a. m. | B37: MARTES | C37: 46224 | D37: 8:02 a. m. | F37: 6:10 p. m. | H37: 10.13
A38: 8:00 a. m. | B38: MIÉRCOLES | C38: 46225 | D38: 7:51 a. m. | F38: 6:04 p. m. | H38: 10.22
A39: 8:00 a. m. | B39: JUEVES | C39: 46226 | D39: 7:54 a. m. | F39: 6:05 p. m. | H39: 10.18
A40: 8:00 a. m. | B40: VIERNES | C40: 46227 | D40: 7:59 a. m. | F40: 6:02 p. m. | H40: 10.05
A41: 7:30 a. m. | B41: SÁBADO | C41: 46228 | D41: 7:23 a. m. | F41: 3:03 p. m. | H41: 7.67
A42: LIBRE | B42: DOMINGO | C42: 46229 | H42: 0
A43: 6:30 a. m. | B43: LUNES | C43: 46230 | D43: 6:16 a. m. | F43: 6:40 p. m. | H43: 12.4
A44: 6:30 a. m. | B44: MARTES | C44: 46231 | D44: 6:18 a. m. | F44: 6:04 p. m. | H44: 11.77
A45: 8:00 a. m. | B45: MIÉRCOLES | C45: 46232 | D45: 7:59 a. m. | F45: 6:01 p. m. | H45: 10.03
A46: 9:00 a. m. | B46: JUEVES | C46: 46233 | D46: 8:38 a. m. | F46: 6:04 p. m. | H46: 9.43
A47: 9:00 a. m. | B47: VIERNES | C47: 46234 | D47: 8:56 a. m. | F47: 6:06 p. m. | H47: 9.17
F48: TOTALES | H48: =SUM(H17:H47) -> 231.08
A50: VALES | E50: DETALLE DE PRESTAMOS / DESCUENTOS / MULTAS
A51: FECHA | B51: DETALLE | D51: MONTO | E51: FECHA | F51: DETALLE | H51: IMPORTE
A52: 46226 | B52: ADELANTO | D52: 200000
A55: TOTAL | D55: =SUM(D52:D54) -> 200000 | E55: PENDIENTE DE PAGO | H55: =+H52 -> 0
E56: PENDIENTE A PAGAR PRESTAMOS | H56: 0
A57: HRS PENDIENTES
A58: MES | D58: HRS
A59: ACUMULADO 2024 | D59: -396.88
A60: ENERO | D60: 0
A61: FEBRERO | D61: 0
A62: MARZO | D62: 0
A63: ABRIL
A64: MAYO
A65: JUNIO
A66: JULIO
A67: AGOSTO
A68: SEPTIEMBRE
A69: OCTUBRE
A70: NOVIEMBRE
A71: DICIEMBRE
A72: TOTAL | D72: =SUM(D59:D71) -> -396.88

Sheet CHOLI
I2: AUMENTO
I3: AGOSTO/SEPTIEMBRE
A5: =+MAYRA!A5 -> SUELDO JULIO 2026 | F5: SUELDO | H5: =+A8+C8+E8+G8+B10+C10+C12+E12+G12+G14 -> 1762530.2 | I5: AGUINALDOS | K5: =+B6 -> RODRIGO FERNANDEZ
A6: Nombre: | B6: RODRIGO FERNANDEZ | D6: DNI: | E6: 44061846 | F6: Escalafon: | H6: 3 | I6: JULIO | J6: 1185221.5 | K6: =+MAYRA!L6 -> Mes: JULIO 2026
A7: SUELDO BASICO | C7: PREMIO INCENTIVO | E7: VIATICO | G7: PREMIO PRESENTISMO | I7: AGOSTO | K7: Sueldo Basico | L7: =+A8 -> 1185221.5
A8: 1185221.5 | C8: =+L21 -> 56335.39 | E8: =+L23 -> 122500 | G8: =+L25 -> 91875 | I8: SEPTIEMBRE | K8: Premio Incentivo | L8: =+C8 -> 56335.39
A9: ANTIGÜEDAD | B9: 0 | C9: VACACIONES/AGUINALDOS/EXTRAS | E9: VALES/DESCUENTOS/MULTAS | G9: TIPO DE SEGURO | I9: OCTUBRE | K9: Viatico | L9: =+E8 -> 122500
A10: 45870 | B10: 0 | C10: 0 | E10: =+D57+H57 -> 400000 | G10: AP | I10: NOVIEMBRE | K10: Premio Presentismo | L10: =+G8 -> 91875
A11: PREMIOS COMPLEMENTARIOS | C11: KEDDER | D11: 0 | E11: CASETTE | F11: 1 | G11: PREMIO GUARDIAS | H11: 1 | I11: DICIEMBRE | K11: Antigüedad | L11: =+B10 -> 0
C12: =+L36*D11 -> 0 | E12: =+L37*F11 -> 78000 | G12: =+L39*H11 -> 11594.62 | I12: TOTAL | J12: =SUM(J6:J11) -> 1185221.5 | K12: Vacas/Aguinaldos/Extras | L12: =+C10 -> 0
A13: HRS ACORDADAS | B13: HRS TRABAJADAS | C13: HRS EXTRAS TRABAJADAS | E13: VALOR HRS EXTRAS | G13: IMPORTE HRS EXTRAS TRABAJADAS | I13: 6 MESES | J13: =+J12/6 -> 197536.91 | K13: Premios Complem. (Kedder/Casette) | L13: =+C12+E12 -> 78000
A14: 220 | B14: =+H51 -> 273 | C14: =+B14-A14 -> 53 | E14: 4094.41 | G14: =+C14*E14 -> 217003.73 | I14: AGUINALDOS | J14: =+J13/2 -> 98768.455 | K14: Premio Guardias | L14: =+G12 -> 11594.62
A15: INICIO DEL ACUERDO | C15: VIGENCIA DEL ACUERDO | E15: % DEL ACUERDO | K15: Hrs Extras | L15: =+G14 -> 217003.73
A16: 46054 | C16: 6 MESES | E16: Según IPC Básico (15%) Y 7,5% (Excepcion) - Presentismo + Viático // Premio Según IPC Básico (15%) + 15% (Excepcion) Basico + Hs Extra + Premios Complementarios | K16: Total | L16: =SUM(L7:L15) -> 1762530.2
A17: IMPORTE TOTAL A COBRAR | G17: =+H5-E10 -> 1362530.2 | K17: Vales | L17: =+E10 -> 400000
A18: Convocatoria | B18: Dia | C18: Fecha | D18: Inicio de Actividades | F18: Fin de Actividades | H18: Hrs trabajadas | K18: A cobrar | L18: =+L16-L17 -> 1362530.2
A19: 9:00 a. m. | B19: MIERCOLES | C19: 46204 | D19: 8:50 a. m. | F19: 6:05 p. m. | H19: 9.25
A20: 9:00 a. m. | B20: JUEVES | C20: 46205 | D20: 8:37 a. m. | F20: 6:00 p. m. | H20: 9.38 | K20: PREMIO INCENTIVO
A21: 9:00 a. m. | B21: VIERNES | C21: 46206 | D21: 8:44 a. m. | F21: 5:30 p. m. | H21: 8.77 | K21: 1 Cat | L21: 56335.39
A22: 9:00 a. m. | B22: SÁBADO | C22: 46207 | D22: 9:03 a. m. | F22: 3:47 p. m. | H22: 6.73 | K22: VIÁTICO
A23: LIBRE | B23: DOMINGO | C23: 46208 | H23: 0 | K23: 1 Cat | L23: 122500
A24: 9:00 a. m. | B24: LUNES | C24: 46209 | D24: 8:11 a. m. | F24: 6:04 p. m. | H24: 9.88 | K24: PREMIO PRESENTISMO
A25: LIBRE | B25: MARTES | C25: 46210 | H25: 0 | K25: 1 Cat | L25: 91875
A26: 9:00 a. m. | B26: MIÉRCOLES | C26: 46211 | D26: 9:00 a. m. | F26: 6:03 p. m. | H26: 9.05 | K26: ANTIGÜEDAD
A27: 9:00 a. m. | B27: JUEVES | C27: 46212 | D27: 8:52 a. m. | F27: 6:03 p. m. | H27: 9.18 | K27: 1 Años | L27: 12500
A28: 9:00 a. m. | B28: VIERNES | C28: 46213 | D28: 8:43 a. m. | F28: 6:07 p. m. | H28: 9.4 | K28: 2 Años | L28: 20000
A29: 9:00 a. m. | B29: SÁBADO | C29: 46214 | D29: 8:58 a. m. | F29: 4:26 p. m. | H29: 7.47 | K29: 3 Años | L29: 27500
A30: LIBRE | B30: DOMINGO | C30: 46215 | H30: 0 | K30: 4 Años | L30: 35000
A31: 9:00 a. m. | B31: LUNES | C31: 46216 | D31: 8:59 a. m. | F31: 6:06 p. m. | H31: 9.12 | K31: 5 Años | L31: 42500
A32: 9:00 a. m. | B32: MARTES | C32: 46217 | D32: 9:00 a. m. | F32: 6:07 p. m. | H32: 9.12 | K32: 6 Años | L32: 63750
A33: LIBRE | B33: MIÉRCOLES | C33: 46218 | H33: 0 | K33: 7 Años | L33: 127500
A34: 9:00 a. m. | B34: JUEVES | C34: 46219 | D34: 9:06 a. m. | F34: 6:24 p. m. | H34: 9.3 | K34: 8 Años | L34: 200000
A35: 9:00 a. m. | B35: VIERNES | C35: 46220 | D35: 8:56 a. m. | F35: 7:17 p. m. | H35: 10.35 | K35: PREMIOS COMPLEMENTARIOS
A36: X | B36: SÁBADO | C36: 46221 | D36: 12:00 p. m. | F36: 8:05 p. m. | H36: 8.08 | I36: VIAJE SGO DEL ESTERO | K36: KEDDER | L36: 52000
A37: 7:00 a. m. | B37: DOMINGO | C37: 46222 | D37: 7:00 a. m. | F37: 2:00 p. m. | H37: 7 | I37: SGO DEL ESTERO | K37: CASETTE | L37: 78000
A38: 9:00 a. m. | B38: LUNES | C38: 46223 | D38: 7:00 a. m. | F38: 9:00 p. m. | H38: 14 | I38: SGO DEL ESTERO | K38: PREMIO GUARDIAS
A39: 8:00 a. m. | B39: MARTES | C39: 46224 | D39: 8:00 a. m. | F39: 9:00 p. m. | H39: 13 | I39: SGO DEL ESTERO | K39: 1 Cat (X Show) | L39: 11594.62
A40: 8:00 a. m. | B40: MIÉRCOLES | C40: 46225 | D40: 8:00 a. m. | F40: 7:00 p. m. | H40: 11 | I40: SGO DEL ESTERO
A41: 9:00 a. m. | B41: JUEVES | C41: 46226 | D41: 8:00 a. m. | F41: 7:00 p. m. | H41: 11 | I41: SGO DEL ESTERO
A42: 9:00 a. m. | B42: VIERNES | C42: 46227 | D42: 8:00 a. m. | F42: 7:00 p. m. | H42: 11 | I42: SGO DEL ESTERO
A43: 9:00 a. m. | B43: SÁBADO | C43: 46228 | D43: 7:00 a. m. | F43: 4:00 p. m. | H43: 9 | I43: SGO DEL ESTERO
B44: SÁBADO | C44: 46228 | D44: 5:00 p. m. | F44: 3:00 a. m. | H44: 10 | I44: GUARDIA
A45: 9:00 a. m. | B45: DOMINGO | C45: 46229 | D45: 9:00 a. m. | F45: 7:30 p. m. | H45: 10.5 | I45: SGO DEL ESTERO
A46: 9:00 a. m. | B46: LUNES | C46: 46230 | D46: 8:00 a. m. | F46: 7:00 p. m. | H46: 11 | I46: SGO DEL ESTERO
A47: 9:00 a. m. | B47: MARTES | C47: 46231 | D47: 8:00 a. m. | F47: 5:30 p. m. | H47: 9.5 | I47: SGO DEL ESTERO/Regreso Cba camioneta Veck
A48: 7:30 a. m. | B48: MIÉRCOLES | C48: 46232 | D48: 7:35 a. m. | F48: 7:46 p. m. | H48: 12.18
A49: 9:00 a. m. | B49: JUEVES | C49: 46233 | D49: 8:52 a. m. | F49: 6:02 p. m. | H49: 9.17
A50: 9:00 a. m. | B50: VIERNES | C50: 46234 | D50: 8:48 a. m. | F50: 6:22 p. m. | H50: 9.57
F51: TOTALES | H51: =SUM(H19:H50) -> 273
A53: VALES | E53: DETALLE DE PRESTAMOS / DESCUENTOS / MULTAS
A54: FECHA | B54: DETALLE | D54: MONTO | E54: FECHA | F54: DETALLE | H54: IMPORTE
A55: 46227 | B55: ADELANTO | D55: 400000
A57: TOTAL | D57: =SUM(D55:D56) -> 400000 | E57: PENDIENTE DE PAGO | H57: =+H56 -> 0
E58: PENDIENTE A PAGAR PRESTAMOS | H58: 0
A59: HRS PENDIENTES
A60: MES | D60: HRS
A61: ACUMULADO 2024 | D61: -396.88
A62: ENERO | D62: 0
A63: FEBRERO | D63: 0
A64: MARZO | D64: 0
A65: ABRIL
A66: MAYO
A67: JUNIO
A68: JULIO
A69: AGOSTO
A70: SEPTIEMBRE
A71: OCTUBRE
A72: NOVIEMBRE
A73: DICIEMBRE
A74: TOTAL | D74: =SUM(D61:D73) -> -396.88

Sheet PEPO
I2: AUMENTO
I3: AGOSTO/SEPTIEMBRE
A5: =+MAYRA!A5 -> SUELDO JULIO 2026 | F5: SUELDO | H5: =+A8+C8+E8+G8+B10+C10+C12+E12+G12+G14 -> 1812638.3 | I5: AGUINALDOS | K5: =+B6 -> JOSE LUIS PEREZ STRIPPOLI
A6: Nombre: | B6: JOSE LUIS PEREZ STRIPPOLI | D6: DNI: | E6: 35318400 | F6: Escalafon: | H6: 3 | I6: JULIO | J6: 1185221.5 | K6: =+MAYRA!L6 -> Mes: JULIO 2026
A7: SUELDO BASICO | C7: PREMIO INCENTIVO | E7: VIATICO | G7: PREMIO PRESENTISMO | I7: AGOSTO | K7: Sueldo Basico | L7: =+A8 -> 1185221.5
A8: 1185221.5 | C8: =+L21 -> 56335.39 | E8: =+L23 -> 122500 | G8: =+L25 -> 91875 | I8: SEPTIEMBRE | K8: Premio Incentivo | L8: =+C8 -> 56335.39
A9: ANTIGÜEDAD | B9: 0 | C9: VACACIONES/AGUINALDOS/EXTRAS | E9: VALES/DESCUENTOS/MULTAS | G9: TIPO DE SEGURO | I9: OCTUBRE | K9: Viatico | L9: =+E8 -> 122500
A10: 45870 | B10: 0 | C10: 0 | E10: =+D57+H57 -> 300000 | G10: AP | I10: NOVIEMBRE | K10: Premio Presentismo | L10: =+G8 -> 91875
A11: PREMIOS COMPLEMENTARIOS | C11: KEDDER | D11: 0 | E11: CASETTE | F11: 1 | G11: PREMIO GUARDIAS | H11: 0 | I11: DICIEMBRE | K11: Antigüedad | L11: =+B10 -> 0
C12: =+L36*D11 -> 0 | E12: =+L37*F11 -> 78000 | G12: =+L39*H11 -> 0 | I12: TOTAL | J12: =SUM(J6:J11) -> 1185221.5 | K12: Vacas/Aguinaldos/Extras | L12: =+C10 -> 0
A13: HRS ACORDADAS | B13: HRS TRABAJADAS | C13: HRS EXTRAS TRABAJADAS | E13: VALOR HRS EXTRAS | G13: IMPORTE HRS EXTRAS TRABAJADAS | I13: 6 MESES | J13: =+J12/6 -> 197536.91 | K13: Premios Complem. (Kedder/Casette) | L13: =+C12+E12 -> 78000
A14: 220 | B14: =+H50 -> 288.07 | C14: =+B14-A14 -> 68.07 | E14: 4094.41 | G14: =+C14*E14 -> 278706.49 | I14: AGUINALDOS | J14: =+J13/2 -> 98768.455 | K14: Premio Guardias | L14: =+G12 -> 0
A15: INICIO DEL ACUERDO | C15: VIGENCIA DEL ACUERDO | E15: % DEL ACUERDO | K15: Hrs Extras | L15: =+G14 -> 278706.49
A16: 46054 | C16: 6 MESES | E16: Según IPC Básico (15%) Y 7,5% (Excepcion) - Presentismo + Viático // Premio Según IPC Básico (15%) + 15% (Excepcion) Basico + Hs Extra + Premios Complementarios | K16: Total | L16: =SUM(L7:L15) -> 1812638.3
A17: IMPORTE TOTAL A COBRAR | G17: =+H5-E10 -> 1512638.3 | K17: Vales | L17: =+E10 -> 300000
A18: Convocatoria | B18: Dia | C18: Fecha | D18: Inicio de Actividades | F18: Fin de Actividades | H18: Hrs trabajadas | K18: A cobrar | L18: =+L16-L17 -> 1512638.3
A19: 9:00 a. m. | B19: MIERCOLES | C19: 46204 | D19: 9:10 a. m. | F19: 6:01 p. m. | H19: 8.85
A20: 9:00 a. m. | B20: JUEVES | C20: 46205 | D20: 9:06 a. m. | F20: 6:01 p. m. | H20: 8.92 | K20: PREMIO INCENTIVO
A21: 9:00 a. m. | B21: VIERNES | C21: 46206 | D21: 9:15 a. m. | F21: 5:32 p. m. | H21: 8.28 | K21: 1 Cat | L21: 56335.39
A22: 9:00 a. m. | B22: SÁBADO | C22: 46207 | D22: 9:05 a. m. | F22: 8:39 p. m. | H22: 11.57 | I22: GUARDIA KEMPES | K22: VIÁTICO
A23: LIBRE | B23: DOMINGO | C23: 46208 | H23: 0 | K23: 1 Cat | L23: 122500
A24: 9:00 a. m. | B24: LUNES | C24: 46209 | D24: 8:59 a. m. | F24: 7:29 p. m. | H24: 10.5 | K24: PREMIO PRESENTISMO
A25: LIBRE | B25: MARTES | C25: 46210 | H25: 0 | K25: 1 Cat | L25: 91875
A26: 9:00 a. m. | B26: MIÉRCOLES | C26: 46211 | D26: 9:00 a. m. | F26: 6:00 p. m. | H26: 9 | K26: ANTIGÜEDAD
A27: 9:00 a. m. | B27: JUEVES | C27: 46212 | D27: 8:53 a. m. | F27: 6:02 p. m. | H27: 9.15 | K27: 1 Años | L27: 12500
A28: 9:00 a. m. | B28: VIERNES | C28: 46213 | D28: 9:07 a. m. | F28: 7:32 p. m. | H28: 10.42 | K28: 2 Años | L28: 20000
A29: 7:30 a. m. | B29: SÁBADO | C29: 46214 | D29: 6:41 a. m. | F29: 7:18 p. m. | H29: 12.62 | K29: 3 Años | L29: 27500
A30: 7:30 a. m. | B30: DOMINGO | C30: 46215 | D30: 6:55 a. m. | F30: 9:45 p. m. | H30: 14.83 | K30: 4 Años | L30: 35000
A31: VACACIONES | B31: LUNES | C31: 46216 | H31: 8 | K31: 5 Años | L31: 42500
A32: VACACIONES | B32: MARTES | C32: 46217 | H32: 8 | K32: 6 Años | L32: 63750
A33: VACACIONES | B33: MIÉRCOLES | C33: 46218 | H33: 8 | K33: 7 Años | L33: 127500
A34: VACACIONES | B34: JUEVES | C34: 46219 | H34: 8 | K34: 8 Años | L34: 200000
A35: VACACIONES | B35: VIERNES | C35: 46220 | H35: 8 | K35: PREMIOS COMPLEMENTARIOS
A36: X | B36: SÁBADO | C36: 46221 | D36: 3:11 p. m. | F36: 8:05 p. m. | H36: 4.9 | I36: VIAJE SGO DEL ESTERO | K36: KEDDER | L36: 52000
A37: 7:00 a. m. | B37: DOMINGO | C37: 46222 | D37: 7:00 a. m. | F37: 2:00 p. m. | H37: 7 | I37: SGO DEL ESTERO | K37: CASETTE | L37: 78000
A38: 7:00 a. m. | B38: LUNES | C38: 46223 | D38: 7:00 a. m. | F38: 9:00 p. m. | H38: 14 | I38: SGO DEL ESTERO | K38: PREMIO GUARDIAS
A39: 8:00 a. m. | B39: MARTES | C39: 46224 | D39: 8:00 a. m. | F39: 9:00 p. m. | H39: 13 | I39: SGO DEL ESTERO | K39: 1 Cat (X Show) | L39: 11594.62
A40: 8:00 a. m. | B40: MIÉRCOLES | C40: 46225 | D40: 8:00 a. m. | F40: 7:00 p. m. | H40: 11 | I40: SGO DEL ESTERO
A41: 9:00 a. m. | B41: JUEVES | C41: 46226 | D41: 8:00 a. m. | F41: 7:00 p. m. | H41: 11 | I41: SGO DEL ESTERO
A42: 9:00 a. m. | B42: VIERNES | C42: 46227 | D42: 8:00 a. m. | F42: 7:00 p. m. | H42: 11 | I42: SGO DEL ESTERO
A43: 9:00 a. m. | B43: SÁBADO | C43: 46228 | D43: 4:00 p. m. | F43: 3:00 a. m. | H43: 11 | I43: SGO DEL ESTERO/GUARDIA
A44: 9:00 a. m. | B44: DOMINGO | C44: 46229 | D44: 9:00 a. m. | F44: 7:30 p. m. | H44: 10.5 | I44: SGO DEL ESTERO
A45: 9:00 a. m. | B45: LUNES | C45: 46230 | D45: 8:00 a. m. | F45: 7:00 p. m. | H45: 11 | I45: SGO DEL ESTERO
A46: 9:00 a. m. | B46: MARTES | C46: 46231 | D46: 8:00 a. m. | F46: 5:30 p. m. | H46: 9.5 | I46: SGO DEL ESTERO/Regreso Cba camioneta Veck
A47: 7:30 a. m. | B47: MIÉRCOLES | C47: 46232 | D47: 7:36 a. m. | F47: 7:45 p. m. | H47: 12.15
A48: 9:00 a. m. | B48: JUEVES | C48: 46233 | D48: 9:09 a. m. | F48: 6:02 p. m. | H48: 8.88
A49: 9:00 a. m. | B49: VIERNES | C49: 46234 | D49: 9:21 a. m. | F49: 6:21 p. m. | H49: 9
F50: TOTALES | H50: =SUM(H19:H49) -> 288.07
A52: VALES | E52: DETALLE DE PRESTAMOS / DESCUENTOS / MULTAS
A53: FECHA | B53: DETALLE | D53: MONTO | E53: FECHA | F53: DETALLE | H53: IMPORTE
A54: 46227 | B54: ADELANTO | D54: 300000
A57: TOTAL | D57: =SUM(D54:D56) -> 300000 | E57: PENDIENTE DE PAGO | H57: =+H56 -> 0
E58: PENDIENTE A PAGAR PRESTAMOS | H58: 0
A59: HRS PENDIENTES
A60: MES | D60: HRS
A61: ACUMULADO 2024 | D61: -396.88
A62: ENERO | D62: 0
A63: FEBRERO | D63: 0
A64: MARZO | D64: 0
A65: ABRIL
A66: MAYO
A67: JUNIO
A68: JULIO
A69: AGOSTO
A70: SEPTIEMBRE
A71: OCTUBRE
A72: NOVIEMBRE
A73: DICIEMBRE
A74: TOTAL | D74: =SUM(D61:D73) -> -396.88

Sheet GONZA
I2: AUMENTO
I3: ENERO/FEBRERO
A5: =+MAYRA!A5 -> SUELDO JULIO 2026 | F5: SUELDO | H5: =+A8+C8+E8+G8+B10+C10+G10+G12 -> 1230629.6 | I5: AGUINALDOS | K5: =+B6 -> GONZALO CATALANO
A6: Nombre: | B6: GONZALO CATALANO | D6: DNI: | E6: 0 | F6: Escalafon: | H6: 3 | I6: JULIO | J6: 1168000 | K6: =+MAYRA!L6 -> Mes: JULIO 2026
A7: SUELDO BASICO | C7: PREMIO INCENTIVO | E7: VIATICO | G7: PREMIO PRESENTISMO | I7: AGOSTO | K7: Sueldo Basico | L7: =+A8 -> 1168000
A8: =1000000*16.8%+1000000 -> 1168000 | E8: =+L22 -> 46720 | I8: SEPTIEMBRE | K8: Premio Incentivo | L8: =+C8 -> 0
A9: ANTIGÜEDAD | B9: 0 | C9: VACACIONES/AGUINALDOS/EXTRAS | E9: VALES/DESCUENTOS/MULTAS | G9: PREMIO GUARDIA | H9: 1 | I9: OCTUBRE | K9: Viatico | L9: =+E8 -> 46720
A10: 45931 | B10: 0 | C10: 0 | E10: =+D54+H54 -> 300000 | G10: =+L35*H9 -> 11055.12 | I10: NOVIEMBRE | K10: Premio Presentismo | L10: =+G8 -> 0
A11: HRS ACORDADAS | B11: HRS TRABAJADAS | C11: HRS EXTRAS TRABAJADAS | E11: VALOR HRS EXTRAS | G11: IMPORTE HRS EXTRAS TRABAJADAS | I11: DICIEMBRE | K11: Antigüedad | L11: =+B10 -> 0
A12: 220 | B12: =+H48 -> 221.34 | C12: =+B12-A12 -> 1.34 | E12: =2898.19*25%+2898.19 -> 3622.7375 | G12: =+C12*E12 -> 4854.4682 | I12: TOTAL | J12: =SUM(J6:J11) -> 1168000 | K12: Vacas/Aguinaldos/Extras | L12: =+C10 -> 0
A13: TIPO DE SEGURO | B13: INICIO DEL ACUERDO | D13: VIGENCIA DEL ACUERDO | F13: % DEL ACUERDO | I13: 6 MESES | J13: =+J12/6 -> 194666.67 | K13: Premio Guardia | L13: =+G10 -> 11055.12
A14: AP | B14: 46113 | D14: 9 MESES | F14: 16,8% (IPC) Básico + Viático + Premio Incentivo + Antigüedad + Presentismo + Guardias // 16,8% (IPC) + 8,2% (Excepción) Hs Extra | I14: AGUINALDOS | J14: =+J13/2 -> 97333.333 | K14: Hrs Extras | L14: =+G12 -> 4854.4682
A15: IMPORTE TOTAL A COBRAR | G15: =+H5-E10 -> 930629.59 | K15: Total | L15: =SUM(L7:L14) -> 1230629.6
A16: Convocatoria | B16: Dia | C16: Fecha | D16: Inicio de Actividades | F16: Fin de Actividades | H16: Hrs trabajadas | K16: Vales | L16: =+E10 -> 300000
A17: 9:00 a. m. | B17: MIERCOLES | C17: 46204 | D17: 10:10 a. m. | F17: 5:30 p. m. | H17: 7.33 | K17: A cobrar | L17: =+L15-L16 -> 930629.59
A18: 9:00 a. m. | B18: JUEVES | C18: 46205 | D18: 10:00 a. m. | F18: 5:40 p. m. | H18: 7.67
A19: 9:00 a. m. | B19: VIERNES | C19: 46206 | D19: 9:42 a. m. | F19: 5:31 p. m. | H19: 7.82 | K19: PREMIO INCENTIVO
A20: 9:00 a. m. | B20: SÁBADO | C20: 46207 | D20: 9:23 a. m. | F20: 3:46 p. m. | H20: 6.38 | K20: 1 Cat | L20: =30000*16.8%+30000 -> 35040
A21: LIBRE | B21: DOMINGO | C21: 46208 | H21: 0 | K21: VIÁTICO
A22: 9:00 a. m. | B22: LUNES | C22: 46209 | D22: 9:30 a. m. | F22: 6:04 p. m. | H22: 8.57 | K22: 1 Cat | L22: =40000*16.8%+40000 -> 46720
A23: LIBRE | B23: MARTES | C23: 46210 | H23: 0 | K23: PREMIO PRESENTISMO
A24: 9:00 a. m. | B24: MIÉRCOLES | C24: 46211 | D24: 9:29 a. m. | F24: 6:02 p. m. | H24: 8.55 | K24: 1 Cat | L24: =110000*16.8%+110000 -> 128480
A25: 9:00 a. m. | B25: JUEVES | C25: 46212 | D25: 9:31 a. m. | F25: 6:00 p. m. | H25: 8.48 | K25: ANTIGÜEDAD
A26: FRANCO | B26: VIERNES | C26: 46213 | H26: 0 | K26: 1 Años | L26: =12500*16.8%+12500 -> 14600
A27: FRANCO | B27: SÁBADO | C27: 46214 | H27: 0 | K27: 2 Años | L27: =20000*16.8%+20000 -> 23360
A28: FRANCO | B28: DOMINGO | C28: 46215 | H28: 0 | K28: 3 Años | L28: =27500*16.8%+27500 -> 32120
A29: VACACIONES | B29: LUNES | C29: 46216 | H29: 8 | K29: 4 Años | L29: =35000*16.8%+35000 -> 40880
A30: VACACIONES | B30: MARTES | C30: 46217 | H30: 8 | K30: 5 Años | L30: =42500*16.8%+42500 -> 49640
A31: VACACIONES | B31: MIÉRCOLES | C31: 46218 | H31: 8 | K31: 6 Años | L31: =63750*16.8%+63750 -> 74460
A32: VACACIONES | B32: JUEVES | C32: 46219 | H32: 8 | K32: 7 Años | L32: =127500*16.8%+127500 -> 148920
A33: VACACIONES | B33: VIERNES | C33: 46220 | H33: 8 | K33: 8 Años | L33: =200000*16.8%+200000 -> 233600
A34: VACACIONES | B34: SÁBADO | C34: 46221 | H34: 8 | K34: PREMIO GUARDIAS
A35: VACACIONES | B35: DOMINGO | C35: 46222 | H35: 8 | K35: 1 Cat (X Show) | L35: =9465*16.8%+9465 -> 11055.12
A36: 9:00 a. m. | B36: LUNES | C36: 46223 | D36: 9:06 a. m. | F36: 5:55 p. m. | H36: 8.82 | I36: FORJA
A37: 9:00 a. m. | B37: MARTES | C37: 46224 | D37: 9:22 a. m. | F37: 6:07 p. m. | H37: 8.75
A38: 9:00 a. m. | B38: MIÉRCOLES | C38: 46225 | D38: 9:35 a. m. | F38: 6:07 p. m. | H38: 8.53
A39: 9:00 a. m. | B39: JUEVES | C39: 46226 | D39: 9:28 a. m. | F39: 6:04 p. m. | H39: 8.6
A40: 9:00 a. m. | B40: VIERNES | C40: 46227 | D40: 9:19 a. m. | F40: 6:03 p. m. | H40: 8.73
A41: 8:00 a. m. | B41: SÁBADO | C41: 46228 | D41: 8:20 a. m. | F41: 5:41 p. m. | H41: 9.35
A42: 8:00 a. m. | B42: DOMINGO | C42: 46229 | D42: 8:55 a. m. | F42: 7:47 p. m. | H42: 10.87
A43: 8:00 a. m. | B43: LUNES | C43: 46230 | D43: 8:55 a. m. | F43: 6:53 p. m. | H43: 9.97
A44: 8:00 a. m. | B44: MARTES | C44: 46231 | D44: 8:29 a. m. | F44: 6:00 p. m. | H44: 9.52
A45: 8:00 a. m. | B45: MIÉRCOLES | C45: 46232 | D45: 8:31 a. m. | F45: 9:30 p. m. | H45: 12.98 | I45: Kempes-Talleres
A46: 9:00 a. m. | B46: JUEVES | C46: 46233 | D46: 9:10 a. m. | F46: 11:35 p. m. | H46: 14.42 | I46: Kempes-Talleres//Guardia
A47: FRANCO | B47: VIERNES | C47: 46234 | H47: 0
F48: TOTALES | H48: =SUM(H17:H47) -> 221.34
A50: VALES | E50: DETALLE DE PRESTAMOS / DESCUENTOS / MULTAS
A51: FECHA | B51: DETALLE | D51: MONTO | E51: FECHA | F51: DETALLE | H51: IMPORTE
A52: 46227 | B52: ADELANTO | D52: 300000
A54: TOTAL | D54: =SUM(D52:D53) -> 300000 | E54: PENDIENTE DE PAGO | H54: 0
E55: PENDIENTE A PAGAR PRESTAMOS | H55: 0
A56: HRS PENDIENTES
A57: MES | D57: HRS
A58: ACUMULADO 2024 | D58: -396.88
A59: ENERO | D59: 0
A60: FEBRERO | D60: 0
A61: MARZO | D61: 0
A62: ABRIL
A63: MAYO
A64: JUNIO
A65: JULIO
A66: AGOSTO
A67: SEPTIEMBRE
A68: OCTUBRE
A69: NOVIEMBRE
A70: DICIEMBRE
A71: TOTAL | D71: =SUM(D58:D70) -> -396.88

Sheet NICO
I2: AUMENTO
I3: SEPTIEMBRE/OCTUBRE
A5: =+MAYRA!A5 -> SUELDO JULIO 2026 | F5: SUELDO | H5: =+A8+D8+E8+G10 -> 596000 | I5: AGUINALDOS | K5: =+B6 -> NICOLAS BIBILONI
A6: Nombre: | B6: NICOLAS BIBILONI | D6: DNI: | E6: 0 | F6: Escalafon: | H6: 3 | I6: JULIO | J6: 576000 | K6: =+MAYRA!L6 -> Mes: JULIO 2026
A7: SUELDO BASICO | C7: ANTIGÜEDAD | D7: 2 | E7: VACACIONES/AGUINALDOS/EXTRAS | G7: VALES/DESCUENTOS/MULTAS | I7: AGOSTO | K7: Sueldo Basico | L7: =+A8 -> 576000
A8: 576000 | C8: 45170 | D8: =+L19 -> 20000 | E8: 0 | G8: =+D54+H54 -> 0 | I8: SEPTIEMBRE | K8: Antigüedad | L8: =+D8 -> 20000
A9: HRS ACORDADAS | B9: HRS TRABAJADAS | C9: HRS EXTRAS TRABAJADAS | E9: VALOR HRS EXTRAS | G9: IMPORTE HRS EXTRAS TRABAJADAS | I9: OCTUBRE | K9: Vacas/Aguinaldos/Extras | L9: =+E8 -> 0
A10: 120 | B10: =+H46 -> 61 | C10: =+B10-A10 -> -59 | E10: 3000 | G10: 0 | I10: NOVIEMBRE | K10: Hrs Extras | L10: =+G10 -> 0
A11: TIPO DE SEGURO | B11: INICIO DEL ACUERDO | D11: VIGENCIA DEL ACUERDO | F11: % DEL ACUERDO | I11: DICIEMBRE | K11: Total | L11: =SUM(L7:L10) -> 596000
A12: AP | B12: 46082 | D12: 6 MESES | F12: 15,5% + 4,5% (Excepcion) Basico + Hs Extra | I12: TOTAL | J12: =SUM(J6:J11) -> 576000 | K12: Vales | L12: =+G8 -> 0
A13: IMPORTE TOTAL A COBRAR | G13: 312800 | I13: 6 MESES | J13: =+J12/6 -> 96000 | K13: A cobrar | L13: 308000
A14: Convocatoria | B14: Dia | C14: Fecha | D14: Inicio de Actividades | F14: Fin de Actividades | H14: Hrs trabajadas | I14: AGUINALDOS | J14: =+J13/2 -> 48000
B15: MIERCOLES | C15: 46204 | H15: 0 | K15: PREMIO PRESENTISMO
B16: JUEVES | C16: 46205 | D16: 1:00 p. m. | F16: 5:00 p. m. | H16: 4 | K16: 1 Cat | L16: 35000
B17: VIERNES | C17: 46206 | D17: 1:00 p. m. | F17: 5:00 p. m. | H17: 4 | K17: ANTIGÜEDAD
B18: SÁBADO | C18: 46207 | H18: 0 | K18: 1 Años | L18: 12500
B19: DOMINGO | C19: 46208 | H19: 0 | K19: 2 Años | L19: 20000
B20: LUNES | C20: 46209 | D20: 1:00 p. m. | F20: 5:00 p. m. | H20: 4 | K20: 3 Años | L20: 27500
B21: MARTES | C21: 46210 | H21: 0 | K21: 4 Años | L21: 35000
B22: MIÉRCOLES | C22: 46211 | H22: 0 | K22: 5 Años | L22: 42500
B23: JUEVES | C23: 46212 | D23: 1:00 p. m. | F23: 5:00 p. m. | H23: 4 | K23: 6 Años | L23: 63750
B24: VIERNES | C24: 46213 | D24: 1:00 p. m. | F24: 5:00 p. m. | H24: 4 | K24: 7 Años | L24: 127500
B25: SÁBADO | C25: 46214 | H25: 0 | K25: 8 Años | L25: 200000
B26: DOMINGO | C26: 46215 | H26: 0
B27: LUNES | C27: 46216 | D27: 1:00 p. m. | F27: 5:00 p. m. | H27: 4
B28: MARTES | C28: 46217 | D28: 1:00 p. m. | F28: 5:00 p. m. | H28: 4
B29: MIÉRCOLES | C29: 46218 | H29: 0
B30: JUEVES | C30: 46219 | D30: 1:00 p. m. | F30: 5:00 p. m. | H30: 4
B31: VIERNES | C31: 46220 | D31: 1:00 p. m. | F31: 5:00 p. m. | H31: 4
B32: SÁBADO | C32: 46221 | H32: 0
B33: DOMINGO | C33: 46222 | H33: 0
B34: LUNES | C34: 46223 | D34: 1:00 p. m. | F34: 5:00 p. m. | H34: 4
B35: MARTES | C35: 46224 | H35: 0
B36: MIÉRCOLES | C36: 46225 | H36: 0
B37: JUEVES | C37: 46226 | H37: 0
B38: VIERNES | C38: 46227 | D38: 1:00 p. m. | F38: 5:00 p. m. | H38: 4
B39: SÁBADO | C39: 46228 | H39: 0
B40: DOMINGO | C40: 46229 | H40: 0
B41: LUNES | C41: 46230 | D41: 1:00 p. m. | F41: 5:00 p. m. | H41: 4
B42: MARTES | C42: 46231 | H42: 0
B43: MIÉRCOLES | C43: 46232 | D43: 12:00 p. m. | F43: 5:00 p. m. | H43: 5
B44: JUEVES | C44: 46233 | D44: 1:00 p. m. | F44: 5:00 p. m. | H44: 4
B45: VIERNES | C45: 46234 | D45: 1:00 p. m. | F45: 5:00 p. m. | H45: 4
F46: TOTALES | H46: =SUM(H15:H45) -> 61
A48: VALES | E48: DETALLE DE PRESTAMOS / DESCUENTOS / MULTAS
A49: FECHA | B49: DETALLE | D49: MONTO | E49: FECHA | F49: DETALLE | H49: IMPORTE
A54: TOTAL | D54: =SUM(D50:D53) -> 0 | E54: PENDIENTE DE PAGO | H54: =+H51 -> 0
E55: PENDIENTE A PAGAR PRESTAMOS | H55: =+H52+H53 -> 0
A56: HRS PENDIENTES
A57: MES | D57: HRS
A58: ACUMULADO 2024 | D58: -396.88
A59: ENERO | D59: 0
A60: FEBRERO | D60: 0
A61: MARZO | D61: 0
A62: ABRIL
A63: MAYO
A64: JUNIO
A65: JULIO
A66: AGOSTO
A67: SEPTIEMBRE
A68: OCTUBRE
A69: NOVIEMBRE
A70: DICIEMBRE
A71: TOTAL | D71: =SUM(D58:D70) -> -396.88

Sheet SANTI
I2: AUMENTO
I3: FEBRERO/MARZO
A5: =+MAYRA!A5 -> SUELDO JULIO 2026 | F5: SUELDO | H5: =+A8+C8+F8+B10+C10+G12 -> 937467.47 | I5: AGUINALDOS | K5: =+B6 -> SANTIAGO BIBILONI
A6: Nombre: | B6: SANTIAGO BIBILONI | D6: DNI: | E6: 0 | F6: Escalafon: | H6: 4 | I6: JULIO | J6: 644050 | K6: =+MAYRA!L6 -> Mes: JULIO 2026
A7: SUELDO BASICO | C7: PREMIO INCENTIVO | F7: PREMIO PRESENTISMO | I7: AGOSTO | K7: Sueldo Basico | L7: =+A8 -> 644050
A8: =550000*17.1%+550000 -> 644050 | C8: =+L18 -> 29275 | F8: =+L20 -> 52695 | I8: SEPTIEMBRE | K8: Premio Incentivo | L8: =+C8 -> 29275
A9: ANTIGÜEDAD | B9: 0 | C9: VACACIONES/AGUINALDOS/EXTRAS | E9: VALES/DESCUENTOS/MULTAS | G9: TIPO DE SEGURO | I9: OCTUBRE | K9: Premio Presentismo | L9: =+F8 -> 52695
A10: 45962 | B10: 0 | C10: 0 | E10: =+D54+H54 -> 100000 | G10: AP | I10: NOVIEMBRE | K10: Antigüedad | L10: =+B10 -> 0
A11: HRS ACORDADAS | B11: HRS TRABAJADAS | C11: HRS EXTRAS TRABAJADAS | E11: VALOR HRS EXTRAS | G11: IMPORTE HRS EXTRAS TRABAJADAS | I11: DICIEMBRE | K11: Vacas/Aguinaldos/Extras | L11: =+C10 -> 0
A12: 120 | B12: =+H48 -> 180.19 | C12: =+B12-A12 -> 60.19 | E12: =3000*17.1%+3000 -> 3513 | G12: =+C12*E12 -> 211447.47 | I12: TOTAL | J12: =SUM(J6:J11) -> 644050 | K12: Hrs Extras | L12: =+G12 -> 211447.47
A13: INICIO DEL ACUERDO | C13: VIGENCIA DEL ACUERDO | E13: % DEL ACUERDO | I13: 6 MESES | J13: =+J12/6 -> 107341.67 | K13: Total | L13: =SUM(L7:L12) -> 937467.47
A14: 46143 | C14: 9 MESES | E14: 17,1% Básico + Premio Incentivo + Viatico + Presentismo + Hs Extra + Antigüedad | I14: AGUINALDOS | J14: =+J13/2 -> 53670.833 | K14: Vales | L14: =+E10 -> 100000
A15: IMPORTE TOTAL A COBRAR | G15: =+H5-E10 -> 837467.47 | K15: A cobrar | L15: =+L13-L14 -> 837467.47
A16: Convocatoria | B16: Dia | C16: Fecha | D16: Inicio de Actividades | F16: Fin de Actividades | H16: Hrs trabajadas
A17: LIBRE | B17: MIERCOLES | C17: 46204 | H17: 0 | K17: PREMIO INCENTIVO
A18: 9:00 a. m. | B18: JUEVES | C18: 46205 | D18: 8:48 a. m. | F18: 6:31 p. m. | H18: 9.72 | K18: 1 Cat | L18: =25000*17.1%+25000 -> 29275
A19: 9:00 a. m. | B19: VIERNES | C19: 46206 | D19: 9:04 a. m. | F19: 5:52 p. m. | H19: 8.8 | K19: PREMIO PRESENTISMO
A20: LIBRE | B20: SÁBADO | C20: 46207 | H20: 0 | K20: 1 Cat | L20: =45000*17.1%+45000 -> 52695
A21: LIBRE | B21: DOMINGO | C21: 46208 | H21: 0 | K21: ANTIGÜEDAD
A22: 9:00 a. m. | B22: LUNES | C22: 46209 | D22: 8:55 a. m. | F22: 6:22 p. m. | H22: 9.45 | K22: 1 Años | L22: =12500*17.1%+12500 -> 14637.5
A23: LIBRE | B23: MARTES | C23: 46210 | H23: 0 | K23: 2 Años | L23: =20000*17.1%+20000 -> 23420
A24: 9:00 a. m. | B24: MIÉRCOLES | C24: 46211 | D24: 9:09 a. m. | F24: 6:25 p. m. | H24: 9.27 | K24: 3 Años | L24: =27500*17.1%+27500 -> 32202.5
A25: 9:00 a. m. | B25: JUEVES | C25: 46212 | D25: 8:55 a. m. | F25: 6:35 p. m. | H25: 9.67 | K25: 4 Años | L25: =35000*17.1%+35000 -> 40985
A26: 9:00 a. m. | B26: VIERNES | C26: 46213 | D26: 8:57 a. m. | F26: 7:13 p. m. | H26: 10.27 | K26: 5 Años | L26: =42500*17.1%+42500 -> 49767.5
A27: LIBRE | B27: SÁBADO | C27: 46214 | H27: 0 | K27: 6 Años | L27: =63750*17.1%+63750 -> 74651.25
A28: LIBRE | B28: DOMINGO | C28: 46215 | H28: 0 | K28: 7 Años | L28: =127500*17.1%+127500 -> 149302.5
A29: VACACIONES | B29: LUNES | C29: 46216 | H29: 8 | K29: 8 Años | L29: =200000*17.1%+200000 -> 234200
A30: VACACIONES | B30: MARTES | C30: 46217 | H30: 8
A31: VACACIONES | B31: MIÉRCOLES | C31: 46218 | H31: 8
A32: VACACIONES-POLO | B32: JUEVES | C32: 46219 | D32: 1:00 p. m. | F32: 6:34 p. m. | H32: 8
A33: VACACIONES | B33: VIERNES | C33: 46220 | H33: 8
A34: VACACIONES | B34: SÁBADO | C34: 46221 | H34: 8
A35: VACACIONES | B35: DOMINGO | C35: 46222 | H35: 8
A36: 9:00 a. m. | B36: LUNES | C36: 46223 | D36: 8:43 a. m. | F36: 5:50 p. m. | H36: 9.12
A37: 9:00 a. m. | B37: MARTES | C37: 46224 | D37: 9:20 a. m. | F37: 6:41 p. m. | H37: 9.35 | I37: NO LLEGADA TARDE/AUTORIZO MATIAS (reunion Neper)
A38: 9:00 a. m. | B38: MIÉRCOLES | C38: 46225 | D38: 8:52 a. m. | F38: 6:14 p. m. | H38: 9.37
A39: LIBRE | B39: JUEVES | C39: 46226 | H39: 0
A40: LIBRE | B40: VIERNES | C40: 46227 | H40: 0
A41: LIBRE | B41: SÁBADO | C41: 46228 | H41: 0
A42: LIBRE | B42: DOMINGO | C42: 46229 | H42: 0
A43: 9:00 a. m. | B43: LUNES | C43: 46230 | D43: 8:59 a. m. | F43: 6:11 p. m. | H43: 9.2
A44: LIBRE | B44: MARTES | C44: 46231 | H44: 0
A45: 9:00 a. m. | B45: MIÉRCOLES | C45: 46232 | D45: 8:23 a. m. | F45: 7:05 p. m. | H45: 10.7
A46: 9:00 a. m. | B46: JUEVES | C46: 46233 | D46: 8:55 a. m. | F46: 6:49 p. m. | H46: 9.9
A47: 9:00 a. m. | B47: VIERNES | C47: 46234 | D47: 9:09 a. m. | F47: 6:31 p. m. | H47: 9.37
F48: TOTALES | H48: =SUM(H17:H47) -> 180.19
A50: VALES | E50: DETALLE DE PRESTAMOS / DESCUENTOS / MULTAS
A51: FECHA | B51: DETALLE | D51: MONTO | E51: FECHA | F51: DETALLE | H51: IMPORTE
A52: 46227 | B52: ADELANTO | D52: 100000
A54: TOTAL | D54: =SUM(D52:D53) -> 100000 | E54: PENDIENTE DE PAGO | H54: 0
E55: PENDIENTE A PAGAR PRESTAMOS | H55: 0
A56: HRS PENDIENTES
A57: MES | D57: HRS
A58: ACUMULADO 2024 | D58: -396.88
A59: ENERO | D59: 0
A60: FEBRERO | D60: 0
A61: MARZO | D61: 0
A62: ABRIL
A63: MAYO
A64: JUNIO
A65: JULIO
A66: AGOSTO
A67: SEPTIEMBRE
A68: OCTUBRE
A69: NOVIEMBRE
A70: DICIEMBRE
A71: TOTAL | D71: =SUM(D58:D70) -> -396.88

Sheet TOTALES
A1: SUELDOS JULIO 2026
A2: NOMBRE | B2: SUELDO FINAL | C2: A COBRAR | E2: EFECTIVO | F2: TRANSFERENCIA | G2: SALDOS / FALTANTES
A3: ANDREA | B3: =+ANDRE!H5 -> 2104265 | C3: =+ANDRE!G15 -> 1304265 | F3: =+C3 -> 1304265
A4: LORE | B4: =+LORE!H5 -> 1456957.1 | C4: =+LORE!G15 -> 1156957.1 | F4: =+C4 -> 1156957.1
A5: JAZ | B5: =+JAZ!H5 -> 1536653.9 | C5: =+JAZ!G15 -> 829317.35 | F5: =+C5 -> 829317.35
A6: FLOR | B6: =+FLOR!H5 -> 1080000 | C6: =+FLOR!G17 -> 780000 | E6: 780000
A7: FURIA | B7: =+FURIA!H5 -> 2391133.6 | C7: =+FURIA!G15 -> 1591133.6 | E7: 1591200
A8: MARIO | B8: =+MARIO!H5 -> 2639630.3 | C8: =+MARIO!G17 -> 2389630.3 | F8: =+C8 -> 2389630.3
A9: FAUSTO | B9: =+FAUSTO!H5 -> 1685923.2 | C9: =+FAUSTO!G17 -> 1480473.2 | E9: 1480500
A10: MILTON | B10: =+MILTON!H5 -> 1684333.1 | C10: =+MILTON!G17 -> 1584333.1 | F10: =+C10 -> 1584333.1
A11: CHARA | B11: =+CHARA!H5 -> 1630567.9 | C11: =+CHARA!G17 -> 1630567.9 | E11: 1630600
A12: TONI | B12: =+TONI!H5 -> 1943826.2 | C12: =+TONI!G15 -> 1943826.2 | E12: 1943900
A13: DAVID | B13: =+DAVID!H5 -> 2298936.4 | C13: =+DAVID!G15 -> 1648936.4 | E13: 1649000
A14: CARLOS | B14: =+CARLOS!H5 -> 2039290.8 | C14: =+CARLOS!G15 -> 1739290.8 | E14: 1739300
A15: POLA | B15: =+POLA!H5 -> 1674811.3 | C15: =+POLA!G15 -> 1474811.3 | E15: 1474900
A16: LUIS | B16: =+LUIS!H5 -> 2259750 | C16: =+LUIS!G15 -> 1694450 | E16: 578900 | F16: 1115575
A17: GERARDO | B17: =+GERARDO!H5 -> 1570226.6 | C17: =+GERARDO!G15 -> 1170226.6 | E17: 1170300
A18: LEANDRO | B18: =+LEANDRO!H5 -> 1297083.4 | C18: =+LEANDRO!G15 -> 187083.42 | E18: 187100
A19: PABLO | B19: =+PABLO!H5 -> 1424860 | C19: =+PABLO!G15 -> 1224860 | E19: 1224900
A20: CHOLI | B20: =+CHOLI!H5 -> 1762530.2 | C20: =+CHOLI!G17 -> 1362530.2 | E20: 247000 | F20: 1115575
A21: PEPO | B21: =+PEPO!H5 -> 1812638.3 | C21: =+PEPO!G17 -> 1512638.3 | E21: 397100 | F21: 1115575
A22: GONZA | B22: =+GONZA!H5 -> 1230629.6 | C22: =+GONZA!G15 -> 930629.59 | E22: 930700
A23: NICO | B23: =+NICO!H5 -> 596000 | C23: =+NICO!G13 -> 312800 | E23: 312800
A24: SANTI | B24: =+SANTI!H5 -> 937467.47 | C24: =+SANTI!G15 -> 837467.47 | E24: 837500
A25: Totales | B25: =SUM(B3:B23) -> 36120047 | C25: =SUM(C3:C24) -> 28786228
A28: SUELDOS JULIO 2026 - DIRECTORES
A29: NOMBRE | B29: SUELDO FINAL | C29: A COBRAR | E29: EFECTIVO | F29: TRANSFERENCIA | G29: SALDOS / FALTANTES
A30: POLLO | B30: 2000000 | C30: 2000000
A31: VECKY | B31: 2000000 | C31: 2000000
A32: MAYRA | B32: =+MAYRA!$I$5 -> 2979079.9 | C32: =+MAYRA!$H$10 -> 2112919.5 | F32: =+C32 -> 2112919.5
A33: Totales | B33: =SUM(B30:B32) -> 6979079.9 | C33: =SUM(C30:C32) -> 6112919.5
B35: =+B33+B25 -> 43099127 | C35: =+C33+C25 -> 34899147 | E35: =SUM(E3:E34) -> 18175700 | F35: =SUM(F3:F34) -> 12724147 | G35: =SUM(G3:G34) -> 0
