Workbook

Sheet COWORKING ENERO 2026
A1: CAJA CHICA MAYRA - COWORKING
A2: SEGUIMIENTO DE CAJA | D2: MES: ENERO 2026
A4: FECHA | B4: CONCEPTO | C4: INGRESO | D4: EGRESO | E4: SALDO
E5: 0
A6: 46023 | B6: Saldo Diciembre 2025 | C6: =+'[1]COWORKING DICIEMBRE 2025'!E17 -> 79513.23 | E6: =+E5+C6-D6 -> 79513.23 | G6: SERVICIO | H6: VTO. | I6: PAGO | J6: ESTADO
A7: 46024 | B7: Ecogas Coworking 12/25 | D7: 47094.94 | E7: =+E6+C7-D7 -> 32418.29 | G7: ALQUILER CO | H7: 46032 | I7: 46027 | J7: PAGADO
A8: 46027 | B8: Transf. Matias p/Pagos Co | C8: 569714.79 | E8: =+E7+C8-D8 -> 602133.08 | G8: MUNICIPALIDAD CO
A9: 46027 | B9: Efectivo Juan Pablo p/Pagos Co | C9: 911500 | E9: =+E8+C9-D9 -> 1513633.1 | G9: RENTAS CO
A10: 46027 | B10: Efectivo Galara p/Pagos Co | C10: 1040000 | E10: =+E9+C10-D10 -> 2553633.1 | G10: EPEC CO | H10: 46024 | I10: 46027 | J10: PAGADO
A11: 46027 | B11: Epec Coworking 12/25 | D11: 328793.7 | E11: =+E10+C11-D11 -> 2224839.4 | G11: AGUA CO
A12: 46027 | B12: Alquiler Co - Efectivo | D12: 1747200 | E12: =+E11+C12-D12 -> 477639.38 | G12: ECOGAS CO | H12: 46048 | I12: 46041 | J12: PAGADO
A13: 46041 | B13: Municipalidad Coworking 12/25 | D13: 48153.64 | E13: =+E12+C13-D13 -> 429485.74 | G13: CLARO WIFI CO
A14: 46041 | B14: Rentas Coworking 12/25 | D14: 97810 | E14: =+E13+C14-D14 -> 331675.74 | G14: VITTAL
A15: 46041 | B15: Agua Coworking 12/25 | D15: 151669.36 | E15: =+E14+C15-D15 -> 180006.38
A16: 46041 | B16: Wifi -Claro Coworking 01/26 | D16: 44525.18 | E16: =+E15+C16-D16 -> 135481.2
A17: 46041 | B17: Área Protegida Coworking 12/25 | D17: 62296.05 | E17: =+E16+C17-D17 -> 73185.15
A18: 46041 | B18: Ecogas Coworking 01/26 | D18: 47827.68 | E18: =+E17+C18-D18 -> 25357.47
E19: =+E18+C19-D19 -> 25357.47

Sheet COWORKING FEBRERO 2026
A1: CAJA CHICA MAYRA - COWORKING
A2: SEGUIMIENTO DE CAJA | D2: MES: FEBRERO 2026
A4: FECHA | B4: CONCEPTO | C4: INGRESO | D4: EGRESO | E4: SALDO
E5: 0
A6: 46054 | B6: Saldo Enero 2026 | C6: =+'COWORKING ENERO 2026'!E19 -> 25357.47 | E6: =+E5+C6-D6 -> 25357.47 | G6: SERVICIO | H6: VTO. | I6: PAGO | J6: ESTADO
A7: 46057 | B7: Transf. Matias p/Pagos Co | C7: 569909.81 | E7: =+E6+C7-D7 -> 595267.28 | G7: ALQUILER CO | H7: 46058 | I7: 46062 | J7: PAGADO
A8: 46057 | B8: Transf. Matias p/Pagos Co | C8: 5000 | E8: =+E7+C8-D8 -> 600267.28 | G8: MUNICIPALIDAD CO | H8: 46063 | I8: 46064 | J8: PAGADO
A9: 46057 | B9: Epec Coworking 1/26 | D9: 358347.3 | E9: =+E8+C9-D9 -> 241919.98 | G9: RENTAS CO | H9: 46063 | I9: 46064 | J9: PAGADO
A10: 46059 | B10: Efectivo Juan Pablo p/Pagos Co | C10: 941000 | E10: =+E9+C10-D10 -> 1182920 | G10: EPEC CO | H10: 46055 | I10: 46057 | J10: PAGADO
A11: 46059 | B11: Efectivo Galara p/Pagos Co | C11: 1070000 | E11: =+E10+C11-D11 -> 2252920 | G11: AGUA CO | H11: 46063 | I11: 46064 | J11: PAGADO
A12: 46062 | B12: Alquiler Co - Efectivo | D12: 1747500 | E12: =+E11+C12-D12 -> 505419.98 | G12: ECOGAS CO | H12: 46080 | I12: 46086 | J12: PAGADO
A13: 46064 | B13: Municipalidad Coworking 1/26 | D13: 47792 | E13: =+E12+C13-D13 -> 457627.98 | G13: CLARO WIFI CO | H13: 46071 | I13: 46064 | J13: PAGADO
A14: 46064 | B14: Rentas Coworking 1/26 | D14: 129760 | E14: =+E13+C14-D14 -> 327867.98 | G14: VITTAL | H14: 46064 | I14: 46064 | J14: PAGADO
A15: 46064 | B15: Agua Coworking 1/26 | D15: 153141.43 | E15: =+E14+C15-D15 -> 174726.55
A16: 46064 | B16: Wifi -Claro Coworking 02/26 | D16: 44525.18 | E16: =+E15+C16-D16 -> 130201.37
A17: 46064 | B17: Área Protegida Coworking 1/26 | D17: 64164.93 | E17: =+E16+C17-D17 -> 66036.44
E18: =+E17+C18-D18 -> 66036.44

Sheet COWORKING MARZO 2026 
A1: CAJA CHICA MAYRA - COWORKING
A2: SEGUIMIENTO DE CAJA | D2: MES: MARZO 2026
A4: FECHA | B4: CONCEPTO | C4: INGRESO | D4: EGRESO | E4: SALDO
E5: 0
A6: 46082 | B6: Saldo Febrero 2026 | C6: =+'COWORKING FEBRERO 2026'!E18 -> 66036.44 | E6: =+E5+C6-D6 -> 66036.44 | G6: SERVICIO | H6: VTO. | I6: PAGO | J6: ESTADO
A7: 46083 | B7: Transf. Matias p/Pagos Co | C7: 518714.98 | E7: =+E6+C7-D7 -> 584751.42 | G7: ALQUILER CO | H7: 46086 | I7: 46090 | J7: PAGADO
A8: 46083 | B8: Epec Coworking 2/26 | D8: 362743.2 | E8: =+E7+C8-D8 -> 222008.22 | G8: MUNICIPALIDAD CO | H8: 46091 | I8: 46092 | J8: PAGADO
A9: 46086 | B9: Ecogas Coworking 02/26 | D9: 47764.96 | E9: =+E8+C9-D9 -> 174243.26 | G9: RENTAS CO | H9: 46090 | I9: 46092 | J9: PAGADO
A10: 46086 | B10: Transf. Galara p/Pagos Co | C10: 1172004 | E10: =+E9+C10-D10 -> 1346247.2 | G10: EPEC CO | H10: 46083 | I10: 46083 | J10: PAGADO
A11: 46086 | B11: Efectivo Juan Pablo p/Pagos Co | C11: 912000 | E11: =+E10+C11-D11 -> 2258247.2 | G11: AGUA CO | H11: 46091 | I11: 46092 | J11: PAGADO
A12: 46090 | B12: Alquiler Co - Efectivo | D12: 1747200 | E12: =+E11+C12-D12 -> 511047.23 | G12: ECOGAS CO | H12: 46106 | I12: 46112 | J12: PAGADO
A13: 46092 | B13: Municipalidad Coworking 2/26 | D13: 47843.66 | E13: =+E12+C13-D13 -> 463203.57 | G13: CLARO WIFI CO | H13: 46100 | I13: 46092 | J13: PAGADO
A14: 46092 | B14: Rentas Coworking 2/26 | D14: 129880.7 | E14: =+E13+C14-D14 -> 333322.87 | G14: VITTAL | H14: 46091 | I14: 46098 | J14: PAGADO
A15: 46092 | B15: Agua Coworking 2/26 | D15: 153141.43 | E15: =+E14+C15-D15 -> 180181.44
A16: 46092 | B16: Wifi -Claro Coworking 03/26 | D16: 46071.95 | E16: =+E15+C16-D16 -> 134109.49
A17: 46098 | B17: Área Protegida Coworking 2/26 | D17: 65704.89 | E17: =+E16+C17-D17 -> 68404.6
A18: 46112 | B18: Ecogas Coworking 03/26 | D18: 48884.58 | E18: =+E17+C18-D18 -> 19520.02
A19: 46112 | B19: Transf. Matias p/Pagos Co | C19: 617786.02 | E19: =+E18+C19-D19 -> 637306.04
A20: 46112 | B20: Epec Coworking 3/26 | D20: 402442.6 | E20: =+E19+C20-D20 -> 234863.44
E21: =+E20+C21-D21 -> 234863.44

Sheet COWORKING ABRIL 2026
A1: CAJA CHICA MAYRA - COWORKING
A2: SEGUIMIENTO DE CAJA | D2: MES: ABRIL 2026
A4: FECHA | B4: CONCEPTO | C4: INGRESO | D4: EGRESO | E4: SALDO
E5: 0
A6: 46113 | B6: Saldo Marzo 2026 | C6: =+'COWORKING MARZO 2026 '!E21 -> 234863.44 | E6: =+E5+C6-D6 -> 234863.44 | G6: SERVICIO | H6: VTO. | I6: PAGO | J6: ESTADO
A7: 46118 | B7: Efectivo Juan Pablo p/Pagos Co | C7: 1022300 | E7: =+E6+C7-D7 -> 1257163.4 | G7: ALQUILER CO | H7: 46122 | I7: 46118 | J7: PAGADO
A8: 46118 | B8: Efectivo Galara p/Pagos Co | C8: 1162400 | E8: =+E7+C8-D8 -> 2419563.4 | G8: MUNICIPALIDAD CO | H8: 46122 | I8: 46121 | J8: PAGADO
A9: 46118 | B9: Alquiler Co - Efectivo | D9: 1903200 | E9: =+E8+C9-D9 -> 516363.44 | G9: RENTAS CO | H9: 46119 | I9: 46121 | J9: PAGADO
A10: 46121 | B10: Municipalidad Coworking 3/26 | D10: 47792 | E10: =+E9+C10-D10 -> 468571.44 | G10: EPEC CO | H10: 46112 | I10: 46112 | J10: PAGADO
A11: 46121 | B11: Rentas Coworking 3/26 | D11: 129760 | E11: =+E10+C11-D11 -> 338811.44 | G11: AGUA CO | H11: 46128 | I11: 46121 | J11: PAGADO
A12: 46121 | B12: Agua Coworking 3/26 | D12: 153141.43 | E12: =+E11+C12-D12 -> 185670.01 | G12: ECOGAS CO | H12: 46139 | I12: 46121 | J12: PAGADO
A13: 46121 | B13: Wifi -Claro Coworking 04/26 | D13: 48960.76 | E13: =+E12+C13-D13 -> 136709.25 | G13: CLARO WIFI CO | H13: 46128 | I13: 46121 | J13: PAGADO
A14: 46121 | B14: Área Protegida Coworking 3/26 | D14: 67413.22 | E14: =+E13+C14-D14 -> 69296.03 | G14: VITTAL | H14: 46122 | I14: 46121 | J14: PAGADO
A15: 46141 | B15: Ecogas Coworking 04/26 | D15: 29702.17 | E15: =+E14+C15-D15 -> 39593.86
A16: 46141 | B16: Transferencia Juan Pablo p/pago Epec | C16: 408031.5 | E16: =+E15+C16-D16 -> 447625.36
A17: 46141 | B17: Epec Coworking 4/26 | D17: 408031.5 | E17: =+E16+C17-D17 -> 39593.86
E18: =+E17+C18-D18 -> 39593.86

Sheet COWORKING MAYO 2026
A1: CAJA CHICA MAYRA - COWORKING
A2: SEGUIMIENTO DE CAJA | D2: MES: MAYO 2026
A4: FECHA | B4: CONCEPTO | C4: INGRESO | D4: EGRESO | E4: SALDO
E5: 0
A6: 46143 | B6: Saldo Abril 2026 | C6: =+'COWORKING ABRIL 2026'!E18 -> 39593.86 | E6: =+E5+C6-D6 -> 39593.86 | G6: SERVICIO | H6: VTO. | I6: PAGO | J6: ESTADO
A7: 46147 | B7: Transferencia Adrian por saldo Juan Pablo + Galara | C7: 1781657.2 | E7: =+E6+C7-D7 -> 1821251 | G7: ALQUILER CO | H7: 46152 | I7: 46153 | J7: PAGADO
A8: 46148 | B8: Municipalidad Coworking 4/26 | D8: 47792 | E8: =+E7+C8-D8 -> 1773459 | G8: MUNICIPALIDAD CO | H8: 46153 | I8: 46147 | J8: PAGADO
A9: 46148 | B9: Rentas Coworking 4/26 | D9: 129760 | E9: =+E8+C9-D9 -> 1643699 | G9: RENTAS CO | H9: 46148 | I9: 46147 | J9: PAGADO
A10: 46148 | B10: Agua Coworking 4/26 | D10: 162212.97 | E10: =+E9+C10-D10 -> 1481486.1 | G10: EPEC CO | H10: 46141 | I10: 46141 | J10: PAGADO
A11: 46148 | B11: Wifi -Claro Coworking 5/26 | D11: 50417.63 | E11: =+E10+C11-D11 -> 1431068.4 | G11: AGUA CO | H11: 46150 | I11: 46147 | J11: PAGADO
A12: 46148 | B12: Área Protegida Coworking 4/26 | D12: 69570.44 | E12: =+E11+C12-D12 -> 1361498 | G12: ECOGAS CO | H12: 46168 | I12: 46168 | J12: PAGADO
A13: 46150 | B13: Transf. Matias p/Pagos Co | C13: 611407.34 | E13: =+E12+C13-D13 -> 1972905.3 | G13: CLARO WIFI CO | H13: 46160 | I13: 46147 | J13: PAGADO
A14: 46153 | B14: Alquiler Co - Efectivo | D14: 1903200 | E14: =+E13+C14-D14 -> 69705.34 | G14: VITTAL | H14: 46147 | I14: 46148 | J14: PAGADO
A15: 46168 | B15: Ecogas Coworking 05/26 | D15: 33900 | E15: =+E14+C15-D15 -> 35805.34
A16: 46168 | B16: Transf. Lu por Juan Pablo | C16: 1063963.6 | E16: =+E15+C16-D16 -> 1099768.9
A17: 46170 | B17: Epec Coworking 5/26 | D17: 450487.6 | E17: =+E16+C17-D17 -> 649281.33
E18: =+E17+C18-D18 -> 649281.33

Sheet COWORKING JUNIO 2026
A1: CAJA CHICA MAYRA - COWORKING
A2: SEGUIMIENTO DE CAJA | D2: MES: JUNIO 2026
A4: FECHA | B4: CONCEPTO | C4: INGRESO | D4: EGRESO | E4: SALDO
E5: 0
A6: 46174 | B6: Saldo Mayo 2026 | C6: =+'COWORKING MAYO 2026'!E18 -> 649281.33 | E6: =+E5+C6-D6 -> 649281.33 | G6: SERVICIO | H6: VTO. | I6: PAGO | J6: ESTADO
A7: 46178 | B7: Transf. Matias p/Pagos Co | C7: 546178.75 | E7: =+E6+C7-D7 -> 1195460.1 | G7: ALQUILER CO | H7: 46183 | I7: 46182 | J7: PAGADO
A8: 46178 | B8: Efectivo Adrian p/Pagos Co | C8: 1205000 | E8: =+E7+C8-D8 -> 2400460.1 | G8: MUNICIPALIDAD CO | I8: 46182 | J8: PAGADO
A9: 46182 | B9: Alquiler Co - Efectivo | D9: 1903200 | E9: =+E8+C9-D9 -> 497260.08 | G9: RENTAS CO | I9: 46182 | J9: PAGADO
A10: 46182 | B10: Municipalidad Coworking 5/26 | D10: 47792 | E10: =+E9+C10-D10 -> 449468.08 | G10: EPEC CO | H10: 46170 | I10: 46170 | J10: PAGADO
A11: 46182 | B11: Rentas Coworking 5/26 | D11: 90830 | E11: =+E10+C11-D11 -> 358638.08 | G11: AGUA CO | I11: 46182 | J11: PAGADO
A12: 46182 | B12: Agua Coworking 5/26 | D12: 163667.91 | E12: =+E11+C12-D12 -> 194970.17 | G12: ECOGAS CO | H12: 46199 | I12: 46203 | J12: PAGADO
A13: 46182 | B13: Wifi -Claro Coworking 6/26 | D13: 52164.19 | E13: =+E12+C13-D13 -> 142805.98 | G13: CLARO WIFI CO | I13: 46182 | J13: PAGADO
A14: 46182 | B14: Área Protegida Coworking 5/26 | D14: 71587.98 | E14: =+E13+C14-D14 -> 71218 | G14: VITTAL | I14: 46182 | J14: PAGADO
A15: 46203 | B15: Ecogas Coworking 06/26 | D15: 50110.76 | E15: =+E14+C15-D15 -> 21107.24
E16: =+E15+C16-D16 -> 21107.24

Sheet COWORKING JULIO 2026
A1: CAJA CHICA MAYRA - COWORKING
A2: SEGUIMIENTO DE CAJA | D2: MES: JULIO 2026
A4: FECHA | B4: CONCEPTO | C4: INGRESO | D4: EGRESO | E4: SALDO
E5: 0
A6: 46204 | B6: Saldo Junio 2026 | C6: =+'COWORKING JUNIO 2026'!E16 -> 21107.24 | E6: =+E5+C6-D6 -> 21107.24 | G6: SERVICIO | H6: VTO. | I6: PAGO | J6: ESTADO
A7: 46206 | B7: Transf. Matias p/Pagos Co | C7: 562888.74 | E7: =+E6+C7-D7 -> 583995.98 | G7: ALQUILER CO | H7: 46213 | I7: 46211 | J7: PAGADO
A8: 46206 | B8: Epec Coworking 6/26 | D8: 317541 | E8: =+E7+C8-D8 -> 266454.98 | G8: MUNICIPALIDAD CO
A9: 46209 | B9: Transf. Adrian p/Pagos Co | C9: 1210500 | E9: =+E8+C9-D9 -> 1476955 | G9: RENTAS CO
A10: 46209 | B10: Transf. Juan Pablo p/Pagos Co | C10: 1068357.6 | E10: =+E9+C10-D10 -> 2545312.5 | G10: EPEC CO | H10: 46202 | I10: 46206 | J10: PAGADO
A11: 46211 | B11: Alquiler Co - Transferencia | D11: 2036000 | E11: =+E10+C11-D11 -> 509312.54 | G11: AGUA CO
A12: 46230 | B12: Municipalidad Coworking 6/26 | D12: 55137 | E12: =+E11+C12-D12 -> 454175.54 | G12: ECOGAS CO
A13: 46230 | B13: Rentas Coworking 6/26 | D13: 91990 | E13: =+E12+C13-D13 -> 362185.54 | G13: CLARO WIFI CO
A14: 46230 | B14: Agua Coworking 6/26 | D14: 168335.39 | E14: =+E13+C14-D14 -> 193850.15 | G14: VITTAL
A15: 46230 | B15: Wifi -Claro Coworking 7/26 | D15: 54192.23 | E15: =+E14+C15-D15 -> 139657.92
A16: 46230 | B16: Área Protegida Coworking 6/26 | D16: 72948.16 | E16: =+E15+C16-D16 -> 66709.76
A17: 46231 | B17: Ecogas Coworking 07/26 | D17: 51054.34 | E17: =+E16+C17-D17 -> 15655.42
A18: 46231 | B18: Transf. Matias p/Pagos Co | C18: 625158.87 | E18: =+E17+C18-D18 -> 640814.29
A19: 46231 | B19: Epec Coworking 7/26 | D19: 479036.5 | E19: =+E18+C19-D19 -> 161777.79
E20: =+E19+C20-D20 -> 161777.79

Sheet COWORKING AGOSTO 2026
A1: CAJA CHICA MAYRA - COWORKING
A2: SEGUIMIENTO DE CAJA | D2: MES: AGOSTO 2026
A4: FECHA | B4: CONCEPTO | C4: INGRESO | D4: EGRESO | E4: SALDO
E5: 0
A6: 46235 | B6: Saldo Julio 2026 | C6: =+'COWORKING JULIO 2026'!E20 -> 161777.79 | E6: =+E5+C6-D6 -> 161777.79 | G6: SERVICIO | H6: VTO. | I6: PAGO | J6: ESTADO
A7: 46238 | B7: Efectivo Juan Pablo p/Pagos Co | C7: 1122000 | E7: =+E6+C7-D7 -> 1283777.8 | G7: ALQUILER CO
A8: 46239 | B8: Efectivo Adrian p/Pagos Co | C8: 1273000 | E8: =+E7+C8-D8 -> 2556777.8 | G8: MUNICIPALIDAD CO
A9: 46240 | B9: Alquiler Co - Efectivo | D9: 2036000 | E9: =+E8+C9-D9 -> 520777.79 | G9: RENTAS CO
A10: 46247 | B10: Municipalidad Coworking 7/26 | D10: 54491.14 | E10: =+E9+C10-D10 -> 466286.65 | G10: EPEC CO
A11: 46247 | B11: Rentas Coworking 7/26 | D11: 91080 | E11: =+E10+C11-D11 -> 375206.65 | G11: AGUA CO
A12: 46247 | B12: Agua Coworking 7/26 | D12: 178536.24 | E12: =+E11+C12-D12 -> 196670.41 | G12: ECOGAS CO
A13: 46247 | B13: Wifi -Claro Coworking 8/26 | D13: 56911.77 | E13: =+E12+C13-D13 -> 139758.64 | G13: CLARO WIFI CO
A14: 46247 | B14: Área Protegida Coworking 7/26 | D14: 74334.16 | E14: =+E13+C14-D14 -> 65424.48 | G14: VITTAL
E15: =+E14+C15-D15 -> 65424.48
