Workbook

Sheet RESUMEN
C5: EVENTO | D5: TURISMO CARRETERA (TC) - OSCAR CABALEN
C7: FECHA DEL EVENTO | D7: 30 Y 31 DE MAYO 2026
A13: CONCILIACION | B13: CATEGORIA | C13: DEBE | D13: HABER | E13: SALDO | G13: RESUMEN GENERAL EVENTO - PN
E14: 0
A15: TOTAL EGRESOS EVENTO TC | B15: 1 | C15: =+'EG-TC 1'!M105 -> -10 | D15: 0 | E15: =+E14+C15+D15 -> -10 | G15: INGRESOS TOTALES | H15: =+D26 -> 280
A16: TOTAL EGRESOS SOCIETARIOS | B16: 2 | C16: =+'EG-RET SOC 2'!M75 -> -10 | D16: 0 | E16: =+E15+C16+D16 -> -20
A17: TOTAL EGRESOS EXTRAORDINARIOS TC | B17: 3 | C17: =+'EG-EXTRA 3'!M47 -> -10 | D17: 0 | E17: =+E16+C17+D17 -> -30 | G17: EGRESOS TOTALES | H17: =+C26 -> -52
A18: TOTAL EGRESOS IMPUESTOS - (DEVOLUCIONES + DESCONOCIMIENTO) | B18: 4 | C18: =+'EG-IMP 4'!$M$30 -> -12 | D18: 0 | E18: =+E17+C18+D18 -> -42
A19: TOTAL PRESTAMOS | B19: 5 | C19: =+'EG-PREST 5'!M27 -> -10 | D19: =+'ING TICKETS 6'!M61 -> 0 | E19: =+E18+C19+D19 -> -52 | G19: SALDO | H19: =+H15+H17 -> 228
A20: TOTAL INGRESOS TICKETS | B20: 6 | D20: =+'ING TICKETS 6'!M60 -> 200 | E20: =+E19+C20+D20 -> 148
A21: TOTAL SPONSORS | B21: 7 | D21: =+'ING SPON 7'!M37 -> 50 | E21: =+E20+C21+D21 -> 198
A22: TOTAL CORPORATIVO (AGUS) | B22: 8 | D22: =+'ING CORP 8'!M40 -> 10 | E22: =+E21+C22+D22 -> 208 | G22: DISTRIBUCION SOCIOS
A23: TOTAL COMIDA BEBIDA - GASTRONOMICO | B23: 9 | D23: =+'ING GASTRO 9'!M38 -> 10 | E23: =+E22+C23+D23 -> 218 | G23: SOCIO 1 (50%) | H23: =+H19/2 -> 114
A24: TOTAL SERVICE CHARGE | B24: 10 | D24: =+'ING SERV CHARGE 10'!M26 -> 10 | G24: SOCIO 2 (50%) | H24: =+H19/2 -> 114
C26: =SUM(C15:C25) -> -52 | D26: =SUM(D15:D25) -> 280 | E26: =+D26+C26 -> 228

Sheet EG-TC 1
F3: EVENTO | G3: TURISMO CARRETERA (TC) - OSCAR CABALEN
F5: FECHA DEL EVENTO | G5: 30 Y 31 DE MAYO 2026
B12: FECHA | C12: CONCEPTO | D12: DESCRIPCION | K12: DEBE | L12: HABER | M12: SALDO
M13: 0
A14: 1 | B14: 46152 | C14: test eg | D14: testing importador | K14: 10 | L14: 0 | M14: =+M13-K14+L14 -> -10
A15: 2 | K15: 0 | L15: 0 | M15: =+M14-K15+L15 -> -10
A16: 3 | K16: 0 | L16: 0 | M16: =+M15-K16+L16 -> -10
A17: 4 | K17: 0 | L17: 0 | M17: =+M16-K17+L17 -> -10
A18: 5 | K18: 0 | L18: 0 | M18: =+M17-K18+L18 -> -10
A19: 6 | K19: 0 | L19: 0 | M19: =+M18-K19+L19 -> -10
A20: 7 | K20: 0 | L20: 0 | M20: =+M19-K20+L20 -> -10
A21: 8 | K21: 0 | L21: 0 | M21: =+M20-K21+L21 -> -10
A22: 9 | K22: 0 | L22: 0 | M22: =+M21-K22+L22 -> -10
A23: 10 | K23: 0 | L23: 0 | M23: =+M22-K23+L23 -> -10
A24: 11 | K24: 0 | L24: 0 | M24: =+M23-K24+L24 -> -10
A25: 12 | K25: 0 | L25: 0 | M25: =+M24-K25+L25 -> -10
A26: 13 | K26: 0 | L26: 0 | M26: =+M25-K26+L26 -> -10
... A101: 88 | K101: 0 | L101: 0 | M101: =+M100-K101+L101 -> -10
K102: 0 | L102: 0 | M102: =+M101-K102+L102 -> -10
K103: 0 | L103: 0 | M103: =+M102-K103+L103 -> -10
K104: 0 | L104: 0 | M104: =+M103-K104+L104 -> -10
B105: TOTALES | K105: =SUM(K14:K104) -> 10 | M105: =+M104 -> -10

Sheet EG-RET SOC 2
F8: EVENTO | G8: TURISMO CARRETERA (TC) - OSCAR CABALEN
F10: FECHA DEL EVENTO | G10: 30 Y 31 DE MAYO 2026
B15: FECHA | C15: CONCEPTO | D15: DESCRIPCION | K15: DEBE | L15: HABER | M15: SALDO
M16: 0
A17: 1 | K17: 0 | L17: 0 | M17: =+M16-K17+L17 -> 0
A18: 2 | K18: 0 | L18: 0 | M18: =+M17-K18+L18 -> 0
A19: 3 | K19: 0 | L19: 0 | M19: =+M18-K19+L19 -> 0
A20: 4 | K20: 0 | L20: 0 | M20: =+M19-K20+L20 -> 0
A21: 5 | K21: 0 | L21: 0 | M21: =+M20-K21+L21 -> 0
A22: 6 | K22: 0 | L22: 0 | M22: =+M21-K22+L22 -> 0
A23: 7 | K23: 0 | L23: 0 | M23: =+M22-K23+L23 -> 0
A24: 8 | K24: 0 | L24: 0 | M24: =+M23-K24+L24 -> 0
A25: 9 | K25: 0 | L25: 0 | M25: =+M24-K25+L25 -> 0
A26: 10 | K26: 0 | L26: 0 | M26: =+M25-K26+L26 -> 0
A27: 11 | K27: 0 | L27: 0 | M27: =+M26-K27+L27 -> 0
A28: 12 | K28: 0 | L28: 0 | M28: =+M27-K28+L28 -> 0
... A54: 38 | K54: 0 | L54: 0 | M54: =+M53-K54+L54 -> 0
A55: 39 | D55: testeando el importer eg ret soc 2 | K55: 10 | L55: 0 | M55: =+M54-K55+L55 -> -10
A56: 40 | K56: 0 | L56: 0 | M56: =+M55-K56+L56 -> -10
A57: 41 | K57: 0 | L57: 0 | M57: =+M56-K57+L57 -> -10
A58: 42 | K58: 0 | L58: 0 | M58: =+M57-K58+L58 -> -10
A59: 43 | K59: 0 | L59: 0 | M59: =+M58-K59+L59 -> -10
A60: 44 | K60: 0 | L60: 0 | M60: =+M59-K60+L60 -> -10
A61: 45 | K61: 0 | L61: 0 | M61: =+M60-K61+L61 -> -10
A62: 46 | K62: 0 | L62: 0 | M62: =+M61-K62+L62 -> -10
A63: 47 | K63: 0 | L63: 0 | M63: =+M62-K63+L63 -> -10
A64: 48 | K64: 0 | L64: 0 | M64: =+M63-K64+L64 -> -10
A65: 49 | K65: 0 | L65: 0 | M65: =+M64-K65+L65 -> -10
A66: 50 | K66: 0 | L66: 0 | M66: =+M65-K66+L66 -> -10
A67: 51 | K67: 0 | L67: 0 | M67: =+M66-K67+L67 -> -10
... A72: 56 | K72: 0 | L72: 0 | M72: =+M71-K72+L72 -> -10
K73: 0 | L73: 0 | M73: =+M72-K73+L73 -> -10
K74: 0 | L74: 0 | M74: =+M73-K74+L74 -> -10
B75: TOTALES | K75: =SUM(K16:K74) -> 10 | L75: =SUM(L16:L74) -> 0 | M75: =+M74 -> -10

Sheet EG-EXTRA 3
I4: EVENTO | J4: TURISMO CARRETERA (TC) - OSCAR CABALEN
F5: EVENTO | G5: TURISMO CARRETERA (TC) - OSCAR CABALEN
I6: FECHA DEL EVENTO | J6: 30 Y 31 DE MAYO 2026 | L6: 30 Y 31 DE MAYO 2026
F7: FECHA DEL EVENTO | G7: 30 Y 31 DE MAYO 2026
B12: FECHA | C12: CONCEPTO | D12: DESCRIPCION | K12: DEBE | L12: HABER | M12: SALDO
M13: 0
A14: 1 | B14: 46152 | C14: testeando el importer eg extra 3 | K14: 10 | L14: 0 | M14: =+M13-K14+L14 -> -10
A15: 2 | K15: 0 | L15: 0 | M15: =+M14-K15+L15 -> -10
A16: 3 | K16: 0 | L16: 0 | M16: =+M15-K16+L16 -> -10
A17: 4 | K17: 0 | L17: 0 | M17: =+M16-K17+L17 -> -10
A18: 5 | K18: 0 | L18: 0 | M18: =+M17-K18+L18 -> -10
A19: 6 | K19: 0 | L19: 0 | M19: =+M18-K19+L19 -> -10
A20: 7 | K20: 0 | L20: 0 | M20: =+M19-K20+L20 -> -10
A21: 8 | K21: 0 | L21: 0 | M21: =+M20-K21+L21 -> -10
A22: 9 | K22: 0 | L22: 0 | M22: =+M21-K22+L22 -> -10
A23: 10 | K23: 0 | L23: 0 | M23: =+M22-K23+L23 -> -10
A24: 11 | K24: 0 | L24: 0 | M24: =+M23-K24+L24 -> -10
A25: 12 | K25: 0 | L25: 0 | M25: =+M24-K25+L25 -> -10
A26: 13 | K26: 0 | L26: 0 | M26: =+M25-K26+L26 -> -10
... A43: 30 | K43: 0 | L43: 0 | M43: =+M42-K43+L43 -> -10
K44: 0 | L44: 0 | M44: =+M43-K44+L44 -> -10
K45: 0 | L45: 0 | M45: =+M44-K45+L45 -> -10
K46: 0 | L46: 0 | M46: =+M45-K46+L46 -> -10
B47: TOTALES | K47: =SUM(K14:K46) -> 10 | M47: =+M46 -> -10
C54: ECHEQS EMITIDOS ENJOY - BANCOR CTA TC
C55: N° ECHEQ | D55: RAZON SOCIAL | E55: DETALLE | F55: IMPORTE PAGADO | G55: IMPORTE PENDIENTE | H55: FECHA EMISION
C56: 1 | D56: VERONICA GLORIA HADAC | E56: HONORARIOS ABOGADA - ARREGLO SADAIC - JUICIO 2025 | F56: -924800 | G56: 0 | H56: 46093
C57: 2 | D57: SADAIC - SOCIEDAD ARG. DE AUTORES Y COMPOSITORES | E57: JUICIO TOTAL - ARREGLO SADAIC - JUICIO 2025 | F57: -1000000 | G57: 0 | H57: 46093
C58: 3 | D58: SADAIC - SOCIEDAD ARG. DE AUTORES Y COMPOSITORES | E58: JUICIO TOTAL - ARREGLO SADAIC - JUICIO 2025 | G58: 1000000 | H58: 46093
C59: 4 | D59: SADAIC - SOCIEDAD ARG. DE AUTORES Y COMPOSITORES | E59: JUICIO TOTAL - ARREGLO SADAIC - JUICIO 2025 | G59: 1000000 | H59: 46093
C60: 5 | D60: SADAIC - SOCIEDAD ARG. DE AUTORES Y COMPOSITORES | E60: JUICIO TOTAL - ARREGLO SADAIC - JUICIO 2025 | G60: 1000000 | H60: 46093
D72: TOTAL | F72: =SUM(F56:F70) -> -1924800 | G72: =SUM(G56:G71) -> 3000000
F74: TOTAL GRAL. | G74: =+G72-F72 -> 4924800

Sheet EG-IMP 4
F6: EVENTO | G6: TURISMO CARRETERA (TC) - OSCAR CABALEN
F8: FECHA DEL EVENTO | G8: 30 Y 31 DE MAYO 2026
B12: FECHA | C12: CONCEPTO | D12: DESCRIPCION | E12: CATEGORIA | F12: MOTIVO | G12: DE DONDE SALE | H12: NETO | I12: IVA | J12: BRUTO | K12: DEBE | L12: HABER | M12: SALDO
M13: 0
A14: 1 | C14: IMUESTOS | D14: PAYWAY - COSTOS FINANCIEROS | E14: 4 | K14: 10 | L14: 0 | M14: =+M13-K14+L14 -> -10 | P14: IMPUESTOS
A15: 2 | C15: IMUESTOS | D15: PAYWAY - IMPUESTOS | E15: 4 | K15: 0 | L15: 0 | M15: =+M14-K15+L15 -> -10 | O15: PAYWAY | P15: =+K14+K15+K16 -> 10
A16: 3 | C16: PERDIDA | D16: PAYWAY - CONTRACARGOS | E16: 4 | K16: 0 | L16: 0 | M16: =+M15-K16+L16 -> -10 | O16: REBA | P16: =+K17+K18+K19+K20 -> 0
A17: 4 | C17: IMUESTOS | D17: REBA - MANTENIMIENTO DE CUENTA + IVA SOBRE COMISIONES | E17: 4 | K17: 0 | L17: 0 | M17: =+M16-K17+L17 -> -10 | O17: AUTOENTRADA | P17: =+K21+K22 -> 0
A18: 5 | C18: IMUESTOS | D18: REBA - IMP. LEY 25413 S/CREDITOS | E18: 4 | K18: 0 | L18: 0 | M18: =+M17-K18+L18 -> -10 | O18: =+D23 -> IVA | P18: =+K23 -> 0
A19: 6 | C19: IMUESTOS | D19: REBA - IMP. LEY 25413 S/DÉBITOS | E19: 4 | K19: 0 | L19: 0 | M19: =+M18-K19+L19 -> -10 | O19: =+D24 -> INGRESOS BRUTOS | P19: =+K24 -> 0
A20: 7 | C20: IMUESTOS | D20: REBA - SIRCREB | E20: 4 | K20: 0 | L20: 0 | M20: =+M19-K20+L20 -> -10 | O20: =+D25 -> MUNICIPALIDAD | P20: =+K25 -> 0
A21: 8 | C21: AUTOENTRADA | D21: AUTOENTRADA - SERVICE CHARGE | E21: 4 | K21: 0 | L21: 0 | M21: =+M20-K21+L21 -> -10 | O21: =+D26 -> GANANCIAS | P21: =+K26 -> 0
A22: 9 | C22: AUTOENTRADA | D22: AUTOENTRADA - MEDIOS DE PAGO | E22: 4 | K22: 0 | L22: 0 | M22: =+M21-K22+L22 -> -10
A23: 10 | C23: IMPUESTOS | D23: IVA | E23: 4 | K23: 0 | L23: 0 | M23: =+M22-K23+L23 -> -10
A24: 11 | C24: IMPUESTOS | D24: INGRESOS BRUTOS | E24: 4 | K24: 0 | L24: 0 | M24: =+M23-K24+L24 -> -10
A25: 12 | C25: IMPUESTOS | D25: MUNICIPALIDAD | E25: 4 | K25: 0 | L25: 0 | M25: =+M24-K25+L25 -> -10
A26: 13 | C26: IMPUESTOS | D26: GANANCIAS | E26: 4 | K26: 0 | L26: 0 | M26: =+M25-K26+L26 -> -10
K27: 2 | L27: 0 | M27: =+M26-K27+L27 -> -12
K28: 0 | L28: 0 | M28: =+M27-K28+L28 -> -12
K29: 0 | L29: 0 | M29: =+M28-K29+L29 -> -12
B30: TOTALES | K30: =SUM(K14:K29) -> 12 | M30: =+M29 -> -12

Sheet EG-PREST 5
I4: EVENTO | J4: TURISMO CARRETERA (TC) - OSCAR CABALEN
F5: EVENTO | G5: TURISMO CARRETERA (TC) - OSCAR CABALEN
I6: FECHA DEL EVENTO | J6: 30 Y 31 DE MAYO 2026 | L6: 30 Y 31 DE MAYO 2026
F7: FECHA DEL EVENTO | G7: 30 Y 31 DE MAYO 2026
B12: FECHA | C12: CONCEPTO | D12: DESCRIPCION | K12: DEBE | L12: HABER | M12: SALDO
M13: 0
A14: 1 | B14: 46152 | C14: testeando el importador eg-prest | D14: testeando el importador eg-prest | K14: 10 | L14: 0 | M14: =+M13-K14+L14 -> -10
A15: 2 | K15: 0 | L15: 0 | M15: =+M14-K15+L15 -> -10
A16: 3 | K16: 0 | L16: 0 | M16: =+M15-K16+L16 -> -10
A17: 4 | K17: 0 | L17: 0 | M17: =+M16-K17+L17 -> -10
A18: 5 | K18: 0 | L18: 0 | M18: =+M17-K18+L18 -> -10
A19: 6 | K19: 0 | L19: 0 | M19: =+M18-K19+L19 -> -10
A20: 7 | K20: 0 | L20: 0 | M20: =+M19-K20+L20 -> -10
A21: 8 | K21: 0 | L21: 0 | M21: =+M20-K21+L21 -> -10
A22: 9 | K22: 0 | L22: 0 | M22: =+M21-K22+L22 -> -10
A23: 10 | K23: 0 | L23: 0 | M23: =+M22-K23+L23 -> -10
K24: 0 | L24: 0 | M24: =+M23-K24+L24 -> -10
K25: 0 | L25: 0 | M25: =+M24-K25+L25 -> -10
K26: 0 | L26: 0 | M26: =+M25-K26+L26 -> -10
B27: TOTALES | K27: =SUM(K14:K26) -> 10 | M27: =+M26 -> -10

Sheet ING TICKETS 6
F4: EVENTO | G4: TURISMO CARRETERA (TC) - OSCAR CABALEN | I4: EVENTO | J4: TURISMO CARRETERA (TC) - OSCAR CABALEN
F6: FECHA DEL EVENTO | G6: 30 Y 31 DE MAYO 2026 | I6: FECHA DEL EVENTO | J6: 30 Y 31 DE MAYO 2026 | L6: 30 Y 31 DE MAYO 2026
B12: FECHA | C12: DESCRIPCION | K12: DEBE | L12: HABER | M12: SALDO
M13: 0
A14: 1 | B14: 46152 | C14: testeando el importador ing tickets | K14: 0 | L14: 200 | M14: =+M13-K14+L14 -> 200
A15: 2 | K15: 0 | L15: 0 | M15: =+M14-K15+L15 -> 200
A16: 3 | K16: 0 | L16: 0 | M16: =+M15-K16+L16 -> 200
A17: 4 | K17: 0 | L17: 0 | M17: =+M16-K17+L17 -> 200
A18: 5 | K18: 0 | L18: 0 | M18: =+M17-K18+L18 -> 200
A19: 6 | K19: 0 | L19: 0 | M19: =+M18-K19+L19 -> 200
A20: 7 | K20: 0 | L20: 0 | M20: =+M19-K20+L20 -> 200
A21: 8 | K21: 0 | L21: 0 | M21: =+M20-K21+L21 -> 200
A22: 9 | K22: 0 | L22: 0 | M22: =+M21-K22+L22 -> 200
A23: 10 | K23: 0 | L23: 0 | M23: =+M22-K23+L23 -> 200
A24: 11 | K24: 0 | L24: 0 | M24: =+M23-K24+L24 -> 200
A25: 12 | K25: 0 | L25: 0 | M25: =+M24-K25+L25 -> 200
A26: 13 | K26: 0 | L26: 0 | M26: =+M25-K26+L26 -> 200
... A56: 43 | K56: 0 | L56: 0 | M56: =+M55-K56+L56 -> 200
K57: 0 | L57: 0 | M57: =+M56-K57+L57 -> 200
K58: 0 | L58: 0 | M58: =+M57-K58+L58 -> 200
K59: 0 | L59: 0 | M59: =+M58-K59+L59 -> 200
B60: TOTALES | K60: =SUM(K14:K59) -> 0 | L60: =SUM(L14:L59) -> 200 | M60: =+M59 -> 200

Sheet ING SPON 7
F4: EVENTO | G4: TURISMO CARRETERA (TC) - OSCAR CABALEN | I4: EVENTO | J4: TURISMO CARRETERA (TC) - OSCAR CABALEN
F6: FECHA DEL EVENTO | G6: 30 Y 31 DE MAYO 2026 | I6: FECHA DEL EVENTO | J6: 30 Y 31 DE MAYO 2026 | L6: 30 Y 31 DE MAYO 2026
B12: FECHA | C12: DESCRIPCION | K12: DEBE | L12: HABER | M12: SALDO
M13: 0
A14: 1 | B14: 46152 | C14: sponsor 1 | K14: 0 | L14: 50 | M14: =+M13-K14+L14 -> 50
A15: 2 | K15: 0 | L15: 0 | M15: =+M14-K15+L15 -> 50
A16: 3 | K16: 0 | L16: 0 | M16: =+M15-K16+L16 -> 50
A17: 4 | K17: 0 | L17: 0 | M17: =+M16-K17+L17 -> 50
K18: 0 | L18: 0 | M18: =+M17-K18+L18 -> 50
K19: 0 | L19: 0 | M19: =+M18-K19+L19 -> 50
K20: 0 | L20: 0 | M20: =+M19-K20+L20 -> 50
K21: 0 | L21: 0 | M21: =+M20-K21+L21 -> 50
K22: 0 | L22: 0 | M22: =+M21-K22+L22 -> 50
K23: 0 | L23: 0 | M23: =+M22-K23+L23 -> 50
K24: 0 | L24: 0 | M24: =+M23-K24+L24 -> 50
K25: 0 | L25: 0 | M25: =+M24-K25+L25 -> 50
K26: 0 | L26: 0 | M26: =+M25-K26+L26 -> 50
K27: 0 | L27: 0 | M27: =+M26-K27+L27 -> 50
K28: 0 | L28: 0 | M28: =+M27-K28+L28 -> 50
K29: 0 | L29: 0 | M29: =+M28-K29+L29 -> 50
... K36: 0 | L36: 0 | M36: =+M35-K36+L36 -> 50
B37: TOTALES | K37: =SUM(K14:K36) -> 0 | L37: =SUM(L14:L36) -> 50 | M37: =+M36 -> 50

Sheet ING CORP 8
I4: EVENTO | J4: TURISMO CARRETERA (TC) - OSCAR CABALEN
F5: EVENTO | G5: TURISMO CARRETERA (TC) - OSCAR CABALEN
I6: FECHA DEL EVENTO | J6: 30 Y 31 DE MAYO 2026 | L6: 30 Y 31 DE MAYO 2026
F7: FECHA DEL EVENTO | G7: 30 Y 31 DE MAYO 2026
B12: FECHA | C12: DESCRIPCION | K12: DEBE | L12: HABER | M12: SALDO
L13: 0 | M13: 0
A14: 1 | B14: 46152 | C14: ing corp | K14: 0 | L14: 10 | M14: =+M13-K14+L14 -> 10
A15: 2 | K15: 0 | L15: 0 | M15: =+M14-K15+L15 -> 10
A16: 3 | K16: 0 | L16: 0 | M16: =+M15-K16+L16 -> 10
A17: 4 | K17: 0 | L17: 0 | M17: =+M16-K17+L17 -> 10
A18: 5 | K18: 0 | L18: 0 | M18: =+M17-K18+L18 -> 10
A19: 6 | K19: 0 | L19: 0 | M19: =+M18-K19+L19 -> 10
A20: 7 | K20: 0 | L20: 0 | M20: =+M19-K20+L20 -> 10
A21: 8 | K21: 0 | L21: 0 | M21: =+M20-K21+L21 -> 10
A22: 9 | K22: 0 | L22: 0 | M22: =+M21-K22+L22 -> 10
A23: 10 | K23: 0 | L23: 0 | M23: =+M22-K23+L23 -> 10
A24: 11 | K24: 0 | L24: 0 | M24: =+M23-K24+L24 -> 10
A25: 12 | K25: 0 | L25: 0 | M25: =+M24-K25+L25 -> 10
A26: 13 | K26: 0 | L26: 0 | M26: =+M25-K26+L26 -> 10
... A36: 23 | K36: 0 | L36: 0 | M36: =+M35-K36+L36 -> 10
K37: 0 | L37: 0 | M37: =+M36-K37+L37 -> 10
K38: 0 | L38: 0 | M38: =+M37-K38+L38 -> 10
K39: 0 | L39: 0 | M39: =+M38-K39+L39 -> 10
B40: TOTALES | K40: =SUM(K14:K39) -> 0 | L40: =SUM(L14:L39) -> 10 | M40: =+M39 -> 10

Sheet ING GASTRO 9
F4: EVENTO | G4: TURISMO CARRETERA (TC) - OSCAR CABALEN | J4: TURISMO CARRETERA (TC) - OSCAR CABALEN
F6: FECHA DEL EVENTO | G6: 30 Y 31 DE MAYO 2026 | J6: 30 Y 31 DE MAYO 2026 | L6: 30 Y 31 DE MAYO 2026
B12: FECHA | C12: DESCRIPCION | K12: DEBE | L12: HABER | M12: SALDO
M13: 0
A14: 1 | B14: 46152 | C14: ingreso gastro | K14: 0 | L14: 10 | M14: 0
A15: 2 | K15: 0 | L15: 0 | M15: 0
A16: 3 | K16: 0 | L16: 0 | M16: 0
A17: 4 | K17: 0 | L17: 0 | M17: 0
A18: 5 | K18: 0 | L18: 0 | M18: 0
A19: 6 | K19: 0 | L19: 0 | M19: 0
A20: 7 | K20: 0 | L20: 0 | M20: 0
A21: 8 | K21: 0 | L21: 0 | M21: 0
A22: 9 | K22: 0 | L22: 0 | M22: 0
A23: 10 | K23: 0 | L23: 0 | M23: 0
A24: 11 | K24: 0 | L24: 0 | M24: 0
A25: 12 | K25: 0 | L25: 0 | M25: 0
A26: 13 | K26: 0 | L26: 0 | M26: 0
... A35: 22 | K35: 0 | L35: 0 | M35: 0
K36: 0 | L36: 0 | M36: 0
K37: 0 | L37: 0 | M37: 0
B38: TOTALES | K38: =SUM(K32:K37) -> 0 | L38: 10 | M38: 10

Sheet ING SERV CHARGE 10
F4: EVENTO | G4: TURISMO CARRETERA (TC) - OSCAR CABALEN
F6: FECHA DEL EVENTO | G6: 30 Y 31 DE MAYO 2026
B12: FECHA | C12: DESCRIPCION | K12: DEBE | L12: HABER | M12: SALDO
M13: 0
A14: 1 | B14: 46152 | C14: ing serv charge | K14: 0 | L14: 10 | M14: =+M4-K14+L14 -> 10
A15: 2 | K15: 0 | L15: 0 | M15: =+M5-K15+L15 -> 0
A16: 3 | K16: 0 | L16: 0 | M16: =+M6-K16+L16 -> 0
A17: 4 | K17: 0 | L17: 0 | M17: =+M7-K17+L17 -> 0
A18: 5 | K18: 0 | L18: 0 | M18: =+M8-K18+L18 -> 0
A19: 6 | K19: 0 | L19: 0 | M19: =+M9-K19+L19 -> 0
A20: 7 | K20: 0 | L20: 0 | M20: =+M10-K20+L20 -> 0
A21: 8 | K21: 0 | L21: 0 | M21: =+M11-K21+L21 -> 0
A22: 9 | K22: 0 | L22: 0 | M22: =+M13-K22+L22 -> 0
A23: 10 | K23: 0 | L23: 0 | M23: =+M14-K23+L23 -> 10
A24: 11 | K24: 0 | L24: 0 | M24: =+M23-K24+L24 -> 10
K25: 0 | L25: 0 | M25: =+M24-K25+L25 -> 10
B26: TOTALES | K26: =SUM(K22:K25) -> 0 | L26: =SUM(L22:L25) -> 0 | M26: =+M25 -> 10

Sheet xxx
I4: EVENTO | J4: TURISMO CARRETERA (TC) - OSCAR CABALEN
I6: FECHA DEL EVENTO | J6: 30 Y 31 DE MAYO 2026
B12: FECHA | C12: DESCRIPCION | M12: DEBE | N12: HABER | O12: SALDO
A13: 1 | B13: 45757 | C13: SALDO INICIAL | O13: 10
A14: 2 | M14: 0 | N14: 0 | O14: =+O13-M14+N14 -> 10
A15: 3 | M15: 0 | N15: 0 | O15: =+O14-M15+N15 -> 10
A16: 4 | M16: 0 | N16: 0 | O16: =+O15-M16+N16 -> 10
A17: 5 | M17: 0 | N17: 0 | O17: =+O16-M17+N17 -> 10
A18: 6 | M18: 0 | N18: 0 | O18: =+O17-M18+N18 -> 10
A19: 7 | M19: 0 | N19: 0 | O19: =+O18-M19+N19 -> 10
A20: 8 | M20: 0 | N20: 0 | O20: =+O19-M20+N20 -> 10
A21: 9 | M21: 0 | N21: 0 | O21: =+O20-M21+N21 -> 10
A22: 10 | M22: 0 | N22: 0 | O22: =+O21-M22+N22 -> 10
A23: 11 | M23: 0 | N23: 0 | O23: =+O22-M23+N23 -> 10
A24: 12 | M24: 0 | N24: 0 | O24: =+O23-M24+N24 -> 10
A25: 13 | M25: 0 | N25: 0 | O25: =+O24-M25+N25 -> 10
... A52: 40 | M52: 0 | N52: 0 | O52: =+O51-M52+N52 -> 10
B53: TOTALES | O53: =+O52 -> 10
